Workbook

Sheet I. Chân Dung KH
A1: CHÂN DUNG KHÁCH HÀNG (PERSONA) – THEO SẢN PHẨM VÀ ĐỊA ĐIỂM
A2: Phân tích chi tiết đối tượng phụ huynh mục tiêu, nỗi đau, insight và messaging phù hợp cho từng cấp học và từng địa điểm
A4: A. PERSONA THEO CẤP HỌC
A5: Cấp học | B5: Tên Persona | C5: Tuổi | D5: Giới tính | E5: Nghề nghiệp | F5: Thu nhập/tháng | G5: Hành vi Online | H5: Kênh tiếp cận chính | I5: Nỗi đau #1 | J5: Nỗi đau #2 | K5: Nỗi đau #3 | L5: Insight mua hàng | M5: Messaging chính | N5: CTA hiệu quả | O5: Objection thường gặp | P5: Cách xử lý Objection
A6: MN (Mầm non) | B6: Chị Lan – Mẹ bỉm sữa | C6: 26-35 | D6: Nữ 85% | E6: Nhân viên VP, kinh doanh nhỏ | F6: 15-30 triệu | G6: Facebook 3h/ngày, Zalo, TikTok, group MN | H6: Meta Ads, Zalo OA, TikTok | I6: Sợ con bị bắt nạt / không an toàn | J6: Thiếu thời gian đưa đón, cần trường gần nhà | K6: Lo giáo viên không tận tâm, thay đổi liên tục | L6: Tin review PH khác > quảng cáo; Quyết định nhanh nếu tour ấn tượng | M6: Môi trường an toàn, camera 24/7, GV tận tâm, gần nhà | N6: Đăng ký tham quan trường MIỄN PHÍ | O6: Học phí cao hơn trường khác | P6: So sánh giá trị: ăn sạch, GV/trẻ tỷ lệ thấp, camera, ngoại khóa
A7: MN (Mầm non) | B7: Anh Tuấn – Ba trẻ quan tâm GD | C7: 30-40 | D7: Nam 15% | E7: Quản lý, kỹ sư, CNTT | F7: 25-50 triệu | G7: Google Search, YouTube review | H7: Google Ads, YouTube | I7: Muốn con phát triển toàn diện sớm | J7: Lo trường không có chương trình song ngữ tốt | K7: Không biết trường nào uy tín gần nhà | L7: So sánh kỹ trên Google trước khi tour | M7: Song ngữ từ 3 tuổi, chương trình STEAM | N7: Xem chi tiết chương trình học | O7: Muốn chờ vợ quyết định | P7: Mời cả 2 PH cùng tour, tặng ưu đãi
A8: TH (Tiểu học) | B8: Chị Mai – PH lớp 1 lo lắng | C8: 30-42 | D8: Nữ 75% | E8: Nhân viên, giáo viên, kinh doanh | F8: 20-40 triệu | G8: Facebook, Zalo group, tìm Google | H8: Meta Ads, Google Search, Zalo | I8: Sợ con không theo kịp chương trình | J8: Lo trường tư "nhẹ" hơn trường công | K8: Áp lực tiếng Anh – con chưa có nền tảng | L8: Tham khảo 3-5 trường trước khi chọn; Tour 2 lần | M8: Lộ trình tiếng Anh rõ ràng, sĩ số nhỏ 25-30, GV theo sát | N8: Đặt lịch tham quan + tư vấn 1-1 | O8: Trường công miễn phí mà cũng tốt | P8: Sĩ số 50 vs 25, không ngoại khóa, GV không theo sát
A9: TH (Tiểu học) | B9: Anh Hùng – PH chuyển con từ công sang tư | C9: 35-45 | D9: Nam 25% | E9: Chủ DN nhỏ, quản lý | F9: 30-60 triệu | G9: Google, Facebook, hỏi bạn bè | H9: Google Ads, Remarketing | I9: Con đang học công nhưng không phát triển | J9: Muốn môi trường tốt hơn, ít bạo lực | K9: Lo con không thích nghi khi chuyển | L9: Quyết định nhanh khi thấy cơ sở vật chất tốt | M9: Chuyển cấp linh hoạt, hỗ trợ hòa nhập, CSVC hiện đại | N9: Đăng ký chuyển trường – Hỗ trợ hồ sơ nhanh | O9: Con đã quen trường cũ | P9: Hỗ trợ hòa nhập 2 tuần, buddy system
A10: THCS (Cấp 2) | B10: Chị Hoa – PH lớp 6 giai đoạn bản lề | C10: 35-48 | D10: Nữ 65% | E10: Nhân viên, công chức, kinh doanh | F10: 25-50 triệu | G10: Facebook, Google, Webinar, Forum | H10: Meta Ads, Google Ads, Webinar | I10: Sợ con sa sút vì giai đoạn dậy thì | J10: Lo trường không theo sát tâm lý HS | K10: Áp lực kết quả thi cuối cấp | L10: Tham gia webinar trước khi tour; Cần dữ liệu đầu ra | M10: Theo sát HS giai đoạn bản lề, GV chủ nhiệm tâm huyết | N10: Đăng ký webinar: Lộ trình con tôi sau lớp 5 | O10: Học phí THCS cao hơn TH nhiều | P10: ROI dài hạn: nền tảng cho lớp 10, đại học
A11: THCS (Cấp 2) | B11: Anh Minh – PH muốn con có lộ trình rõ | C11: 38-50 | D11: Nam 35% | E11: Quản lý, chuyên gia, DN | F11: 40-80 triệu | G11: Google Search, YouTube, LinkedIn | H11: Google Ads, YouTube, Webinar | I11: Muốn con có định hướng nghề nghiệp sớm | J11: Lo trường chỉ dạy lý thuyết, thiếu thực hành | K11: Muốn chương trình quốc tế/song ngữ chuẩn | L11: So sánh đầu ra, tỷ lệ đỗ THPT top, chương trình quốc tế | M11: Lộ trình 6→12 rõ ràng, chương trình Cambridge/IB option | N11: Xem lộ trình đào tạo 7 năm | O11: Trường xa nhà | P11: Xe đưa đón, kế hoạch bán trú
A12: THPT (Cấp 3) | B12: Chị Thảo – PH lớp 10 áp lực thi | C12: 38-52 | D12: Nữ 60% | E12: Nhân viên, giáo viên, kinh doanh | F12: 30-60 triệu | G12: Facebook, Google, Webinar, tìm học bổng | H12: Google Ads, Meta Ads, Webinar | I12: Lo con không đỗ trường công top | J12: Áp lực tài chính: học phí THPT tư cao | K12: Lo con không vào được đại học tốt | L12: Quyết định theo học bổng + đầu ra đại học | M12: Học bổng lên đến 100%, đầu ra ĐH top, tỷ lệ đỗ ĐH 95%+ | N12: Đăng ký thi học bổng lớp 10 | O12: Trường tư chất lượng không bằng chuyên | P12: Data đầu ra: % ĐH top, học bổng du học, IELTS
A13: THPT (Cấp 3) | B13: Anh Đức – PH chuyển trường lớp 10-11 | C13: 40-55 | D13: Nam 40% | E13: Chủ DN, quản lý cấp cao | F13: 50-100+ triệu | G13: Google Search, YouTube, referral | H13: Google Ads, Remarketing | I13: Con đang học trường không phù hợp | J13: Muốn môi trường quốc tế + du học pathway | K13: Cần chuyển nhanh, ít gián đoạn | L13: Quyết định rất nhanh khi thấy phù hợp | M13: Chuyển trường linh hoạt, nhận hồ sơ quanh năm, pathway du học | N13: Liên hệ tư vấn chuyển trường 24h | O13: Sợ con mất bạn bè | P13: Chương trình hòa nhập, buddy system, câu lạc bộ
A16: B. NỖI ĐAU KHÁCH HÀNG THEO ĐỊA ĐIỂM
A17: Địa điểm | B17: Tên cũ (trước sáp nhập) | C17: Tên mới (hiện tại) | D17: Cấp học | E17: Đặc điểm PH khu vực | F17: Nỗi đau đặc thù #1 | G17: Nỗi đau đặc thù #2 | H17: Nỗi đau đặc thù #3 | I17: Messaging phù hợp | J17: Kênh ưu tiên | K17: Đối thủ chính | L17: Lợi thế VA tại đây
A18: MN VA Gò Vấp | B18: Q. Gò Vấp, TP.HCM | C18: Q. Gò Vấp, TP.HCM | D18: MN | E18: Thu nhập trung bình-khá, đông dân, nhiều gia đình trẻ | F18: Trường MN quá tải, thiếu chỗ gửi an toàn | G18: Giao thông kẹt, cần trường gần nhà | H18: Lo bạo lực, thiếu camera giám sát | I18: An toàn #1, gần nhà, camera 24/7 | J18: Meta Ads, Zalo OA | K18: MN Sài Gòn, MN Sao Mai | L18: Flagship, CSVC mới, GV ổn định
A19: MN Nhân Lễ | B19: H. Cần Giuộc, Long An | C19: TX. Cần Giuộc, Tây Ninh | D19: MN | E19: Thu nhập trung bình, vùng KDC mới, ít lựa chọn | F19: Rất ít trường tư chất lượng trong KDC | G19: PH làm ở KCN, cần trường bán trú tốt | H19: Lo con thiếu ngoại ngữ vùng tỉnh | I19: Trường chuẩn quốc tế ngay KDC, bán trú chu đáo | J19: Zalo OA, Facebook local | K19: MN công lập địa phương | L19: Duy nhất trường tư chất lượng trong KDC
A20: MN Thái Sơn | B20: H. Cần Giuộc, Long An | C20: TX. Cần Giuộc, Tây Ninh | D20: MN+TH | E20: PH KDC Thái Sơn, thu nhập khá, mới về định cư | F20: Thiếu trường tốt gần KDC mới | G20: Muốn con có bạn bè trong khu | H20: Lo chất lượng GD vùng mới phát triển | I20: Ngay trong KDC, không cần đưa đón xa | J20: Zalo OA, Facebook group KDC | K20: MN công, MN tư nhỏ lẻ | L20: Nằm ngay trong KDC, liên cấp MN+TH
A21: MN Mekong Xanh | B21: TP. Rạch Giá, Kiên Giang | C21: TP. Rạch Giá, An Giang | D21: MN+TH | E21: PH KĐT mới, thu nhập khá, nhiều công chức/DN | F21: Ít lựa chọn trường tư trong KĐT | G21: Muốn chương trình song ngữ mà vùng tỉnh không có | H21: Lo con thua thiệt so với TP.HCM | I21: Song ngữ chuẩn TP.HCM ngay tại tỉnh | J21: Zalo OA, Facebook local, Google local | K21: Trường công lập, TT Anh ngữ | L21: Chuẩn TP.HCM, liên cấp, KĐT cao cấp
A22: TH VA Gò Vấp | B22: Q. Gò Vấp, TP.HCM | C22: Q. Gò Vấp, TP.HCM | D22: TH | E22: PH trung lưu-khá, so sánh kỹ nhiều trường | F22: Quá nhiều lựa chọn, không biết trường nào tốt | G22: Lo tiếng Anh không đủ mạnh so với international school | H22: Sĩ số lớp quá đông ở trường công | I22: Sĩ số 25, lộ trình tiếng Anh có chứng chỉ, GV 1-1 | J22: Meta Ads, Google Search | K22: TH Việt Úc, TH iSchool, TH FPT | L22: Học phí hợp lý hơn international, vẫn song ngữ chuẩn
A23: TH VA Bình Tân | B23: Q. Bình Tân, TP.HCM | C23: Q. Bình Tân, TP.HCM | D23: TH | E23: PH thu nhập trung bình, khu đông dân, công nhân + KD nhỏ | F23: Rất ít trường tư chất lượng khu vực Bình Tân | G23: Lo an ninh khu vực, muốn trường khép kín | H23: Giá phải hợp lý với thu nhập | I23: An toàn, khép kín, học phí phù hợp, bán trú tốt | J23: Meta Ads, Zalo local | K23: TH Bình Tân, TH Phước Kiểng | L23: Duy nhất trường tư song ngữ quy mô tại BT
A24: TH Thái Sơn | B24: H. Cần Giuộc, Long An | C24: TX. Cần Giuộc, Tây Ninh | D24: TH | E24: PH KDC Thái Sơn, muốn con học tại chỗ | F24: Phải đi xa để học trường tốt | G24: Lo con mệt vì di chuyển hàng ngày | H24: Chương trình tỉnh yếu hơn TP | I24: Chuẩn TP.HCM ngay KDC, không cần đi xa | J24: Zalo, Facebook local | K24: TH công lập xã | L24: Liên cấp, ngay trong KDC
A25: TH Mekong Xanh | B25: TP. Rạch Giá, Kiên Giang | C25: TP. Rạch Giá, An Giang | D25: TH | E25: PH KĐT, muốn con có nền tảng tốt | F25: Không có trường tư song ngữ tại TP Rạch Giá | G25: Muốn con thi vào trường tốt sau này | H25: Lo GV giỏi không về tỉnh dạy | I25: GV từ TP.HCM, chương trình chuẩn quốc gia + song ngữ | J25: Zalo, Facebook, Google local | K25: TH công, TT Anh ngữ | L25: Duy nhất TH tư song ngữ quy mô
A26: THCS VA Gò Vấp | B26: Q. Gò Vấp, TP.HCM | C26: Q. Gò Vấp, TP.HCM | D26: THCS | E26: PH lo lắng giai đoạn dậy thì, cần theo sát | F26: Trường công THCS sĩ số 45-50, GV không theo sát | G26: Lo con sa sút vì bạn bè tiêu cực | H26: Áp lực thi THPT cạnh tranh | I26: Sĩ số nhỏ, GV chủ nhiệm theo sát, lộ trình 6→12 | J26: Google Ads, Meta, Webinar | K26: THCS Việt Úc, THCS iSchool | L26: Liên cấp THCS-THPT, không cần thi chuyển
A27: THPT VA Gò Vấp | B27: Q. Gò Vấp, TP.HCM | C27: Q. Gò Vấp, TP.HCM | D27: THPT | E27: PH áp lực thi lớp 10, tìm giải pháp B nếu rớt công | F27: Con không đỗ trường công top → hoang mang | G27: Học phí THPT tư cao, lo tài chính | H27: Lo đầu ra đại học không tốt bằng trường chuyên | I27: Học bổng 100%, đầu ra ĐH 95%+, pathway du học | J27: Google Ads, Meta, Webinar | K27: THPT Nguyễn Khuyến, THPT Trương Vĩnh Ký | L27: Học bổng lớn, lộ trình đa dạng, tỷ lệ ĐH cao
A30: C. HÀNH TRÌNH KHÁCH HÀNG (CUSTOMER JOURNEY) THEO CẤP
A31: Giai đoạn | B31: Awareness | C31: Consideration | D31: Decision | E31: Tour/Visit | F31: Enrollment | G31: Advocacy
A32: MN | B32: Thấy ads FB/TikTok → nghe PH review → tìm Google | C32: So sánh 2-3 trường → đọc review → hỏi group | D32: Gọi hotline / Zalo → Hỏi học phí → Book tour | E32: Tour campus → gặp GV → xem phòng học → lunch trial | F32: Nộp hồ sơ → đóng cọc → nhận thông báo | G32: Review Google → giới thiệu bạn → share FB
A33: TH | B33: Tìm Google "trường TH song ngữ" → thấy ads Meta | C33: So sánh 3-5 trường → tour 2 lần → hỏi PH hiện tại | D33: Webinar/Open Day → tư vấn 1-1 → nhận ưu đãi | E33: Tour chi tiết → ngồi lớp thử → gặp GV chủ nhiệm | F33: Thi đầu vào (nếu có) → nộp hồ sơ → đóng phí | G33: Review → referral program → PH ambassador
A34: THCS | B34: Webinar "chuyển cấp" → Google "THCS tốt GV" → FB ads | C34: So sánh đầu ra → xem chương trình → hỏi alumni PH | D34: Tư vấn riêng → xem lộ trình 6→12 → học bổng | E34: Tour + ngồi lớp + gặp HS hiện tại + GV chủ nhiệm | F34: Nộp hồ sơ → phỏng vấn → đóng cọc | G34: PH chia sẻ experience → alumni success story
A35: THPT | B35: Google "tuyển sinh lớp 10" → Webinar → FB/TikTok | C35: So sánh vs công → check đầu ra ĐH → học bổng | D35: Thi học bổng → tư vấn chuyên sâu → financial plan | E35: Tour VIP → gặp BGH → xem lab/thư viện/CLB | F35: Thi tuyển/xét tuyển → nhận kết quả → enrollment | G35: Đầu ra ĐH → alumni network → PH referral

Sheet 0. Dashboard
B1: 🎯 DASHBOARD ĐIỀU HÀNH – KẾ HOẠCH TUYỂN SINH VIỆT ANH 2026
B2: Giai đoạn: 26/03/2026 – 30/09/2026 | Tổng ngân sách: 13 tỷ đồng | Mục tiêu: 1,300 học sinh
B4: 📊 KPI TỔNG QUAN (tự động liên kết từ các sheet)
B5: Chỉ số | C5: Mục tiêu | D5: Thực tế MTD | E5: Vs Target | F5: Trạng thái | G5: Nguồn dữ liệu | H5: Sheet liên kết
B6: 🏫 Nhập học tích lũy | C6: ='1. Input'!B5 -> 1300 | D6: 0 | E6: =IF(C6>0,D6/C6,0) -> 0 | F6: → Nhập tay | G6: 1. Input | H6: Nhập tay từ CRM
B7: 🎯 School Tour tích lũy | C7: ='4. Funnel'!D3 -> 1300 | D7: 0 | E7: =IF(C7>0,D7/C7,0) -> 0 | F7: → Nhập tay | G7: 4. Funnel | H7: Nhập tay từ GHL
B8: 📥 Leads tích lũy | C8: ='4. Funnel'!D4 -> 3715 | D8: 0 | E8: =IF(C8>0,D8/C8,0) -> 0 | F8: → Nhập tay | G8: 4. Funnel | H8: Nhập tay từ GHL
B9: 💰 Chi phí Paid Media | C9: ='2. Paid Media'!C10 -> 425000000 | D9: 0 | E9: =IF(C9>0,D9/C9,0) -> 0 | F9: → Nhập tay | G9: 2. Paid Media | H9: Birch / Ads Manager
B10: 📊 CPL trung bình | C10: 200000 | D10: 0 | E10: =IF(C10>0,D10/C10,0) -> 0 | F10: → Nhập tay | G10: 14. Weekly Battleplan | H10: Nhập tay tuần
B11: 🏃 Lead→Tour rate | C11: 0.3 | D11: 0 | E11: =IF(C11>0,D11/C11,0) -> 0 | F11: → Nhập tay | G11: 4. Funnel | H11: Tính từ GHL
B12: ✅ Tour→Nhập học rate | C12: 0.35 | D12: 0 | E12: =IF(C12>0,D12/C12,0) -> 0 | F12: → Nhập tay | G12: 4. Funnel | H12: Tính từ GHL
B13: ⚡ Response <5 min | C13: 0.85 | D13: 0 | E13: =IF(C13>0,D13/C13,0) -> 0 | F13: → Nhập tay | G13: 14. Weekly Battleplan | H13: Nhập tay tuần
B15: 💰 NGÂN SÁCH PAID MEDIA THEO KÊNH (liên kết 2. Paid Media)
B16: Kênh | C16: % Mix | D16: Ngân sách | E16: Vai trò | F16: CPL Mục tiêu | G16: Quản lý | H16: Ghi chú
B17: Meta / Facebook + Instagram | C17: 0.38 | D17: 3230000000 | E17: Demand + lead local | F17: 120000 | G17: Birch + GHL | H17: Kênh chủ lực
B18: Google Search | C18: 0.18 | D18: 1530000000 | E18: Intent-based | F18: 180000 | G18: Birch | H18: THCS/THPT
B19: Google Display / YouTube | C19: 0.07 | D19: 595000000 | E19: Phủ + video | F19: N/A | G19: Birch | H19: Testimonial
B20: TikTok Ads | C20: 0.1 | D20: 850000000 | E20: Video social proof | F20: 90000 | G20: Birch + GHL | H20: 100 video
B21: Zalo Ads + OA | C21: 0.07 | D21: 595000000 | E21: Nurture local | F21: 80000 | G21: GHL | H21: K12 local
B22: Webinar Ads | C22: 0.05 | D22: 425000000 | E22: Webinar lộ trình | F22: 50000 | G22: Meta + GHL | H22: THCS/THPT
B23: Remarketing đa nền tảng | C23: 0.12 | D23: 1020000000 | E23: Đuổi lại khách | F23: 150000 | G23: Birch | H23: 12%
B24: Local SEO / GMB | C24: 0.05 | D24: 425000000 | E24: Local presence | F24: N/A | G24: Manual + GHL | H24: 8 địa điểm
B25: TỔNG PAID MEDIA | C25: 1.02 | D25: 8670000000
B27: 🏫 PHÂN BỔ THEO CƠ SỞ (liên kết 3. Master Table)
B28: Cơ sở | C28: Cấp | D28: HS Mục tiêu | E28: CAC | F28: Meta (đ) | G28: G.Search (đ) | H28: TikTok (đ) | I28: Zalo (đ)
B29: MN VA Gò Vấp | C29: MN | D29: 200 | E29: 0.85 | F29: 405838877 | G29: 192239468 | H29: 106799704 | I29: 74759793
B30: MN Nhân Lễ | C30: MN | D30: 60 | E30: 0.85 | F30: 121751663 | G30: 57671840 | H30: 32039911 | I30: 22427938
B31: MN Thái Sơn | C31: MN | D31: 60 | E31: 0.85 | F31: 121751663 | G31: 57671840 | H31: 32039911 | I31: 22427938
B32: MN Mekong Xanh | C32: MN | D32: 60 | E32: 0.85 | F32: 121751663 | G32: 57671840 | H32: 32039911 | I32: 22427938
B33: TH VA Gò Vấp | C33: TH | D33: 150 | E33: 1 | F33: 358093126 | G33: 169623060 | H33: 94235033 | I33: 65964523
B34: TH VA Bình Tân | C34: TH | D34: 150 | E34: 1 | F34: 358093126 | G34: 169623060 | H34: 94235033 | I34: 65964523
B35: TH Thái Sơn | C35: TH | D35: 60 | E35: 1 | F35: 143237251 | G35: 67849224 | H35: 37694013 | I35: 26385809
B36: TH Mekong Xanh | C36: TH | D36: 60 | E36: 1 | F36: 143237251 | G36: 67849224 | H36: 37694013 | I36: 26385809
B37: THCS VA Gò Vấp | C37: THCS | D37: 200 | E37: 1.2 | F37: 572949002 | G37: 271396896 | H37: 150776053 | I37: 105543237
B38: THPT VA Gò Vấp | C38: THPT | D38: 200 | E38: 1.35 | F38: 644567627 | G38: 305321508 | H38: 169623060 | I38: 118736142
B39: Brand hệ thống | C39: Chung | D39: 100 | E39: 1 | F39: 238728751 | G39: 113082040 | H39: 62823356 | I39: 43976349
B41: 🗂️ NAVIGATOR – DANH SÁCH CÁC SHEET (Click để xem)
B42: # | C42: Tên Sheet | D42: Mô tả | E42: Dùng cho | F42: Cập nhật | G42: Tần suất | H42: Liên kết đến
B43: 1 | C43: 1. Input | D43: Thông số đầu vào toàn kế hoạch | E43: Ban điều hành | F43: 26/03 | G43: Đầu mùa | H43: Master Table, Funnel
B44: 2 | C44: 2. Paid Media | D44: Mix kênh, ngân sách, KPI mỗi kênh | E44: Marketing Lead | F44: Hàng tháng | G44: Tháng | H44: Master Table
B45: 3 | C45: 3. Master Table | D45: Phân bổ NS theo từng cơ sở | E45: Tất cả | F45: Đầu mùa | G45: Đầu mùa | H45: Paid Media, Funnel
B46: 4 | C46: 4. Funnel | D46: Funnel chuyển đổi & KPI | E46: Tất cả | F46: Tuần | G46: Tuần | H46: Dashboard, Battleplan
B47: 5 | C47: 5. Google Ads Chi Tiết | D47: Campaign, KW, RSA, Birch setup | E47: Perf. Marketing | F47: Tuần | G47: Tuần | H47: KPI Weekly
B48: 6 | C48: 6. Meta Ads Chi Tiết | D48: Campaign, Audience, Creative, Pixel | E48: Perf. Marketing | F48: Tuần | G48: Tuần | H48: KPI Weekly
B49: 7 | C49: 7. TikTok Ads Chi Tiết | D49: 100 video, campaign, GTM | E49: Content + Perf. | F49: Tuần | G49: Tuần | H49: KPI Weekly
B50: 8 | C50: 8. GoHighLevel Setup | D50: CRM, Pipeline, Automation, Zalo | E50: CRM + Sales | F50: Ngày 1 | G50: Setup | H50: Admissions KPI
B51: 9 | C51: 9. GTM Tracking | D51: Tag, trigger, conversion setup | E51: Tech/Dev | F51: Ngày 1 | G51: Setup | H51: Pixel, GA4
B52: 10 | C52: 10. Lịch Công Việc | D52: Checklist ngày/tuần/tháng marketer | E52: Marketing | F52: Hàng ngày | G52: Daily | H52: Battleplan, Todo
B53: 11 | C53: 11. Timeline | D53: Lịch giải ngân 7 tháng | E53: Ban điều hành | F53: Hàng tháng | G53: Tháng | H53: Dashboard
... B64: H | C64: G. Birch + GHL Integration | D64: Automation rules + webhook payload | E64: Tech + Marketing | F64: Ngày 1 | G64: Setup | H64: Birch Rules
B66: 🆕 SHEETS BỔ SUNG V7
B67: I | C67: I. Chân Dung KH | D67: Persona + nỗi đau theo sản phẩm và địa điểm | E67: Marketing + Sales | F67: Đầu mùa | G67: Setup | H67: Persona, Funnel
B68: J | C68: J. Webinar Chi Tiết | D68: Kế hoạch 8 webinar + quy trình + KPI | E68: Marketing + BGH | F68: Hàng tháng | G68: Tháng | H68: Campaign, GHL
B69: K | C69: K. Social Media Calendar | D69: Lịch đăng bài theo kênh, cơ sở, tháng | E69: Content Creator | F69: Hàng tuần | G69: Tuần | H69: Content
B70: L | C70: L. Analytics & Remarketing | D70: GA4 events, remarketing audiences, automation tracking | E70: Performance | F70: Hàng tuần | G70: Tuần | H70: GTM, Birch
B73: 📊 KPI THEO KÊNH (liên kết chi tiết)
B74: Kênh | C74: NS 7 tháng | D74: % Mix | E74: CPL Target | F74: Leads Target | G74: Tours Target | H74: Sheet chi tiết | I74: Tool quản lý
B75: Meta Ads | C75: 3230000000 | D75: 38% | E75: 120000 | F75: 4250 | G75: 1275 | H75: F. Meta Ads Plan | I75: Birch + Meta Ads Manager
B76: Google Search | C76: 1530000000 | D76: 18% | E76: 180000 | F76: 2010 | G76: 603 | H76: G. Google Ads Plan | I76: Birch + Google Ads
B77: Google Display/YT | C77: 595000000 | D77: 7% | E77: - | F77: - | G77: - | H77: 5. Google Ads Chi Tiết | I77: Birch
B78: TikTok Ads | C78: 850000000 | D78: 10% | E78: 90000 | F78: 1420 | G78: 426 | H78: 7. TikTok Ads Chi Tiết | I78: Birch + TikTok Ads
B79: Zalo Ads+OA | C79: 595000000 | D79: 7% | E79: 80000 | F79: 1120 | G79: 336 | H79: 13. Zalo Ads + OA | I79: GHL + Zalo OA
B80: Webinar Ads | C80: 425000000 | D80: 5% | E80: 50000 | F80: 1060 | G80: 256 | H80: J. Webinar Chi Tiết | I80: Meta + GHL
B81: Remarketing | C81: 1020000000 | D81: 12% | E81: 150000 | F81: - | G81: - | H81: L. Analytics & Remarketing | I81: Birch cross-platform
B82: Local SEO/GMB | C82: 425000000 | D82: 5% | E82: - | F82: - | G82: - | H82: 12. Danh bạ | I82: Manual + GHL

Sheet 1. Input
A1: INPUT & ĐIỀU KHIỂN – BẢN V5 (BỎ PHÚ NHUẬN, CẬP NHẬT ĐỊA GIỚI)
A2: ⚠️ Phú Nhuận ĐÃ BỎ. Ngân sách phân bổ lại cho các cơ sở còn lại. Cần Giuộc → Tây Ninh. Rạch Giá → An Giang.
A3: Hạng mục | B3: Giá trị | C3: Đơn vị | D3: Ghi chú
A4: Tổng ngân sách | B4: 13000000000 | C4: đ | D4: 13 tỷ
A5: Mục tiêu nhập học | B5: 1300 | C5: HS | D5: Không còn Phú Nhuận → phân bổ lại
A6: NC → Lead | B6: 0.2 | C6: % | D6: Benchmark K12: 18-25%
A7: Lead → School Tour | B7: 0.3 | C7: % | D7: SLA < 5 phút + GHL automation
A8: Tour → Nhập học | B8: 0.35 | C8: % | D8: Thực tế K12 VN
A9: CRM / GoHighLevel | B9: 200000000 | C9: đ | D9: GHL + Zalo + SMS + landing
A10: School Tour / Open Day / Event | B10: 800000000 | C10: đ | D10: Điểm chuyển đổi #1
A11: Nhân sự Sales | B11: 800000000 | C11: đ | D11: Lương + KPI + hoa hồng
A12: Content / Brand / Sales Enablement | B12: 700000000 | C12: đ | D12: Kho sẵn + creative mới
A13: Nhân sự Marketing (5 người × 6T) | B13: 450000000 | C13: đ | D13: 5 người × 6 tháng × 15 triệu
A14: Học bổng / Promotion | B14: 1000000000 | C14: đ | D14: Kích hoạt quyết định
A15: Paid Media | B15: 8500000000 | C15: đ | D15: 65.4% tổng NS
A16: Training / QA / Data / Mystery call | B16: 550000000 | C16: đ | D16: 100+100+200+150 triệu
A18: KIỂM TRA | B18: =SUM(B9:B16) -> 13000000000
A19: Chênh lệch | B19: =B4-B18 -> 0
A20: Trạng thái | B20: =IF(ABS(B19)<1000,"✅ Khớp 13 tỷ","❌ LỆCH") -> ✅ Khớp 13 tỷ
A22: CHI TIẾT BỔ SUNG
A23: Số cơ sở | B23: 6 | C23: cơ sở | D23: Bỏ Phú Nhuận, còn 6 cơ sở hoạt động
A24: Số cấp học | B24: 4 | C24: cấp | D24: MN, TH, THCS, THPT
A25: Số LP cần tạo | B25: 8 | C25: trang | D25: 1 LP/campus + 1 webinar + 1 tỉnh MN + 1 tỉnh TH
A26: Số pipeline GHL | B26: 4 | C26: pipeline | D26: MN, TH, THCS, THPT
A27: Thời gian chiến dịch | B27: 7 | C27: tháng | D27: 26/03 - 30/09/2026
A28: Số tuần tác chiến | B28: 28 | C28: tuần | D28: Tuần 1 (26/03) → Tuần 28 (30/09)
A29: Số nhân sự Marketing | B29: 5 | C29: người | D29: PM×1, Content×2, Performance×1, CRM×1
A30: Số nhân sự Sales | B30: 6 | C30: người | D30: 1 Sales Lead + 5 Tư vấn viên (round-robin)
A31: Kho content sẵn có | B31: 2000 | C31: bài | D31: Ảnh+video+bài viết kho cũ
A32: Video testimonial | B32: 100 | C32: video | D32: Kho 100 video PH+HS+GV sẵn sàng
A33: Webinar planned | B33: 8 | C33: buổi | D33: 6 chính + 2 bổ sung
A34: Open Day planned | B34: 2 | C34: sự kiện | D34: Tháng 5 + Tháng 6
A35: Lead response SLA | B35: 5 | C35: phút | D35: Gọi lại trong 5 phút, mục tiêu 85%
A36: Benchmark NC→Lead | B36: 18-25% | C36: % | D36: K12 VN trung bình
A37: Benchmark Lead→Tour | B37: 25-35% | C37: % | D37: Cần SLA tốt + GHL automation
A38: Benchmark Tour→Enroll | B38: 30-40% | C38: % | D38: Phụ thuộc tour quality + follow-up
A40: DANH SÁCH CƠ SỞ (ĐỊA GIỚI MỚI + CŨ)
A41: STT | B41: Tên cơ sở | C41: Cấp | D41: Địa chỉ | E41: Khu vực mới | F41: Khu vực cũ (trước sáp nhập) | G41: Hotline
A42: 1 | B42: MN VA Gò Vấp | C42: MN | D42: 573 Đ. Lê Đức Thọ, P. An Hội Tây | E42: Q. Gò Vấp, TP.HCM | F42: Q. Gò Vấp, TP.HCM (không đổi) | G42: 0916 961 409
A43: 2 | B43: MN Nhân Lễ | C43: MN | D43: 22 Đường D2, KDC Cần Giuộc | E43: TX. Cần Giuộc, tỉnh Tây Ninh | F43: H. Cần Giuộc, tỉnh Long An | G43: 0916 961 409
A44: 3 | B44: MN+TH Thái Sơn | C44: MN+TH | D44: KDC Thái Sơn, Cần Giuộc | E44: TX. Cần Giuộc, tỉnh Tây Ninh | F44: H. Cần Giuộc, tỉnh Long An | G44: 0916 961 409
A45: 4 | B45: MN+TH Mekong Xanh | C45: MN+TH | D45: Lô E7, KĐT Tây Bắc, TP. Rạch Giá | E45: TP. Rạch Giá, tỉnh An Giang | F45: TP. Rạch Giá, tỉnh Kiên Giang | G45: 0916 961 409
A46: 5 | B46: TH VA Gò Vấp | C46: TH | D46: 160/72 Phan Huy Ích | E46: Q. Gò Vấp, TP.HCM | F46: Q. Gò Vấp, TP.HCM (không đổi) | G46: 0916 961 409
A47: 6 | B47: TH VA Bình Tân | C47: TH | D47: Số 7 đường 38A, Tân Tạo | E47: Q. Bình Tân, TP.HCM | F47: Q. Bình Tân, TP.HCM (không đổi) | G47: 0916 961 409
A48: 7 | B48: THCS VA Gò Vấp | C48: THCS | D48: 160/72 Phan Huy Ích | E48: Q. Gò Vấp, TP.HCM | F48: Q. Gò Vấp, TP.HCM (không đổi) | G48: 091 696 1409
A49: 8 | B49: THPT VA Gò Vấp | C49: THPT | D49: 160/72 Phan Huy Ích | E49: Q. Gò Vấp, TP.HCM | F49: Q. Gò Vấp, TP.HCM (không đổi) | G49: 091 696 1409

Sheet 2. Paid Media
A1: MIX KÊNH PAID MEDIA – 8.5 TỶ (TÁCH SEARCH/DISPLAY, KHÔNG CÓ PHÚ NHUẬN)
A2: Kênh | B2: % Mix | C2: Ngân sách | D2: Vai trò | E2: KPI | F2: CPL mục tiêu | G2: Quản lý bởi | H2: Ghi chú
A3: Meta / Facebook + Instagram | B3: 0.38 | C3: =B3*'1. Input'!B15 -> 3230000000 | D3: Demand + lead local | E3: CPL, Volume | F3: 120000 | G3: Birch + GHL | H3: Kênh chủ lực
A4: Google Search (TÁCH RIÊNG) | B4: 0.18 | C4: =B4*'1. Input'!B15 -> 1530000000 | D4: Intent-based | E4: CPC, Quality | F4: 180000 | G4: Birch | H4: Đo riêng THCS/THPT
A5: Google Display / YouTube | B5: 0.07 | C5: =B5*'1. Input'!B15 -> 595000000 | D5: Phủ + video | E5: CPM, View | G5: Birch | H5: Testimonial 15-30s
A6: TikTok Ads | B6: 0.1 | C6: =B6*'1. Input'!B15 -> 850000000 | D6: Video social proof | E6: CPV, Lead | F6: 90000 | G6: Birch + GHL | H6: 100 video = vàng
A7: Zalo Ads + OA | B7: 0.07 | C7: =B7*'1. Input'!B15 -> 595000000 | D7: Nurture local | E7: Open, CTR | F7: 80000 | G7: GoHighLevel | H7: Hidden champion K12
A8: Webinar Ads (THCS/THPT) | B8: 0.05 | C8: =B8*'1. Input'!B15 -> 425000000 | D8: Webinar lộ trình | E8: Đăng ký | F8: 50000 | G8: Meta + GHL | H8: KHÔNG cho MN/TH
A9: Remarketing đa nền tảng | B9: 0.12 | C9: =B9*'1. Input'!B15 -> 1020000000 | D9: Đuổi lại khách | E9: ROAS, Conv | F9: 150000 | G9: Birch | H9: Giảm 15%→12%
A10: Local SEO / Google Business | B10: 0.05 | C10: =B10*'1. Input'!B15 -> 425000000 | D10: Local presence | E10: Map, Clicks | G10: Manual + GHL | H10: 8 địa điểm
A11: TỔNG | B11: =SUM(B3:B10) -> 1.02 | C11: =SUM(C3:C10) -> 8670000000
A13: NGÂN SÁCH PAID MEDIA THEO THÁNG
A14: Kênh | B14: T4 (12%) | C14: T5 (24%) | D14: T6 (28%) | E14: T7 (24%) | F14: T8 (8%) | G14: T9 (2%) | H14: Tổng 7 tháng
A15: Meta / FB+IG | B15: =0.12*C3 -> 387600000 | C15: =0.24*C3 -> 775200000 | D15: =0.28*C3 -> 904400000 | E15: =0.24*C3 -> 775200000 | F15: =0.08*C3 -> 258400000 | G15: =0.02*C3 -> 64600000 | H15: =SUM(B15:G15) -> 3165400000
A16: Google Search | B16: =0.12*C4 -> 183600000 | C16: =0.24*C4 -> 367200000 | D16: =0.28*C4 -> 428400000 | E16: =0.24*C4 -> 367200000 | F16: =0.08*C4 -> 122400000 | G16: =0.02*C4 -> 30600000 | H16: =SUM(B16:G16) -> 1499400000
A17: Google Display/YT | B17: =0.12*C5 -> 71400000 | C17: =0.24*C5 -> 142800000 | D17: =0.28*C5 -> 166600000 | E17: =0.24*C5 -> 142800000 | F17: =0.08*C5 -> 47600000 | G17: =0.02*C5 -> 11900000 | H17: =SUM(B17:G17) -> 583100000
A18: TikTok Ads | B18: =0.12*C6 -> 102000000 | C18: =0.24*C6 -> 204000000 | D18: =0.28*C6 -> 238000000 | E18: =0.24*C6 -> 204000000 | F18: =0.08*C6 -> 68000000 | G18: =0.02*C6 -> 17000000 | H18: =SUM(B18:G18) -> 833000000
A19: Zalo Ads+OA | B19: =0.12*C7 -> 71400000 | C19: =0.24*C7 -> 142800000 | D19: =0.28*C7 -> 166600000 | E19: =0.24*C7 -> 142800000 | F19: =0.08*C7 -> 47600000 | G19: =0.02*C7 -> 11900000 | H19: =SUM(B19:G19) -> 583100000
A20: Webinar Ads | B20: =0.12*C8 -> 51000000 | C20: =0.24*C8 -> 102000000 | D20: =0.28*C8 -> 119000000 | E20: =0.24*C8 -> 102000000 | F20: =0.08*C8 -> 34000000 | G20: =0.02*C8 -> 8500000 | H20: =SUM(B20:G20) -> 416500000
A21: Remarketing | B21: =0.12*C9 -> 122400000 | C21: =0.24*C9 -> 244800000 | D21: =0.28*C9 -> 285600000 | E21: =0.24*C9 -> 244800000 | F21: =0.08*C9 -> 81600000 | G21: =0.02*C9 -> 20400000 | H21: =SUM(B21:G21) -> 999600000
A22: Local SEO/GMB | B22: =0.12*C10 -> 51000000 | C22: =0.24*C10 -> 102000000 | D22: =0.28*C10 -> 119000000 | E22: =0.24*C10 -> 102000000 | F22: =0.08*C10 -> 34000000 | G22: =0.02*C10 -> 8500000 | H22: =SUM(B22:G22) -> 416500000
A24: CHI TIẾT VAI TRÒ TỪNG KÊNH
A25: Kênh | B25: Vai trò trong funnel | C25: Giai đoạn KH | D25: Resource cần | E25: Daily operations | F25: Weekly optimization | G25: Tool chính
A26: Meta Ads | B26: Demand generation + Lead local + Social proof | C26: Awareness → Consideration | D26: 30+ creative (image+video), 12 audiences | E26: Check CPL, scale/pause, creative refresh | F26: A/B test creative, audience expansion, budget realloc | G26: Meta Ads Manager + Birch
A27: Google Search | B27: Intent-based capture + Brand defense | C27: Consideration → Decision | D27: 20 campaigns, 200+ keywords, 15 RSA | E27: Search terms review, bid adjust, QS check | F27: Negative KW update, RSA test, campaign restructure | G27: Google Ads + Birch
A28: Google Display/YT | B28: Awareness phủ + Video retarget | C28: Awareness + Remarketing | D28: 5 display banners, 3 video 15-30s | E28: Check CPM, placement exclusion | F28: Placement review, video performance | G28: Google Ads + Birch
A29: TikTok Ads | B29: Video social proof + Gen Z/Millennial reach | C29: Awareness → Lead | D29: 100 video kho sẵn, 5 new/tháng | E29: Check CPV, engagement, 3s retention | F29: Video performance ranking, upload new | G29: TikTok Ads + Birch
A30: Zalo Ads+OA | B30: Local nurture + Broadcast + Remarketing | C30: Consideration → Decision | D30: 8 broadcast templates, 4 ad creatives | E30: Check OA messages, broadcast schedule | F30: Segment refresh, broadcast content planning | G30: Zalo Ads + GHL
A31: Webinar Ads | B31: Education + Trust building + Conversion | C31: Consideration → Decision | D31: LP webinar, email sequence, Zoom setup | E31: Monitor registrations, reminder blast | F31: Post-webinar analysis, follow-up sequence | G31: Meta + Google + GHL
A32: Remarketing | B32: Re-engage warm/hot leads across platforms | C32: Decision → Conversion | D32: Dynamic creative, countdown, offers | E32: Check frequency, exclude converted | F32: Audience refresh, creative rotation | G32: All platforms + Birch
A33: Local SEO/GMB | B33: Local presence + Map visibility + Reviews | C33: Awareness (local) | D33: Ảnh, posts, review management | E33: Reply reviews, check listing accuracy | F33: Post 1 bài/tuần, update photos | G33: Google Business + Manual

Sheet 3. Master Table
A1: PHÂN BỔ – BỎ PHÚ NHUẬN – 11 DÒNG CƠ SỞ (Cần Giuộc→Tây Ninh, Rạch Giá→An Giang)
A2: Cấp | B2: Địa điểm | C2: Địa chỉ / Tỉnh | D2: HS | E2: CAC | F2: Điểm | G2: % | H2: Tổng NS | I2: Paid | J2: Tour | K2: Meta | L2: G.Search | M2: G.Display | N2: TikTok | O2: Zalo | P2: Webinar | Q2: Remarket | R2: Local SEO
A3: MN | B3: MN VA Gò Vấp | C3: 573 Lê Đức Thọ, Gò Vấp, TP.HCM | D3: 200 | E3: 0.85 | F3: =D3*E3 -> 170 | G3: =F3/F$14 -> 0.12564671 | H3: =G3*'1. Input'!B4 -> 1.6334072e+09 | I3: =G3*'1. Input'!B15 -> 1.067997e+09 | J3: =G3*'1. Input'!B10 -> 1.0051737e+08 | K3: =I3*'2. Paid Media'!B3 -> 4.0583888e+08 | L3: =I3*'2. Paid Media'!B4 -> 1.9223947e+08 | M3: =I3*'2. Paid Media'!B5 -> 74759793 | N3: =I3*'2. Paid Media'!B6 -> 1.067997e+08 | O3: =I3*'2. Paid Media'!B7 -> 74759793 | P3: =I3*'2. Paid Media'!B8 -> 53399852 | Q3: =I3*'2. Paid Media'!B9 -> 1.2815965e+08 | R3: =I3*'2. Paid Media'!B10 -> 53399852
A4: MN | B4: MN Nhân Lễ | C4: 22 D2, KDC Cần Giuộc, Tây Ninh | D4: 60 | E4: 0.85 | F4: =D4*E4 -> 51 | G4: =F4/F$14 -> 0.037694013 | H4: =G4*'1. Input'!B4 -> 4.9002217e+08 | I4: =G4*'1. Input'!B15 -> 3.2039911e+08 | J4: =G4*'1. Input'!B10 -> 30155211 | K4: =I4*'2. Paid Media'!B3 -> 1.2175166e+08 | L4: =I4*'2. Paid Media'!B4 -> 57671840 | M4: =I4*'2. Paid Media'!B5 -> 22427938 | N4: =I4*'2. Paid Media'!B6 -> 32039911 | O4: =I4*'2. Paid Media'!B7 -> 22427938 | P4: =I4*'2. Paid Media'!B8 -> 16019956 | Q4: =I4*'2. Paid Media'!B9 -> 38447894 | R4: =I4*'2. Paid Media'!B10 -> 16019956
A5: MN | B5: MN Thái Sơn | C5: KDC Thái Sơn, Cần Giuộc, Tây Ninh | D5: 60 | E5: 0.85 | F5: =D5*E5 -> 51 | G5: =F5/F$14 -> 0.037694013 | H5: =G5*'1. Input'!B4 -> 4.9002217e+08 | I5: =G5*'1. Input'!B15 -> 3.2039911e+08 | J5: =G5*'1. Input'!B10 -> 30155211 | K5: =I5*'2. Paid Media'!B3 -> 1.2175166e+08 | L5: =I5*'2. Paid Media'!B4 -> 57671840 | M5: =I5*'2. Paid Media'!B5 -> 22427938 | N5: =I5*'2. Paid Media'!B6 -> 32039911 | O5: =I5*'2. Paid Media'!B7 -> 22427938 | P5: =I5*'2. Paid Media'!B8 -> 16019956 | Q5: =I5*'2. Paid Media'!B9 -> 38447894 | R5: =I5*'2. Paid Media'!B10 -> 16019956
A6: MN | B6: MN Mekong Xanh | C6: Lô E7, KĐT Tây Bắc, Rạch Giá, An Giang | D6: 60 | E6: 0.85 | F6: =D6*E6 -> 51 | G6: =F6/F$14 -> 0.037694013 | H6: =G6*'1. Input'!B4 -> 4.9002217e+08 | I6: =G6*'1. Input'!B15 -> 3.2039911e+08 | J6: =G6*'1. Input'!B10 -> 30155211 | K6: =I6*'2. Paid Media'!B3 -> 1.2175166e+08 | L6: =I6*'2. Paid Media'!B4 -> 57671840 | M6: =I6*'2. Paid Media'!B5 -> 22427938 | N6: =I6*'2. Paid Media'!B6 -> 32039911 | O6: =I6*'2. Paid Media'!B7 -> 22427938 | P6: =I6*'2. Paid Media'!B8 -> 16019956 | Q6: =I6*'2. Paid Media'!B9 -> 38447894 | R6: =I6*'2. Paid Media'!B10 -> 16019956
A7: TH | B7: TH VA Gò Vấp | C7: 160/72 Phan Huy Ích, Gò Vấp, TP.HCM | D7: 150 | E7: 1 | F7: =D7*E7 -> 150 | G7: =F7/F$14 -> 0.11086475 | H7: =G7*'1. Input'!B4 -> 1.4412417e+09 | I7: =G7*'1. Input'!B15 -> 9.4235033e+08 | J7: =G7*'1. Input'!B10 -> 88691796 | K7: =I7*'2. Paid Media'!B3 -> 3.5809313e+08 | L7: =I7*'2. Paid Media'!B4 -> 1.6962306e+08 | M7: =I7*'2. Paid Media'!B5 -> 65964523 | N7: =I7*'2. Paid Media'!B6 -> 94235033 | O7: =I7*'2. Paid Media'!B7 -> 65964523 | P7: =I7*'2. Paid Media'!B8 -> 47117517 | Q7: =I7*'2. Paid Media'!B9 -> 1.1308204e+08 | R7: =I7*'2. Paid Media'!B10 -> 47117517
A8: TH | B8: TH VA Bình Tân | C8: Số 7 đường 38A, Tân Tạo, Bình Tân, TP.HCM | D8: 150 | E8: 1 | F8: =D8*E8 -> 150 | G8: =F8/F$14 -> 0.11086475 | H8: =G8*'1. Input'!B4 -> 1.4412417e+09 | I8: =G8*'1. Input'!B15 -> 9.4235033e+08 | J8: =G8*'1. Input'!B10 -> 88691796 | K8: =I8*'2. Paid Media'!B3 -> 3.5809313e+08 | L8: =I8*'2. Paid Media'!B4 -> 1.6962306e+08 | M8: =I8*'2. Paid Media'!B5 -> 65964523 | N8: =I8*'2. Paid Media'!B6 -> 94235033 | O8: =I8*'2. Paid Media'!B7 -> 65964523 | P8: =I8*'2. Paid Media'!B8 -> 47117517 | Q8: =I8*'2. Paid Media'!B9 -> 1.1308204e+08 | R8: =I8*'2. Paid Media'!B10 -> 47117517
A9: TH | B9: TH Thái Sơn | C9: KDC Thái Sơn, Cần Giuộc, Tây Ninh | D9: 60 | E9: 1 | F9: =D9*E9 -> 60 | G9: =F9/F$14 -> 0.044345898 | H9: =G9*'1. Input'!B4 -> 5.7649667e+08 | I9: =G9*'1. Input'!B15 -> 3.7694013e+08 | J9: =G9*'1. Input'!B10 -> 35476718 | K9: =I9*'2. Paid Media'!B3 -> 1.4323725e+08 | L9: =I9*'2. Paid Media'!B4 -> 67849224 | M9: =I9*'2. Paid Media'!B5 -> 26385809 | N9: =I9*'2. Paid Media'!B6 -> 37694013 | O9: =I9*'2. Paid Media'!B7 -> 26385809 | P9: =I9*'2. Paid Media'!B8 -> 18847007 | Q9: =I9*'2. Paid Media'!B9 -> 45232816 | R9: =I9*'2. Paid Media'!B10 -> 18847007
A10: TH | B10: TH Mekong Xanh | C10: Lô E7, KĐT Tây Bắc, Rạch Giá, An Giang | D10: 60 | E10: 1 | F10: =D10*E10 -> 60 | G10: =F10/F$14 -> 0.044345898 | H10: =G10*'1. Input'!B4 -> 5.7649667e+08 | I10: =G10*'1. Input'!B15 -> 3.7694013e+08 | J10: =G10*'1. Input'!B10 -> 35476718 | K10: =I10*'2. Paid Media'!B3 -> 1.4323725e+08 | L10: =I10*'2. Paid Media'!B4 -> 67849224 | M10: =I10*'2. Paid Media'!B5 -> 26385809 | N10: =I10*'2. Paid Media'!B6 -> 37694013 | O10: =I10*'2. Paid Media'!B7 -> 26385809 | P10: =I10*'2. Paid Media'!B8 -> 18847007 | Q10: =I10*'2. Paid Media'!B9 -> 45232816 | R10: =I10*'2. Paid Media'!B10 -> 18847007
A11: THCS | B11: THCS VA Gò Vấp | C11: 160/72 Phan Huy Ích, Gò Vấp, TP.HCM | D11: 200 | E11: 1.2 | F11: =D11*E11 -> 240 | G11: =F11/F$14 -> 0.17738359 | H11: =G11*'1. Input'!B4 -> 2.3059867e+09 | I11: =G11*'1. Input'!B15 -> 1.5077605e+09 | J11: =G11*'1. Input'!B10 -> 1.4190687e+08 | K11: =I11*'2. Paid Media'!B3 -> 5.72949e+08 | L11: =I11*'2. Paid Media'!B4 -> 2.713969e+08 | M11: =I11*'2. Paid Media'!B5 -> 1.0554324e+08 | N11: =I11*'2. Paid Media'!B6 -> 1.5077605e+08 | O11: =I11*'2. Paid Media'!B7 -> 1.0554324e+08 | P11: =I11*'2. Paid Media'!B8 -> 75388027 | Q11: =I11*'2. Paid Media'!B9 -> 1.8093126e+08 | R11: =I11*'2. Paid Media'!B10 -> 75388027
A12: THPT | B12: THPT VA Gò Vấp | C12: 160/72 Phan Huy Ích, Gò Vấp, TP.HCM | D12: 200 | E12: 1.35 | F12: =D12*E12 -> 270 | G12: =F12/F$14 -> 0.19955654 | H12: =G12*'1. Input'!B4 -> 2.594235e+09 | I12: =G12*'1. Input'!B15 -> 1.6962306e+09 | J12: =G12*'1. Input'!B10 -> 1.5964523e+08 | K12: =I12*'2. Paid Media'!B3 -> 6.4456763e+08 | L12: =I12*'2. Paid Media'!B4 -> 3.0532151e+08 | M12: =I12*'2. Paid Media'!B5 -> 1.1873614e+08 | N12: =I12*'2. Paid Media'!B6 -> 1.6962306e+08 | O12: =I12*'2. Paid Media'!B7 -> 1.1873614e+08 | P12: =I12*'2. Paid Media'!B8 -> 84811530 | Q12: =I12*'2. Paid Media'!B9 -> 2.0354767e+08 | R12: =I12*'2. Paid Media'!B10 -> 84811530
A13: Liên cấp | B13: Brand hệ thống | C13: Retarget + brand awareness chung | D13: 100 | E13: 1 | F13: =D13*E13 -> 100 | G13: =F13/F$14 -> 0.07390983 | H13: =G13*'1. Input'!B4 -> 9.6082779e+08 | I13: =G13*'1. Input'!B15 -> 6.2823356e+08 | J13: =G13*'1. Input'!B10 -> 59127864 | K13: =I13*'2. Paid Media'!B3 -> 2.3872875e+08 | L13: =I13*'2. Paid Media'!B4 -> 1.1308204e+08 | M13: =I13*'2. Paid Media'!B5 -> 43976349 | N13: =I13*'2. Paid Media'!B6 -> 62823356 | O13: =I13*'2. Paid Media'!B7 -> 43976349 | P13: =I13*'2. Paid Media'!B8 -> 31411678 | Q13: =I13*'2. Paid Media'!B9 -> 75388027 | R13: =I13*'2. Paid Media'!B10 -> 31411678
A14: TỔNG | D14: =SUM(D3:D13) -> 1300 | F14: =SUM(F3:F13) -> 1353 | G14: =SUM(G3:G13) -> 1 | H14: =SUM(H3:H13) -> 13000000000 | I14: =SUM(I3:I13) -> 8500000000 | J14: =SUM(J3:J13) -> 800000000 | K14: =SUM(K3:K13) -> 3230000000 | L14: =SUM(L3:L13) -> 1530000000 | M14: =SUM(M3:M13) -> 595000000 | ... R14: =SUM(R3:R13) -> 425000000

Sheet 4. Funnel
A1: FUNNEL & KPI (NC→Lead 20% | Lead→Tour 30% | Tour→Nhập 35%)
A2: Tầng | B2: Tỷ lệ | C2: Nguồn | D2: Sản lượng | E2: Chi phí BQ | F2: Ghi chú
A3: Nhập học | D3: ='1. Input'!B5 -> 1300 | E3: =ROUND('1. Input'!B4/D3,0) -> 10000000 | F3: 1,300 HS mục tiêu
A4: School Tour | B4: ='1. Input'!B8 -> 0.35 | D4: =ROUNDUP(D3/B4,0) -> 3715 | E4: =ROUND('1. Input'!B4/D4,0) -> 3499327
A5: Leads | B5: ='1. Input'!B7 -> 0.3 | D5: =ROUNDUP(D4/B5,0) -> 12384 | E5: =ROUND('1. Input'!B4/D5,0) -> 1049742
A6: New Contacts | B6: ='1. Input'!B6 -> 0.2 | D6: =ROUNDUP(D5/B6,0) -> 61920 | E6: =ROUND('1. Input'!B4/D6,0) -> 209948
A8: B. FUNNEL THEO CẤP HỌC
A9: Cấp | B9: New Contacts | C9: NC→Lead % | D9: Leads | E9: Lead→Tour % | F9: Tours | G9: Tour→Enroll % | H9: Enrolled | I9: CPL mục tiêu | J9: Cost/Tour | K9: CAC | L9: Ghi chú
A10: MN (4 cơ sở) | B10: 9524 | C10: 20% | D10: 1905 | E10: 32% | F10: 610 | G10: 37% | H10: 380 | I10: 100000 | J10: 500000 | K10: 8500000 | L10: Conversion cao nhất, CAC thấp
A11: TH (4 cơ sở) | B11: 10000 | C11: 20% | D11: 2000 | E11: 30% | F11: 600 | G11: 35% | H11: 420 | I11: 120000 | J11: 700000 | K11: 10000000 | L11: Volume lớn, spread 4 campus
A12: THCS (1 cơ sở) | B12: 4762 | C12: 20% | D12: 952 | E12: 28% | F12: 267 | G12: 33% | H12: 200 | I12: 160000 | J12: 1500000 | K12: 12000000 | L12: Higher intent, cần webinar
A13: THPT (1 cơ sở) | B13: 3810 | C13: 20% | D13: 762 | E13: 26% | F13: 198 | G13: 30% | H13: 200 | I13: 180000 | J13: 2000000 | K13: 13500000 | L13: Học bổng + webinar = key
A14: Brand/Chung | B14: 2381 | C14: 20% | D14: 476 | E14: 25% | F14: 119 | G14: 28% | H14: 100 | I14: 200000 | J14: - | K14: - | L14: Hỗ trợ brand, không đo CAC riêng
A17: C. FUNNEL THEO ĐỊA ĐIỂM (CƠ SỞ)
A18: Cơ sở | B18: Cấp | C18: Khu vực mới (cũ) | D18: HS mục tiêu | E18: Leads cần | F18: Tours cần | G18: Lead→Tour target | H18: Tour→Enroll target | I18: Kênh chính | J18: Độ khó | K18: Ghi chú
A19: MN VA Gò Vấp | B19: MN | C19: Gò Vấp, TP.HCM | D19: 200 | E19: 1905 | F19: 610 | G19: 32% | H19: 37% | I19: Meta + Zalo | J19: Trung bình | K19: Flagship, brand mạnh
A20: MN Nhân Lễ | B20: MN | C20: TX. Cần Giuộc, Tây Ninh (cũ: H. Cần Giuộc, Long An) | D20: 60 | E20: 572 | F20: 183 | G20: 32% | H20: 37% | I20: Zalo + Facebook local | J20: Khó | K20: Thị trường nhỏ, cần local trust
A21: MN Thái Sơn | B21: MN | C21: TX. Cần Giuộc, Tây Ninh (cũ: H. Cần Giuộc, Long An) | D21: 60 | E21: 572 | F21: 183 | G21: 32% | H21: 37% | I21: Zalo + Facebook local | J21: Khó | K21: KDC nhỏ, cần word-of-mouth
A22: MN Mekong Xanh | B22: MN | C22: TP. Rạch Giá, An Giang (cũ: TP. Rạch Giá, Kiên Giang) | D22: 60 | E22: 572 | F22: 183 | G22: 32% | H22: 37% | I22: Zalo + Google local | J22: Rất khó | K22: Thị trường mới, chưa có brand
A23: TH VA Gò Vấp | B23: TH | C23: Gò Vấp, TP.HCM | D23: 150 | E23: 1429 | F23: 429 | G23: 30% | H23: 35% | I23: Meta + Google | J23: Trung bình | K23: Cạnh tranh cao với Việt Úc, iSchool
A24: TH VA Bình Tân | B24: TH | C24: Bình Tân, TP.HCM | D24: 150 | E24: 1429 | F24: 429 | G24: 30% | H24: 35% | I24: Meta + Zalo | J24: Dễ-TB | K24: Ít đối thủ tư thục tại BT
A25: TH Thái Sơn | B25: TH | C25: TX. Cần Giuộc, Tây Ninh (cũ: H. Cần Giuộc, Long An) | D25: 60 | E25: 572 | F25: 171 | G25: 30% | H25: 35% | I25: Zalo + Facebook | J25: Khó | K25: Thị trường nhỏ
A26: TH Mekong Xanh | B26: TH | C26: TP. Rạch Giá, An Giang (cũ: TP. Rạch Giá, Kiên Giang) | D26: 60 | E26: 572 | F26: 171 | G26: 30% | H26: 35% | I26: Zalo + Google local | J26: Rất khó | K26: Mới, chưa có track record
A27: THCS VA Gò Vấp | B27: THCS | C27: Gò Vấp, TP.HCM | D27: 200 | E27: 2858 | F27: 800 | G27: 28% | H27: 33% | I27: Google + Meta + Webinar | J27: Cao | K27: Webinar là key, giai đoạn bản lề
A28: THPT VA Gò Vấp | B28: THPT | C28: Gò Vấp, TP.HCM | D28: 200 | E28: 2540 | F28: 660 | G28: 26% | H28: 30% | I28: Google + Meta + Webinar | J28: Rất cao | K28: Cần học bổng + đầu ra ĐH + webinar
A29: Brand hệ thống | B29: Liên cấp | C29: Tất cả | D29: 100 | E29: 1429 | F29: 357 | G29: 25% | H29: 28% | I29: Remarketing + Brand | J29: - | K29: Hỗ trợ toàn bộ funnel

Sheet 5. Google Ads Chi Tiết
A1: KẾ HOẠCH GOOGLE ADS – CẤU TRÚC TÀI KHOẢN + CAMPAIGN + KEYWORD + RSA + BIRCH
A3: A. CẤU TRÚC TÀI KHOẢN GOOGLE ADS
A4: Cấp độ | B4: Tên | C4: Mô tả | D4: Ngân sách | E4: Ghi chú
A5: Account | B5: VA_TuyenSinh_2026 | C5: Tài khoản chính cho tuyển sinh | D5: ='1. Input'!B15*0.25 -> 2125000000 | E5: Tổng Google = 25% Paid Media
A6: Campaign | B6: S_BRAND_System | C6: Brand search toàn hệ thống | D6: Auto | E6: Luôn bật, không pause
A7: Campaign | B7: S_MN_GV_Generic | C7: Search mầm non Gò Vấp generic | D7: Daily cap | E7: Keyword: mầm non song ngữ gò vấp
A8: Campaign | B8: S_MN_GV_HighIntent | C8: Search mầm non Gò Vấp high intent | D8: Daily cap | E8: Keyword: học phí mầm non, tuyển sinh mầm non
A9: Campaign | B9: S_MN_Tinh_Generic | C9: Search mầm non tỉnh (Tây Ninh, An Giang) | D9: Daily cap | E9: Local intent tỉnh
A10: Campaign | B10: S_TH_GV_Generic | C10: Search tiểu học Gò Vấp | D10: Daily cap | E10: Lớp 1, song ngữ, học phí
A11: Campaign | B11: S_TH_BT_Generic | C11: Search tiểu học Bình Tân | D11: Daily cap | E11: Local + song ngữ
A12: Campaign | B12: S_TH_Tinh_Generic | C12: Search tiểu học tỉnh | D12: Daily cap | E12: Thái Sơn + Mekong Xanh
A13: Campaign | B13: S_THCS_GV_Generic | C13: Search THCS Gò Vấp generic | D13: Daily cap | E13: Lớp 6, trường cấp 2
A14: Campaign | B14: S_THCS_GV_HighIntent | C14: Search THCS Gò Vấp high intent | D14: Daily cap | E14: Tuyển sinh lớp 6, học phí
A15: Campaign | B15: S_THPT_GV_Generic | C15: Search THPT Gò Vấp generic | D15: Daily cap | E15: Lớp 10, trường cấp 3
A16: Campaign | B16: S_THPT_GV_HighIntent | C16: Search THPT Gò Vấp high intent | D16: Daily cap | E16: Tuyển sinh lớp 10, học bổng
A17: Campaign | B17: S_THPT_GV_Webinar | C17: Search THPT webinar | D17: Daily cap | E17: Hội thảo, lộ trình, chọn trường
... A24: Campaign | B24: PMAX_Test | C24: Performance Max test | D24: Daily cap 2% | E24: Chỉ test từ T6, không scale sớm
A26: B. KEYWORD BANK (EXACT + PHRASE)
A27: Cấp | B27: Nhóm | C27: Match | D27: Keyword | E27: Campaign | F27: Ghi chú
A28: MN | B28: Brand | C28: Exact | D28: [trường mầm non việt anh gò vấp] | E28: S_BRAND
A29: MN | B29: Brand | C29: Exact | D29: [mầm non việt anh lê đức thọ] | E29: S_BRAND
A30: MN | B30: Generic | C30: Exact | D30: [trường mầm non song ngữ gò vấp] | E30: S_MN_GV_Generic | F30: Top KW
A31: MN | B31: Generic | C31: Exact | D31: [trường mầm non tư thục gò vấp] | E31: S_MN_GV_Generic
A32: MN | B32: Generic | C32: Phrase | D32: "trường mầm non gần nhà" | E32: S_MN_GV_Generic | F32: Local
A33: MN | B33: Generic | C33: Phrase | D33: "mầm non song ngữ" | E33: S_MN_GV_Generic
A34: MN | B34: HighIntent | C34: Exact | D34: [học phí mầm non song ngữ gò vấp] | E34: S_MN_GV_HighIntent | F34: HOT
A35: MN | B35: HighIntent | C35: Exact | D35: [tuyển sinh mầm non gò vấp] | E35: S_MN_GV_HighIntent | F35: HOT
A36: MN | B36: Pain | C36: Phrase | D36: "trường mầm non an toàn" | E36: S_MN_GV_Generic
A37: MN | B37: Pain | C37: Phrase | D37: "trường mầm non có camera" | E37: S_MN_GV_Generic
A38: TH | B38: Brand | C38: Exact | D38: [trường việt anh gò vấp] | E38: S_BRAND
A39: TH | B39: Brand | C39: Exact | D39: [trường việt anh bình tân] | E39: S_BRAND
A40: TH | B40: Generic | C40: Exact | D40: [trường tiểu học song ngữ gò vấp] | E40: S_TH_GV_Generic
A41: TH | B41: Generic | C41: Exact | D41: [trường tiểu học tư thục bình tân] | E41: S_TH_BT_Generic
A42: TH | B42: HighIntent | C42: Exact | D42: [tuyển sinh lớp 1 trường tư] | E42: S_TH_GV_HighIntent | F42: HOT
A43: TH | B43: HighIntent | C43: Exact | D43: [học phí tiểu học song ngữ] | E43: S_TH_GV_HighIntent | F43: HOT
A44: THCS | B44: Generic | C44: Exact | D44: [trường thcs tư thục gò vấp] | E44: S_THCS_GV_Generic
A45: THCS | B45: Generic | C45: Phrase | D45: "trường cấp 2 song ngữ" | E45: S_THCS_GV_Generic
A46: THCS | B46: HighIntent | C46: Exact | D46: [tuyển sinh lớp 6 trường tư] | E46: S_THCS_GV_HighIntent | F46: HOT
A47: THCS | B47: HighIntent | C47: Exact | D47: [học phí thcs song ngữ] | E47: S_THCS_GV_HighIntent
A48: THPT | B48: Generic | C48: Exact | D48: [trường thpt tư thục gò vấp] | E48: S_THPT_GV_Generic
A49: THPT | B49: Generic | C49: Phrase | D49: "trường cấp 3 song ngữ" | E49: S_THPT_GV_Generic
A50: THPT | B50: HighIntent | C50: Exact | D50: [tuyển sinh lớp 10 trường tư] | E50: S_THPT_GV_HighIntent | F50: HOT
A51: THPT | B51: HighIntent | C51: Exact | D51: [học bổng lớp 10] | E51: S_THPT_GV_HighIntent | F51: HOT
A52: THPT | B52: HighIntent | C52: Exact | D52: [chuyển trường cấp 3] | E52: S_THPT_GV_HighIntent | F52: Late intake
A53: THPT | B53: Webinar | C53: Phrase | D53: "hội thảo chọn trường lớp 10" | E53: S_THPT_GV_Webinar
A55: C. NEGATIVE KEYWORDS
A56: Scope | B56: Match | C56: Keyword | D56: Lý do
A57: Toàn TK | B57: Phrase | C57: miễn phí | D57: Không phù hợp
A58: Toàn TK | B58: Phrase | C58: giáo án | D58: Không phù hợp
A59: Toàn TK | B59: Phrase | C59: tuyển dụng | D59: Nhầm
A60: Toàn TK | B60: Phrase | C60: việc làm | D60: Nhầm
A61: Toàn TK | B61: Phrase | C61: giáo viên | D61: Nhầm
A62: Toàn TK | B62: Phrase | C62: đại học | D62: Sai cấp
A63: Toàn TK | B63: Phrase | C63: du học | D63: Sai
A64: Toàn TK | B64: Phrase | C64: gia sư | D64: Sai
A65: Toàn TK | B65: Phrase | C65: trường công | D65: Sai đối tượng
A66: Toàn TK | B66: Phrase | C66: điểm chuẩn | D66: Sai intent
A67: Toàn TK | B67: Phrase | C67: đề thi | D67: Sai intent
... A72: THPT | B72: Phrase | C72: đề toán | D72: Sai
A74: D. RSA – MẪU QUẢNG CÁO
A75: Cấp | B75: Loại | C75: Nội dung | D75: Pin vị trí | E75: Ghi chú
A76: MN | B76: Headline | C76: Tuyển Sinh Mầm Non 2026 | D76: H1
A77: MN | B77: Headline | C77: Trường Mầm Non Song Ngữ Gò Vấp | D77: H2 | E77: Campus
A78: MN | B78: Headline | C78: Môi Trường An Toàn Cho Bé | E78: USP
A79: MN | B79: Headline | C79: Đăng Ký School Tour Ngay | E79: CTA
A80: MN | B80: Headline | C80: Học Phí Phù Hợp, Minh Bạch
A81: MN | B81: Headline | C81: Gần Nhà, Thuận Tiện Đưa Đón | E81: Local
A82: MN | B82: Description | C82: Tìm hiểu chương trình mầm non và lịch tham quan trường. Đăng ký tư vấn nhanh. | D82: D1
A83: MN | B83: Description | C83: Môi trường an toàn, giáo viên tận tâm. Xem cơ sở thực tế ngay. | D83: D2
A84: TH | B84: Headline | C84: Tuyển Sinh Lớp 1 Năm Học 2026 | D84: H1
A85: TH | B85: Headline | C85: Trường Tiểu Học Song Ngữ Gò Vấp | D85: H2
A86: TH | B86: Headline | C86: Tiếng Anh Có Lộ Trình Rõ Ràng | E86: USP
A87: TH | B87: Headline | C87: Mời Tham Quan Trường Ngay | E87: CTA
A88: TH | B88: Description | C88: Tìm hiểu chương trình tiểu học và lộ trình tiếng Anh phù hợp cho con. | D88: D1
A89: THCS | B89: Headline | C89: Tuyển Sinh Lớp 6 Năm 2026 | D89: H1
A90: THCS | B90: Headline | C90: Trường THCS Việt Anh Gò Vấp | D90: H2
A91: THCS | B91: Headline | C91: Theo Sát Học Sinh Giai Đoạn Bản Lề | E91: USP
A92: THCS | B92: Description | C92: THCS cần môi trường nghiêm túc, theo sát từng học sinh. Đăng ký tư vấn. | D92: D1
A93: THPT | B93: Headline | C93: Tuyển Sinh Lớp 10 Năm 2026 | D93: H1
A94: THPT | B94: Headline | C94: Trường THPT Việt Anh Gò Vấp | D94: H2
A95: THPT | B95: Headline | C95: Học Bổng Tuyển Sinh Lớp 10 | E95: Offer
A96: THPT | B96: Headline | C96: Định Hướng Đại Học Và Tương Lai | E96: USP
A97: THPT | B97: Description | C97: Đăng ký tư vấn lớp 10, học bổng và tham quan campus ngay hôm nay. | D97: D1
A99: E. BIRCH PPC – CẤU HÌNH CHI TIẾT
A100: Bước | B100: Hành động | C100: Chi tiết | D100: Tool/Nơi thực hiện | E100: Timeline | F100: Trạng thái
A101: 1 | B101: Tạo Workspace | C101: TruongVietAnh_GoogleAds_2026 | D101: Birch > Workspace | E101: Ngày 1 | F101: ☐
A102: 2 | B102: Kết nối Google Ads | C102: Link account có admin rights | D102: Birch > Settings > Ad Platforms | E102: Ngày 1 | F102: ☐
A103: 3 | B103: Kết nối GA4 | C103: Link GA4 property website + LP | D103: Birch > Settings > Google Analytics | E103: Ngày 1 | F103: ☐
A104: 4 | B104: Kết nối Google Sheets | C104: Share sheet cho service account Birch | D104: Google Sheets > Share | E104: Ngày 1 | F104: ☐
A105: 5 | B105: Tạo Custom Metrics | C105: Qualified Rate, Booked Tour Rate, Cost/Tour, CAC | D105: Birch > Custom Metrics | E105: Ngày 2 | F105: ☐
A106: 6 | B106: Rule: Alert CPL cao | C106: IF CPL > target 20% for 3 days → Slack alert | D106: Birch > Automation Rules | E106: Ngày 2 | F106: ☐
A107: 7 | B107: Rule: Alert zero lead | C107: IF spend > 500K + leads = 0 for 3 days → alert | D107: Birch > Automation Rules | E107: Ngày 2 | F107: ☐
A108: 8 | B108: Rule: Scale campaign tốt | C108: IF CPL < target + Qualified > 50% → tăng budget 15% | D108: Birch > Automation Rules | E108: Tuần 2 | F108: ☐
A109: 9 | B109: Rule: Giảm campaign yếu | C109: IF CPL > target 30% + tour = 0 → giảm 15% | D109: Birch > Automation Rules | E109: Tuần 2 | F109: ☐
A110: 10 | B110: Rule: Pause KW lãng phí | C110: IF KW spend > 500K + conv = 0 → pause | D110: Birch > Automation Rules | E110: Tuần 2 | F110: ☐
A111: 11 | B111: Rule: Brand always-on | C111: IF brand campaign paused → auto-notify | D111: Birch > Automation Rules | E111: Ngày 2 | F111: ☐
... A113: 13 | B113: Negative KW auto-check | C113: Shared negative list, auto-update weekly | D113: Birch > Rules + Manual | E113: Tuần 1 | F113: ☐
A115: F. LANDING PAGE BLUEPRINT
A116: LP | B116: URL slug | C116: Cấp học | D116: Cơ sở | E116: Khối cần có | F116: Form fields | G116: GTM Events
A117: LP_MN_GV | B117: /mam-non-go-vap | C117: MN | D117: Gò Vấp | E117: Hero video + USP + Ảnh + Testi + FAQ + Map + Form | F117: Tên, SĐT, Cơ sở, Cấp, Nhu cầu | G117: form_submit, click_call, click_zalo
...

Sheet 6. Meta Ads Chi Tiết
A1: KẾ HOẠCH META ADS – CẤU TRÚC + AUDIENCE + CREATIVE + PIXEL + GHL
A3: A. CẤU TRÚC TÀI KHOẢN META ADS (BỎ PHÚ NHUẬN)
A4: Campaign | B4: Objective | C4: Audience | D4: Creative | E4: Budget/tháng | F4: LP | G4: GHL Pipeline | H4: GTM/Pixel Events
A5: MN_GV_LeadGen | B5: Lead Generation | C5: Geo 5km MN GV | Age 25-40 | Interest Parenting | Lookalike 1-3% | D5: Video testi PH 15-30s + Carousel campus + Lead form | E5: =0.38*'1. Input'!B15*0.25/6 -> 1.3458333e+08 | F5: LP_MN_GV | G5: Pipeline MN | H5: Lead, ViewContent, CompleteRegistration
A6: MN_Tinh_LeadGen | B6: Lead Generation | C6: Geo Cần Giuộc (Tây Ninh) + Rạch Giá (An Giang) | Age 25-40 | D6: Video testi + Ảnh campus local + Lead form | E6: =0.38*'1. Input'!B15*0.12/6 -> 64600000 | F6: LP_MN_Tinh | G6: Pipeline MN | H6: Lead, ViewContent
A7: TH_GV_LeadGen | B7: Lead Generation | C7: Geo 8km TH GV | Age 28-45 | Lookalike PH TH | D7: Video lớp học + Carousel chương trình + Messenger | E7: =0.38*'1. Input'!B15*0.18/6 -> 96900000 | F7: LP_TH_GV | G7: Pipeline TH | H7: Lead, ViewContent
A8: TH_BT_LeadGen | B8: Lead Generation | C8: Geo 8km Bình Tân | Age 28-45 | D8: Video + Lead form | E8: =0.38*'1. Input'!B15*0.15/6 -> 80750000 | F8: LP_TH_BT | G8: Pipeline TH | H8: Lead
A9: TH_Tinh_LeadGen | B9: Lead Generation | C9: Geo Thái Sơn + Mekong Xanh | D9: Video local + Lead form | E9: =0.38*'1. Input'!B15*0.08/6 -> 43066667 | F9: LP_TH_Tinh | G9: Pipeline TH | H9: Lead
A10: THCS_GV_Conv | B10: Conversions | C10: Geo TP.HCM | Age 30-50 | Custom: Web 30d | D10: Video HS+GV + Testi 60s + Webinar ads | E10: =0.38*'1. Input'!B15*0.2/6 -> 1.0766667e+08 | F10: LP_THCS_GV | G10: Pipeline THCS | H10: Lead, WebinarReg, ViewContent
A11: THPT_GV_Conv | B11: Conversions | C11: Geo TP.HCM + miền Nam | Age 35-55 | Lookalike PH THPT | D11: Video đầu ra + Học bổng + Testi | E11: =0.38*'1. Input'!B15*0.2/6 -> 1.0766667e+08 | F11: LP_THPT_GV | G11: Pipeline THPT | H11: Lead, ScholarshipClick
A12: Remarketing_All | B12: Conversions | C12: PageView 7-30d | Exclude enrolled | Dynamic by cấp | D12: Carousel campus + ưu đãi + Countdown | E12: =0.12*'1. Input'!B15*0.5/6 -> 85000000 | F12: Dynamic | G12: Retarget tag | H12: Purchase, Lead
A14: B. PIXEL + CAPI + GTM SETUP
A15: Bước | B15: Hành động | C15: Chi tiết | D15: Tool | E15: Timeline | F15: Trạng thái
A16: 1 | B16: Cài Meta Pixel qua GTM | C16: Tạo tag Meta Pixel Base Code trong GTM → fire on All Pages | D16: GTM + Meta | E16: Ngày 1 | F16: ☐
A17: 2 | B17: Tạo Custom Events trong GTM | C17: form_submit, click_call, click_zalo, webinar_register, scholarship_click | D17: GTM | E17: Ngày 1 | F17: ☐
A18: 3 | B18: Cài Conversion API (CAPI) | C18: Server-side tracking qua GHL webhook → Meta CAPI endpoint | D18: GHL + Meta | E18: Ngày 2 | F18: ☐
A19: 4 | B19: Tạo Custom Conversions | C19: 4 events: Form MN, Form TH, Form THCS/THPT, Tour Scheduled | D19: Meta Events Manager | E19: Ngày 2 | F19: ☐
A20: 5 | B20: Verify domain | C20: Xác minh domain truongvietanh.com trong Business Manager | D20: Meta Business Suite | E20: Ngày 1 | F20: ☐
A21: 6 | B21: Tạo Audience Library | C21: 8 saved audiences (4 cấp × 2 geo) + Lookalike 1%/3%/5% + Custom 7d/14d/30d/60d | D21: Meta Ads Manager | E21: Ngày 2 | F21: ☐
A22: 7 | B22: Sync GHL → Meta | C22: Upload enrolled parents list → Exclusion | Monthly refresh | D22: GHL + Meta | E22: Tuần 2 | F22: ☐
A23: 8 | B23: Setup Birch cho Meta | C23: Kết nối Meta Ads → Birch | Tạo rules CPL, budget pacing | D23: Birch | E23: Ngày 3 | F23: ☐
A25: C. CREATIVE RESOURCE PLAN – PHÂN BỔ ẢNH/VIDEO CHO META ADS
A26: Campaign | B26: Loại Creative | C26: Số lượng | D26: Format | E26: Nội dung | F26: Nguồn ảnh/video | G26: Refresh cycle | H26: A/B Test | I26: Ghi chú
A27: MN_GV_LeadGen | B27: Video testimonial PH | C27: 3 | D27: 9:16 Reel 15-30s | E27: PH chia sẻ: "Con tôi vui khi đến trường" | F27: Quay tại campus, PH thật | G27: 3 tuần | H27: Test 3 PH khác nhau | I27: Hook 3s quan trọng nhất
A28: MN_GV_LeadGen | B28: Carousel campus | C28: 2 | D28: 1:1 1080x1080 | E28: 6 slides: Sân chơi, Phòng học, Bếp ăn, Camera, GV, Hoạt động | F28: Chụp tại campus GV | G28: 4 tuần | H28: Test order slides | I28: Ảnh thật, không stock
A29: MN_GV_LeadGen | B29: Lead Form ad | C29: 2 | D29: 1:1 1080x1080 | E29: Image + text: "Đăng ký tour MN Việt Anh" | Form prefill | F29: Thiết kế Canva | G29: 2 tuần | H29: Test benefit vs offer | I29: Form ngắn: Tên+SĐT+Cấp
A30: TH_GV_LeadGen | B30: Video "Nền tảng lớp 1" | C30: 2 | D30: 9:16 Reel 30-60s | E30: Lớp học thực tế, HS đọc TA, GV tương tác | F30: Quay tại TH GV | G30: 4 tuần | H30: Test 30s vs 60s | I30: Show HS thật đang học
A31: TH_GV_LeadGen | B31: Carousel chương trình | C31: 2 | D31: 1:1 1080x1080 | E31: 6 slides: Chương trình, TA, STEM, Ngoại khóa, Sĩ số, Tour | F31: Chụp + thiết kế | G31: 4 tuần | H31: Test headline | I31: Infographic style
A32: TH_BT_LeadGen | B32: Image + text local | C32: 3 | D32: 1:1 1080x1080 | E32: Ảnh campus BT + text "Trường tư song ngữ Bình Tân" | F32: Chụp tại campus BT | G32: 3 tuần | H32: Test 3 images | I32: Local feel quan trọng
A33: THCS_GV_LeadGen | B33: Video testi HS + GV | C33: 3 | D33: 9:16 Reel 30-60s | E33: HS THCS chia sẻ + GV chủ nhiệm nói về lộ trình | F33: Quay tại THCS GV | G33: 3 tuần | H33: Test HS vs GV focus | I33: Emotional storytelling
A34: THCS_GV_Webinar | B34: Video invite webinar | C34: 2 | D34: 9:16 Reel 15s | E34: Teaser: "Hội thảo chuyển cấp 5→6 – Miễn phí" | F34: Thiết kế motion | G34: 2 tuần | H34: Test countdown vs benefit | I34: Urgency + value
A35: THPT_GV_LeadGen | B35: Video "Lộ trình THPT" | C35: 3 | D35: 9:16 Reel 30-60s | E35: Alumni ĐH chia sẻ + BGH nói về đầu ra | F35: Quay tại THPT + ĐH | G35: 3 tuần | H35: Test alumni vs BGH | I35: Data-driven: % ĐH top
A36: THPT_HocBong | B36: Image học bổng | C36: 3 | D36: 1:1 1080x1080 | E36: "Học bổng lên đến 100% – Deadline [ngày]" | Bold design | F36: Thiết kế Canva/AI | G36: 2 tuần | H36: Test % vs giá trị tiền | I36: Deadline rõ ràng
A37: Retarget_7d_Hot | B37: Dynamic creative | C37: 4 | D37: 1:1 multi-format | E37: Testimonial + ưu đãi + countdown + campus | F37: Mix từ kho | G37: 2 tuần | H37: Auto by Meta | I37: DCO cho remarketing
A38: Brand_Awareness | B38: Brand video 15s | C38: 2 | D38: 16:9 + 9:16 | E38: Montage: 8 campus, HS vui, USP overlay, logo end | F38: Quay + edit pro | G38: 6 tuần | H38: Test 15s vs 30s | I38: CPM optimize
A41: D. DAILY OPERATIONS – META ADS HÀNG NGÀY
A42: Thời gian | B42: Công việc | C42: Chi tiết | D42: Tool | E42: KPI check | F42: Action nếu lệch | G42: Ai làm
A43: 8:00 | B43: Check delivery & spend | C43: Ads Manager → Campaign overview → Check pacing 24h | D43: Meta Ads Manager / Birch | E43: Spend vs daily target ±10% | F43: Overspend → lower budget | Underspend → check ad set | G43: Performance
A44: 8:15 | B44: Check CPL by campaign | C44: Filter last 3 days → Sort by CPL → Identify top/bottom | D44: Meta Ads Manager | E44: CPL < target kênh | F44: CPL > 150% target → pause ad set → review creative | G44: Performance
A45: 8:30 | B45: Check ad set learning phase | C45: Review ad sets: Learning, Active, Learning Limited | D45: Meta Ads Manager | E45: 50 conversions / 7 ngày | F45: Learning Limited → consolidate ad sets hoặc tăng budget | G45: Performance
A46: 8:45 | B46: Review ad rejections | C46: Check ad review status → Fix rejected ads | D46: Meta Ads Manager | E46: No rejected ads | F46: Edit ad → resubmit → nếu lặp lại → contact support | G46: Performance
A47: 9:00 | B47: Check Frequency & CTR | C47: Campaign level → Frequency col + CTR | D47: Meta Ads Manager | E47: Freq < 3, CTR > 1% | F47: Freq > 3 → refresh creative | CTR < 0.8% → new copy/image | G47: Performance
A48: 14:00 | B48: Audience overlap check | C48: Meta → Audience overlap tool → Check cross-campaign | D48: Meta Audience Tool | E48: Overlap < 30% | F48: > 30% → exclude hoặc merge audiences | G48: Performance
A49: 15:00 | B49: Scale decision (daily) | C49: Top 3 ad sets by CPL + quality → increase 15-20% | D49: Meta Ads Manager | E49: CPL < target + Q.Rate > 45% | F49: Scale immediately, monitor 24h | G49: Performance
A50: 17:00 | B50: Log daily metrics | C50: Ghi spend, leads, CPL, CTR vào KPI tracker | D50: Excel/Sheets | E50: - | F50: - | G50: Performance
A53: E. AUDIENCE LIBRARY – DANH SÁCH AUDIENCE CHI TIẾT
A54: Audience Name | B54: Type | C54: Targeting chi tiết | D54: Size est. | E54: Dùng cho Campaign | F54: Refresh | G54: Ghi chú
A55: Prospecting_MN_GV | B55: Saved | C55: Geo: Gò Vấp 5km | Age 25-40 | Female | Interest: Parenting, Preschool, Child development | D55: 200K-400K | E55: MN_GV_LeadGen | F55: Đầu mùa | G55: Core audience MN
A56: Prospecting_TH_GV | B56: Saved | C56: Geo: Gò Vấp 8km | Age 28-45 | Parents | Interest: Education, Primary school | D56: 300K-500K | E56: TH_GV_LeadGen | F56: Đầu mùa | G56: Core audience TH
A57: Prospecting_TH_BT | B57: Saved | C57: Geo: Bình Tân 8km | Age 28-45 | Parents | D57: 250K-400K | E57: TH_BT_LeadGen | F57: Đầu mùa | G57: Bình Tân local
A58: Prospecting_THCS | B58: Saved | C58: Geo: TP.HCM | Age 32-48 | Interest: Secondary education, Exam prep | D58: 500K-800K | E58: THCS_GV_LeadGen | F58: Đầu mùa | G58: Broader for THCS
A59: Prospecting_THPT | B59: Saved | C59: Geo: TP.HCM + miền Nam | Age 36-55 | Interest: High school, Scholarship, University | D59: 600K-1M | E59: THPT_GV_LeadGen | F59: Đầu mùa | G59: Broadest for THPT
A60: LAL_1%_Enrolled | B60: Lookalike | C60: Source: Enrolled parents list | 1% lookalike VN | D60: 700K-1M | E60: All Lead Gen | F60: Hàng tháng | G60: Best quality LAL
A61: LAL_3%_Leads | B61: Lookalike | C61: Source: All qualified leads | 3% lookalike VN | D61: 2M-3M | E61: Scale campaigns | F61: Hàng tháng | G61: Volume LAL
A62: Custom_Web_7d | B62: Custom | C62: Website visitors last 7 days | All pages | D62: 5K-20K | E62: Retarget_7d_Hot | F62: Auto | G62: Hottest remarketing
A63: Custom_Web_30d | B63: Custom | C63: Website visitors last 30 days | D63: 20K-50K | E63: Retarget_21d_Warm | F63: Auto | G63: Warm remarketing
A64: Custom_Fee_Page | B64: Custom | C64: Visitors to /hoc-phi pages | Last 14 days | D64: 2K-8K | E64: Retarget_7d_Hot | F64: Auto | G64: Highest intent
A65: Custom_Video_50 | B65: Custom | C65: Video viewers 50%+ | Last 30 days | D65: 10K-30K | E65: Retarget_21d_Warm | F65: Auto | G65: Engaged viewers
A66: Exclusion_Enrolled | B66: Custom | C66: Upload enrolled parents list | D66: 1K-5K | E66: ALL campaigns | F66: Hàng tháng | G66: MUST exclude always

Sheet 7. TikTok Ads Chi Tiết
A1: KẾ HOẠCH TIKTOK ADS – 100 VIDEO TESTIMONIAL + CẤU TRÚC + GTM
A3: A. CẤU TRÚC CAMPAIGN TIKTOK
A4: Campaign | B4: Objective | C4: Targeting | D4: Creative (từ kho 100 video) | E4: Budget/tháng | F4: KPI | G4: GTM Events | H4: Ghi chú
A5: Spark_Testi_MN | B5: Traffic/Lead | C5: Age 25-45 | Parenting | Geo HCM+Tỉnh | D5: Boost organic testi PH MN | Hook 3s | 15-30s | E5: =0.1*'1. Input'!B15*0.3/6 -> 42500000 | F5: CPV ≤ 2K | Engage ≥ 5% | G5: ViewContent, ClickLink | H5: Dùng 100 video có sẵn
A6: Spark_Testi_THPT | B6: Traffic/Lead | C6: Age 30-55 | Education | Geo HCM | D6: Boost testi HS THPT + GV | Hook 3s | E6: =0.1*'1. Input'!B15*0.25/6 -> 35416667 | F6: CPV ≤ 2.5K | Lead | G6: ViewContent, Lead | H6: Social proof
A7: InFeed_CampusTour | B7: Traffic | C7: Age 25-45 | Geo radius 10km | D7: Virtual tour video | Day-in-the-life | CTA tour | E7: =0.1*'1. Input'!B15*0.2/6 -> 28333333 | F7: CPL ≤ 90K | CTR ≥ 1.5% | G7: ViewContent, ClickLink | H7: Quay sẵn hoặc UGC
A8: LeadGen_Form | B8: Lead Gen | C8: Age 28-45 | School selection | Lookalike | D8: Video HS + Instant form: Tên+SĐT+Cấp | E8: =0.1*'1. Input'!B15*0.2/6 -> 28333333 | F8: CPL ≤ 80K | Form ≥ 3% | G8: Lead, FormSubmit | H8: Form → GHL auto
A9: TopView_Brand | B9: Reach | C9: Broad 25-50 HCM | 1 ngày | D9: Video 15s brand hệ thống | 8 cơ sở | E9: =0.1*'1. Input'!B15*0.05/6 -> 7083333.3 | F9: Reach ≥ 2M | CPM ≤ 50K | G9: Impression | H9: Chỉ 2-3 ngày peak
A11: B. TIKTOK PIXEL + GTM SETUP
A12: Bước | B12: Hành động | C12: Chi tiết | D12: Tool | E12: Timeline | F12: Trạng thái
A13: 1 | B13: Tạo TikTok Pixel | C13: Tạo pixel trong TikTok Ads Manager | D13: TikTok Ads | E13: Ngày 1 | F13: ☐
A14: 2 | B14: Cài qua GTM | C14: Tạo Custom HTML tag với TikTok Pixel base code → All Pages | D14: GTM | E14: Ngày 1 | F14: ☐
A15: 3 | B15: Tạo Event tags | C15: ViewContent (LP view), ClickButton (CTA), SubmitForm, CompleteRegistration | D15: GTM | E15: Ngày 1 | F15: ☐
A16: 4 | B16: Test với TikTok Pixel Helper | C16: Verify events firing đúng trên mỗi LP | D16: Chrome Extension | E16: Ngày 1 | F16: ☐
A17: 5 | B17: Tạo Custom Audiences | C17: Website visitors 7d/14d/30d + Video viewers 50%+ + Form submitters | D17: TikTok Ads | E17: Ngày 2 | F17: ☐
A18: 6 | B18: Tạo Lookalike | C18: Từ enrolled parents list + Form submitters | D18: TikTok Ads | E18: Tuần 2 | F18: ☐
A19: 7 | B19: Setup Birch cho TikTok | C19: Kết nối TikTok → Birch | Budget pacing rules | D19: Birch | E19: Ngày 3 | F19: ☐

Sheet 8. GoHighLevel Setup
A1: GOHIGHLEVEL – SETUP TỪ ĐẦU + CRM + AUTOMATION + SALES + ZALO
A3: A. SETUP TÀI KHOẢN GHL TỪ ĐẦU
A4: Bước | B4: Module | C4: Hành động chi tiết | D4: Kết quả cần có | E4: Timeline | F4: Trạng thái
A5: 1 | B5: Account | C5: Tạo sub-account cho Việt Anh | Timezone VN | Currency VND | D5: Account live | E5: Ngày 1 | F5: ☐
A6: 2 | B6: Custom Fields | C6: Tạo fields: Campus, Grade, Source Channel, Campaign ID, Campaign Name, Keyword Theme, Lead Status, Qualified Flag, Tour Date, Tour Attended, Application, Deposit, Enrollment | D6: Tất cả fields có | E6: Ngày 1 | F6: ☐
A7: 3 | B7: Pipelines | C7: Tạo 4 pipelines: MN, TH, THCS, THPT | Stages: New → Contacted → Qualified → Tour Booked → Tour Done → Offer → Enrolled → Lost | D7: 4 pipelines active | E7: Ngày 1 | F7: ☐
A8: 4 | B8: Tags | C8: Tạo tag system: src_google, src_meta, src_tiktok, src_zalo, src_organic, campus_gv, campus_bt, campus_tinh, grade_mn, grade_th, grade_thcs, grade_thpt, qualified, booked_tour, tour_attended, enrolled, lost | D8: Tags ready | E8: Ngày 1 | F8: ☐
A9: 5 | B9: Users & Teams | C9: Tạo users cho sales team | Assign theo campus | Round-robin rules | D9: Team assigned | E9: Ngày 1 | F9: ☐
A10: 6 | B10: Phone & SMS | C10: Setup Twilio / VN SMS provider | Verify phone numbers | SMS templates | D10: SMS working | E10: Ngày 2 | F10: ☐
A11: 7 | B11: Zalo OA | C11: Kết nối Zalo OA | Tạo 8 template messages | Auto-reply menu | D11: Zalo connected | E11: Ngày 2 | F11: ☐
A12: 8 | B12: Email | C12: Setup domain, DKIM, SPF | Email templates: Welcome, Tour reminder, Follow-up, Scholarship, Thank you | D12: Email verified | E12: Ngày 2 | F12: ☐
A13: 9 | B13: Calendar | C13: Tạo booking calendar cho 6 cơ sở (bỏ PN) | Availability slots | Auto SMS confirm | D13: Calendar live | E13: Ngày 2 | F13: ☐
A14: 10 | B14: Forms | C14: Tạo 8 forms (1/LP) | UTM auto-capture | Pipeline auto-assign | D14: Forms embedded | E14: Ngày 3 | F14: ☐
A15: 11 | B15: Landing Pages | C15: Build hoặc embed 8 LP trong GHL | Form + tracking + Zalo widget | D15: LPs live | E15: Ngày 3-5 | F15: ☐
A17: B. AUTOMATION WORKFLOWS
A18: Workflow | B18: Trigger | C18: Actions | D18: SLA | E18: Kết quả | F18: Timeline | G18: Trạng thái
A19: Auto-assign lead | B19: New contact created | C19: Round-robin assign theo campus + Push notification + SMS to sales | D19: < 5 phút | E19: Lead có owner ngay | F19: Ngày 3 | G19: ☐
A20: Welcome sequence | B20: New lead + src_google/meta/tiktok | C20: SMS welcome 30s + Zalo message 5 phút + Email brochure 1h | D20: Tự động | E20: Mọi lead được chào | F20: Ngày 3 | G20: ☐
A21: Nurture chưa tour | B21: Lead > 48h chưa book tour | C21: SMS Day 2 → Zalo Day 4 → Email Day 7 → Call task Day 10 | D21: 4 touchpoints | E21: Tăng Lead→Tour | F21: Ngày 4 | G21: ☐
A22: Tour reminder | B22: Appointment booked | C22: SMS 48h trước + Zalo 2h trước + Email confirm | D22: Auto | E22: Giảm no-show | F22: Ngày 4 | G22: ☐
A23: Post-tour follow-up | B23: Tour completed (status changed) | C23: Thank you SMS 2h + Offer email 24h + Call task 48h | D23: 3 touchpoints | E23: Tăng Tour→Enroll | F23: Ngày 4 | G23: ☐
A24: Lost re-engage | B24: Marked Lost > 30 ngày | C24: Monthly email + SMS promo | Re-enter pipeline nếu click | D24: Monthly | E24: Reactivation | F24: Tuần 2 | G24: ☐
A25: Webinar sequence | B25: Webinar registered | C25: Confirm email + SMS 24h + Zalo 2h + Post-webinar call 24h | D25: 4 touchpoints | E25: Tăng attend + tour | F25: Ngày 5 | G25: ☐
A26: Scholarship workflow | B26: Scholarship form submitted | C26: Auto email confirm + Assign to senior counselor + Task create | D26: Immediate | E26: THPT priority | F26: Ngày 5 | G26: ☐
A27: Webhook → Sheets | B27: Any status change (qualified/tour/enroll) | C27: Custom webhook → Middleware → Google Sheets → Birch reads | D27: Real-time | E27: Birch data sync | F27: Tuần 2 | G27: ☐
A29: C. CRM + SALES INTEGRATION
A30: Module | B30: Setup | C30: Mục đích | D30: Ai dùng | E30: Ghi chú
A31: Pipeline Dashboard | B31: Kanban view theo campus + cấp | C31: Theo dõi real-time | D31: Sales Manager | E31: Filter by campus
A32: Conversations | B32: Unified inbox: SMS + Zalo + Email + FB Messenger | C32: Tất cả kênh 1 chỗ | D32: Sales team | E32: Reply nhanh
A33: Opportunities | B33: Gắn giá trị = học phí năm 1 | Track close rate | C33: Forecast revenue | D33: Manager + BGH | E33: Dự báo doanh thu
A34: Reporting | B34: Lead by source, campaign, campus | Conversion funnel | SLA tracking | C34: Đo hiệu quả | D34: Marketing + Sales | E34: Auto weekly email
A35: Call tracking | B35: Ghi âm cuộc gọi + log duration + outcome | C35: QA + Training | D35: QA team | E35: Mystery call chấm điểm
A36: Review request | B36: Sau enrollment → auto gửi review link Google Business | C36: Tăng review organic | D36: Auto | E36: Giúp Local SEO
A38: D. GHL + BIRCH INTEGRATION CHI TIẾT
A39: # | B39: Bước | C39: Hành động | D39: Chi tiết kỹ thuật | E39: Kết quả cần có | F39: Tool | G39: Timeline | H39: Trạng thái
A40: 1 | B40: Webhook Setup | C40: Tạo webhook từ GHL → Google Sheets | D40: GHL Workflow → Custom Webhook → POST to Sheets API middleware | E40: Data sync real-time | F40: GHL + Apps Script | G40: Ngày 3 | H40: ☐
A41: 2 | B41: Middleware Build | C41: Xây middleware nhận webhook GHL | D41: Node.js/Apps Script → Parse payload → Write to Google Sheets | E41: Middleware running 24/7 | F41: Apps Script / Cloud Run | G41: Ngày 3-4 | H41: ☐
A42: 3 | B42: Sheet Structure | C42: Tạo Google Sheet cho Birch đọc | D42: Columns: Date, Contact ID, Campus, Grade, Source, Campaign, Status, Qualified, Tour, Enrolled | E42: Sheet ready for Birch | F42: Google Sheets | G42: Ngày 3 | H42: ☐
A43: 4 | B43: Birch Connect Sheet | C43: Kết nối Birch với Google Sheets | D43: Birch Settings → Data Sources → Google Sheets → Share sheet | E43: Birch reads GHL data | F43: Birch | G43: Ngày 4 | H43: ☐
A44: 5 | B44: Custom Metrics Birch | C44: Tạo metrics kết hợp ads + CRM | D44: Qualified Rate = Q.Leads/Total Leads | Tour Rate = Tours/Leads | CAC = Spend/Enrolled | E44: Birch shows CRM metrics | F44: Birch Custom Metrics | G44: Ngày 4 | H44: ☐
A45: 6 | B45: Auto Scale Rule | C45: Rule: Scale campaign nếu quality tốt | D45: IF CPL < target AND Qualified Rate > 50% AND Tour Rate > 20% → Increase budget 15% | E45: Auto budget increase | F45: Birch Automation | G45: Tuần 2 | H45: ☐
A46: 7 | B46: Auto Pause Rule | C46: Rule: Pause nếu quality xấu | D46: IF CPL > target 30% AND Tour Rate < 10% for 5 days → Pause adset + Alert | E46: Auto protection | F46: Birch Automation | G46: Tuần 2 | H46: ☐
A47: 8 | B47: Campus Alert Rule | C47: Rule: Alert khi campus hụt target | D47: IF Campus X enrolled < monthly target 20% by mid-month → Alert Slack | E47: Campus gap detection | F47: Birch Automation | G47: Tuần 2 | H47: ☐
A48: 9 | B48: Meta CAPI Setup | C48: Conversion API từ GHL → Meta | D48: GHL Workflow → On status change → POST to Meta CAPI endpoint with event data | E48: Server-side tracking active | F48: GHL + Meta CAPI | G48: Ngày 4 | H48: ☐
A49: 10 | B49: Google Offline Conv | C49: Upload offline conversions Google | D49: GHL → Tour completed → Upload to Google Ads as offline conversion via API | E49: Google Ads sees tour data | F49: GHL + Google Ads API | G49: Ngày 5 | H49: ☐
A50: 11 | B50: Lead Scoring Setup | C50: Xây lead scoring trong GHL | D50: Score: +10 form submit, +20 call answered, +30 tour booked, +50 tour attended, -10 no answer 3x | E50: Lead priority ranking | F50: GHL Lead Scoring | G50: Ngày 5 | H50: ☐
A51: 12 | B51: Dashboard GHL | C51: Build dashboard CRM realtime | D51: Pipeline view + Lead by source + Tour calendar + SLA tracker + Revenue forecast | E51: Dashboard live | F51: GHL Dashboard Builder | G51: Ngày 5-6 | H51: ☐
A54: E. GHL + ADS PLATFORMS INTEGRATION MAP
A55: Nền tảng Ads | B55: Loại Integration | C55: Data Flow | D55: Mục đích | E55: Setup Tool | F55: Automation | G55: Trạng thái
A56: Meta Ads | B56: Lead Form Sync | C56: Meta Lead Form → GHL (instant) | D56: Auto-import lead từ Meta form vào GHL pipeline | E56: GHL Integration + Zapier | F56: New lead → Auto-assign → Welcome SMS 30s | G56: ☐
A57: Meta Ads | B57: CAPI (Server) | C57: GHL Status Change → Meta CAPI | D57: Gửi offline events: Qualified, Tour, Enrolled về Meta | E57: GHL Webhook + Meta CAPI | F57: Improve Meta optimization + audience quality | G57: ☐
A58: Meta Ads | B58: Audience Sync | C58: GHL Enrolled List → Meta Custom Audience | D58: Exclude enrolled + Create lookalike từ best leads | E58: GHL Export + Meta Upload | F58: Monthly refresh audience exclusion | G58: ☐
A59: Google Ads | B59: Offline Conversion | C59: GHL Tour/Enroll → Google Ads Offline Conv | D59: Google Ads optimize cho Tour thay vì chỉ form submit | E59: GHL → Sheets → Google Ads API | F59: Weekly upload offline conversions | G59: ☐
A60: Google Ads | B60: Birch Bridge | C60: GHL → Sheets → Birch → Google Ads | D60: Birch dùng CRM data để auto-optimize budget | E60: Birch + Google Sheets | F60: Auto scale/pause dựa trên CRM quality | G60: ☐
A61: TikTok Ads | B61: Lead Form Sync | C61: TikTok Lead Form → GHL | D61: Import TikTok leads vào GHL auto | E61: Zapier / Make.com | F61: New lead → Pipeline + Welcome seq | G61: ☐
A62: TikTok Ads | B62: Pixel Events | C62: Website → TikTok Pixel → Events | D62: Track form submit, call click cho TikTok optimization | E62: GTM + TikTok Pixel | F62: Event-based optimization | G62: ☐
A63: Zalo Ads | B63: OA Connect | C63: Zalo OA → GHL Conversations | D63: Tất cả Zalo message hiện trong GHL inbox | E63: GHL Zalo Integration | F63: Auto-reply + broadcast từ GHL | G63: ☐
A64: Zalo Ads | B64: Pixel Sync | C64: Website → Zalo Pixel → Remarketing | D64: Build Zalo remarketing audience từ web visitors | E64: GTM + Zalo Pixel | F64: Retarget OA followers + web visitors | G64: ☐
A65: All Platforms | B65: UTM Tracking | C65: UTM params → GHL Custom Fields | D65: Attribution chính xác: biết lead từ campaign/keyword nào | E65: GHL Form + Hidden fields | F65: Auto-capture UTM vào contact record | G65: ☐
A66: Birch PPC | B66: Cross-platform | C66: All Ads → Birch → Rules + Reports | D66: Quản lý budget, pacing, alerts tất cả ads từ 1 dashboard | E66: Birch Workspace | F66: Auto email report T2+T5 cho team | G66: ☐
A69: F. GHL AUTOMATION WORKFLOWS – CHI TIẾT TỪNG BƯỚC
A70: Workflow | B70: Bước | C70: Action | D70: Delay | E70: Channel | F70: Nội dung tóm tắt | G70: Condition | H70: KPI đo
A71: Welcome Sequence | B71: 1 | C71: SMS gửi ngay | D71: 30 giây | E71: SMS | F71: Chào [Tên], cảm ơn bạn quan tâm Việt Anh. Tư vấn viên sẽ gọi trong 5 phút! | G71: New lead created | H71: Delivery rate
A72: Welcome Sequence | B72: 2 | C72: Assign to Sales | D72: 1 phút | E72: System | F72: Round-robin assign theo campus + grade → Push notification | G72: Auto | H72: Assign time < 2 min
A73: Welcome Sequence | B73: 3 | C73: Zalo message | D73: 5 phút | E73: Zalo | F73: Chào [Tên]! Tôi là [Sales]. Rất vui được tư vấn. Bạn quan tâm cấp nào? | G73: IF Zalo connected | H73: Reply rate ≥ 25%
A74: Welcome Sequence | B74: 4 | C74: Email brochure | D74: 1 giờ | E74: Email | F74: Email chào đón + brochure PDF + link website + CTA book tour | G74: All leads | H74: Open rate ≥ 30%
A75: Welcome Sequence | B75: 5 | C75: Internal alert | D75: 5 phút | E75: System | F75: IF lead chưa được gọi sau 5 min → Alert manager Slack/Zalo | G75: No call logged | H75: SLA compliance
A76: Nurture No-Tour | B76: 1 | C76: SMS nhắc nhẹ | D76: Day 2 | E76: SMS | F76: [Tên] ơi, đã tìm hiểu về trường chưa? Mời bạn đặt lịch tour miễn phí! | G76: Lead > 48h, no tour booked | H76: Reply rate
A77: Nurture No-Tour | B77: 2 | C77: Zalo article | D77: Day 4 | E77: Zalo | F77: Gửi article: "5 tiêu chí chọn trường [Cấp] cho con" + CTA tour | G77: Still no tour | H77: Click rate
A78: Nurture No-Tour | B78: 3 | C78: Email testimonial | D78: Day 7 | E78: Email | F78: Email testimonial video PH + campus photos + CTA book tour | G78: Still no tour | H78: Open + Click
A79: Nurture No-Tour | B79: 4 | C79: Task: Gọi điện | D79: Day 10 | E79: System | F79: Tạo task cho sales: Gọi [Tên] – lead chưa tour 10 ngày | G79: Still no tour | H79: Call outcome
A80: Nurture No-Tour | B80: 5 | C80: SMS ưu đãi | D80: Day 14 | E80: SMS | F80: Ưu đãi đặc biệt cho [Tên]: Giảm [X]% nếu nộp hồ sơ trong tuần! | G80: Still no tour | H80: Conv rate
A81: Post-Tour | B81: 1 | C81: SMS cảm ơn | D81: 2 giờ | E81: SMS | F81: Cảm ơn [Tên] đã đến tham quan! Nếu cần thêm thông tin, nhắn ngay! | G81: Tour completed | H81: Reply rate
... A85: Post-Tour | B85: 5 | C85: SMS deadline | D85: Day 7 | E85: SMS | F85: Cuối cùng! Ưu đãi [X]% hết hạn [Ngày]. Nộp hồ sơ ngay! | G85: No enrollment | H85: Conv rate

Sheet 9. GTM Tracking
A1: GOOGLE TAG MANAGER – TRACKING SETUP TOÀN BỘ KÊNH
A3: A. TAGS CẦN CÀI TRONG GTM
A4: Tag | B4: Type | C4: Platform | D4: Trigger | E4: Ghi chú | F4: Timeline | G4: Trạng thái
A5: GA4 Config | B5: GA4 Configuration | C5: Google Analytics | D5: All Pages | E5: GA4 property chính | F5: Ngày 1 | G5: ☐
A6: GA4 - form_submit | B6: GA4 Event | C6: Google Analytics | D6: Form submission (all LPs) | E6: Khi form được submit | F6: Ngày 1 | G6: ☐
A7: GA4 - click_call | B7: GA4 Event | C7: Google Analytics | D7: Click on tel: links | E7: Bấm gọi hotline | F7: Ngày 1 | G7: ☐
A8: GA4 - click_zalo | B8: GA4 Event | C8: Google Analytics | D8: Click on Zalo widget/link | E8: Bấm Zalo | F8: Ngày 1 | G8: ☐
A9: GA4 - webinar_register | B9: GA4 Event | C9: Google Analytics | D9: Webinar form submit | E9: Đăng ký webinar | F9: Ngày 1 | G9: ☐
A10: GA4 - scholarship_click | B10: GA4 Event | C10: Google Analytics | D10: Click scholarship CTA | E10: THPT scholarship | F10: Ngày 1 | G10: ☐
A11: Meta Pixel Base | B11: Custom HTML | C11: Meta | D11: All Pages | E11: Pixel ID + PageView event | F11: Ngày 1 | G11: ☐
A12: Meta - Lead | B12: Custom HTML | C12: Meta | D12: Form submission | E12: Conversion event cho Meta | F12: Ngày 1 | G12: ☐
A13: Meta - ViewContent | B13: Custom HTML | C13: Meta | D13: LP Page View | E13: Content view tracking | F13: Ngày 1 | G13: ☐
A14: Meta - CompleteRegistration | B14: Custom HTML | C14: Meta | D14: Thank you page view | E14: Tour/webinar confirmed | F14: Ngày 1 | G14: ☐
A15: TikTok Pixel Base | B15: Custom HTML | C15: TikTok | D15: All Pages | E15: Pixel ID + PageView | F15: Ngày 1 | G15: ☐
... A20: Zalo Pixel | B20: Custom HTML | C20: Zalo | D20: All Pages + Form | E20: Zalo Ads tracking | F20: Ngày 2 | G20: ☐
A22: B. TRIGGERS CẦN TẠO
A23: Trigger | B23: Type | C23: Condition | D23: Dùng cho tags | E23: Ghi chú
A24: All Pages | B24: Page View | C24: Mọi trang | D24: GA4, Meta, TikTok, Google Ads RMKT, Zalo | E24: Base trigger
A25: Form Submit - All | B25: Form Submission | C25: Form ID contains 'ghl' hoặc class | D25: GA4 form, Meta Lead, TikTok Submit, GG Ads Conv | E25: Tất cả form trên LP
A26: Click Call | B26: Click - Just Links | C26: Click URL contains 'tel:' | D26: GA4 click_call, Google Ads call conv | E26: Hotline click
A27: Click Zalo | B27: Click - Just Links | C27: Click URL contains 'zalo.me' | D27: GA4 click_zalo | E27: Zalo widget click
A28: Click CTA Button | B28: Click - All Elements | C28: CSS selector cho CTA buttons | D28: TikTok ClickButton | E28: Tour / tư vấn buttons
A29: Thank You Page | B29: Page View | C29: Page URL contains '/thank-you' hoặc '/cam-on' | D29: Meta CompleteReg, GA4 conversion | E29: Sau form submit
A30: Webinar Form | B30: Form Submission | C30: Form contains 'webinar' | D30: GA4 webinar_register | E30: Chỉ webinar forms
A31: Scholarship CTA | B31: Click - All Elements | C31: Element contains 'scholarship' / 'hoc-bong' | D31: GA4 scholarship_click | E31: THPT only

Sheet 10. Lịch Công Việc Marketer
A1: LỊCH CÔNG VIỆC MARKETER – HÀNG NGÀY / TUẦN / THÁNG / QUÝ / NĂM
A3: A. CÔNG VIỆC HÀNG NGÀY (MỖI NGÀY LÀM VIỆC)
A4: STT | B4: Kênh | C4: Công việc | D4: Chi tiết | E4: Thời gian | F4: Ai làm | G4: Checklist
A5: 1 | B5: Google Ads | C5: Kiểm tra spend vs budget | D5: Login Birch → check pacing alert | Nếu overspend → giảm | E5: 8:00-8:15 | F5: Performance | G5: ☐
A6: 2 | B6: Google Ads | C6: Rà search terms | D6: Birch Explorer → Search terms | Thêm negative nếu cần | E6: 8:15-8:30 | F6: Performance | G6: ☐
A7: 3 | B7: Meta Ads | C7: Kiểm tra CPL và lead volume | D7: Birch hoặc Meta Ads Manager → check CPL by campaign | E7: 8:30-8:45 | F7: Performance | G7: ☐
A8: 4 | B8: TikTok | C8: Kiểm tra CPV và engagement | D8: TikTok Ads Manager → check Spark Ads performance | E8: 8:45-9:00 | F8: Performance | G8: ☐
A9: 5 | B9: GHL/CRM | C9: Kiểm tra lead mới từ đêm qua | D9: GHL Dashboard → New leads → Verify source tags đúng | E9: 9:00-9:15 | F9: Marketing Manager | G9: ☐
A10: 6 | B10: GHL/CRM | C10: Check SLA phản hồi | D10: GHL → Pipeline → Lead chưa được gọi > 5 phút → escalate | E10: 9:15-9:30 | F10: Marketing Manager | G10: ☐
A11: 7 | B11: Content | C11: Đăng bài social media | D11: 3-4 bài/ngày: FB + IG + TikTok organic | Dùng kho 2,000 bài | E11: 9:30-10:30 | F11: Content Creator | G11: ☐
A12: 8 | B12: Zalo | C12: Kiểm tra Zalo OA messages | D12: Reply tin nhắn mới + Check broadcast schedule | E12: 10:30-11:00 | F12: Content/Sales | G12: ☐
A13: 9 | B13: All | C13: Báo cáo nhanh buổi sáng | D13: Gửi Slack/Zalo group: lead hôm qua, booked tour, spend | E13: 11:00-11:15 | F13: Marketing Manager | G13: ☐
A14: 10 | B14: All | C14: Sync với Sales | D14: 15 phút meeting: lead quality, objection, tour feedback | E14: 14:00-14:15 | F14: MM + Sales Lead | G14: ☐
A16: B. CÔNG VIỆC HÀNG TUẦN (MỖI THỨ HAI + THỨ NĂM)
A17: STT | B17: Kênh | C17: Công việc | D17: Chi tiết | E17: Ngày | F17: Ai làm | G17: Checklist
A18: 1 | B18: Google Ads | C18: Tối ưu bidding | D18: Review CPA targets | Adjust bids by campaign | Pause KW yếu | E18: Thứ 2 | F18: Performance | G18: ☐
A19: 2 | B19: Google Ads | C19: Cập nhật negative KW | D19: Rà search terms tuần | Thêm negative | Check quality score | E19: Thứ 2 | F19: Performance | G19: ☐
A20: 3 | B20: Meta Ads | C20: A/B test creative | D20: Test 2 creative mới / tuần | Compare CTR, CPL, quality | E20: Thứ 2 | F20: Performance + Content | G20: ☐
A21: 4 | B21: TikTok | C21: Upload video mới | D21: 2-3 video mới từ kho testimonial | Test hook mới | E21: Thứ 2 | F21: Content | G21: ☐
A22: 5 | B22: Zalo | C22: Broadcast schedule | D22: Lên lịch broadcast tour/ưu đãi cho tuần | Segment by campus | E22: Thứ 2 | F22: Content | G22: ☐
A23: 6 | B23: GHL | C23: Pipeline review | D23: Rà pipeline: leads stuck, overdue follow-ups, tour no-shows | E23: Thứ 2 | F23: MM + Sales | G23: ☐
A24: 7 | B24: Birch | C24: Review rules | D24: Kiểm tra rules nào fired | CPL alerts | Budget pacing | E24: Thứ 2 | F24: Performance | G24: ☐
A25: 8 | B25: All | C25: Báo cáo tuần | D25: Weekly report: spend, leads, tours, enrollments by campus | E25: Thứ 5 | F25: Marketing Manager | G25: ☐
A26: 9 | B26: All | C26: Họp tuần MKT + Sales | D26: 30 phút: KPI review, blockers, campus feedback, action items | E26: Thứ 5 | F26: All team | G26: ☐
A27: 10 | B27: Local SEO | C27: Check Google Business | D27: Reply reviews mới | Post bài mới | Check info chính xác | E27: Thứ 5 | F27: Content | G27: ☐
A29: C. CÔNG VIỆC HÀNG THÁNG
A30: STT | B30: Kênh | C30: Công việc | D30: Chi tiết | E30: Ngày | F30: Ai làm | G30: Checklist
A31: 1 | B31: All | C31: Monthly report | D31: Tổng spend, leads, tours, enrollments, CAC by campus + channel | E31: Ngày 1-3 | F31: MM | G31: ☐
A32: 2 | B32: Google Ads | C32: Cấu trúc lại campaigns | D32: Pause campaigns yếu | Tạo campaigns mới nếu cần | Shift budget | E32: Ngày 1-5 | F32: Performance | G32: ☐
A33: 3 | B33: Meta Ads | C33: Refresh audiences | D33: Update Lookalike | Refresh Custom audiences | Exclude enrolled | E33: Ngày 1-5 | F33: Performance | G33: ☐
A34: 4 | B34: TikTok | C34: Content refresh | D34: Quay 3-5 video mới nếu cần | Update Spark Ads library | E34: Ngày 5-10 | F34: Content + Campus | G34: ☐
A35: 5 | B35: GHL | C35: CRM cleanup | D35: Merge duplicates | Update lost reasons | Archive old leads | E35: Ngày 5-10 | F35: Sales + MM | G35: ☐
A36: 6 | B36: GHL | C36: Automation review | D36: Kiểm tra workflow performance | Adjust nurture timing | Test SMS | E36: Ngày 5-10 | F36: MM | G36: ☐
A37: 7 | B37: Birch | C37: Rule optimization | D37: Review rule performance | Adjust thresholds | Add new rules | E37: Ngày 5-10 | F37: Performance | G37: ☐
A38: 8 | B38: All | C38: Họp tháng với BGH | D38: CAC, ROI, campus performance, budget shift proposal, next month plan | E38: Ngày 5-7 | F38: MM + BGH | G38: ☐
A39: 9 | B39: Content | C39: Kế hoạch content tháng sau | D39: Calendar editorial: 90 bài social + 4-8 blog + video plan | E39: Ngày 25-30 | F39: Content Lead | G39: ☐
A40: 10 | B40: Local SEO | C40: GMB monthly update | D40: Cập nhật ảnh, bài viết, sự kiện cho 6 cơ sở | Review response | E40: Ngày 15 | F40: Content | G40: ☐
A42: D. CÔNG VIỆC HÀNG QUÝ
A43: STT | B43: Công việc | C43: Chi tiết | D43: Ai làm | E43: Checklist
A44: 1 | B44: Review chiến lược tổng | C44: So sánh KPI thực vs plan | Điều chỉnh mix kênh | Shift budget | D44: MM + BGH | E44: ☐
A45: 2 | B45: Audit toàn bộ tracking | C45: GTM audit: tất cả tags fire đúng? | Pixel health check | CAPI verify | D45: Performance + Dev | E45: ☐
A46: 3 | B46: Competitor analysis | C46: Rà đối thủ: ads library, keyword, LP, ưu đãi, positioning | D46: MM | E46: ☐
A47: 4 | B47: Content audit | C47: Rà kho content: video nào perform tốt? Bài nào traffic cao? | Gap analysis | D47: Content Lead | E47: ☐
A48: 5 | B48: CRM & automation review | C48: Workflow nào convert tốt? Nurture nào cần sửa? SLA trend? | D48: MM + Sales | E48: ☐
A49: 6 | B49: Training team | C49: Cập nhật kỹ năng: Google Ads mới, Meta policy, TikTok trends, GHL features | D49: MM | E49: ☐
A51: E. CÔNG VIỆC HÀNG NĂM (CUỐI MÙA)
A52: STT | B52: Công việc | C52: Chi tiết | D52: Ai làm | E52: Checklist
A53: 1 | B53: Post-mortem toàn chiến dịch | C53: Tổng kết: spend, leads, tours, enrollments, CAC, ROI theo campus + kênh | D53: MM + Sales + BGH | E53: ☐
A54: 2 | B54: Lưu playbook | C54: Ghi lại: top campaigns, top keywords, top creatives, best practices, lessons learned | D54: MM | E54: ☐
A55: 3 | B55: Chuẩn bị mùa sau | C55: Budget proposal + Channel mix + Campus priority + Content plan cho năm sau | D55: MM | E55: ☐
A56: 4 | B56: Cập nhật assets | C56: Refresh video, ảnh, testimonial mới | Quay phụ huynh mới nhập học | D56: Content + Campus | E56: ☐
A57: 5 | B57: Review tools & contracts | C57: GHL, Birch, domain, hosting, SMS credits, Zalo OA | Renew/upgrade nếu cần | D57: MM + IT | E57: ☐

Sheet 11. Timeline
A1: TIMELINE GIẢI NGÂN 03-09/2026
A2: Giai đoạn | B2: % | C2: Ngân sách | D2: Trọng tâm | E2: Paid Media | F2: KPI | G2: Checkpoint
A3: 26/03–31/03 | B3: 0.04 | C3: =B3*'1. Input'!B4 -> 520000000 | D3: Setup Birch+GHL+GTM+Pixel+LP | E3: =0.02*'1. Input'!B15 -> 170000000 | F3: Tracking live | G3: Go/No-go 31/03
A4: Tháng 4 | B4: 0.14 | C4: =B4*'1. Input'!B4 -> 1820000000 | D4: Meta+TikTok mở phủ | Webinar #1-2 | Tour #1-3 | E4: =0.12*'1. Input'!B15 -> 1020000000 | F4: 1,400 leads/420 tours | G4: CPL review tuần 2
A5: Tháng 5 | B5: 0.22 | C5: =B5*'1. Input'!B4 -> 2860000000 | D5: Scale paid | Open Day #1 | Zalo broadcast tỉnh | E5: =0.24*'1. Input'!B15 -> 2040000000 | F5: 2,400 leads/720 tours | G5: Lead→Tour<25%→dừng
A6: Tháng 6 | B6: 0.24 | C6: =B6*'1. Input'!B4 -> 3120000000 | D6: Tour cao điểm | Remarket mạnh | Open Day #2 | E6: =0.28*'1. Input'!B15 -> 2380000000 | F6: 2,800 leads/840 tours | G6: Check 53% target
A7: Tháng 7 | B7: 0.22 | C7: =B7*'1. Input'!B4 -> 2860000000 | D7: Chốt sale | Học bổng cuối | Pipeline GHL | E7: =0.24*'1. Input'!B15 -> 2040000000 | F7: 2,400 leads/720 tours | G7: <73%→dự phòng
A8: Tháng 8 | B8: 0.1 | C8: =B8*'1. Input'!B4 -> 1300000000 | D8: Vét cuối | Retarget database | E8: =0.08*'1. Input'!B15 -> 680000000 | F8: 1,200 leads/360 tours | G8: Gần đạt target
A9: Tháng 9 | B9: 0.04 | C9: =B9*'1. Input'!B4 -> 520000000 | D9: Late intake | Chuyển trường | Brand defense | E9: =0.02*'1. Input'!B15 -> 170000000 | F9: 400 leads/120 tours | G9: Post-mortem
A10: TỔNG | B10: =SUM(B3:B9) -> 1 | C10: =SUM(C3:C9) -> 13000000000

Sheet 12. Danh bạ
A1: DANH BẠ CƠ SỞ (BỎ PHÚ NHUẬN – CẬP NHẬT ĐỊA GIỚI MỚI)
A2: Khu vực | B2: Tên trường | C2: Cấp | D2: Địa chỉ | E2: Hotline | F2: Trạng thái | G2: Ghi chú
A3: TP.HCM | B3: Việt Anh Gò Vấp | C3: TH+THCS+THPT | D3: 160/72 Phan Huy Ích, Gò Vấp | E3: 091 696 1409 | F3: ✅ | G3: Cơ sở lớn, 3 cấp
A4: TP.HCM | B4: Việt Anh Bình Tân | C4: Tiểu học | D4: Số 7 đường 38A, Tân Tạo, Bình Tân | E4: 0916 961 409 | F4: ✅ | G4: Khu đông dân
A5: TP.HCM | B5: MN Việt Anh Gò Vấp | C5: Mầm non | D5: 573 Đ. Lê Đức Thọ, P. An Hội Tây, Gò Vấp | E5: 0916 961 409 | F5: ✅ | G5: Flagship MN
A6: Tây Ninh | B6: MN Nhân Lễ | C6: Mầm non | D6: 22 Đường D2, KDC Cần Giuộc, Tây Ninh | E6: 0916 961 409 | F6: ✅ | G6: Cần Giuộc → Tây Ninh
A7: Tây Ninh | B7: MN+TH Thái Sơn | C7: MN+TH | D7: KDC Thái Sơn, Cần Giuộc, Tây Ninh | E7: 0916 961 409 | F7: ✅ | G7: Cần Giuộc → Tây Ninh
A8: An Giang | B8: MN+TH Mekong Xanh | C8: MN+TH | D8: Lô E7, KĐT Tây Bắc, TP. Rạch Giá, An Giang | E8: 0916 961 409 | F8: ✅ | G8: Rạch Giá → An Giang
A10: ⚠️ Phú Nhuận ĐÃ BỎ (sắp đóng cửa). Ngân sách Phú Nhuận phân bổ lại cho các cơ sở còn lại.
A11: 📌 Cần Giuộc → thuộc tỉnh TÂY NINH (trước là Long An). Rạch Giá → thuộc tỉnh AN GIANG (trước là Kiên Giang).

Sheet 13. Zalo Ads + OA
A1: KẾ HOẠCH ZALO ADS + ZALO OA – NURTURE LOCAL + BROADCAST
A3: A. ZALO ADS CAMPAIGNS
A4: Campaign | B4: Audience | C4: Creative | D4: Budget/tháng | E4: KPI | F4: GHL Integration | G4: GTM
A5: Zalo_MN_Local | B5: Geo Gò Vấp+Tỉnh | Age 25-40 | Interest Parenting | C5: Image+text: Tour invitation, campus ảnh, ưu đãi | D5: =0.07*'1. Input'!B15*0.35/6 -> 34708333 | E5: Open ≥ 40% | CTR ≥ 5% | F5: Lead → Pipeline MN | G5: Zalo Pixel via GTM
A6: Zalo_TH_Local | B6: Geo Gò Vấp+BT+Tỉnh | Age 28-45 | C6: Image+text: Tuyển sinh lớp 1, chương trình | D6: =0.07*'1. Input'!B15*0.25/6 -> 24791667 | E6: Open ≥ 35% | CTR ≥ 4% | F6: Lead → Pipeline TH | G6: Zalo Pixel
A7: Zalo_THCS_THPT | B7: Geo TP.HCM | Age 30-55 | C7: Webinar invite, lộ trình, học bổng | D7: =0.07*'1. Input'!B15*0.2/6 -> 19833333 | E7: Open ≥ 35% | Reg ≥ 3% | F7: Lead → Pipeline THCS/THPT | G7: Zalo Pixel
A8: Zalo_Remarketing | B8: OA followers + Web visitors | C8: Tour reminder, ưu đãi cuối, deadline | D8: =0.07*'1. Input'!B15*0.2/6 -> 19833333 | E8: Conv ≥ 5% | F8: Retarget pipeline | G8: Zalo Pixel
A10: B. ZALO OA SETUP + BROADCAST
A11: Bước | B11: Hành động | C11: Chi tiết | D11: Timeline | E11: Trạng thái
A12: 1 | B12: Tạo/Verify Zalo OA | C12: 1 OA chính cho hệ thống Việt Anh | Verify business | D12: Ngày 1 | E12: ☐
A13: 2 | B13: Kết nối GHL | C13: API Zalo OA → GHL | Auto-reply + Broadcast + Nurture | D13: Ngày 2 | E13: ☐
A14: 3 | B14: Tạo menu auto-reply | C14: Menu: Tư vấn MN | TH | THCS | THPT | Học phí | Tour | Hotline | D14: Ngày 2 | E14: ☐
A15: 4 | B15: Tạo 8 broadcast templates | C15: Welcome, Tour invite, Tour reminder, Ưu đãi, Webinar, Scholarship, Thank you, Re-engage | D15: Ngày 3 | E15: ☐
A16: 5 | B16: Segment followers | C16: By campus, cấp, trạng thái lead | Auto-tag từ GHL | D16: Ngày 3 | E16: ☐
A17: 6 | B17: Lịch broadcast tuần | C17: Thứ 3: Tour invite | Thứ 6: Ưu đãi/content | Trước webinar: Reminder | D17: Tuần 1 | E17: ☐
A18: 7 | B18: Cài Zalo Pixel qua GTM | C18: Custom HTML tag trong GTM | Events: PageView, Lead, Form | D18: Ngày 2 | E18: ☐
A20: C. CHIẾN LƯỢC CONTENT ZALO OA – 8 MẪU BROADCAST
A21: # | B21: Template Name | C21: Mục đích | D21: Nội dung mẫu | E21: CTA | F21: Segment gửi | G21: Tần suất | H21: GHL Trigger | I21: KPI
A22: 1 | B22: Welcome Message | C22: Chào đón lead mới | D22: Chào [Tên]! Cảm ơn bạn quan tâm Trường Việt Anh. Chúng tôi có MN, TH, THCS, THPT tại 8 cơ sở. Nhấn menu để tìm hiểu thêm! | E22: Chọn cấp học quan tâm | F22: New OA follower | G22: Auto (khi follow) | H22: New contact → Welcome seq | I22: Reply rate ≥ 30%
A23: 2 | B23: Tour Invitation | C23: Mời tham quan trường | D23: [Tên] ơi, cuối tuần này Việt Anh mở cửa đón PH tham quan. Cơ sở [Campus]: [Địa chỉ]. Đăng ký tour tại đây! | E23: Đăng ký tour ngay | F23: Lead chưa book tour | G23: 2 lần/tuần (T3, T6) | H23: Lead > 48h no tour | I23: Tour booked rate ≥ 8%
A24: 3 | B24: Tour Reminder | C24: Nhắc lịch tour | D24: [Tên] ơi, lịch tham quan trường của bạn vào [Ngày] lúc [Giờ] tại [Campus]. Chúng tôi rất mong gặp bạn! | E24: Xác nhận tham dự | F24: Lead đã book tour | G24: Auto (48h + 2h trước) | H24: Tour booked trigger | I24: Show-up rate ≥ 70%
A25: 4 | B25: Ưu đãi tuyển sinh | C25: Push ưu đãi/học bổng | D25: Tin vui! Việt Anh dành ưu đãi [%] cho hồ sơ nộp trước [Deadline]. Áp dụng [Cấp]. Liên hệ ngay! | E25: Nhận ưu đãi ngay | F25: Lead qualified chưa enroll | G25: 1-2 lần/tháng | H25: Manual schedule | I25: CTR ≥ 5%
A26: 5 | B26: Webinar Invitation | C26: Mời dự hội thảo online | D26: Hội thảo "[Tên WB]" – [Ngày] lúc [Giờ]. Chủ đề: [Topic]. Đăng ký miễn phí ngay! | E26: Đăng ký webinar | F26: Lead theo cấp phù hợp | G26: Trước WB 7 ngày + 2 ngày | H26: Manual + GHL | I26: Reg rate ≥ 5%
A27: 6 | B27: Scholarship Alert | C27: Thông báo học bổng | D27: Chương trình học bổng [Cấp] 2026 đã mở đăng ký! Giá trị đến [X]%. Deadline: [Ngày]. Đăng ký thi ngay! | E27: Đăng ký thi HB | F27: THCS/THPT leads | G27: 1 lần/tháng | H27: Manual | I27: Reg rate ≥ 8%
A28: 7 | B28: Thank You / Post-tour | C28: Cảm ơn sau tour | D28: Cảm ơn [Tên] đã đến tham quan Việt Anh! Hy vọng bạn ấn tượng. Nếu cần thêm thông tin, nhắn ngay cho chúng tôi. | E28: Nộp hồ sơ ngay | F28: Lead đã tour | G28: Auto (2h sau tour) | H28: Tour completed trigger | I28: Reply rate ≥ 20%
A29: 8 | B29: Re-engage / Win-back | C29: Kích hoạt lại lead cũ | D29: [Tên] ơi, Việt Anh vẫn còn chỗ cho [Cấp]. Ưu đãi đặc biệt cho PH quay lại. Hẹn gặp bạn tuần này! | E29: Đặt lịch lại | F29: Lead lost > 30 ngày | G29: 1 lần/tháng | H29: Lost 30d trigger | I29: Reactivation ≥ 3%
A32: D. LỊCH BROADCAST ZALO OA HÀNG TUẦN
A33: Ngày | B33: Giờ gửi | C33: Template | D33: Segment | E33: Nội dung tóm tắt | F33: KPI | G33: Ghi chú
A34: Thứ 3 | B34: 10:00 | C34: Tour Invitation | D34: Lead chưa tour + campus tương ứng | E34: Mời tour cuối tuần | Cơ sở phù hợp | F34: Open ≥ 40%, CTR ≥ 5% | G34: Segment theo campus, cấp
A35: Thứ 5 | B35: 14:00 | C35: Ưu đãi / Webinar | D35: Tất cả lead active | E35: Ưu đãi tuần hoặc reminder webinar | F35: Open ≥ 35%, CTR ≥ 4% | G35: Tuần có WB → WB invite
A36: Thứ 6 | B36: 09:00 | C36: Tour Reminder | D36: Lead đã book tour T7/CN | E36: Nhắc tour cuối tuần + địa chỉ + parking | F36: Open ≥ 60% | G36: Auto từ GHL
A37: Thứ 7 | B37: 08:00 | C37: Tour Reminder 2h | D37: Lead tour hôm nay | E37: Nhắc tour sáng nay + SĐT liên hệ | F37: Open ≥ 70% | G37: Auto từ GHL
A38: Cuối tháng | B38: 10:00 | C38: Scholarship / Deadline | D38: Lead qualified THCS/THPT | E38: Deadline ưu đãi, học bổng sắp hết | F38: CTR ≥ 6% | G38: 1 lần/tháng
A39: Đầu tháng | B39: 10:00 | C39: Re-engage | D39: Lost leads > 30 ngày | E39: Win-back message + ưu đãi quay lại | F39: Reactivation ≥ 3% | G39: Monthly, manual approval
A42: E. ZALO ADS – CHI TIẾT AUDIENCE & CREATIVE THEO CHIẾN DỊCH
A43: Campaign | B43: Audience Size est. | C43: Detailed Targeting | D43: Placement | E43: Creative Type | F43: Số lượng creative | G43: A/B Test | H43: Daily Budget | I43: Optimization Goal | J43: Tracking
A44: Zalo_MN_Local | B44: 150,000-300,000 | C44: Geo: Gò Vấp 5km + Cần Giuộc + Rạch Giá | Age 25-40 | Female 85% | Interest: Parenting, Baby, Preschool | D44: Zalo Feed + Article | E44: Image card + Short text | F44: 5 image + 3 article | G44: Test 2 headline, 2 image | H44: =0.07*8500000000*0.35/6/30 -> 1156944.4 | I44: Click to OA / Lead form | J44: Zalo Pixel + UTM → GA4
A45: Zalo_TH_Local | B45: 200,000-400,000 | C45: Geo: Gò Vấp + Bình Tân + Tỉnh | Age 28-45 | Parents | Interest: Education, School | D45: Zalo Feed + Article | E45: Image card + Carousel | F45: 4 image + 2 carousel | G45: Test headline + CTA | H45: =0.07*8500000000*0.25/6/30 -> 826388.89 | I45: Click to OA / Lead form | J45: Zalo Pixel + UTM → GA4
A46: Zalo_THCS_THPT | B46: 300,000-500,000 | C46: Geo: TP.HCM rộng | Age 30-55 | Interest: Education, University prep, Scholarship | D46: Zalo Feed + Article + Banner | E46: Image + Video teaser 15s | F46: 4 image + 2 video + 2 article | G46: Test video vs image | H46: =0.07*8500000000*0.2/6/30 -> 661111.11 | I46: Lead form / Webinar reg | J46: Zalo Pixel + UTM → GA4
A47: Zalo_Remarketing | B47: 50,000-100,000 | C47: OA followers + Website pixel visitors | All ages | Exclude enrolled | D47: Zalo Feed + Push notification | E47: Countdown + Ưu đãi + Tour reminder | F47: 3 countdown + 2 offer | G47: Test urgency vs benefit | H47: =0.07*8500000000*0.2/6/30 -> 661111.11 | I47: Conversion / Tour booked | J47: Zalo Pixel + GHL sync
A50: F. ZALO OA AUTO-REPLY MENU CHI TIẾT
A51: Menu Level 1 | B51: Menu Level 2 | C51: Auto-reply Content | D51: GHL Action | E51: Next Step
A52: 📚 Tư vấn Mầm non | B52: - | C52: Cảm ơn bạn! MN Việt Anh có 4 cơ sở: GV, Nhân Lễ, Thái Sơn, Mekong Xanh. Bạn muốn tìm hiểu cơ sở nào? | D52: Tag: grade_mn + Assign sales | E52: Chọn cơ sở → Info + Book tour
A53: 📖 Tư vấn Tiểu học | B53: - | C53: TH Việt Anh có tại: Gò Vấp, Bình Tân, Thái Sơn, Mekong Xanh. Song ngữ từ lớp 1. Bạn quan tâm cơ sở nào? | D53: Tag: grade_th + Assign sales | E53: Chọn cơ sở → Info + Book tour
A54: 🎓 Tư vấn THCS | B54: - | C54: THCS Việt Anh tại Gò Vấp. Lộ trình 6→12 liên cấp, GV chủ nhiệm theo sát. Để lại SĐT để được tư vấn chi tiết! | D54: Tag: grade_thcs + Create contact | E54: Sales gọi lại < 5 phút
A55: 🏫 Tư vấn THPT | B55: - | C55: THPT Việt Anh Gò Vấp. Học bổng đến 100%, đầu ra ĐH top. Để lại SĐT hoặc nhấn "Đăng ký thi học bổng"! | D55: Tag: grade_thpt + Create contact | E55: Sales gọi + Gửi brochure
A56: 💰 Học phí | B56: - | C56: Học phí Việt Anh dao động theo cấp và cơ sở. Nhấn cấp học để xem chi tiết hoặc liên hệ hotline 0916 961 409. | D56: Tag: fee_inquiry + Hot lead | E56: Gửi bảng phí → Book tour
A57: 📅 Đặt lịch Tour | B57: - | C57: Tuyệt vời! Chọn cơ sở và thời gian phù hợp. Chúng tôi sẽ xác nhận ngay! | D57: Create appointment in GHL | E57: Confirm SMS + Zalo 2h trước
A58: 📞 Gọi Hotline | B58: - | C58: Hotline: 0916 961 409 (tất cả cơ sở). Giờ tư vấn: 7:30-17:30 T2-T7, 8:00-12:00 CN. | D58: Log call_intent | E58: Track click_call
A59: 🎯 Hội thảo/Webinar | B59: - | C59: Hội thảo miễn phí sắp tới: [Tên WB] ngày [Date]. Đăng ký ngay! | D59: Tag: webinar_interest | E59: Gửi link đăng ký WB

Sheet 14. Weekly Battleplan
A1: KẾ HOẠCH TÁC CHIẾN TUẦN 1-28 (03-09/2026)
A2: Tuần | B2: Ngày | C2: Giai đoạn | D2: Mục tiêu tuần | E2: Marketing Action | F2: Sales Action | G2: Campus Action | H2: Trạng thái
A3: 1 | B3: 26/03-01/04 | C3: Setup | D3: Dựng nền tảng | E3: Setup GTM+Pixel+GHL+Birch+LP | F3: Chốt SLA+script+CRM tags | G3: Hotline+GMB+Tour slots | H3: ☐
A4: 2 | B4: 02-08/04 | C4: Setup | D4: Chuẩn hóa LP+Forms | E4: Test LP 6 cơ sở + Forms → GHL | F4: Test nhận lead+gọi lại | G4: Chụp ảnh+video bổ sung | H4: ☐
A5: 3 | B5: 09-15/04 | C5: Pilot | D5: Pilot campaign đợt 1 | E5: Bật Brand+Generic+HighIntent | 2 RSA/adgroup | F5: Gọi 100% lead <5 phút | G5: Tour slots ít nhất 2/tuần | H5: ☐
A6: 4 | B6: 16-22/04 | C6: Pilot | D6: Đánh giá pilot | E6: Rà search terms+pause yếu+keep tốt | F6: QA 20 cuộc gọi đầu | G6: Đánh giá 5 tour đầu | H6: ☐
A7: 5 | B7: 23-29/04 | C7: Scale 1 | D7: Scale sau pilot | E7: Tăng budget campaigns thắng+mở thêm cơ sở | F7: 4 touchpoints/lead 3 ngày | G7: Open campus cuối tuần | H7: ☐
A8: 6 | B8: 30/04-06/05 | C8: Scale 1 | D8: Mở webinar | E8: LP webinar THCS+THPT+Search webinar ads | F8: Script gọi webinar lead | G8: Diễn giả+slide+CTA | H8: ☐
A9: 7 | B9: 07-13/05 | C9: Scale 1 | D9: Tối ưu quality | E9: Tách HI/webinar/brand+bidding optimize | F9: Rà Lead→Tour by counselor | G9: Show-up rate report | H9: ☐
A10: 8 | B10: 14-20/05 | C10: Scale 1 | D10: Mở competitor | E10: Competitor THCS+THPT GV+LP compare | F10: Script xử lý so sánh | G10: Bảng so sánh mềm | H10: ☐
A11: 9 | B11: 21-27/05 | C11: Scale 1 | D11: Khóa baseline T4-5 | E11: Tổng hợp CPL/campus/quality | Plan T6 | F11: Top 5 lost reasons | G11: Best practice tour | H11: ☐
A12: 10 | B12: 28/05-03/06 | C12: Scale 2 | D12: Scale mạnh T6 | E12: Tăng NS THCS+THPT GV+brand defense | F12: Ưu tiên lead Google | G12: Tăng tour slots | H12: ☐
A13: 11 | B13: 04-10/06 | C13: Scale 2 | D13: YouTube+DG | E13: Video testi THCS/THPT+YouTube retarget | F13: Tag video-engaged lead | G13: Quay thêm testimonial | H13: ☐
A14: 12 | B14: 11-17/06 | C14: Scale 2 | D14: Test PMax | E14: PMax test 2% | Track riêng | F14: Source PMax riêng | G14: Giữ nguyên quy trình | H14: ☐
... A30: 28 | B30: 29-30/09 | C30: Close | D30: Đóng mùa | E30: Tổng kết: spend/leads/tours/enrollments/CAC | Playbook | F30: Tổng kết per counselor | Lost reasons | G30: Tổng kết tour+testimonial mới | H30: ☐

Sheet A. KPI Weekly Tracker
B1: 📈 KPI WEEKLY TRACKER – 3 ĐỘI (Marketing | Tuyển Sinh | Ban Cơ Sở)
B2: Hướng dẫn: Nhập dữ liệu thực tế vào cột "Thực tế" mỗi tuần. Cột "Vs Target" tự tính. Tô màu xanh=đạt, vàng=cần theo dõi, đỏ=cần can thiệp.
B3: KPI / Chỉ số | C3: Tuần 1 26/03 | D3: Tuần 2 02/04 | E3: Tuần 3 09/04 | F3: Tuần 4 16/04 | G3: Tuần 5 23/04 | H3: Tuần 6 30/04 | I3: MTD Tích lũy | J3: Target | K3: Vs Target | L3: % đạt | M3: Cảnh báo
B4: 🎯 MARKETING – GOOGLE ADS
B5: Spend Google (đ) | C5: 0 | D5: 0 | E5: 0 | F5: 0 | G5: 0 | H5: 0 | I5: =SUM(C5:H5) -> 0 | J5: 0 | K5: =IF(J5>0,I5/J5,0) -> 0 | L5: =IF(J5>0,I5/J5,"N/A") -> N/A | M5: -
B6: Impressions | C6: 0 | D6: 0 | E6: 0 | F6: 0 | G6: 0 | H6: 0 | I6: =SUM(C6:H6) -> 0 | J6: 0 | K6: =IF(J6>0,I6/J6,0) -> 0 | L6: =IF(J6>0,I6/J6,"N/A") -> N/A | M6: -
B7: Clicks | C7: 0 | D7: 0 | E7: 0 | F7: 0 | G7: 0 | H7: 0 | I7: =SUM(C7:H7) -> 0 | J7: 0 | K7: =IF(J7>0,I7/J7,0) -> 0 | L7: =IF(J7>0,I7/J7,"N/A") -> N/A | M7: -
B8: CTR (%) | C8: 0 | D8: 0 | E8: 0 | F8: 0 | G8: 0 | H8: 0 | I8: =SUM(C8:H8) -> 0 | J8: 0.06 | K8: =IF(J8>0,I8/J8,0) -> 0 | L8: =IF(J8>0,I8/J8,"N/A") -> 0 | M8: Ngưỡng: 0.05
B9: CPC trung bình (đ) | C9: 0 | D9: 0 | E9: 0 | F9: 0 | G9: 0 | H9: 0 | I9: =SUM(C9:H9) -> 0 | J9: 0 | K9: =IF(J9>0,I9/J9,0) -> 0 | L9: =IF(J9>0,I9/J9,"N/A") -> N/A | M9: -
B10: Leads (Google) | C10: 0 | D10: 0 | E10: 0 | F10: 0 | G10: 0 | H10: 0 | I10: =SUM(C10:H10) -> 0 | J10: 0 | K10: =IF(J10>0,I10/J10,0) -> 0 | L10: =IF(J10>0,I10/J10,"N/A") -> N/A | M10: -
B11: Qualified Leads (Google) | C11: 0 | D11: 0 | E11: 0 | F11: 0 | G11: 0 | H11: 0 | I11: =SUM(C11:H11) -> 0 | J11: 0 | K11: =IF(J11>0,I11/J11,0) -> 0 | L11: =IF(J11>0,I11/J11,"N/A") -> N/A | M11: -
B12: CPL Google (đ) | C12: 0 | D12: 0 | E12: 0 | F12: 0 | G12: 0 | H12: 0 | I12: =SUM(C12:H12) -> 0 | J12: 180000 | K12: =IF(J12>0,I12/J12,0) -> 0 | L12: =IF(J12>0,I12/J12,"N/A") -> 0 | M12: Ngưỡng: 220000
B13: Qualified Rate | C13: 0 | D13: 0 | E13: 0 | F13: 0 | G13: 0 | H13: 0 | I13: =SUM(C13:H13) -> 0 | J13: 0.5 | K13: =IF(J13>0,I13/J13,0) -> 0 | L13: =IF(J13>0,I13/J13,"N/A") -> 0 | M13: Ngưỡng: 0.4
B14: Booked Tours (Google) | C14: 0 | D14: 0 | E14: 0 | F14: 0 | G14: 0 | H14: 0 | I14: =SUM(C14:H14) -> 0 | J14: 0 | K14: =IF(J14>0,I14/J14,0) -> 0 | L14: =IF(J14>0,I14/J14,"N/A") -> N/A | M14: -
B15: Cost / Booked Tour | C15: 0 | D15: 0 | E15: 0 | F15: 0 | G15: 0 | H15: 0 | I15: =SUM(C15:H15) -> 0 | J15: 0 | K15: =IF(J15>0,I15/J15,0) -> 0 | L15: =IF(J15>0,I15/J15,"N/A") -> N/A | M15: -
B17: 🎯 MARKETING – META ADS
B18: Spend Meta (đ) | C18: 0 | D18: 0 | E18: 0 | F18: 0 | G18: 0 | H18: 0 | I18: =SUM(C18:H18) -> 0 | J18: 0 | K18: =IF(J18>0,I18/J18,0) -> 0 | L18: =IF(J18>0,I18/J18,"N/A") -> N/A | M18: -
B19: Reach / Impressions | C19: 0 | D19: 0 | E19: 0 | F19: 0 | G19: 0 | H19: 0 | I19: =SUM(C19:H19) -> 0 | J19: 0 | K19: =IF(J19>0,I19/J19,0) -> 0 | L19: =IF(J19>0,I19/J19,"N/A") -> N/A | M19: -
B20: CPM (đ) | C20: 0 | D20: 0 | E20: 0 | F20: 0 | G20: 0 | H20: 0 | I20: =SUM(C20:H20) -> 0 | J20: 0 | K20: =IF(J20>0,I20/J20,0) -> 0 | L20: =IF(J20>0,I20/J20,"N/A") -> N/A | M20: -
B21: CTR Meta (%) | C21: 0 | D21: 0 | E21: 0 | F21: 0 | G21: 0 | H21: 0 | I21: =SUM(C21:H21) -> 0 | J21: 0.015 | K21: =IF(J21>0,I21/J21,0) -> 0 | L21: =IF(J21>0,I21/J21,"N/A") -> 0 | M21: Ngưỡng: 0.01
B22: Leads (Meta) | C22: 0 | D22: 0 | E22: 0 | F22: 0 | G22: 0 | H22: 0 | I22: =SUM(C22:H22) -> 0 | J22: 0 | K22: =IF(J22>0,I22/J22,0) -> 0 | L22: =IF(J22>0,I22/J22,"N/A") -> N/A | M22: -
B23: CPL Meta (đ) | C23: 0 | D23: 0 | E23: 0 | F23: 0 | G23: 0 | H23: 0 | I23: =SUM(C23:H23) -> 0 | J23: 120000 | K23: =IF(J23>0,I23/J23,0) -> 0 | L23: =IF(J23>0,I23/J23,"N/A") -> 0 | M23: Ngưỡng: 180000
B24: Qualified Rate Meta | C24: 0 | D24: 0 | E24: 0 | F24: 0 | G24: 0 | H24: 0 | I24: =SUM(C24:H24) -> 0 | J24: 0.45 | K24: =IF(J24>0,I24/J24,0) -> 0 | L24: =IF(J24>0,I24/J24,"N/A") -> 0 | M24: Ngưỡng: 0.35
B25: Booked Tours (Meta) | C25: 0 | D25: 0 | E25: 0 | F25: 0 | G25: 0 | H25: 0 | I25: =SUM(C25:H25) -> 0 | J25: 0 | K25: =IF(J25>0,I25/J25,0) -> 0 | L25: =IF(J25>0,I25/J25,"N/A") -> N/A | M25: -
B27: 🎯 MARKETING – TIKTOK / ZALO
B28: Spend TikTok (đ) | C28: 0 | D28: 0 | E28: 0 | F28: 0 | G28: 0 | H28: 0 | I28: =SUM(C28:H28) -> 0 | J28: 0 | K28: =IF(J28>0,I28/J28,0) -> 0 | L28: =IF(J28>0,I28/J28,"N/A") -> N/A | M28: -
B29: Views / CPV | C29: 0 | D29: 0 | E29: 0 | F29: 0 | G29: 0 | H29: 0 | I29: =SUM(C29:H29) -> 0 | J29: 0 | K29: =IF(J29>0,I29/J29,0) -> 0 | L29: =IF(J29>0,I29/J29,"N/A") -> N/A | M29: -
B30: Leads TikTok | C30: 0 | D30: 0 | E30: 0 | F30: 0 | G30: 0 | H30: 0 | I30: =SUM(C30:H30) -> 0 | J30: 0 | K30: =IF(J30>0,I30/J30,0) -> 0 | L30: =IF(J30>0,I30/J30,"N/A") -> N/A | M30: -
B31: CPL TikTok (đ) | C31: 0 | D31: 0 | E31: 0 | F31: 0 | G31: 0 | H31: 0 | I31: =SUM(C31:H31) -> 0 | J31: 90000 | K31: =IF(J31>0,I31/J31,0) -> 0 | L31: =IF(J31>0,I31/J31,"N/A") -> 0 | M31: Ngưỡng: 130000
B32: Spend Zalo (đ) | C32: 0 | D32: 0 | E32: 0 | F32: 0 | G32: 0 | H32: 0 | I32: =SUM(C32:H32) -> 0 | J32: 0 | K32: =IF(J32>0,I32/J32,0) -> 0 | L32: =IF(J32>0,I32/J32,"N/A") -> N/A | M32: -
B33: Leads Zalo | C33: 0 | D33: 0 | E33: 0 | F33: 0 | G33: 0 | H33: 0 | I33: =SUM(C33:H33) -> 0 | J33: 0 | K33: =IF(J33>0,I33/J33,0) -> 0 | L33: =IF(J33>0,I33/J33,"N/A") -> N/A | M33: -
B34: CPL Zalo (đ) | C34: 0 | D34: 0 | E34: 0 | F34: 0 | G34: 0 | H34: 0 | I34: =SUM(C34:H34) -> 0 | J34: 80000 | K34: =IF(J34>0,I34/J34,0) -> 0 | L34: =IF(J34>0,I34/J34,"N/A") -> 0 | M34: Ngưỡng: 120000
B36: 🏃 TUYỂN SINH – PIPELINE
B37: Leads mới (tất cả kênh) | C37: 0 | D37: 0 | E37: 0 | F37: 0 | G37: 0 | H37: 0 | I37: =SUM(C37:H37) -> 0 | J37: 0 | K37: =IF(J37>0,I37/J37,0) -> 0 | L37: =IF(J37>0,I37/J37,"N/A") -> N/A | M37: -
B38: Leads đã gọi | C38: 0 | D38: 0 | E38: 0 | F38: 0 | G38: 0 | H38: 0 | I38: =SUM(C38:H38) -> 0 | J38: 0 | K38: =IF(J38>0,I38/J38,0) -> 0 | L38: =IF(J38>0,I38/J38,"N/A") -> N/A | M38: -
B39: Response < 5 phút (%) | C39: 0 | D39: 0 | E39: 0 | F39: 0 | G39: 0 | H39: 0 | I39: =SUM(C39:H39) -> 0 | J39: 0.85 | K39: =IF(J39>0,I39/J39,0) -> 0 | L39: =IF(J39>0,I39/J39,"N/A") -> 0 | M39: Ngưỡng: 0.7
B40: Tỷ lệ bắt máy (%) | C40: 0 | D40: 0 | E40: 0 | F40: 0 | G40: 0 | H40: 0 | I40: =SUM(C40:H40) -> 0 | J40: 0.45 | K40: =IF(J40>0,I40/J40,0) -> 0 | L40: =IF(J40>0,I40/J40,"N/A") -> 0 | M40: Ngưỡng: 0.35
B41: Lịch tour đặt (Booked) | C41: 0 | D41: 0 | E41: 0 | F41: 0 | G41: 0 | H41: 0 | I41: =SUM(C41:H41) -> 0 | J41: 0 | K41: =IF(J41>0,I41/J41,0) -> 0 | L41: =IF(J41>0,I41/J41,"N/A") -> N/A | M41: -
B42: Lead → Tour rate (%) | C42: 0 | D42: 0 | E42: 0 | F42: 0 | G42: 0 | H42: 0 | I42: =SUM(C42:H42) -> 0 | J42: 0.3 | K42: =IF(J42>0,I42/J42,0) -> 0 | L42: =IF(J42>0,I42/J42,"N/A") -> 0 | M42: Ngưỡng: 0.2
B43: Tour Attended (Show-up) | C43: 0 | D43: 0 | E43: 0 | F43: 0 | G43: 0 | H43: 0 | I43: =SUM(C43:H43) -> 0 | J43: 0 | K43: =IF(J43>0,I43/J43,0) -> 0 | L43: =IF(J43>0,I43/J43,"N/A") -> N/A | M43: -
B44: Show-up rate (%) | C44: 0 | D44: 0 | E44: 0 | F44: 0 | G44: 0 | H44: 0 | I44: =SUM(C44:H44) -> 0 | J44: 0.65 | K44: =IF(J44>0,I44/J44,0) -> 0 | L44: =IF(J44>0,I44/J44,"N/A") -> 0 | M44: Ngưỡng: 0.5
B45: Hồ sơ / Đăng ký | C45: 0 | D45: 0 | E45: 0 | F45: 0 | G45: 0 | H45: 0 | I45: =SUM(C45:H45) -> 0 | J45: 0 | K45: =IF(J45>0,I45/J45,0) -> 0 | L45: =IF(J45>0,I45/J45,"N/A") -> N/A | M45: -
B46: Deposits / Đặt cọc | C46: 0 | D46: 0 | E46: 0 | F46: 0 | G46: 0 | H46: 0 | I46: =SUM(C46:H46) -> 0 | J46: 0 | K46: =IF(J46>0,I46/J46,0) -> 0 | L46: =IF(J46>0,I46/J46,"N/A") -> N/A | M46: -
B47: Nhập học (Enrollment) | C47: 0 | D47: 0 | E47: 0 | F47: 0 | G47: 0 | H47: 0 | I47: =SUM(C47:H47) -> 0 | J47: 0 | K47: =IF(J47>0,I47/J47,0) -> 0 | L47: =IF(J47>0,I47/J47,"N/A") -> N/A | M47: -
B48: Tour → Enroll rate (%) | C48: 0 | D48: 0 | E48: 0 | F48: 0 | G48: 0 | H48: 0 | I48: =SUM(C48:H48) -> 0 | J48: 0.35 | K48: =IF(J48>0,I48/J48,0) -> 0 | L48: =IF(J48>0,I48/J48,"N/A") -> 0 | M48: Ngưỡng: 0.25
B50: 🏫 BAN CƠ SỞ – CAMPUS OPS
B51: Hotline uptime (%) | C51: 0 | D51: 0 | E51: 0 | F51: 0 | G51: 0 | H51: 0 | I51: =SUM(C51:H51) -> 0 | J51: 1 | K51: =IF(J51>0,I51/J51,0) -> 0 | L51: =IF(J51>0,I51/J51,"N/A") -> 0 | M51: Ngưỡng: 0.95
B52: GMB views | C52: 0 | D52: 0 | E52: 0 | F52: 0 | G52: 0 | H52: 0 | I52: =SUM(C52:H52) -> 0 | J52: 0 | K52: =IF(J52>0,I52/J52,0) -> 0 | L52: =IF(J52>0,I52/J52,"N/A") -> N/A | M52: -
B53: Tour slots tổng | C53: 0 | D53: 0 | E53: 0 | F53: 0 | G53: 0 | H53: 0 | I53: =SUM(C53:H53) -> 0 | J53: 0 | K53: =IF(J53>0,I53/J53,0) -> 0 | L53: =IF(J53>0,I53/J53,"N/A") -> N/A | M53: -
B54: Tour slots đã book | C54: 0 | D54: 0 | E54: 0 | F54: 0 | G54: 0 | H54: 0 | I54: =SUM(C54:H54) -> 0 | J54: 0 | K54: =IF(J54>0,I54/J54,0) -> 0 | L54: =IF(J54>0,I54/J54,"N/A") -> N/A | M54: -
B55: Slot fill rate (%) | C55: 0 | D55: 0 | E55: 0 | F55: 0 | G55: 0 | H55: 0 | I55: =SUM(C55:H55) -> 0 | J55: 0.7 | K55: =IF(J55>0,I55/J55,0) -> 0 | L55: =IF(J55>0,I55/J55,"N/A") -> 0 | M55: Ngưỡng: 0.5
B56: No-show count | C56: 0 | D56: 0 | E56: 0 | F56: 0 | G56: 0 | H56: 0 | I56: =SUM(C56:H56) -> 0 | J56: 0 | K56: =IF(J56>0,I56/J56,0) -> 0 | L56: =IF(J56>0,I56/J56,"N/A") -> N/A | M56: -
B57: Ảnh/video mới upload | C57: 0 | D57: 0 | E57: 0 | F57: 0 | G57: 0 | H57: 0 | I57: =SUM(C57:H57) -> 0 | J57: 0 | K57: =IF(J57>0,I57/J57,0) -> 0 | L57: =IF(J57>0,I57/J57,"N/A") -> N/A | M57: -

Sheet B. Todo Daily
B1: 📋 TODO LIST HÀNG NGÀY – MARKETING + TUYỂN SINH + CƠ SỞ
B2: Dùng mỗi ngày. Đánh dấu ✅ khi hoàn thành. Ghi chú vào cột Notes. Link đến Campaign Tracker để track số liệu.
B3: STT | C3: Kênh/Đội | D3: Công việc | E3: Chi tiết hành động | F3: Thời gian | G3: Ai làm | H3: Trạng thái | I3: Ghi chú
B4: ── BUỔI SÁNG (8:00–10:00) ──
B5: 2 | C5: Google Ads | D5: Check pacing & spend | E5: Login Birch → check daily pacing | Alert overspend >110% → giảm ngay | F5: 8:00 | G5: Performance Marketer | H5: ☐
B6: 3 | C6: Google Ads | D6: Rà search terms | E6: Xem search terms mới → Thêm negative nếu sai intent | Min 2 lần/tuần | F6: 8:15 | G6: Performance Marketer | H6: ☐
B7: 4 | C7: Meta Ads | D7: Check CPL & CPM | E7: Ads Manager → filter 3-day window | CPL >120k → review ad set | F7: 8:20 | G7: Performance Marketer | H7: ☐
B8: 5 | C8: Meta Ads | D8: Kiểm tra ad delivery | E8: Ad set nào learning phase? Nào đang scale? Nào bị từ chối? | F8: 8:30 | G8: Performance Marketer | H8: ☐
B9: 6 | C9: TikTok | D9: Check CPV và engagement | E9: TikTok Ads Manager → CPV, CTR, likes | Video nào dưới 3s quit rate cao? | F9: 8:40 | G9: Content + Perf. | H9: ☐
B10: 7 | C10: Zalo OA | D10: Kiểm tra broadcast | E10: Xem open rate, click | Gửi broadcast mới nếu có plan | F10: 8:50 | G10: CRM Executive | H10: ☐
B11: 8 | C11: GHL / CRM | D11: Review lead mới đêm qua | E11: GHL → All leads → Filter "Created yesterday" | Check source, stage | F11: 9:00 | G11: Sales Lead | H11: ☐
B12: 9 | C12: GHL / CRM | D12: Gọi lead chưa liên lạc | E12: Gọi tất cả lead >12h chưa gọi | Log trong CRM | F12: 9:10 | G12: Tư vấn viên | H12: ☐
B13: ── BUỔI TRƯA (12:00–13:00) ──
B14: 11 | C14: GHL / CRM | D14: Follow-up booked tour | E14: Nhắn Zalo/gọi lead có tour hôm nay/ngày mai | Xác nhận show-up | F14: 12:00 | G14: Tư vấn viên | H14: ☐
B15: 12 | C15: Google Ads | D15: Check Quality Score | E15: Review keyword QS thấp (<5) → cải thiện ad/LP | F15: 12:20 | G15: Performance Marketer | H15: ☐
B16: 13 | C16: Campus | D16: Chuẩn bị tour chiều | E16: Kiểm tra phòng tư vấn, tài liệu, bảng hiệu | Campus lead xác nhận | F16: 12:30 | G16: Campus Manager | H16: ☐
B17: ── BUỔI CHIỀU (14:00–17:00) ──
B18: 15 | C18: GHL / CRM | D18: Xử lý lead pipeline | E18: Review pipeline từng stage | Identify stuck leads | Update notes | F18: 14:00 | G18: Tư vấn viên | H18: ☐
B19: 16 | C19: Meta Ads | D19: Check top/bottom ad sets | E19: Identify top 3 performers → +15-20% budget | Bottom 2 → pause/fix | F19: 14:30 | G19: Performance Marketer | H19: ☐
B20: 17 | C20: Content | D20: Upload/boost nội dung | E20: Post Story, Reel, TikTok mới | Boost post organic nếu engaging | F20: 15:00 | G20: Content Creator | H20: ☐
B21: 18 | C21: Campus | D21: Tiến hành tour | E21: Đón phụ huynh, tư vấn, giới thiệu campus | Log feedback sau tour | F21: 15:00 | G21: Campus Manager | H21: ☐
B22: 19 | C22: GHL / CRM | D22: Post-tour follow-up | E22: Gọi/nhắn phụ huynh đã tour ngày hôm nay trong 2h | Note CRM | F22: 17:00 | G22: Tư vấn viên | H22: ☐
B23: ── CUỐI NGÀY (17:00–18:00) ──
B24: 21 | C24: Reporting | D24: Điền Daily Metrics | E24: Điền số vào A. KPI Weekly Tracker: leads, spend, tours, enrolls | F24: 17:00 | G24: Performance Marketer | H24: ☐
B25: 22 | C25: Google Ads | D25: Set bid adjustment nếu cần | E25: Device, location, time-of-day bid adj | Chạy cao hơn 9-11am, 7-9pm | F25: 17:15 | G25: Performance Marketer | H25: ☐
B26: 23 | C26: GHL | D26: Tag và phân loại leads cuối ngày | E26: GHL → Today leads → Verify tags đúng: source, campus, grade, intent | F26: 17:30 | G26: CRM Executive | H26: ☐
B27: 24 | C27: Reporting | D27: Báo cáo nhanh cho team | E27: Gửi Slack/Zalo: tổng leads hôm nay, tours, enrolls, anomaly | F27: 17:45 | G27: Marketing Lead | H27: ☐
B28: 25 | C28: Campus | D28: Cập nhật lead feedback | E28: Log tour feedback, câu hỏi PH, lý do chưa chốt vào CRM/sheet | F28: 17:50 | G28: Campus Manager | H28: ☐

Sheet C. Todo Weekly
B1: 📅 TODO LIST HÀNG TUẦN – MARKETING + TUYỂN SINH + BAN CƠ SỞ (28 TUẦN)
B2: Mỗi tuần họp ngắn Thứ 2 sáng để assign task. Họp review Thứ 6 chiều. Tất cả trạng thái phải cập nhật trước 17:00 Thứ 6.
B3: STT | C3: Đội | D3: Công việc | E3: Chi tiết / Tiêu chí hoàn thành | F3: Kết quả cần có | G3: Deadline | H3: Trạng thái | I3: Notes
B4: ── MARKETING – GOOGLE ADS ──
B5: 1 | C5: Marketing | D5: Review search terms report | E5: Download search terms tuần → Thêm negatives → Update Birch rule | F5: Negative list cập nhật | G5: Thứ 2 | H5: ☐
B6: 2 | C6: Marketing | D6: So sánh CPL theo campaign | E6: Birch → Campaign report → Sort by CPL | Scale top 3, pause bottom 2 | F6: Decision log | G6: Thứ 3 | H6: ☐
B7: 3 | C7: Marketing | D7: Kiểm tra Quality Score | E7: KW QS <5 → Cải thiện ad copy hoặc landing page phù hợp | F7: QS avg ≥7 | G7: Thứ 4 | H7: ☐
B8: 4 | C8: Marketing | D8: Cập nhật Birch automation rules | E8: Review rule performance → Điều chỉnh threshold nếu cần | F8: Rules live | G8: Thứ 4 | H8: ☐
B9: 5 | C9: Marketing | D9: A/B test report Google | E9: 2 RSA test → winner tiếp tục, loser pause | Document kết quả | F9: Test concluded | G9: Thứ 6 | H9: ☐
B10: ── MARKETING – META ADS ──
B11: 6 | C11: Marketing | D11: Creative refresh Meta | E11: Thay ad 7-10 ngày 1 lần | Freq >3 → cần creative mới ngay | F11: New creative live | G11: Thứ 2 | H11: ☐
B12: 7 | C12: Marketing | D12: Audience expansion review | E12: Lookalike tốt → expand 1% → 2% | Interest test mới | F12: Audience updated | G12: Thứ 3 | H12: ☐
B13: 8 | C13: Marketing | D13: Pixel health check | E13: Events Manager → check pixel events, match rate, deduplication | F13: Match rate ≥80% | G13: Thứ 4 | H13: ☐
B14: 9 | C14: Marketing | D14: Budget reallocation Meta | E14: Ad set thắng → +15-20% | Thua → pause hoặc pivot creative | F14: Budget optimized | G14: Thứ 5 | H14: ☐
B15: 10 | C15: Marketing | D15: Retargeting audience update | E15: Refresh audience lists: 7d/21d/60d | Loại lead đã enrolled | F15: Audience fresh | G15: Thứ 5 | H15: ☐
B16: ── MARKETING – TIKTOK / ZALO / WEBINAR ──
B17: 11 | C17: Marketing | D17: TikTok video performance | E17: 3-second retention, completion rate, CTR | Boost video tốt | F17: Top 3 identified | G17: Thứ 3 | H17: ☐
B18: 12 | C18: Marketing | D18: Zalo broadcast lên kế hoạch | E18: Draft nội dung tuần sau | Segment theo campus, grade, stage | F18: Draft approved | G18: Thứ 5 | H18: ☐
B19: 13 | C19: Marketing | D19: Webinar prep (nếu có tuần này) | E19: Landing page live, email sequence, reminder Zalo, test Zoom link | F19: Go/No-go | G19: Thứ 3 | H19: ☐
B20: ── TUYỂN SINH ──
B21: 14 | C21: Tuyển sinh | D21: Weekly pipeline review | E21: GHL → Review tất cả pipeline stages | Xác định stuck leads | F21: Pipeline clean | G21: Thứ 2 | H21: ☐
B22: 15 | C22: Tuyển sinh | D22: QA cuộc gọi ngẫu nhiên | E22: Nghe lại 5-10 cuộc gọi/tuần | Score theo 5 tiêu chí | Coaching | F22: QA report | G22: Thứ 4 | H22: ☐
B23: 16 | C23: Tuyển sinh | D23: Lost lead analysis | E23: Tổng hợp top 5 lý do lost | Cập nhật objection script | F23: Script updated | G23: Thứ 5 | H23: ☐
B24: 17 | C24: Tuyển sinh | D24: Confirm tours tuần sau | E24: Gọi tất cả lead đã booked tour tuần sau | Xác nhận 100% | F24: Confirmation rate | G24: Thứ 6 | H24: ☐
B25: 18 | C25: Tuyển sinh | D25: CRM data hygiene | E25: Xóa/merge duplicate | Verify tags | Update lost reasons | F25: CRM clean | G25: Thứ 6 | H25: ☐
B26: ── BAN CƠ SỞ ──
B27: 19 | C27: Campus | D27: Tour slot management | E27: Update slot availability tuần sau | Thêm slot nếu demand cao | F27: Slots published | G27: Thứ 2 | H27: ☐
B28: 20 | C28: Campus | D28: GMB (Google Business) update | E28: Post 1 bài/tuần | Cập nhật giờ mở cửa | Reply reviews mới | F28: Post live | G28: Thứ 3 | H28: ☐
B29: 21 | C29: Campus | D29: Testimonial collection | E29: Thu thập 1-2 testimonial PH/HS/tuần | Video ngắn hoặc text | F29: 1-2 pieces | G29: Thứ 5 | H29: ☐
B30: 22 | C30: Campus | D30: Hotline health check | E30: Test gọi hotline từng cơ sở | Verify pickup trong 3 ring | F30: 100% pickup | G30: Thứ 6 | H30: ☐
B31: ── REPORTING & REVIEW TUẦN ──
B32: 23 | C32: All | D32: Weekly KPI report | E32: Điền đủ vào A. KPI Weekly Tracker | Share với team | F32: Report sent | G32: Thứ 6 17:00 | H32: ☐
B33: 24 | C33: All | D33: Campaign Tracker update | E33: Điền spend, leads, tours, enrolls vào D. Campaign Tracker | F33: Tracker updated | G33: Thứ 6 17:00 | H33: ☐
B34: 25 | C34: Management | D34: Weekly review meeting | E34: Xem 12 KPI | Q: Scale gì, Pause gì, LP nào yếu, Campus nào cần fix | F34: Decision log | G34: Thứ 6 16:00 | H34: ☐
B35: 26 | C35: All | D35: Todo tuần sau prep | E35: Xem Battleplan tuần tiếp → Assign tasks → Set priorities | F35: Next week ready | G35: Thứ 6 17:30 | H35: ☐

Sheet D. Todo Monthly
B1: 📆 TODO LIST HÀNG THÁNG – REVIEW + PLANNING + TUYỂN SINH (Tháng 4–9/2026)
B3: STT | C3: Tháng/Đội | D3: Công việc | E3: Chi tiết / Tiêu chí | F3: KPI cần đạt | G3: Deadline | H3: Owner | I3: Status
B4: THÁNG 4/2026 – SETUP + PILOT
B5: 📌 Ngân sách: 1,820,000,000đ | Mục tiêu: 1,400 leads / 420 tours
B6: 1 | C6: Management | D6: Go/No-go decision 31/03 | E6: Tracking đã live? GHL nhận lead? LP hoạt động? Birch kết nối? | F6: All systems GO | G6: 31/03 | H6: ☐
B7: 2 | C7: Marketing | D7: Launch brand + generic search | E7: Bật Brand Search + Generic cho GV, BT | RSA 2 variant/adgroup | F7: CTR >6% | G7: 09/04 | H7: ☐
B8: 3 | C8: Marketing | D8: Mở Meta campaign đợt 1 | E8: Prospecting MN+TH | Lead Gen THCS+THPT | Test 10-15 creative | F8: CPL <150k | G8: 09/04 | H8: ☐
B9: 4 | C9: Marketing | D9: Webinar #1 (THCS) | E9: Chủ đề: Lộ trình lớp 6 | 100+ đăng ký | Chốt tour sau | F9: 100 reg | G9: 15/04 | H9: ☐
B10: 5 | C10: Tuyển sinh | D10: QA pipeline đầu tiên | E10: Nghe 20 cuộc gọi đầu | Score | Coaching ngay | Fix script | F10: QA report | G10: 15/04 | H10: ☐
B11: 6 | C11: Campus | D11: Confirm tour slots tháng 4 | E11: Tối thiểu 2 slot/campus/tuần | Brief campus manager | F11: Slots live | G11: 07/04 | H11: ☐
B12: 7 | C12: Management | D12: Mid-month CPL review | E12: CPL từng kênh, từng campus | Scale/pause decision | F12: Budget adj | G12: 15/04 | H12: ☐
B13: 8 | C13: Marketing | D13: A/B test landing pages | E13: Test 2 LP version cho THCS/THPT | Measure CVR | F13: Winner selected | G13: 30/04 | H13: ☐
B14: 9 | C14: Management | D14: Monthly review tháng 4 | E14: So với target: leads, tours, CPL, response rate | Plan tháng 5 | F14: Report + plan | G14: 30/04 | H14: ☐
B16: THÁNG 5/2026 – MỞ RỘNG + SCALE
B17: 📌 Ngân sách: 2,860,000,000đ | Mục tiêu: 2,400 leads / 720 tours
B18: 1 | C18: Marketing | D18: Scale campaign thắng tháng 4 | E18: Top 5 adset/campaign → +20-30% budget | KPI-based scaling | F18: Budget scaled | G18: 05/05 | H18: ☐
B19: 2 | C19: Marketing | D19: Mở competitor search | E19: THPT GV chọn lọc | Landing compare mềm | Budget riêng | F19: CPL competitor | G19: 07/05 | H19: ☐
B20: 3 | C20: Marketing | D20: Webinar #2 (THPT) | E20: Chủ đề: Tuyển sinh lớp 10, học bổng | 120+ đăng ký | F20: 120 reg | G20: 14/05 | H20: ☐
B21: 4 | C21: Marketing | D21: TikTok scale top videos | E21: Top 5 video by CPV → Spark Ads | Budget TikTok +30% | F21: CPV ≤2k | G21: 10/05 | H21: ☐
B22: 5 | C22: Tuyển sinh | D22: Open Day #1 | E22: Tổ chức open campus event | PR + paid + Zalo broadcast | F22: 50+ phụ huynh | G22: 17/05 | H22: ☐
B23: 6 | C23: Campus | D23: Zalo broadcast tỉnh | E23: Blast toàn bộ Zalo OA subscriber tỉnh | Mời tour tháng 6 | F23: Open ≥40% | G23: 20/05 | H23: ☐
B24: 7 | C24: Marketing | D24: Remarketing ramp-up | E24: Bật strong retarget: học phí visitors, form-not-submit, video viewers | F24: ROAS tracking | G24: 15/05 | H24: ☐
B25: 8 | C25: Management | D25: Mid-month review tháng 5 | E25: Check 53% target lead | Lead→Tour rate | School tour quality | F25: Decision | G25: 15/05 | H25: ☐
B26: 9 | C26: Management | D26: Monthly review tháng 5 | E26: Full KPI review | Budget reallocation tháng 6 | Creative refresh plan | F26: Report + plan | G26: 31/05 | H26: ☐
B28: THÁNG 6/2026 – CAO ĐIỂM TOUR
B29: 📌 Ngân sách: 3,120,000,000đ | Mục tiêu: 2,800 leads / 840 tours | Check 53% target
B30: 1 | C30: Marketing | D30: Tăng ngân sách THCS/THPT | E30: THCS PN, THCS GV, THPT GV → +25-30% | Dựa trên booked tour data | F30: Budget adj | G30: 01/06 | H30: ☐
B31: 2 | C31: Marketing | D31: Test PMax nhỏ | E31: PMax test 2% Google budget | Chỉ cho THPT | Track riêng quality | F31: Lead quality | G31: 07/06 | H31: ☐
B32: 3 | C32: Marketing | D32: YouTube/Demand Gen scale | E32: Testimonial video THCS/THPT → Retarget | Webinar reminder | F32: View-to-tour | G32: 07/06 | H32: ☐
B33: 4 | C33: Marketing | D33: Webinar #3 (THCS - chuyển cấp) | E33: Lộ trình con tôi học ở đâu sau lớp 5? | 100+ reg | F33: 100 reg | G33: 11/06 | H33: ☐
B34: 5 | C34: Tuyển sinh | D34: Tăng tour slots + staff | E34: Mỗi cơ sở có person phụ trách tour đầy đủ | Cuối tuần +1 slot | F34: Slots full | G34: 05/06 | H34: ☐
B35: 6 | C35: Campus | D35: Open Day #2 | E35: 1 event lớn toàn hệ thống hoặc từng campus | PR mạnh | F35: 100+ phụ huynh | G35: 21/06 | H35: ☐
B36: 7 | C36: Marketing | D36: Creative refresh tháng 6 | E36: Làm mới toàn bộ creative Meta + TikTok sau 4 tuần chạy | F36: New creative | G36: 10/06 | H36: ☐
B37: 8 | C37: Management | D37: Mid-month check 53% target | E37: Nếu <53% cumulative → trigger dự phòng ngân sách | F37: Go/escalate | G37: 15/06 | H37: ☐
B38: 9 | C38: Management | D38: Monthly review tháng 6 | E38: Full KPI | Tour quality | Campus gap analysis | Plan tháng 7 | F38: Report + plan | G38: 30/06 | H38: ☐
B40: THÁNG 7/2026 – CHỐT SALE
B41: 📌 Ngân sách: 2,860,000,000đ | Mục tiêu: 2,400 leads / 720 tours | <73% target → dự phòng
B42: 1 | C42: Marketing | D42: Dồn budget vào high-intent | E42: Học bổng, lớp 6, lớp 10, chốt hồ sơ, deadline | Scale mạnh | F42: CPL stable | G42: 01/07 | H42: ☐
B43: 2 | C43: Marketing | D43: Học bổng campaign | E43: Meta + Google "học bổng lớp 10", "ưu đãi tuyển sinh" | Deadline rõ | F43: Lead quality | G43: 05/07 | H43: ☐
B44: 3 | C44: Tuyển sinh | D44: Retarget pipeline stuck | E44: GHL → Opportunity "No response 7d" → Personal follow-up call | F44: Reactivation | G44: 07/07 | H44: ☐
B45: 4 | C45: Marketing | D45: Brand defense mạnh | E45: Brand search impression share ≥95% | Monitor competitor bids | F45: IS ≥95% | G45: 01/07 | H45: ☐
B46: 5 | C46: Campus | D46: Webinar #4 (THPT học bổng) | E46: Chủ đề học bổng, đầu ra, lộ trình | 120+ reg | Chốt ngay sau | F46: 120 reg | G46: 16/07 | H46: ☐
B47: 6 | C47: Tuyển sinh | D47: 7-day follow-up sequence | E47: Phụ huynh đã tour chưa chốt → 5 điểm chạm trong 7 ngày | F47: Conversion rate | G47: 01/07 | H47: ☐
B48: 7 | C48: Management | D48: Dự phòng ngân sách check | E48: Nếu <73% target → Giải ngân quỹ dự phòng theo kịch bản | F48: Decision | G48: 15/07 | H48: ☐
B49: 8 | C49: Management | D49: Monthly review tháng 7 | E49: Full KPI | Lost reason analysis | Plan tháng 8 chốt cuối | F49: Report + plan | G49: 31/07 | H49: ☐
B51: THÁNG 8/2026 – VÉT CHỈ TIÊU
B52: 📌 Ngân sách: 1,300,000,000đ | Mục tiêu: 1,200 leads / 360 tours | Gần đạt target
B53: 1 | C53: Marketing | D53: Retarget mạnh database cũ | E53: Toàn bộ leads chưa enroll → Remarketing 7d + email + Zalo | F53: Reactivation | G53: 01/08 | H53: ☐
B54: 2 | C54: Marketing | D54: Landing "số chỗ có hạn" | E54: Urgency landing page | CTA "Chốt chỗ ngay" | Countdown timer | F54: CVR boost | G54: 05/08 | H54: ☐
B55: 3 | C55: Marketing | D55: Giảm broad awareness | E55: Tắt cold audience broad | Giữ brand + high-intent + retarget | F55: Budget efficient | G55: 01/08 | H55: ☐
B56: 4 | C56: Tuyển sinh | D56: Gọi lại toàn bộ pending | E56: GHL filter: tour attended nhưng chưa deposit → Personal call | F56: Conversion | G56: 03/08 | H56: ☐
B57: 5 | C57: Campus | D57: Cập nhật số chỗ real-time | E57: Marketing cần biết campus nào còn chỗ → Daily update | F57: Transparency | G57: 01/08 | H57: ☐
B58: 6 | C58: Management | D58: CAC final review từng campus | E58: Tính CAC thực từ spend + tour + enroll | So với target | F58: CAC report | G58: 15/08 | H58: ☐
B59: 7 | C59: Management | D59: Monthly review tháng 8 | E59: Full KPI | Forecast tháng 9 | Late intake plan | Post-mortem prep | F59: Report + plan | G59: 31/08 | H59: ☐
B61: THÁNG 9/2026 – LATE INTAKE + KẾT MÙA
B62: 📌 Ngân sách: 520,000,000đ | Mục tiêu: 400 leads / 120 tours | Late intake + chuyển trường
B63: 1 | C63: Marketing | D63: Chuyển trường campaign | E63: "Chuyển trường THPT", "còn nhận hồ sơ", "nhập học muộn" | F63: Late leads | G63: 01/09 | H63: ☐
B64: 2 | C64: Marketing | D64: Brand search only Google | E64: Chỉ giữ brand + late-intent | Cắt generic broad | F64: CPL efficient | G64: 01/09 | H64: ☐
B65: 3 | C65: Tuyển sinh | D65: Reactivation database | E65: Gọi lại ALL leads từ tháng 4-8 chưa enroll | Personal touch | F65: Reactivation | G65: 05/09 | H65: ☐
B66: 4 | C66: Campus | D66: Late enrollment process | E66: Quy trình hồ sơ nhanh 48h | Brief staff xử lý gấp | F66: Process ready | G66: 01/09 | H66: ☐
B67: 5 | C67: Management | D67: Post-mortem session | E67: Full mùa review: Kênh nào thắng? Kênh nào waste? Học gì? | F67: Learnings doc | G67: 25/09 | H67: ☐
B68: 6 | C68: Management | D68: Kế hoạch 2027 đề xuất | E68: Dựa trên data thực → Đề xuất ngân sách, kênh, campus, KPI 2027 | F68: Draft plan | G68: 30/09 | H68: ☐

Sheet E. Campaign Tracker
B1: 📊 CAMPAIGN TRACKER – THEO DÕI TỪNG CAMPAIGN THEO TUẦN (GOOGLE + META + TIKTOK + ZALO)
B2: Nhập dữ liệu thực tế mỗi tuần vào cột tương ứng. Cột màu xanh = auto-calculated. Liên kết với A. KPI Weekly Tracker.
B3: Campaign Name | C3: Kênh | D3: Campus | E3: Spend (đ) | F3: Impressions | G3: Clicks | H3: CTR | I3: Leads | J3: Q.Leads | K3: CPL (đ) | L3: Q.Rate | M3: Tours | N3: Cost/Tour | O3: Enrolls | P3: Status
B4: S_BRAND_System | C4: G.Search | D4: Hệ thống | E4: 0 | F4: 0 | G4: 0 | H4: =IF(F4>0,G4/F4,0) -> 0 | I4: 0 | J4: 0 | K4: =IF(I4>0,E4/I4,0) -> 0 | L4: =IF(I4>0,J4/I4,0) -> 0 | M4: 0 | N4: =IF(M4>0,E4/M4,0) -> 0 | O4: 0 | P4: ☐ Active
B5: S_MN_GV_Brand | C5: G.Search | D5: MN GV | E5: 0 | F5: 0 | G5: 0 | H5: =IF(F5>0,G5/F5,0) -> 0 | I5: 0 | J5: 0 | K5: =IF(I5>0,E5/I5,0) -> 0 | L5: =IF(I5>0,J5/I5,0) -> 0 | M5: 0 | N5: =IF(M5>0,E5/M5,0) -> 0 | O5: 0 | P5: ☐ Active
B6: S_MN_GV_Generic | C6: G.Search | D6: MN GV | E6: 0 | F6: 0 | G6: 0 | H6: =IF(F6>0,G6/F6,0) -> 0 | I6: 0 | J6: 0 | K6: =IF(I6>0,E6/I6,0) -> 0 | L6: =IF(I6>0,J6/I6,0) -> 0 | M6: 0 | N6: =IF(M6>0,E6/M6,0) -> 0 | O6: 0 | P6: ☐ Active
B7: S_MN_GV_HighIntent | C7: G.Search | D7: MN GV | E7: 0 | F7: 0 | G7: 0 | H7: =IF(F7>0,G7/F7,0) -> 0 | I7: 0 | J7: 0 | K7: =IF(I7>0,E7/I7,0) -> 0 | L7: =IF(I7>0,J7/I7,0) -> 0 | M7: 0 | N7: =IF(M7>0,E7/M7,0) -> 0 | O7: 0 | P7: ☐ Active
B8: S_TH_GV_Generic | C8: G.Search | D8: TH GV | E8: 0 | F8: 0 | G8: 0 | H8: =IF(F8>0,G8/F8,0) -> 0 | I8: 0 | J8: 0 | K8: =IF(I8>0,E8/I8,0) -> 0 | L8: =IF(I8>0,J8/I8,0) -> 0 | M8: 0 | N8: =IF(M8>0,E8/M8,0) -> 0 | O8: 0 | P8: ☐ Active
B9: S_TH_GV_HighIntent | C9: G.Search | D9: TH GV | E9: 0 | F9: 0 | G9: 0 | H9: =IF(F9>0,G9/F9,0) -> 0 | I9: 0 | J9: 0 | K9: =IF(I9>0,E9/I9,0) -> 0 | L9: =IF(I9>0,J9/I9,0) -> 0 | M9: 0 | N9: =IF(M9>0,E9/M9,0) -> 0 | O9: 0 | P9: ☐ Active
B10: S_TH_BT_Generic | C10: G.Search | D10: TH BT | E10: 0 | F10: 0 | G10: 0 | H10: =IF(F10>0,G10/F10,0) -> 0 | I10: 0 | J10: 0 | K10: =IF(I10>0,E10/I10,0) -> 0 | L10: =IF(I10>0,J10/I10,0) -> 0 | M10: 0 | N10: =IF(M10>0,E10/M10,0) -> 0 | O10: 0 | P10: ☐ Active
B11: S_TH_BT_HighIntent | C11: G.Search | D11: TH BT | E11: 0 | F11: 0 | G11: 0 | H11: =IF(F11>0,G11/F11,0) -> 0 | I11: 0 | J11: 0 | K11: =IF(I11>0,E11/I11,0) -> 0 | L11: =IF(I11>0,J11/I11,0) -> 0 | M11: 0 | N11: =IF(M11>0,E11/M11,0) -> 0 | O11: 0 | P11: ☐ Active
B12: S_THCS_GV_Generic | C12: G.Search | D12: THCS GV | E12: 0 | F12: 0 | G12: 0 | H12: =IF(F12>0,G12/F12,0) -> 0 | I12: 0 | J12: 0 | K12: =IF(I12>0,E12/I12,0) -> 0 | L12: =IF(I12>0,J12/I12,0) -> 0 | M12: 0 | N12: =IF(M12>0,E12/M12,0) -> 0 | O12: 0 | P12: ☐ Active
B13: S_THCS_GV_HighIntent | C13: G.Search | D13: THCS GV | E13: 0 | F13: 0 | G13: 0 | H13: =IF(F13>0,G13/F13,0) -> 0 | I13: 0 | J13: 0 | K13: =IF(I13>0,E13/I13,0) -> 0 | L13: =IF(I13>0,J13/I13,0) -> 0 | M13: 0 | N13: =IF(M13>0,E13/M13,0) -> 0 | O13: 0 | P13: ☐ Active
B14: S_THCS_GV_Webinar | C14: G.Search | D14: THCS GV | E14: 0 | F14: 0 | G14: 0 | H14: =IF(F14>0,G14/F14,0) -> 0 | I14: 0 | J14: 0 | K14: =IF(I14>0,E14/I14,0) -> 0 | L14: =IF(I14>0,J14/I14,0) -> 0 | M14: 0 | N14: =IF(M14>0,E14/M14,0) -> 0 | O14: 0 | P14: ☐ Active
B15: S_THPT_GV_Generic | C15: G.Search | D15: THPT GV | E15: 0 | F15: 0 | G15: 0 | H15: =IF(F15>0,G15/F15,0) -> 0 | I15: 0 | J15: 0 | K15: =IF(I15>0,E15/I15,0) -> 0 | L15: =IF(I15>0,J15/I15,0) -> 0 | M15: 0 | N15: =IF(M15>0,E15/M15,0) -> 0 | O15: 0 | P15: ☐ Active
... B42: Zalo_THPT_Webinar | C42: Zalo | D42: THPT GV | E42: 0 | F42: 0 | G42: 0 | H42: =IF(F42>0,G42/F42,0) -> 0 | I42: 0 | J42: 0 | K42: =IF(I42>0,E42/I42,0) -> 0 | L42: =IF(I42>0,J42/I42,0) -> 0 | M42: 0 | N42: =IF(M42>0,E42/M42,0) -> 0 | O42: 0 | P42: ☐ Active
B43: 📊 TỔNG CỘNG | E43: =SUM(E4:E42) -> 0 | F43: =SUM(F4:F42) -> 0 | G43: =SUM(G4:G42) -> 0 | I43: =SUM(I4:I42) -> 0 | J43: =SUM(J4:J42) -> 0 | M43: =SUM(M4:M42) -> 0 | O43: =SUM(O4:O42) -> 0

Sheet F. Meta Ads Plan
B1: 📱 KẾ HOẠCH META ADS CHI TIẾT – 04/2026 → 09/2026 (Facebook + Instagram)
B2: Tổng ngân sách Meta: 3,230,000,000đ (38% Paid Media) | CPL mục tiêu: 120,000đ | Kênh chủ lực tạo demand + lead
B4: 💰 NGÂN SÁCH META THEO THÁNG (04-09/2026)
B5: Tháng | C5: % NS tháng | D5: Ngân sách Meta | E5: Trọng tâm | F5: Kênh ưu tiên | G5: KPI Lead | H5: KPI Tour
B6: Tháng 4 | C6: 0.1 | D6: 323000000 | E6: Setup + test creative | Prospecting cold | F6: Prospecting, Lead Gen | G6: 450 | H6: 135
B7: Tháng 5 | C7: 0.2 | D7: 646000000 | E7: Scale lead | Open Day | Webinar push | F7: Lookalike + Webinar | G7: 900 | H7: 270
B8: Tháng 6 | C8: 0.26 | D8: 839800000 | E8: Tour cao điểm | Remarket mạnh | F8: Retarget + High Intent | G8: 1100 | H8: 330
B9: Tháng 7 | C9: 0.24 | D9: 775200000 | E9: Chốt sale | Học bổng | Pipeline | F9: Remarketing + Deadline | G9: 1000 | H9: 300
B10: Tháng 8 | C10: 0.14 | D10: 452200000 | E10: Vét cuối | Retarget database | F10: Heavy Remarketing | G10: 600 | H10: 180
B11: Tháng 9 | C11: 0.06 | D11: 193800000 | E11: Late intake | Chuyển trường | Brand | F11: Brand + Late Intent | G11: 200 | H11: 60
B12: TỔNG | C12: 1 | D12: 3230000000 | G12: =SUM(G6:G11) -> 4250 | H12: =SUM(H6:H11) -> 1275
B14: 🗂️ CẤU TRÚC CAMPAIGN META ADS – PHÂN THEO CƠ SỞ + MỤC TIÊU
B15: Campaign | C15: Objective | D15: Audience | E15: Creative | F15: Budget/tháng | G15: GHL Pipeline | H15: KPI chính
B16: MN_GV_LeadGen | C16: Lead Gen | D16: Geo 5km MN GV | Age 25-40 | Parenting | LA 1-3% | E16: Video testi 15-30s + Carousel + Lead form | F16: 134583333 | G16: Pipeline MN | H16: CPL <120k, Tour/tháng
B17: MN_NL_Local | C17: Lead Gen | D17: Geo Cần Giuộc-Tây Ninh | Age 25-40 | Local | E17: Ảnh campus + text local | Lead form VN | F17: 40416667 | G17: Pipeline MN NL | H17: CPL <100k
B18: MN_TS_Local | C18: Lead Gen | D18: Geo KDC Thái Sơn | Age 25-40 | Parenting | E18: Image + text đơn giản | Hotline CTA | F18: 40416667 | G18: Pipeline MN TS | H18: CPL <100k
B19: MN_MX_Local | C19: Lead Gen | D19: Geo Rạch Giá-An Giang | Age 25-40 | E19: Ảnh campus + lead form | Local dialect | F19: 40416667 | G19: Pipeline MN MX | H19: CPL <90k
B20: TH_GV_LeadGen | C20: Lead Gen | D20: Geo Gò Vấp | Age 28-42 | Education parent | E20: Video "Nền tảng lớp 1" + Carousel + Form | F20: 100416667 | G20: Pipeline TH GV | H20: CPL <130k
B21: TH_BT_LeadGen | C21: Lead Gen | D21: Geo Bình Tân | Age 28-42 | Parents | E21: Image + text | School tour CTA | F21: 100416667 | G21: Pipeline TH BT | H21: CPL <130k
B22: TH_Tinh_Local | C22: Lead Gen | D22: Geo Tây Ninh + An Giang | Age 28-42 | E22: Local image + text | Hotline + form | F22: 60833333 | G22: Pipeline TH Tỉnh | H22: CPL <100k
B23: THCS_GV_LeadGen | C23: Lead Gen | D23: Geo GV+5km | Age 32-48 | HS cấp 1 parent | E23: Video testi "Chuyển cấp" + Lead form | F23: 154166667 | G23: Pipeline THCS | H23: CPL <160k
B24: THCS_GV_Webinar | C24: Lead Generation | D24: Geo HCM | Age 32-48 | Education | E24: Video webinar invitation + Carousel benefits | F24: 50000000 | G24: Pipeline Webinar | H24: Reg <50k
B25: THPT_GV_LeadGen | C25: Lead Gen | D25: Geo GV+HCM | Age 36-52 | Lớp 9 parent | E25: Video "Lộ trình THPT" + Lead form | F25: 270583333 | G25: Pipeline THPT | H25: CPL <180k
B26: THPT_GV_Webinar | C26: Lead Generation | D26: Geo HCM+Tỉnh | Age 36-52 | E26: Video webinar invitation "Chọn trường lớp 10" | F26: 90000000 | G26: Pipeline Webinar | H26: Reg <50k
B27: THPT_HocBong | C27: Lead Gen | D27: Geo HCM | Age 36-52 | Edu, competition | E27: Image học bổng + USP + deadline | F27: 50000000 | G27: Pipeline HB | H27: CPL <150k
... B31: Brand_Awareness | C31: Awareness | D31: Broad HCM | Age 25-50 | Parents | E31: Brand video <15s | USP overlay | F31: 150000000 | G31: - | H31: CPM, Recall
B34: 🎯 KPI MỤC TIÊU META ADS THEO THÁNG
B35: KPI | C35: Tháng 4 | D35: Tháng 5 | E35: Tháng 6 | F35: Tháng 7 | G35: Tháng 8 | H35: Tháng 9
B36: CPL mục tiêu (đ) | C36: 150000 | D36: 135000 | E36: 120000 | F36: 120000 | G36: 130000 | H36: 150000
B37: CTR mục tiêu | C37: 1.2% | D37: 1.5% | E37: 1.8% | F37: 1.8% | G37: 1.5% | H37: 1.2%
B38: CPM mục tiêu (đ) | C38: 80000 | D38: 75000 | E38: 70000 | F38: 70000 | G38: 75000 | H38: 80000
B39: Leads/tháng | C39: 450 | D39: 900 | E39: 1100 | F39: 1000 | G39: 600 | H39: 200
B40: Qualified Rate | C40: 40% | D40: 45% | E40: 50% | F40: 50% | G40: 48% | H40: 45%
B41: Booked Tour/tháng | C41: 90 | D41: 180 | E41: 220 | F41: 200 | G41: 120 | H41: 40
B42: Cost/Tour mục tiêu | C42: 1800000 | D42: 1500000 | E42: 1200000 | F42: 1200000 | G42: 1500000 | H42: 2000000

Sheet G. Google Ads Plan
B1: 🔍 KẾ HOẠCH GOOGLE ADS CHI TIẾT – 04/2026 → 09/2026 (Search + Display + YouTube + PMax)
B2: Google Search: 1,530,000,000đ | G.Display/YouTube: 595,000,000đ | Tổng: 2,125,000,000đ | CPL mục tiêu: 180,000đ
B4: 💰 NGÂN SÁCH GOOGLE ADS THEO THÁNG
B5: Tháng | C5: Search | D5: Display/YT | E5: PMax Test | F5: Tổng | G5: Trọng tâm | H5: KPI Lead
B6: 26/03-03/2026 | C6: 60000000 | D6: 15000000 | E6: - | F6: 75000000 | G6: Setup + pilot Brand + GV | H6: 80
B7: Tháng 4 | C7: 220000000 | D7: 55000000 | E7: - | F7: 275000000 | G7: Brand + Generic all campus | H7: 250
B8: Tháng 5 | C8: 365000000 | D8: 91000000 | E8: - | F8: 456000000 | G8: Scale generic + webinar search | H8: 430
B9: Tháng 6 | C9: 430000000 | D9: 107000000 | E9: 11000000 | F9: 548000000 | G9: High intent + PMax test | H9: 510
B10: Tháng 7 | C10: 388000000 | D10: 97000000 | E10: 22000000 | F10: 507000000 | G10: Chốt + học bổng search | H10: 470
B11: Tháng 8 | C11: 164000000 | D11: 41000000 | E11: - | F11: 205000000 | G11: Remarketing + brand defense | H11: 190
B12: Tháng 9 | C12: 73000000 | D12: 18000000 | E12: - | F12: 91000000 | G12: Late intent + chuyển trường | H12: 80
B13: TỔNG | C13: =SUM(C6:C12) -> 1700000000 | D13: =SUM(D6:D12) -> 424000000 | F13: =SUM(F6:F12) -> 2157000000 | H13: =SUM(H6:H12) -> 2010
B15: 🎯 KPI MỤC TIÊU GOOGLE ADS THEO THÁNG
B16: KPI | C16: T4 | D16: T5 | E16: T6 | F16: T7 | G16: T8 | H16: T9
B17: CTR Search mục tiêu | C17: 6% | D17: 8% | E17: 10% | F17: 10% | G17: 8% | H17: 7%
B18: CPL mục tiêu (đ) | C18: 200000 | D18: 185000 | E18: 175000 | F18: 175000 | G18: 180000 | H18: 200000
B19: Qualified Rate | C19: 45% | D19: 50% | E19: 55% | F19: 55% | G19: 50% | H19: 48%
B20: Landing CVR | C20: 4% | D20: 6% | E20: 8% | F20: 8% | G20: 7% | H20: 5%
B21: Leads Google/tháng | C21: 250 | D21: 430 | E21: 510 | F21: 470 | G21: 190 | H21: 80
B22: Cost/Booked Tour | C22: 2000000 | D22: 1700000 | E22: 1400000 | F22: 1400000 | G22: 1700000 | H22: 2200000
B23: Brand IS mục tiêu | C23: 80% | D23: 85% | E23: 90% | F23: 90% | G23: 90% | H23: 85%

Sheet H. Birch + GHL Integration
B1: ⚙️ BIRCH + GOHIGHLEVEL – INTEGRATION SETUP + AUTOMATION RULES
B3: 🎛️ BIRCH CONTROL TOWER – GIÁ TRỊ ĐIỀU KHIỂN (Google Sheets single-value cells)
B4: Cell | C4: Tên biến | D4: Giá trị | E4: Ý nghĩa | F4: Cập nhật khi | G4: Owner
B5: B2 | C5: current_month_budget | D5: 1530000000 | E5: Ngân sách Google Search tháng hiện tại | F5: Đầu tháng | G5: Marketing Lead
B6: B3 | C6: remaining_budget | D6: 0 | E6: Ngân sách còn lại (nhập tay hoặc tính) | F6: Hàng tuần | G6: Perf. Marketer
B7: B4 | C7: account_cpl_target | D7: 180000 | E7: CPL mục tiêu toàn account Google | F7: Đầu mùa | G7: Marketing Lead
B8: B5 | C8: cost_per_tour_target | D8: 1500000 | E8: Cost/Booked Tour mục tiêu | F8: Đầu mùa | G8: Marketing Lead
B9: B6 | C9: cac_target | D9: 12000000 | E9: CAC mục tiêu trung bình | F9: Đầu mùa | G9: Management
B10: B7 | C10: min_qualified_rate | D10: 0.5 | E10: Qualified rate tối thiểu để không scale | F10: Đầu mùa | G10: Marketing Lead
B11: B8 | C11: min_booked_tour_rate | D11: 0.2 | E11: Booked tour rate tối thiểu | F11: Đầu mùa | G11: Marketing Lead
B12: B9 | C12: min_showup_rate | D12: 0.6 | E12: Show-up rate tối thiểu | F12: Đầu mùa | G12: Management
B13: B10 | C13: max_daily_scale_pct | D13: 0.15 | E13: Tối đa tăng ngân sách mỗi ngày (15%) | F13: Đầu mùa | G13: Marketing Lead
B14: B11 | C14: max_daily_reduce_pct | D14: 0.15 | E14: Tối đa giảm ngân sách mỗi ngày (15%) | F14: Đầu mùa | G14: Marketing Lead
B15: B12 | C15: pmax_test_cap | D15: 59000000 | E15: Trần ngân sách PMax test | F15: Đầu mùa | G15: Marketing Lead
B16: B13 | C16: brand_is_target | D16: 0.9 | E16: Brand impression share tối thiểu cần giữ | F16: Đầu mùa | G16: Marketing Lead
B19: 🤖 10 AUTOMATION RULES MẪU – BIRCH GOOGLE ADS
B20: # | C20: Tên Rule | D20: Điều kiện (Conditions) | E20: Hành động (Action) | F20: Scope | G20: Priority | H20: Status
B21: R01 | C21: ALERT – CPL Quá Cao | D21: Spend 3 ngày > 500k | CPL > target 120% | Leads > 0 | E21: Gửi cảnh báo Slack + Email ngay | KHÔNG tự thay đổi budget | F21: Campaign (All Search) | G21: Very High | H21: 🟢 Active
B22: R02 | C22: ALERT – Zero Lead Alarm | D22: Spend 2 ngày > threshold | Leads = 0 | Not paused | E22: Gửi cảnh báo khẩn | Pause ad group nếu sau 24h không có lead | F22: Ad Group | G22: Very High | H22: 🟢 Active
B23: R03 | C23: ALERT – Brand IS Drop | D23: Brand campaign | Impression Share < 80% | Any day | E23: Gửi cảnh báo | Increase brand campaign budget +20% | F23: Campaign (Brand) | G23: Very High | H23: 🟢 Active
B24: R04 | C24: SCALE – Campaign Thắng | D24: CPL <= target | Qualified Rate (Sheets) >= 50% | Booked Tour (Sheets) >= 2/tuần | Spend ổn định 5 ngày | E24: Increase daily budget +15% | Max 1 lần/ngày | Không vượt cap từ Sheets | F24: Campaign (Search) | G24: High | H24: 🟡 Review 1st
B25: R05 | C25: REDUCE – Campaign Yếu | D25: CPL > target +25% | Spend > min threshold | Qualified Rate < 40% | E25: Reduce daily budget -15% | Gửi notify | Review landing page | F25: Campaign (Search) | G25: High | H25: 🟡 Review 1st
B26: R06 | C26: PAUSE – Keyword Lãng Phí | D26: Keyword spend > 300k | Conversions = 0 | CPC > avg +50% | E26: Pause keyword | Add to review list | Gửi notify | F26: Keyword | G26: Medium | H26: 🟢 Active
B27: R07 | C27: WEBINAR – Scale Pre-Event | D27: Webinar campaign | Reg Cost trong target | Event date còn 3-7 ngày | E27: Increase budget +25% | Priority: THCS/THPT | Run 48h before event | F27: Campaign (Webinar) | G27: High | H27: 🟡 Review 1st
B28: R08 | C28: PMAX – Test Controlled | D28: PMax campaign | CPL > Search CPL + 30% | Spend > cap từ Sheets | E28: Reduce PMax budget | Protect Search budget | Alert team | F28: Campaign (PMax) | G28: Medium | H28: 🔴 Manual only
B29: R09 | C29: REMARKETING – Activation | D29: Display/RLSA remarketing | Audience size > 1000 | CTR < 0.5% | E29: Refresh creative assets | Notify content team | Try new message | F29: Campaign (Display) | G29: Medium | H29: 🟢 Active
B30: R10 | C30: BRAND – Always-On Guard | D30: Brand campaign | Budget remaining < 20% | Day < 25th month | E30: Increase brand budget từ general pool | Ensure IS ≥ 90% | F30: Campaign (Brand) | G30: Very High | H30: 🟢 Active
B32: 🔄 WEBHOOK PAYLOAD – GHL → GOOGLE SHEETS
A33: Field | B33: GHL Source | C33: Sheet Column | D33: Data Type | E33: Dùng cho | F33: Ví dụ
A34: timestamp | B34: Workflow timestamp | C34: A | D34: DateTime | E34: Time-series analysis | F34: 2026-04-15T09:30:00
A35: contact_id | B35: Contact ID | C35: B | D35: String | E35: Deduplication | F35: abc123xyz
A36: contact_name | B36: Contact Name | C36: C | D36: String | E36: Reference | F36: Nguyễn Văn A
A37: phone | B37: Contact Phone | C37: D | D37: String | E37: Match with ads click ID | F37: 0901234567
A38: email | B38: Contact Email | C38: E | D38: String | E38: Match + exclusion | F38: a@email.com
A39: campus | B39: Custom Field: Campus | C39: F | D39: String | E39: Campus-level reporting | F39: MN GV
A40: grade | B40: Custom Field: Grade | C40: G | D40: String | E40: Grade-level reporting | F40: MN
A41: source_channel | B41: Custom Field: Source Channel | C41: H | D41: String | E41: Attribution | F41: google_search
A42: campaign_id | B42: Custom Field: Campaign ID | C42: I | D42: String | E42: Campaign-level quality | F42: S_MN_GV_Generic
A43: campaign_name | B43: Custom Field: Campaign Name | C43: J | D43: String | E43: Readable name | F43: Search MN GV Generic
A44: keyword_theme | B44: Custom Field: Keyword Theme | C44: K | D44: String | E44: Keyword quality analysis | F44: generic
... A52: utm_campaign | B52: Hidden field / UTM | C52: S | D52: String | E52: Campaign attribution | F52: S_MN_GV_Generic
B55: 📊 BIRCH AUTOMATION RULES – CHI TIẾT
A56: Rule Name | B56: IF Condition | C56: AND Condition | D56: Time Window | E56: THEN Action | F56: Alert Channel | G56: Frequency | H56: Priority
A57: CPL High Alert | B57: CPL > target × 1.2 | C57: Spend > 500,000/day | D57: 3 days rolling | E57: Send alert + Tag campaign for review | F57: Slack + Email | G57: Daily check | H57: 🔴 High
A58: Zero Lead Alert | B58: Leads = 0 | C58: Spend > 500,000 | D58: 3 days rolling | E58: Send alert + Auto-pause if 5 days | F58: Slack + Email | G58: Daily check | H58: 🔴 High
A59: Scale Winner | B59: CPL < target × 0.8 | C59: Qualified Rate > 50% | D59: 7 days rolling | E59: Increase budget +15% | F59: Email notification | G59: Weekly | H59: 🟡 Medium
A60: Pause Loser | B60: CPL > target × 1.3 | C60: Tour Rate < 10% | D60: 5 days rolling | E60: Decrease budget -15% → Pause if persists | F60: Slack + Email | G60: Daily | H60: 🔴 High
A61: KW Waste Pause | B61: Keyword Spend > 500K | C61: Conversions = 0 | D61: 14 days | E61: Pause keyword | F61: Email log | G61: Weekly | H61: 🟡 Medium
A62: Brand Always-On | B62: Brand campaign paused/limited | C62: - | D62: Immediate | E62: Alert + Auto-enable | F62: Slack immediate | G62: Real-time | H62: 🔴 Critical
A63: Budget Pacing | B63: Monthly spend > 80% by mid-month | C63: - | D63: Monthly | E63: Alert + Suggest reduction | F63: Email + Slack | G63: Bi-weekly | H63: 🟡 Medium
A64: Campus Gap | B64: Campus X enrollment < 80% monthly target | C64: - | D64: Mid-month | E64: Alert + Suggest budget shift | F64: Email to management | G64: Monthly | H64: 🟡 Medium
A65: Quality Score Drop | B65: QS drops below 5 on top KWs | C65: Impression share drops | D65: 7 days | E65: Alert + Review ad/LP relevance | F65: Email | G65: Weekly | H65: 🟡 Medium
A66: Weekend Adjust | B66: Weekend (Sat-Sun) | C66: - | D66: Auto | E66: Reduce budget to 70% (lower intent) | F66: Auto-rule | G66: Weekly cycle | H66: 🟢 Low

Sheet J. Webinar Chi Tiết
A1: KẾ HOẠCH WEBINAR CHI TIẾT – TUYỂN SINH VIỆT ANH 2026
A2: Ngân sách Webinar Ads: 425,000,000đ (5%) | Mục tiêu: 6 webinar chính + 2 bổ sung | Target: 800+ registrations tổng | Kênh quảng bá: Meta + Google + Zalo + Email
A4: A. LỊCH WEBINAR 7 THÁNG (04-09/2026)
A5: # | B5: Tên Webinar | C5: Cấp học | D5: Ngày dự kiến | E5: Thời gian | F5: Nền tảng | G5: Chủ đề chính | H5: Diễn giả | I5: Mục tiêu Reg | J5: Mục tiêu Attend | K5: Attend Rate | L5: CTA sau webinar | M5: Ngân sách Ads | N5: Kênh quảng bá | O5: GHL Workflow | P5: Trạng thái
A6: 1 | B6: Lộ trình con tôi sau lớp 5 | C6: THCS | D6: 15/04/2026 | E6: 19:30-21:00 | F6: Zoom + Facebook Live | G6: Chuyển cấp 5→6: Tâm lý, chương trình, tiêu chí chọn trường | H6: BGH THCS + PH cựu HS | I6: 120 | J6: 72 | K6: 60% | L6: Book tour THCS GV | M6: 60000000 | N6: Meta+Google+Zalo+Email | O6: Webinar sequence | P6: ☐
A7: 2 | B7: Tuyển sinh lớp 10 – Học bổng & Lộ trình ĐH | C7: THPT | D7: 22/04/2026 | E7: 19:30-21:00 | F7: Zoom + Facebook Live | G7: Lớp 10 tư thục vs công lập, học bổng, đầu ra ĐH | H7: BGH THPT + Alumni ĐH top | I7: 150 | J7: 90 | K7: 60% | L7: Thi học bổng lớp 10 | M7: 75000000 | N7: Meta+Google+Zalo+Email | O7: Webinar sequence | P7: ☐
A8: 3 | B8: Mầm non song ngữ – Nền tảng vàng 0-6 tuổi | C8: MN | D8: 06/05/2026 | E8: 19:30-20:30 | F8: Zoom + Facebook Live | G8: Phát triển ngôn ngữ sớm, tiêu chí chọn MN an toàn | H8: Chuyên gia GD mầm non + GV MN VA | I8: 100 | J8: 65 | K8: 65% | L8: Book tour MN | M8: 40000000 | N8: Meta+Zalo+TikTok | O8: Webinar sequence | P8: ☐
A9: 4 | B9: Chọn trường tiểu học – Điều PH cần biết | C9: TH | D9: 14/05/2026 | E9: 19:30-21:00 | F9: Zoom + Facebook Live | G9: Tiêu chí chọn trường TH, song ngữ, sĩ số, ngoại khóa | H9: BGH TH + PH hiện tại | I9: 120 | J9: 72 | K9: 60% | L9: Book tour TH GV/BT | M9: 50000000 | N9: Meta+Google+Zalo | O9: Webinar sequence | P9: ☐
A10: 5 | B10: THCS – Giai đoạn bản lề quyết định tương lai | C10: THCS | D10: 11/06/2026 | E10: 19:30-21:00 | F10: Zoom + Facebook Live | G10: Dậy thì & học tập, lộ trình THCS→THPT liên cấp | H10: GV chủ nhiệm THCS + Tâm lý GD | I10: 130 | J10: 78 | K10: 60% | L10: Book tour THCS | M10: 55000000 | N10: Meta+Google+Zalo | O10: Webinar sequence | P10: ☐
A11: 6 | B11: Học bổng THPT 2026 – Cơ hội cuối | C11: THPT | D11: 16/07/2026 | E11: 19:30-21:00 | F11: Zoom + Facebook Live | G11: Deadline học bổng, pathway du học, ĐH top | H11: BGH + Counselor du học | I11: 160 | J11: 96 | K11: 60% | L11: Đăng ký thi HB ngay | M11: 80000000 | N11: Meta+Google+Zalo+Email | O11: Webinar + Scholarship | P11: ☐
A12: 7 | B12: Open Day Online – Tour ảo 8 cơ sở | C12: Liên cấp | D12: 21/06/2026 | E12: 09:00-11:00 | F12: Zoom + YouTube Live | G12: Virtual tour tất cả campus, Q&A trực tiếp với BGH | H12: BGH + Campus Manager | I12: 200 | J12: 120 | K12: 60% | L12: Book tour thực tế | M12: 40000000 | N12: Meta+YouTube+Zalo | O12: Webinar sequence | P12: ☐
A13: 8 | B13: Late intake – Còn nhận hồ sơ T9 | C13: THCS/THPT | D13: 03/09/2026 | E13: 19:30-20:30 | F13: Zoom | G13: Chuyển trường, nhập học muộn, quy trình nhanh | H13: BGH + Sales Lead | I13: 80 | J13: 48 | K13: 60% | L13: Liên hệ tư vấn ngay | M13: 25000000 | N13: Meta+Google+Zalo | O13: Late intake seq | P13: ☐
A16: B. QUY TRÌNH TỔ CHỨC WEBINAR (CHECKLIST)
A17: Giai đoạn | B17: Thời gian | C17: Công việc | D17: Chi tiết | E17: Ai làm | F17: Tool | G17: Trạng thái
A18: Trước 3 tuần | B18: T-21 ngày | C18: Chốt chủ đề + diễn giả | D18: Xác nhận topic, outline, diễn giả chính + backup | E18: Marketing Lead | F18: Email/Meeting | G18: ☐
A19: Trước 3 tuần | B19: T-21 ngày | C19: Tạo Landing Page webinar | D19: LP riêng trên GHL hoặc website, form: Tên+SĐT+Email+Cấp | E19: Performance | F19: GHL/WordPress | G19: ☐
A20: Trước 2 tuần | B20: T-14 ngày | C20: Setup Zoom + test | D20: Tạo meeting, test link, backup plan nếu Zoom lỗi | E20: Tech/Admin | F20: Zoom Pro | G20: ☐
A21: Trước 2 tuần | B21: T-14 ngày | C21: Tạo creative ads webinar | D21: 3-5 creative (image + video teaser 15s) cho Meta + Google | E21: Content Creator | F21: Canva/Premiere | G21: ☐
A22: Trước 2 tuần | B22: T-14 ngày | C22: Launch ads webinar | D22: Meta Lead Gen + Google Search "hội thảo" + Zalo broadcast | E22: Performance | F22: Meta+Google+Zalo | G22: ☐
A23: Trước 2 tuần | B23: T-14 ngày | C23: Setup email sequence GHL | D23: Confirm email → Reminder 48h → Reminder 2h → Post-webinar | E23: CRM Executive | F23: GHL Workflow | G23: ☐
A24: Trước 1 tuần | B24: T-7 ngày | C24: Kiểm tra registrations | D24: Check số reg vs target → Tăng budget ads nếu cần | E24: Marketing Lead | F24: GHL + Ads Manager | G24: ☐
A25: Trước 1 tuần | B25: T-7 ngày | C25: Chuẩn bị slide + script | D25: Slide PPT, script cho host, Q&A prep, CTA slide cuối | E25: Content + BGH | F25: PowerPoint | G25: ☐
A26: Trước 1 tuần | B26: T-7 ngày | C26: SMS reminder blast | D26: Gửi SMS nhắc tất cả registrants | E26: CRM Executive | F26: GHL SMS | G26: ☐
A27: Ngày webinar | B27: T-2h | C27: Zalo reminder | D27: Broadcast Zalo OA nhắc nhở + link Zoom | E27: CRM Executive | F27: GHL/Zalo | G27: ☐
A28: Ngày webinar | B28: T-30 phút | C28: Tech check cuối | D28: Test camera, mic, slide share, backup internet | E28: Tech/Admin | F28: Zoom | G28: ☐
... A35: Sau 1 tuần | B35: T+7 ngày | C35: Nurture sequence tiếp | D35: Attendees chưa tour → SMS Day 7 → Zalo Day 10 → Email Day 14 | E35: CRM Executive | F35: GHL Workflow | G35: ☐
A38: C. KPI WEBINAR THEO THÁNG
A39: KPI | B39: Tháng 4 | C39: Tháng 5 | D39: Tháng 6 | E39: Tháng 7 | F39: Tháng 8 | G39: Tháng 9 | H39: TỔNG
A40: Số webinar | B40: 2 | C40: 2 | D40: 2 | E40: 1 | F40: 0 | G40: 1 | H40: 8
A41: Registrations | B41: 270 | C41: 220 | D41: 330 | E41: 160 | F41: 0 | G41: 80 | H41: 1060
A42: Attend rate | B42: 60% | C42: 62% | D42: 60% | E42: 60% | F42: - | G42: 60% | H42: 60%
A43: Attendees | B43: 162 | C43: 137 | D43: 198 | E43: 96 | F43: 0 | G43: 48 | H43: 641
A44: Tours booked từ WB | B44: 65 | C44: 55 | D44: 79 | E44: 38 | F44: 0 | G44: 19 | H44: 256
A45: Cost/Registration | B45: 50000 | C45: 45000 | D45: 42000 | E45: 50000 | F45: - | G45: 31250 | H45: -
A46: Ngân sách Ads | B46: 135000000 | C46: 90000000 | D46: 95000000 | E46: 80000000 | F46: 0 | G46: 25000000 | H46: 425000000

Sheet K. Social Media Calendar
A1: LỊCH SOCIAL MEDIA CHI TIẾT – THEO KÊNH VÀ ĐỊA ĐIỂM (04-09/2026)
A2: Mục tiêu: 3-4 bài/ngày trên mỗi nền tảng | Kho sẵn: 2,000 bài | Quay mới: 3-5 video/tháng | Tổng: ~540 bài organic trong 6 tháng
A4: A. LỊCH ĐĂNG BÀI TUẦN MẪU (Template cho mỗi tuần)
A5: Thứ | B5: Facebook Page | C5: Instagram | D5: TikTok | E5: Zalo OA | F5: YouTube | G5: Google Business | H5: Thời gian đăng | I5: Loại nội dung | J5: Cơ sở focus | K5: Ghi chú
A6: Thứ 2 | B6: Carousel: Chương trình học (MN/TH) | C6: Reel: "1 ngày tại VA" 30s | D6: Video testi PH 15-30s | E6: Broadcast: Tour tuần này | F6: - | G6: Post: Ảnh campus + CTA | H6: 7:30 + 11:30 + 19:00 | I6: Educational + Social proof | J6: Gò Vấp | K6: Đầu tuần = boost engagement
A7: Thứ 3 | B7: Video: Testimonial PH 60s | C7: Story: Behind-the-scene GV | D7: Carousel: Top 5 lý do chọn VA | E7: Article: Tips chọn trường | F7: - | G7: - | H7: 7:30 + 12:00 + 20:00 | I7: Trust building | J7: Bình Tân + Tỉnh | K7: Zalo article dài, SEO friendly
A8: Thứ 4 | B8: Image: Ảnh hoạt động ngoại khóa | C8: Reel: "GV nói gì về VA" 15s | D8: Video: Day-in-the-life HS | E8: - | F8: Short: Campus tour 60s | G8: Post: Sự kiện sắp tới | H8: 7:30 + 11:30 + 19:30 | I8: Lifestyle + Campus life | J8: Gò Vấp | K8: Hump day = giải trí nhẹ
A9: Thứ 5 | B9: Carousel: So sánh (không nêu tên đối thủ) | C9: Story: Q&A PH thường hỏi | D9: Video testi HS 15-30s | E9: Broadcast: Ưu đãi/Webinar | F9: - | G9: - | H9: 7:30 + 12:00 + 19:00 | I9: Decision support | J9: Liên cấp | K9: Push ưu đãi cuối tuần
A10: Thứ 6 | B10: Video: Highlight tuần (recap) | C10: Reel: Thành tích HS/GV | D10: Video: "3 điều PH không ngờ" | E10: Broadcast: Nhắc tour cuối tuần | F10: Video: Webinar recap/teaser | G10: Post: Review mới từ PH | H10: 7:30 + 11:30 + 20:00 | I10: Achievement + Urgency | J10: Thái Sơn + Mekong | K10: Friday = ưu đãi weekend
A11: Thứ 7 | B11: Live: Tour campus trực tiếp 30 phút | C11: Carousel: Ảnh tour weekend | D11: Video: "Mời PH tham quan" | E11: - | F11: - | G11: Cập nhật giờ tour | H11: 9:00 (live) + 14:00 | I11: Experience + FOMO | J11: Theo lịch tour | K11: Weekend = PH rảnh xem
A12: Chủ nhật | B12: Image: Quote GD + Logo VA | C12: Story: Fun fact về trường | D12: Video nhẹ: Ngày của bé tại VA | E12: - | F12: - | G12: - | H12: 9:00 + 19:00 | I12: Brand + Emotional | J12: Chung | K12: Nhẹ nhàng, warm
A15: B. CHỦ ĐỀ CONTENT THEO THÁNG
A16: Tháng | B16: Chủ đề chính | C16: Pillar Content | D16: Video cần quay | E16: Ảnh cần chụp | F16: Blog/Article | G16: Số bài FB | H16: Số bài IG | I16: Số video TikTok | J16: Số bài Zalo | K16: Tổng content | L16: Trạng thái
A17: Tháng 4 | B17: Khám phá VA – Tour mở cửa | C17: Testimonial PH mùa trước + Campus tour video | D17: 5 video testi + 3 campus tour | E17: 20 ảnh hoạt động mới | F17: 4 blog: Chọn trường, Song ngữ, STEM, An toàn | G17: 28 | H17: 28 | I17: 20 | J17: 8 | K17: 88 | L17: ☐
A18: Tháng 5 | B18: Tại sao VA? – So sánh & Chọn lọc | C18: So sánh chương trình + Open Day recap | D18: 3 video so sánh + 2 Open Day | E18: 15 ảnh Open Day | F18: 4 blog: Sĩ số, Ngoại khóa, GV, Học phí | G18: 30 | H18: 30 | I18: 22 | J18: 10 | K18: 96 | L18: ☐
A19: Tháng 6 | B19: Chuyển cấp – Giai đoạn vàng quyết định | C19: Webinar recap + PH review sau tour | D19: 5 video PH sau tour + 2 webinar clip | E19: 15 ảnh tour | F19: 4 blog: Chuyển cấp 5→6, Lớp 10, Dậy thì, Lộ trình | G19: 30 | H19: 30 | I19: 24 | J19: 12 | K19: 100 | L19: ☐
A20: Tháng 7 | B20: Chốt – Học bổng & Ưu đãi cuối | C20: Học bổng announcement + Deadline countdown | D20: 3 video HS nhận HB + 2 countdown | E20: 10 ảnh ceremony | F20: 2 blog: Học bổng, Đầu ra ĐH | G20: 28 | H20: 28 | I20: 20 | J20: 10 | K20: 90 | L20: ☐
A21: Tháng 8 | B21: Cuối mùa – Cơ hội cuối cùng | C21: Urgency content + Slot còn lại | D21: 2 video "Chỗ có hạn" + 2 PH mới | E21: 10 ảnh chuẩn bị năm học | F21: 2 blog: Late enrollment, Chuyển trường | G21: 24 | H21: 24 | I21: 16 | J21: 8 | K21: 74 | L21: ☐
A22: Tháng 9 | B22: Khai giảng – Welcome & Brand | C22: Khai giảng recap + PH mới share | D22: 3 video khai giảng + 2 PH share | E22: 20 ảnh khai giảng | F22: 2 blog: Năm học mới, Cảm nhận PH | G22: 20 | H22: 20 | I22: 14 | J22: 6 | K22: 62 | L22: ☐
A25: C. CONTENT THEO CƠ SỞ (Phân bổ bài đăng/tháng)
A26: Cơ sở | B26: Cấp | C26: Khu vực | D26: FB/tháng | E26: IG/tháng | F26: TikTok/tháng | G26: Zalo/tháng | H26: GMB/tháng | I26: Nội dung ưu tiên | J26: Giọng văn/tone | K26: Hashtag chính
A27: MN VA Gò Vấp | B27: MN | C27: Gò Vấp, TP.HCM | D27: 12 | E27: 12 | F27: 8 | G27: 4 | H27: 4 | I27: An toàn, GV tận tâm, camera, bé vui | J27: Ấm áp, tin cậy, gần gũi | K27: #MamNonVietAnh #MamNonGoVap
A28: MN Nhân Lễ | B28: MN | C28: TX. Cần Giuộc, Tây Ninh (cũ: H. Cần Giuộc, Long An) | D28: 6 | E28: 4 | F28: 4 | G28: 4 | H28: 2 | I28: Trường trong KDC, bán trú, local trust | J28: Thân thiện, địa phương | K28: #MamNonNhanLe #CanGiuoc #TayNinh
A29: MN+TH Thái Sơn | B29: MN+TH | C29: TX. Cần Giuộc, Tây Ninh (cũ: H. Cần Giuộc, Long An) | D29: 6 | E29: 4 | F29: 4 | G29: 4 | H29: 2 | I29: Liên cấp, KDC Thái Sơn, không cần đi xa | J29: Thân thiện, tiện lợi | K29: #ThaiSon #TruongTuCanGiuoc
A30: MN+TH Mekong Xanh | B30: MN+TH | C30: TP. Rạch Giá, An Giang (cũ: TP. Rạch Giá, Kiên Giang) | D30: 6 | E30: 4 | F30: 4 | G30: 4 | H30: 2 | I30: Chuẩn TP.HCM tại tỉnh, song ngữ | J30: Tự hào, tiên phong | K30: #MekongXanh #RachGia #AnGiang
A31: TH VA Gò Vấp | B31: TH | C31: Gò Vấp, TP.HCM | D31: 12 | E31: 12 | F31: 8 | G31: 4 | H31: 4 | I31: Song ngữ, sĩ số nhỏ, lộ trình TA | J31: Chuyên nghiệp, giáo dục | K31: #TieuHocVietAnh #SongNgu
A32: TH VA Bình Tân | B32: TH | C32: Bình Tân, TP.HCM | D32: 10 | E32: 8 | F32: 6 | G32: 4 | H32: 4 | I32: Khép kín, an toàn, học phí hợp lý | J32: Gần gũi, thiết thực | K32: #TruongVietAnhBinhTan
A33: THCS VA Gò Vấp | B33: THCS | C33: Gò Vấp, TP.HCM | D33: 12 | E33: 12 | F33: 10 | G33: 4 | H33: 4 | I33: Chuyển cấp, GV chủ nhiệm, lộ trình 6→12 | J33: Nghiêm túc, động lực | K33: #THCSVietAnh #Lop6
A34: THPT VA Gò Vấp | B34: THPT | C34: Gò Vấp, TP.HCM | D34: 12 | E34: 12 | F34: 10 | G34: 4 | H34: 4 | I34: Học bổng, đầu ra ĐH, pathway du học | J34: Chuyên nghiệp, tự tin | K34: #THPTVietAnh #HocBong #Lop10
A35: Brand hệ thống | B35: Liên cấp | C35: Chung | D35: 8 | E35: 8 | F35: 6 | G35: 4 | H35: 0 | I35: Giá trị VA, alumni, thành tích | J35: Tự hào, uy tín | K35: #TruongVietAnh #HeThongVietAnh

Sheet L. Analytics & Remarketing
A1: ANALYTICS, REMARKETING & AUTOMATION TRACKING – TUYỂN SINH 2026
A2: Tracking toàn bộ hành vi user → Remarketing → Automation tối ưu → Tăng conversion rate
A4: A. GA4 – SỰ KIỆN & MỤC TIÊU TRACKING
A5: Event Name | B5: Loại | C5: Trigger | D5: Parameters | E5: Dùng cho | F5: Remarketing Audience | G5: GHL Action | H5: Ghi chú
A6: page_view | B6: Auto | C6: Tất cả trang | D6: page_title, page_location, page_referrer | E6: Baseline traffic | F6: All Visitors 7d/14d/30d/60d | G6: - | H6: GA4 auto-collect
A7: scroll | B7: Auto | C7: Scroll 90% | D7: percent_scrolled | E7: Đo engagement | F7: Engaged Visitors (scroll 90%) | G7: - | H7: Chỉ tính LP dài
A8: form_submit | B8: Custom | C8: Submit form trên LP | D8: form_id, campus, grade, source | E8: Conversion chính | F8: Form Submitters → Exclude | G8: Create contact + Pipeline | H8: GTM trigger
A9: click_call | B9: Custom | C9: Click tel: link | D9: phone_number, page | E9: Call tracking | F9: Call Clickers | G9: Log call event | H9: GTM trigger
A10: click_zalo | B10: Custom | C10: Click Zalo widget | D10: zalo_id, page | E10: Zalo engagement | F10: Zalo Engagers | G10: Tag zalo_engaged | H10: GTM trigger
A11: click_cta | B11: Custom | C11: Click CTA buttons | D11: cta_text, cta_position, page | E11: CTA optimization | F11: CTA Clickers no form | G11: - | H11: A/B test CTA text
A12: webinar_register | B12: Custom | C12: Submit webinar form | D12: webinar_id, webinar_name, grade | E12: Webinar tracking | F12: Webinar Registrants | G12: Add to Webinar pipeline | H12: GTM trigger
A13: scholarship_click | B13: Custom | C13: Click scholarship CTA | D13: scholarship_type, grade | E13: Scholarship interest | F13: Scholarship Interested | G13: Tag scholarship_interest | H13: THPT only
A14: video_play | B14: Custom | C14: Play testimonial video | D14: video_title, video_duration, percent | E14: Video engagement | F14: Video Viewers 50%+ | G14: - | H14: Remarketing asset
A15: fee_page_view | B15: Custom | C15: Xem trang học phí | D15: grade, campus | E15: High intent signal | F15: Fee Page Visitors (HOT) | G15: Tag hot_lead | H15: Remarketing ưu tiên #1
A16: thank_you_page | B16: Custom | C16: Đến trang cảm ơn | D16: conversion_type, campus | E16: Conversion confirm | F16: Converted → Exclude | G16: Move to next stage | H16: GTM pageview trigger
... A18: first_visit | B18: Auto | C18: Lần đầu ghé thăm | D18: traffic_type | E18: New user tracking | F18: New Visitors | G18: - | H18: Cần acquisition report
A21: B. REMARKETING AUDIENCES – PHÂN LOẠI CHI TIẾT
A22: Audience Name | B22: Nguồn | C22: Điều kiện | D22: Thời gian | E22: Nền tảng Ads | F22: Creative phù hợp | G22: CTA | H22: Ưu tiên | I22: Budget %
A23: HOT – Fee page visitors | B23: GA4 Custom | C23: Xem trang học phí chưa submit form | D23: 1-7 ngày | E23: Meta + Google Display | F23: Ưu đãi cụ thể + testimonial | G23: Đăng ký tư vấn học phí | H23: 🔴 Cao nhất | I23: 25%
A24: HOT – Form abandon | B24: GA4 Custom | C24: Mở form nhưng không submit | D24: 1-7 ngày | E24: Meta + Google Display | F24: Hoàn thành đăng ký + incentive | G24: Hoàn thành đăng ký nhận quà | H24: 🔴 Cao nhất | I24: 20%
A25: WARM – LP visitors | B25: GA4 Custom | C25: Xem LP > 30s chưa form | D25: 7-21 ngày | E25: Meta + Google + TikTok | F25: Testimonial video + tour invite | G25: Đặt lịch tour miễn phí | H25: 🟡 Cao | I25: 20%
A26: WARM – Video viewers 50%+ | B26: Meta/TikTok | C26: Xem video testi >50% | D26: 14-30 ngày | E26: Meta + TikTok | F26: CTA trực tiếp + deadline | G26: Đăng ký ngay, ưu đãi hết hạn | H26: 🟡 Cao | I26: 15%
A27: WARM – Webinar no-show | B27: GHL Custom | C27: Đăng ký WB nhưng không tham dự | D27: 1-14 ngày | E27: Meta + Zalo | F27: Replay video + tour invite | G27: Xem lại webinar + Book tour | H27: 🟡 Trung bình | I27: 5%
A28: COOL – All website visitors | B28: GA4 | C28: Tất cả visitors chưa convert | D28: 21-60 ngày | E28: Google Display + Meta | F28: Brand awareness + campus life | G28: Khám phá trường Việt Anh | H28: 🟢 Thấp | I28: 10%
A29: COOL – Page engagers | B29: Meta | C29: Like/comment/share FB/IG | D29: 30-60 ngày | E29: Meta | F29: Carousel campus + ưu đãi | G29: Tham quan trường ngay | H29: 🟢 Thấp | I29: 5%
A30: EXCLUDE – Enrolled | B30: GHL Upload | C30: PH đã nhập học | D30: Luôn exclude | E30: Tất cả | F30: - | G30: - | H30: Exclude | I30: -
A31: EXCLUDE – Converted | B31: GA4 | C31: Đã submit form thành công | D31: 7-30 ngày | E31: Tất cả | F31: - | G31: - | H31: Exclude (tạm) | I31: -
A34: C. AUTOMATION TỐI ƯU – HOẠT ĐỘNG HÀNG NGÀY/TUẦN
A35: Hoạt động | B35: Tần suất | C35: Tool | D35: Input data | E35: Action | F35: Output/KPI | G35: Ai làm | H35: Trạng thái
A36: GA4 Realtime monitoring | B36: Hàng ngày | C36: GA4 Realtime | D36: Active users, events, conversions | E36: Check anomaly (traffic drop, 0 conversions) | F36: Alert nếu bất thường | G36: Performance | H36: ☐
A37: UTM audit | B37: Hàng tuần | C37: GA4 + Sheets | D37: Campaign URLs | E37: Verify UTM parameters đúng trên tất cả ads | F37: UTM clean 100% | G37: Performance | H37: ☐
A38: Conversion path analysis | B38: Hàng tuần | C38: GA4 Explore | D38: Multi-channel funnel | E38: Xem path phổ biến nhất → optimize touchpoints | F38: Top 5 paths | G38: Marketing Lead | H38: ☐
A39: Audience refresh | B39: Hàng tuần | C39: Meta + Google + TikTok | D39: GA4 audiences | E39: Update custom audiences, refresh lookalike | F39: Audiences updated | G39: Performance | H39: ☐
A40: Landing page heatmap | B40: 2 tuần/lần | C40: Hotjar/Clarity | D40: Click map, scroll map | E40: Identify drop-off points → A/B test CTA | F40: CVR improvement | G40: Performance | H40: ☐
A41: GHL workflow audit | B41: Hàng tuần | C41: GHL | D41: Workflow stats | E41: Check email open rate, SMS delivery, Zalo response | F41: Workflow optimization | G41: CRM Executive | H41: ☐
A42: Birch rule review | B42: Hàng tuần | C42: Birch PPC | D42: Rule execution log | E42: Which rules fired? CPL trend? Budget pacing? | F42: Rules optimized | G42: Performance | H42: ☐
A43: Pixel health check | B43: Hàng tuần | C43: Meta Events + TikTok Pixel + GA4 Debug | D43: Event firing, match quality | E43: Verify all pixels firing correctly | F43: Match rate ≥80% | G43: Tech/Performance | H43: ☐
A44: Attribution model review | B44: Hàng tháng | C44: GA4 Attribution | D44: Model comparison | E44: Compare last-click vs data-driven | F44: Budget reallocation insight | G44: Marketing Lead | H44: ☐
A45: CRM → Ads sync | B45: Hàng tuần | C45: GHL → Google/Meta | D45: Enrolled list upload | E45: Upload enrolled → Exclusion | Upload leads → Lookalike | F45: Audience quality | G45: CRM + Performance | H45: ☐
A46: Speed & Core Web Vitals | B46: Hàng tháng | C46: PageSpeed Insights | D46: LCP, FID, CLS | E46: LP load <3s mobile | Fix CWV issues | F46: Speed score ≥80 | G46: Tech/Dev | H46: ☐
A47: Cross-device tracking verify | B47: Hàng tháng | C47: GA4 | D47: User Explorer | E47: Verify cross-device journey (mobile ads → desktop form) | F47: Journey mapping | G47: Performance | H47: ☐
