Workbook

Sheet I. Chân Dung KH
A1: CHÂN DUNG KHÁCH HÀNG (PERSONA) – THEO SẢN PHẨM VÀ ĐỊA ĐIỂM
A2: Phân tích chi tiết đối tượng phụ huynh mục tiêu, nỗi đau, insight và messaging phù hợp cho từng cấp học và từng địa điểm
A4: A. PERSONA THEO CẤP HỌC
A5: Cấp học | B5: Tên Persona | C5: Tuổi | D5: Giới tính | E5: Nghề nghiệp | F5: Thu nhập/tháng | G5: Hành vi Online | H5: Kênh tiếp cận chính | I5: Nỗi đau #1 | J5: Nỗi đau #2 | K5: Nỗi đau #3 | L5: Insight mua hàng | M5: Messaging chính | N5: CTA hiệu quả | O5: Objection thường gặp | P5: Cách xử lý Objection
A6: MN (Mầm non) | B6: Chị Lan – Mẹ bỉm sữa | C6: 26-35 | D6: Nữ 85% | E6: Nhân viên VP, kinh doanh nhỏ | F6: 15-30 triệu | G6: Facebook 3h/ngày, Zalo, TikTok, group MN | H6: Meta Ads, Zalo OA, TikTok | I6: Sợ con bị bắt nạt / không an toàn | J6: Thiếu thời gian đưa đón, cần trường gần nhà | K6: Lo giáo viên không tận tâm, thay đổi liên tục | L6: Tin review PH khác > quảng cáo; Quyết định nhanh nếu tour ấn tượng | M6: Môi trường an toàn, camera 24/7, GV tận tâm, gần nhà | N6: Đăng ký tham quan trường MIỄN PHÍ | O6: Học phí cao hơn trường khác | P6: So sánh giá trị: ăn sạch, GV/trẻ tỷ lệ thấp, camera, ngoại khóa
A7: MN (Mầm non) | B7: Anh Tuấn – Ba trẻ quan tâm GD | C7: 30-40 | D7: Nam 15% | E7: Quản lý, kỹ sư, CNTT | F7: 25-50 triệu | G7: Google Search, YouTube review | H7: Google Ads, YouTube | I7: Muốn con phát triển toàn diện sớm | J7: Lo trường không có chương trình song ngữ tốt | K7: Không biết trường nào uy tín gần nhà | L7: So sánh kỹ trên Google trước khi tour | M7: Song ngữ từ 3 tuổi, chương trình STEAM | N7: Xem chi tiết chương trình học | O7: Muốn chờ vợ quyết định | P7: Mời cả 2 PH cùng tour, tặng ưu đãi
A8: TH (Tiểu học) | B8: Chị Mai – PH lớp 1 lo lắng | C8: 30-42 | D8: Nữ 75% | E8: Nhân viên, giáo viên, kinh doanh | F8: 20-40 triệu | G8: Facebook, Zalo group, tìm Google | H8: Meta Ads, Google Search, Zalo | I8: Sợ con không theo kịp chương trình | J8: Lo trường tư "nhẹ" hơn trường công | K8: Áp lực tiếng Anh – con chưa có nền tảng | L8: Tham khảo 3-5 trường trước khi chọn; Tour 2 lần | M8: Lộ trình tiếng Anh rõ ràng, sĩ số nhỏ 25-30, GV theo sát | N8: Đặt lịch tham quan + tư vấn 1-1 | O8: Trường công miễn phí mà cũng tốt | P8: Sĩ số 50 vs 25, không ngoại khóa, GV không theo sát
A9: TH (Tiểu học) | B9: Anh Hùng – PH chuyển con từ công sang tư | C9: 35-45 | D9: Nam 25% | E9: Chủ DN nhỏ, quản lý | F9: 30-60 triệu | G9: Google, Facebook, hỏi bạn bè | H9: Google Ads, Remarketing | I9: Con đang học công nhưng không phát triển | J9: Muốn môi trường tốt hơn, ít bạo lực | K9: Lo con không thích nghi khi chuyển | L9: Quyết định nhanh khi thấy cơ sở vật chất tốt | M9: Chuyển cấp linh hoạt, hỗ trợ hòa nhập, CSVC hiện đại | N9: Đăng ký chuyển trường – Hỗ trợ hồ sơ nhanh | O9: Con đã quen trường cũ | P9: Hỗ trợ hòa nhập 2 tuần, buddy system
A10: THCS (Cấp 2) | B10: Chị Hoa – PH lớp 6 giai đoạn bản lề | C10: 35-48 | D10: Nữ 65% | E10: Nhân viên, công chức, kinh doanh | F10: 25-50 triệu | G10: Facebook, Google, Webinar, Forum | H10: Meta Ads, Google Ads, Webinar | I10: Sợ con sa sút vì giai đoạn dậy thì | J10: Lo trường không theo sát tâm lý HS | K10: Áp lực kết quả thi cuối cấp | L10: Tham gia webinar trước khi tour; Cần dữ liệu đầu ra | M10: Theo sát HS giai đoạn bản lề, GV chủ nhiệm tâm huyết | N10: Đăng ký webinar: Lộ trình con tôi sau lớp 5 | O10: Học phí THCS cao hơn TH nhiều | P10: ROI dài hạn: nền tảng cho lớp 10, đại học
A11: THCS (Cấp 2) | B11: Anh Minh – PH muốn con có lộ trình rõ | C11: 38-50 | D11: Nam 35% | E11: Quản lý, chuyên gia, DN | F11: 40-80 triệu | G11: Google Search, YouTube, LinkedIn | H11: Google Ads, YouTube, Webinar | I11: Muốn con có định hướng nghề nghiệp sớm | J11: Lo trường chỉ dạy lý thuyết, thiếu thực hành | K11: Muốn chương trình quốc tế/song ngữ chuẩn | L11: So sánh đầu ra, tỷ lệ đỗ THPT top, chương trình quốc tế | M11: Lộ trình 6→12 rõ ràng, chương trình Cambridge/IB option | N11: Xem lộ trình đào tạo 7 năm | O11: Trường xa nhà | P11: Xe đưa đón, kế hoạch bán trú
A12: THPT (Cấp 3) | B12: Chị Thảo – PH lớp 10 áp lực thi | C12: 38-52 | D12: Nữ 60% | E12: Nhân viên, giáo viên, kinh doanh | F12: 30-60 triệu | G12: Facebook, Google, Webinar, tìm học bổng | H12: Google Ads, Meta Ads, Webinar | I12: Lo con không đỗ trường công top | J12: Áp lực tài chính: học phí THPT tư cao | K12: Lo con không vào được đại học tốt | L12: Quyết định theo học bổng + đầu ra đại học | M12: Học bổng lên đến 100%, đầu ra ĐH top, tỷ lệ đỗ ĐH 95%+ | N12: Đăng ký thi học bổng lớp 10 | O12: Trường tư chất lượng không bằng chuyên | P12: Data đầu ra: % ĐH top, học bổng du học, IELTS
A13: THPT (Cấp 3) | B13: Anh Đức – PH chuyển trường lớp 10-11 | C13: 40-55 | D13: Nam 40% | E13: Chủ DN, quản lý cấp cao | F13: 50-100+ triệu | G13: Google Search, YouTube, referral | H13: Google Ads, Remarketing | I13: Con đang học trường không phù hợp | J13: Muốn môi trường quốc tế + du học pathway | K13: Cần chuyển nhanh, ít gián đoạn | L13: Quyết định rất nhanh khi thấy phù hợp | M13: Chuyển trường linh hoạt, nhận hồ sơ quanh năm, pathway du học | N13: Liên hệ tư vấn chuyển trường 24h | O13: Sợ con mất bạn bè | P13: Chương trình hòa nhập, buddy system, câu lạc bộ
A16: B. NỖI ĐAU KHÁCH HÀNG THEO ĐỊA ĐIỂM
A17: Địa điểm | B17: Tên cũ (trước sáp nhập) | C17: Tên mới (hiện tại) | D17: Cấp học | E17: Đặc điểm PH khu vực | F17: Nỗi đau đặc thù #1 | G17: Nỗi đau đặc thù #2 | H17: Nỗi đau đặc thù #3 | I17: Messaging phù hợp | J17: Kênh ưu tiên | K17: Đối thủ chính | L17: Lợi thế VA tại đây
A18: MN VA Gò Vấp | B18: Q. Gò Vấp, TP.HCM | C18: Q. Gò Vấp, TP.HCM | D18: MN | E18: Thu nhập trung bình-khá, đông dân, nhiều gia đình trẻ | F18: Trường MN quá tải, thiếu chỗ gửi an toàn | G18: Giao thông kẹt, cần trường gần nhà | H18: Lo bạo lực, thiếu camera giám sát | I18: An toàn #1, gần nhà, camera 24/7 | J18: Meta Ads, Zalo OA | K18: MN Sài Gòn, MN Sao Mai | L18: Flagship, CSVC mới, GV ổn định
A19: MN Nhân Lễ | B19: H. Cần Giuộc, Long An | C19: TX. Cần Giuộc, Tây Ninh | D19: MN | E19: Thu nhập trung bình, vùng KDC mới, ít lựa chọn | F19: Rất ít trường tư chất lượng trong KDC | G19: PH làm ở KCN, cần trường bán trú tốt | H19: Lo con thiếu ngoại ngữ vùng tỉnh | I19: Trường chuẩn quốc tế ngay KDC, bán trú chu đáo | J19: Zalo OA, Facebook local | K19: MN công lập địa phương | L19: Duy nhất trường tư chất lượng trong KDC
A20: MN Thái Sơn | B20: H. Cần Giuộc, Long An | C20: TX. Cần Giuộc, Tây Ninh | D20: MN+TH | E20: PH KDC Thái Sơn, thu nhập khá, mới về định cư | F20: Thiếu trường tốt gần KDC mới | G20: Muốn con có bạn bè trong khu | H20: Lo chất lượng GD vùng mới phát triển | I20: Ngay trong KDC, không cần đưa đón xa | J20: Zalo OA, Facebook group KDC | K20: MN công, MN tư nhỏ lẻ | L20: Nằm ngay trong KDC, liên cấp MN+TH
A21: MN Mekong Xanh | B21: TP. Rạch Giá, Kiên Giang | C21: TP. Rạch Giá, An Giang | D21: MN+TH | E21: PH KĐT mới, thu nhập khá, nhiều công chức/DN | F21: Ít lựa chọn trường tư trong KĐT | G21: Muốn chương trình song ngữ mà vùng tỉnh không có | H21: Lo con thua thiệt so với TP.HCM | I21: Song ngữ chuẩn TP.HCM ngay tại tỉnh | J21: Zalo OA, Facebook local, Google local | K21: Trường công lập, TT Anh ngữ | L21: Chuẩn TP.HCM, liên cấp, KĐT cao cấp
A22: TH VA Gò Vấp | B22: Q. Gò Vấp, TP.HCM | C22: Q. Gò Vấp, TP.HCM | D22: TH | E22: PH trung lưu-khá, so sánh kỹ nhiều trường | F22: Quá nhiều lựa chọn, không biết trường nào tốt | G22: Lo tiếng Anh không đủ mạnh so với international school | H22: Sĩ số lớp quá đông ở trường công | I22: Sĩ số 25, lộ trình tiếng Anh có chứng chỉ, GV 1-1 | J22: Meta Ads, Google Search | K22: TH Việt Úc, TH iSchool, TH FPT | L22: Học phí hợp lý hơn international, vẫn song ngữ chuẩn
A23: TH VA Bình Tân | B23: Q. Bình Tân, TP.HCM | C23: Q. Bình Tân, TP.HCM | D23: TH | E23: PH thu nhập trung bình, khu đông dân, công nhân + KD nhỏ | F23: Rất ít trường tư chất lượng khu vực Bình Tân | G23: Lo an ninh khu vực, muốn trường khép kín | H23: Giá phải hợp lý với thu nhập | I23: An toàn, khép kín, học phí phù hợp, bán trú tốt | J23: Meta Ads, Zalo local | K23: TH Bình Tân, TH Phước Kiểng | L23: Duy nhất trường tư song ngữ quy mô tại BT
A24: TH Thái Sơn | B24: H. Cần Giuộc, Long An | C24: TX. Cần Giuộc, Tây Ninh | D24: TH | E24: PH KDC Thái Sơn, muốn con học tại chỗ | F24: Phải đi xa để học trường tốt | G24: Lo con mệt vì di chuyển hàng ngày | H24: Chương trình tỉnh yếu hơn TP | I24: Chuẩn TP.HCM ngay KDC, không cần đi xa | J24: Zalo, Facebook local | K24: TH công lập xã | L24: Liên cấp, ngay trong KDC
A25: TH Mekong Xanh | B25: TP. Rạch Giá, Kiên Giang | C25: TP. Rạch Giá, An Giang | D25: TH | E25: PH KĐT, muốn con có nền tảng tốt | F25: Không có trường tư song ngữ tại TP Rạch Giá | G25: Muốn con thi vào trường tốt sau này | H25: Lo GV giỏi không về tỉnh dạy | I25: GV từ TP.HCM, chương trình chuẩn quốc gia + song ngữ | J25: Zalo, Facebook, Google local | K25: TH công, TT Anh ngữ | L25: Duy nhất TH tư song ngữ quy mô
A26: THCS VA Gò Vấp | B26: Q. Gò Vấp, TP.HCM | C26: Q. Gò Vấp, TP.HCM | D26: THCS | E26: PH lo lắng giai đoạn dậy thì, cần theo sát | F26: Trường công THCS sĩ số 45-50, GV không theo sát | G26: Lo con sa sút vì bạn bè tiêu cực | H26: Áp lực thi THPT cạnh tranh | I26: Sĩ số nhỏ, GV chủ nhiệm theo sát, lộ trình 6→12 | J26: Google Ads, Meta, Webinar | K26: THCS Việt Úc, THCS iSchool | L26: Liên cấp THCS-THPT, không cần thi chuyển
A27: THPT VA Gò Vấp | B27: Q. Gò Vấp, TP.HCM | C27: Q. Gò Vấp, TP.HCM | D27: THPT | E27: PH áp lực thi lớp 10, tìm giải pháp B nếu rớt công | F27: Con không đỗ trường công top → hoang mang | G27: Học phí THPT tư cao, lo tài chính | H27: Lo đầu ra đại học không tốt bằng trường chuyên | I27: Học bổng 100%, đầu ra ĐH 95%+, pathway du học | J27: Google Ads, Meta, Webinar | K27: THPT Nguyễn Khuyến, THPT Trương Vĩnh Ký | L27: Học bổng lớn, lộ trình đa dạng, tỷ lệ ĐH cao
A30: C. HÀNH TRÌNH KHÁCH HÀNG (CUSTOMER JOURNEY) THEO CẤP
A31: Giai đoạn | B31: Awareness | C31: Consideration | D31: Decision | E31: Tour/Visit | F31: Enrollment | G31: Advocacy
A32: MN | B32: Thấy ads FB/TikTok → nghe PH review → tìm Google | C32: So sánh 2-3 trường → đọc review → hỏi group | D32: Gọi hotline / Zalo → Hỏi học phí → Book tour | E32: Tour campus → gặp GV → xem phòng học → lunch trial | F32: Nộp hồ sơ → đóng cọc → nhận thông báo | G32: Review Google → giới thiệu bạn → share FB
A33: TH | B33: Tìm Google "trường TH song ngữ" → thấy ads Meta | C33: So sánh 3-5 trường → tour 2 lần → hỏi PH hiện tại | D33: Webinar/Open Day → tư vấn 1-1 → nhận ưu đãi | E33: Tour chi tiết → ngồi lớp thử → gặp GV chủ nhiệm | F33: Thi đầu vào (nếu có) → nộp hồ sơ → đóng phí | G33: Review → referral program → PH ambassador
A34: THCS | B34: Webinar "chuyển cấp" → Google "THCS tốt GV" → FB ads | C34: So sánh đầu ra → xem chương trình → hỏi alumni PH | D34: Tư vấn riêng → xem lộ trình 6→12 → học bổng | E34: Tour + ngồi lớp + gặp HS hiện tại + GV chủ nhiệm | F34: Nộp hồ sơ → phỏng vấn → đóng cọc | G34: PH chia sẻ experience → alumni success story
A35: THPT | B35: Google "tuyển sinh lớp 10" → Webinar → FB/TikTok | C35: So sánh vs công → check đầu ra ĐH → học bổng | D35: Thi học bổng → tư vấn chuyên sâu → financial plan | E35: Tour VIP → gặp BGH → xem lab/thư viện/CLB | F35: Thi tuyển/xét tuyển → nhận kết quả → enrollment | G35: Đầu ra ĐH → alumni network → PH referral
A38: HÀNH TRÌNH QUYẾT ĐỊNH CỦA PHỤ HUYNH — CUSTOMER JOURNEY MAP
A39: Cấp Học | B39: Giai Đoạn | C39: Trigger/Channels | D39: Content Cần | E39: Funnel Page | F39: Ads Hiện | G39: CRM Action | H39: KPI
A40: MN | B40: Nhận Thức | C40: Search "trường MN tốt", FB feed, Referral | D40: Blog: Chọn trường như thế nào | E40: forms.truongvietanh.com/awareness-mn | F40: Search Ads (KW: trường MN) | G40: Tag: Awareness | H40: CTR 2%
A41: MN | B41: Tìm Hiểu | C41: Visit website, compare 3 trường | D41: So sánh, review, chứng chỉ | E41: forms.truongvietanh.com/consideration-mn | F41: Remarketing display ads | G41: Tag: Consideration | H41: Time on site 3+min
A42: MN | B42: Tham Quan | C42: Đăng ký tour, gặp hiệu trưởng | D42: Virtual tour, bảng giá, Q&A | E42: forms.truongvietanh.com/tour-mn | F42: Zalo OA message | G42: Event: Tour scheduled | H42: Attendance 85%
A43: MN | B43: Quyết Định | C43: Gặp phụ huynh khác, quyết định | D43: Hồ sơ ghi danh, học phí | E43: forms.truongvietanh.com/enroll-mn | F43: Conversion ads | G43: Create: Lead in CRM | H43: Conversion 15%
A44: MN | B44: Referral | C44: Khuyên bạn bè, review | D44: Referral program info, incentive | E44: forms.truongvietanh.com/refer-mn | F44: None | G44: Tag: Enrolled + Referrer | H44: Referral rate 10%
A45: TH | B45: Nhận Thức | C45: Google search, Facebook, TikTok | D45: Blog: Tại sao TH quốc tế | E45: forms.truongvietanh.com/awareness-th | F45: Video ads + Search ads | G45: Tag: Awareness | H45: Video views 5k+
A46: TH | B46: Tìm Hiểu | C46: Video review, website | D46: Chương trình giáo dục, giáo viên | E46: forms.truongvietanh.com/consideration-th | F46: Story ads, carousel ads | G46: Tag: Consideration | H46: Engagement 5%
A47: TH | B47: Tham Quan | C47: Lớp học trực tiếp, gặp cô | D47: Lịch học, hoạt động ngoài giờ | E47: forms.truongvietanh.com/tour-th | F47: Zalo + Email reminder | G47: Event: Tour scheduled | H47: Tour completed 90%
A48: TH | B48: Quyết Định | C48: Lần 2-3 liên hệ, tư vấn | D48: Học phí, hỗ trợ, timing | E48: forms.truongvietanh.com/enroll-th | F48: Lead magnet ads | G48: Create: Lead | H48: Conversion 20%
A49: TH | B49: Referral | C49: Đã ghi danh, khuyên bạn | D49: Success story, student life | E49: forms.truongvietanh.com/refer-th | F49: Social proof ads | G49: Tag: Referrer | H49: Referral 12%
A50: THCS | B50: Nhận Thức | C50: Search "THCS tốt", YouTube | D50: Success stories, award-winning | E50: forms.truongvietanh.com/awareness-thcs | F50: YouTube ads + Search ads | G50: Tag: Awareness | H50: YouTube views 8k+
... A59: THPT | B59: Referral | C59: Alumni network, success promotion | D59: Alumni story, university acceptance | E59: forms.truongvietanh.com/refer-thpt | F59: LinkedIn + Instagram ads | G59: Tag: Referrer | H59: Referral 18%

Sheet 0. Dashboard
B1: 🎯 DASHBOARD ĐIỀU HÀNH – KẾ HOẠCH TUYỂN SINH VIỆT ANH 2026
B2: Giai đoạn: 26/03/2026 – 30/09/2026 | Tổng ngân sách: 13 tỷ đồng | Mục tiêu: 1,300 học sinh
B4: 📊 KPI TỔNG QUAN (tự động liên kết từ các sheet)
B5: Chỉ số | C5: Mục tiêu | D5: Thực tế MTD | E5: Vs Target | F5: Trạng thái | G5: Nguồn dữ liệu | H5: Sheet liên kết
B6: 🏫 Nhập học tích lũy | C6: ='1. Input'!B5 -> 1300 | D6: 0 | E6: =IF(C6>0,D6/C6,0) -> 0 | F6: → Nhập tay | G6: 1. Input | H6: Nhập tay từ CRM
B7: 🎯 School Tour tích lũy | C7: ='4. Funnel'!D3 -> 0 | D7: 0 | E7: =IF(C7>0,D7/C7,0) -> 0 | F7: → Nhập tay | G7: 4. Funnel | H7: Nhập tay từ GHL
B8: 📥 Leads tích lũy | C8: ='4. Funnel'!D4 -> 0 | D8: 0 | E8: =IF(C8>0,D8/C8,0) -> 0 | F8: → Nhập tay | G8: 4. Funnel | H8: Nhập tay từ GHL
B9: 💰 Chi phí Paid Media | C9: ='2. Paid Media'!C10 -> 425000000 | D9: 0 | E9: =IF(C9>0,D9/C9,0) -> 0 | F9: → Nhập tay | G9: 2. Paid Media | H9: Birch / Ads Manager
B10: 📊 CPL trung bình | C10: 200000 | D10: 0 | E10: =IF(C10>0,D10/C10,0) -> 0 | F10: → Nhập tay | G10: 14. Weekly Battleplan | H10: Nhập tay tuần
B11: 🏃 Lead→Tour rate | C11: 0.3 | D11: 0 | E11: =IF(C11>0,D11/C11,0) -> 0 | F11: → Nhập tay | G11: 4. Funnel | H11: Tính từ GHL
B12: ✅ Tour→Nhập học rate | C12: 0.35 | D12: 0 | E12: =IF(C12>0,D12/C12,0) -> 0 | F12: → Nhập tay | G12: 4. Funnel | H12: Tính từ GHL
B13: ⚡ Response <5 min | C13: 0.85 | D13: 0 | E13: =IF(C13>0,D13/C13,0) -> 0 | F13: → Nhập tay | G13: 14. Weekly Battleplan | H13: Nhập tay tuần
B15: 💰 NGÂN SÁCH PAID MEDIA THEO KÊNH (liên kết 2. Paid Media)
B16: Kênh | C16: % Mix | D16: Ngân sách | E16: Vai trò | F16: CPL Mục tiêu | G16: Quản lý | H16: Ghi chú
B17: Meta / Facebook + Instagram | C17: 0.38 | D17: 3230000000 | E17: Demand + lead local | F17: 120000 | G17: Birch + GHL | H17: Kênh chủ lực
B18: Google Search | C18: 0.18 | D18: 1530000000 | E18: Intent-based | F18: 180000 | G18: Birch | H18: THCS/THPT
B19: Google Display / YouTube | C19: 0.07 | D19: 595000000 | E19: Phủ + video | F19: N/A | G19: Birch | H19: Testimonial
B20: TikTok Ads | C20: 0.1 | D20: 850000000 | E20: Video social proof | F20: 90000 | G20: Birch + GHL | H20: 100 video
B21: Zalo Ads + OA | C21: 0.07 | D21: 595000000 | E21: Nurture local | F21: 80000 | G21: GHL | H21: K12 local
B22: Webinar Ads | C22: 0.05 | D22: 425000000 | E22: Webinar lộ trình | F22: 50000 | G22: Meta + GHL | H22: THCS/THPT
B23: Remarketing đa nền tảng | C23: 0.12 | D23: 1020000000 | E23: Đuổi lại khách | F23: 150000 | G23: Birch | H23: 12%
B24: Local SEO / GMB | C24: 0.05 | D24: 425000000 | E24: Local presence | F24: N/A | G24: Manual + GHL | H24: 8 địa điểm
B25: TỔNG PAID MEDIA | C25: 1.02 | D25: 8670000000
B27: 🏫 PHÂN BỔ THEO CƠ SỞ (liên kết 3. Master Table)
B28: Cơ sở | C28: Cấp | D28: HS Mục tiêu | E28: CAC | F28: Meta (đ) | G28: G.Search (đ) | H28: TikTok (đ) | I28: Zalo (đ)
B29: MN VA Gò Vấp | C29: MN | D29: 200 | E29: 0.85 | F29: 405838877 | G29: 192239468 | H29: 106799704 | I29: 74759793
B30: MN Nhân Lễ | C30: MN | D30: 60 | E30: 0.85 | F30: 121751663 | G30: 57671840 | H30: 32039911 | I30: 22427938
B31: MN Thái Sơn | C31: MN | D31: 60 | E31: 0.85 | F31: 121751663 | G31: 57671840 | H31: 32039911 | I31: 22427938
B32: MN Mekong Xanh | C32: MN | D32: 60 | E32: 0.85 | F32: 121751663 | G32: 57671840 | H32: 32039911 | I32: 22427938
B33: TH VA Gò Vấp | C33: TH | D33: 150 | E33: 1 | F33: 358093126 | G33: 169623060 | H33: 94235033 | I33: 65964523
B34: TH VA Bình Tân | C34: TH | D34: 150 | E34: 1 | F34: 358093126 | G34: 169623060 | H34: 94235033 | I34: 65964523
B35: TH Thái Sơn | C35: TH | D35: 60 | E35: 1 | F35: 143237251 | G35: 67849224 | H35: 37694013 | I35: 26385809
B36: TH Mekong Xanh | C36: TH | D36: 60 | E36: 1 | F36: 143237251 | G36: 67849224 | H36: 37694013 | I36: 26385809
B37: THCS VA Gò Vấp | C37: THCS | D37: 200 | E37: 1.2 | F37: 572949002 | G37: 271396896 | H37: 150776053 | I37: 105543237
B38: THPT VA Gò Vấp | C38: THPT | D38: 200 | E38: 1.35 | F38: 644567627 | G38: 305321508 | H38: 169623060 | I38: 118736142
B39: Brand hệ thống | C39: Chung | D39: 100 | E39: 1 | F39: 238728751 | G39: 113082040 | H39: 62823356 | I39: 43976349
B41: 🗂️ NAVIGATOR – DANH SÁCH CÁC SHEET (Click để xem)
B42: # | C42: Tên Sheet | D42: Mô tả | E42: Dùng cho | F42: Cập nhật | G42: Tần suất | H42: Liên kết đến
B43: 1 | C43: 1. Input | D43: Thông số đầu vào toàn kế hoạch | E43: Ban điều hành | F43: 26/03 | G43: Đầu mùa | H43: Master Table, Funnel
B44: 2 | C44: 2. Paid Media | D44: Mix kênh, ngân sách, KPI mỗi kênh | E44: Marketing Lead | F44: Hàng tháng | G44: Tháng | H44: Master Table
B45: 3 | C45: 3. Master Table | D45: Phân bổ NS theo từng cơ sở | E45: Tất cả | F45: Đầu mùa | G45: Đầu mùa | H45: Paid Media, Funnel
B46: 4 | C46: 4. Funnel | D46: Funnel chuyển đổi & KPI | E46: Tất cả | F46: Tuần | G46: Tuần | H46: Dashboard, Battleplan
B47: 5 | C47: 5. Google Ads Chi Tiết | D47: Campaign, KW, RSA, Birch setup | E47: Perf. Marketing | F47: Tuần | G47: Tuần | H47: KPI Weekly
B48: 6 | C48: 6. Meta Ads Chi Tiết | D48: Campaign, Audience, Creative, Pixel | E48: Perf. Marketing | F48: Tuần | G48: Tuần | H48: KPI Weekly
B49: 7 | C49: 7. TikTok Ads Chi Tiết | D49: 100 video, campaign, GTM | E49: Content + Perf. | F49: Tuần | G49: Tuần | H49: KPI Weekly
B50: 8 | C50: 8. GoHighLevel Setup | D50: CRM, Pipeline, Automation, Zalo | E50: CRM + Sales | F50: Ngày 1 | G50: Setup | H50: Admissions KPI
B51: 9 | C51: 9. GTM Tracking | D51: Tag, trigger, conversion setup | E51: Tech/Dev | F51: Ngày 1 | G51: Setup | H51: Pixel, GA4
B52: 10 | C52: 10. Lịch Công Việc | D52: Checklist ngày/tuần/tháng marketer | E52: Marketing | F52: Hàng ngày | G52: Daily | H52: Battleplan, Todo
B53: 11 | C53: 11. Timeline | D53: Lịch giải ngân 7 tháng | E53: Ban điều hành | F53: Hàng tháng | G53: Tháng | H53: Dashboard
... B64: H | C64: G. Birch + GHL Integration | D64: Automation rules + webhook payload | E64: Tech + Marketing | F64: Ngày 1 | G64: Setup | H64: Birch Rules
B66: 🆕 SHEETS BỔ SUNG V7
B67: I | C67: I. Chân Dung KH | D67: Persona + nỗi đau theo sản phẩm và địa điểm | E67: Marketing + Sales | F67: Đầu mùa | G67: Setup | H67: Persona, Funnel
B68: J | C68: J. Webinar Chi Tiết | D68: Kế hoạch 8 webinar + quy trình + KPI | E68: Marketing + BGH | F68: Hàng tháng | G68: Tháng | H68: Campaign, GHL
B69: K | C69: K. Social Media Calendar | D69: Lịch đăng bài theo kênh, cơ sở, tháng | E69: Content Creator | F69: Hàng tuần | G69: Tuần | H69: Content
B70: L | C70: L. Analytics & Remarketing | D70: GA4 events, remarketing audiences, automation tracking | E70: Performance | F70: Hàng tuần | G70: Tuần | H70: GTM, Birch
B73: 📊 KPI THEO KÊNH (liên kết chi tiết)
B74: Kênh | C74: NS 7 tháng | D74: % Mix | E74: CPL Target | F74: Leads Target | G74: Tours Target | H74: Sheet chi tiết | I74: Tool quản lý
B75: Meta Ads | C75: 3230000000 | D75: 38% | E75: 120000 | F75: 4250 | G75: 1275 | H75: F. Meta Ads Plan | I75: Birch + Meta Ads Manager
B76: Google Search | C76: 1530000000 | D76: 18% | E76: 180000 | F76: 2010 | G76: 603 | H76: G. Google Ads Plan | I76: Birch + Google Ads
B77: Google Display/YT | C77: 595000000 | D77: 7% | E77: - | F77: - | G77: - | H77: 5. Google Ads Chi Tiết | I77: Birch
B78: TikTok Ads | C78: 850000000 | D78: 10% | E78: 90000 | F78: 1420 | G78: 426 | H78: 7. TikTok Ads Chi Tiết | I78: Birch + TikTok Ads
B79: Zalo Ads+OA | C79: 595000000 | D79: 7% | E79: 80000 | F79: 1120 | G79: 336 | H79: 13. Zalo Ads + OA | I79: GHL + Zalo OA
B80: Webinar Ads | C80: 425000000 | D80: 5% | E80: 50000 | F80: 1060 | G80: 256 | H80: J. Webinar Chi Tiết | I80: Meta + GHL
B81: Remarketing | C81: 1020000000 | D81: 12% | E81: 150000 | F81: - | G81: - | H81: L. Analytics & Remarketing | I81: Birch cross-platform
B82: Local SEO/GMB | C82: 425000000 | D82: 5% | E82: - | F82: - | G82: - | H82: 12. Danh bạ | I82: Manual + GHL
A85: ═══ CẬP NHẬT V8: SHEET MỚI + DUAL CRM + KPI MỞ RỘNG ═══
A87: DANH SÁCH TẤT CẢ 31 SHEETS — HYPERLINKS
A88: STT | B88: Sheet Name | C88: Mô tả | D88: Nhóm | E88: Trạng thái
A89: 1 | B89: I. Chân Dung KH | C89: Customer personas: 4 cấp học × 6 cơ sở, pain points, motivation | D89: Chiến lược | E89: ✅ V7+
A90: 2 | B90: 0. Dashboard | C90: Bảng điều khiển tổng hợp — ĐANG XEM | D90: Tổng hợp | E90: ✅ V8
A91: 3 | B91: 1. Input | C91: Thông số đầu vào: budget, target, channels | D91: Tổng hợp | E91: ✅ V7+
A92: 4 | B92: 2. Paid Media | C92: Phân bổ ngân sách Paid Media theo kênh | D92: Quảng cáo | E92: ✅ V7+
A93: 5 | B93: 3. Master Table | C93: Bảng tổng hợp target theo cơ sở × cấp học | D93: Tổng hợp | E93: ✅ V6
A94: 6 | B94: 4. Funnel | C94: Phễu chuyển đổi theo cấp học và cơ sở | D94: Chiến lược | E94: ✅ V7+
A95: 7 | B95: 5. Google Ads Chi Tiết | C95: Campaigns, Ad Groups, Keywords, Budget | D95: Quảng cáo | E95: ✅ V7+
A96: 8 | B96: 6. Meta Ads Chi Tiết | C96: FB + IG Ads: Campaigns, Audiences, Creatives | D96: Quảng cáo | E96: ✅ V7+
A97: 9 | B97: 7. TikTok Ads Chi Tiết | C97: TikTok campaigns, targeting, creatives | D97: Quảng cáo | E97: ✅ V7
A98: 10 | B98: 8. GoHighLevel Setup | C98: GHL setup guide: pipelines, workflows, forms | D98: CRM/Tech | E98: ✅ V7+
A99: 11 | B99: 9. GTM Tracking | C99: Google Tag Manager: pixels, events, CAPI | D99: CRM/Tech | E99: ✅ V7
... A119: 31 | B119: P. Setup & Đồng Bộ | C119: 🆕 100 bước setup GHL+Pancake+Make.com+Birch | D119: CRM/Tech | E119: ✅ V8 NEW
A122: DUAL CRM TRACKING — GHL + PANCAKE CRM
A123: Metric | B123: GHL | C123: Pancake CRM | D123: Đồng bộ | E123: T4 | F123: T5 | G123: T6 | H123: T7 | I123: T8 | J123: T9 | K123: Tổng
A124: Total Contacts | B124: ✅ Master | C124: ✅ Sync | D124: Make.com real-time | E124: 500 | F124: 1,200 | G124: 2,500 | H124: 4,000 | I124: 5,000 | J124: 5,500 | K124: 5,500
A125: New Leads/tháng | B125: ✅ Track | C125: ✅ Capture | D125: Webhook → GHL | E125: 100 | F125: 180 | G125: 300 | H125: 350 | I125: 200 | J125: 100 | K125: 1,230
A126: FB Inbox Leads | B126: Sync from Pancake | C126: ✅ Primary | D126: Pancake → Make → GHL | E126: 40 | F126: 70 | G126: 120 | H126: 140 | I126: 80 | J126: 40 | K126: 490
A127: Zalo Leads | B127: Sync from Pancake | C127: ✅ Primary | D127: Pancake → Make → GHL | E127: 30 | F127: 50 | G127: 80 | H127: 100 | I127: 60 | J127: 30 | K127: 350
A128: Form Leads | B128: ✅ Primary | C128: Sync from GHL | D128: GHL → Make → Pancake | E128: 20 | F128: 40 | G128: 70 | H128: 80 | I128: 40 | J128: 20 | K128: 270
A129: Ad Leads (Meta+Google+TikTok) | B129: ✅ Via Birch | C129: Sync | D129: Birch → GHL → Make → Pancake | E129: 10 | F129: 20 | G129: 30 | H129: 30 | I129: 20 | J129: 10 | K129: 120
A130: Tours Booked | B130: ✅ Calendar | C130: Note sync | D130: GHL → Make → Pancake note | E130: 30 | F130: 60 | G130: 120 | H130: 150 | I130: 80 | J130: 30 | K130: 470
A131: Enrollments | B131: ✅ Pipeline | C131: ✅ Tag | D131: Bidirectional | E131: 15 | F131: 40 | G131: 80 | H131: 120 | I131: 100 | J131: 50 | K131: 405
A132: Response Time (avg) | B132: N/A | C132: ✅ Measure | D132: Report only | E132: <30m | F132: <25m | G132: <20m | H132: <20m | I132: <25m | J132: <30m | K132: <25m
A133: Workflow Emails Sent | B133: ✅ Primary | C133: N/A | D133: GHL only | E133: 500 | F133: 1,500 | G133: 3,000 | H133: 4,000 | I133: 2,500 | J133: 1,000 | K133: 12,500
A134: SMS Sent | B134: ✅ Primary | C134: N/A | D134: GHL only | E134: 200 | F134: 500 | G134: 1,000 | H134: 1,200 | I134: 800 | J134: 400 | K134: 4,100
A135: Make.com Operations/tháng | B135: N/A | C135: N/A | D135: ✅ Monitor | E135: 2,000 | F135: 4,000 | G135: 7,000 | H135: 8,000 | I135: 5,000 | J135: 3,000 | K135: 29,000
A138: SOCIAL MEDIA KPI DASHBOARD — TỔNG HỢP 6 KÊNH
A139: Kênh | B139: Metric chính | C139: Hiện tại | D139: T4 | E139: T5 | F139: T6 | G139: T7 | H139: T8 | I139: T9 | J139: Target cuối
A140: Facebook Page | B140: Followers | C140: 12,000 | D140: 15,000 | E140: 20,000 | F140: 28,000 | G140: 35,000 | H140: 42,000 | I140: 50,000 | J140: 50,000
A141: Facebook Page | B141: Engagement Rate | C141: 2.5% | D141: 3.0% | E141: 3.2% | F141: 3.5% | G141: 3.5% | H141: 3.3% | I141: 3.0% | J141: ≥3.0%
A142: Facebook Groups | B142: Members (tổng) | C142: 8,000 | D142: 10,000 | E142: 13,000 | F142: 18,000 | G142: 22,000 | H142: 26,000 | I142: 30,000 | J142: 30,000
A143: Zalo OA | B143: Followers | C143: 15,000 | D143: 18,000 | E143: 22,000 | F143: 28,000 | G143: 32,000 | H143: 36,000 | I143: 40,000 | J143: 40,000
...

Sheet 1. Input
A1: INPUT & ĐIỀU KHIỂN – BẢN V5 (BỎ PHÚ NHUẬN, CẬP NHẬT ĐỊA GIỚI)
A2: ⚠️ Phú Nhuận ĐÃ BỎ. Ngân sách phân bổ lại cho các cơ sở còn lại. Cần Giuộc → Tây Ninh. Rạch Giá → An Giang.
A3: Hạng mục | B3: Giá trị | C3: Đơn vị | D3: Ghi chú
A4: Tổng ngân sách | B4: 13000000000 | C4: đ | D4: 13 tỷ
A5: Mục tiêu nhập học | B5: 1300 | C5: HS | D5: Không còn Phú Nhuận → phân bổ lại
A6: NC → Lead | B6: 0.2 | C6: % | D6: Benchmark K12: 18-25%
A7: Lead → School Tour | B7: 0.3 | C7: % | D7: SLA < 5 phút + GHL automation
A8: Tour → Nhập học | B8: 0.35 | C8: % | D8: Thực tế K12 VN
A9: CRM / GoHighLevel | B9: 200000000 | C9: đ | D9: GHL + Zalo + SMS + landing
A10: School Tour / Open Day / Event | B10: 800000000 | C10: đ | D10: Điểm chuyển đổi #1
A11: Nhân sự Sales | B11: 800000000 | C11: đ | D11: Lương + KPI + hoa hồng
A12: Content / Brand / Sales Enablement | B12: 700000000 | C12: đ | D12: Kho sẵn + creative mới
A13: Nhân sự Marketing (5 người × 6T) | B13: 450000000 | C13: đ | D13: 5 người × 6 tháng × 15 triệu
A14: Học bổng / Promotion | B14: 1000000000 | C14: đ | D14: Kích hoạt quyết định
A15: Paid Media | B15: 8500000000 | C15: đ | D15: 65.4% tổng NS
A16: Training / QA / Data / Mystery call | B16: 550000000 | C16: đ | D16: 100+100+200+150 triệu
A18: KIỂM TRA | B18: =SUM(B9:B16) -> 13000000000
A19: Chênh lệch | B19: =B4-B18 -> 0
A20: Trạng thái | B20: =IF(ABS(B19)<1000,"✅ Khớp 13 tỷ","❌ LỆCH") -> ✅ Khớp 13 tỷ
A22: CHI TIẾT BỔ SUNG
A23: Số cơ sở | B23: 6 | C23: cơ sở | D23: Bỏ Phú Nhuận, còn 6 cơ sở hoạt động
A24: Số cấp học | B24: 4 | C24: cấp | D24: MN, TH, THCS, THPT
A25: Số LP cần tạo | B25: 8 | C25: trang | D25: 1 LP/campus + 1 webinar + 1 tỉnh MN + 1 tỉnh TH
A26: Số pipeline GHL | B26: 4 | C26: pipeline | D26: MN, TH, THCS, THPT
A27: Thời gian chiến dịch | B27: 7 | C27: tháng | D27: 26/03 - 30/09/2026
A28: Số tuần tác chiến | B28: 28 | C28: tuần | D28: Tuần 1 (26/03) → Tuần 28 (30/09)
A29: Số nhân sự Marketing | B29: 5 | C29: người | D29: PM×1, Content×2, Performance×1, CRM×1
A30: Số nhân sự Sales | B30: 6 | C30: người | D30: 1 Sales Lead + 5 Tư vấn viên (round-robin)
A31: Kho content sẵn có | B31: 2000 | C31: bài | D31: Ảnh+video+bài viết kho cũ
A32: Video testimonial | B32: 100 | C32: video | D32: Kho 100 video PH+HS+GV sẵn sàng
A33: Webinar planned | B33: 8 | C33: buổi | D33: 6 chính + 2 bổ sung
A34: Open Day planned | B34: 2 | C34: sự kiện | D34: Tháng 5 + Tháng 6
A35: Lead response SLA | B35: 5 | C35: phút | D35: Gọi lại trong 5 phút, mục tiêu 85%
A36: Benchmark NC→Lead | B36: 18-25% | C36: % | D36: K12 VN trung bình
A37: Benchmark Lead→Tour | B37: 25-35% | C37: % | D37: Cần SLA tốt + GHL automation
A38: Benchmark Tour→Enroll | B38: 30-40% | C38: % | D38: Phụ thuộc tour quality + follow-up
A40: DANH SÁCH CƠ SỞ (ĐỊA GIỚI MỚI + CŨ)
A41: STT | B41: Tên cơ sở | C41: Cấp | D41: Địa chỉ | E41: Khu vực mới | F41: Khu vực cũ (trước sáp nhập) | G41: Hotline
A42: 1 | B42: MN VA Gò Vấp | C42: MN | D42: 573 Đ. Lê Đức Thọ, P. An Hội Tây | E42: Q. Gò Vấp, TP.HCM | F42: Q. Gò Vấp, TP.HCM (không đổi) | G42: 0916 961 409
A43: 2 | B43: MN Nhân Lễ | C43: MN | D43: 22 Đường D2, KDC Cần Giuộc | E43: TX. Cần Giuộc, tỉnh Tây Ninh | F43: H. Cần Giuộc, tỉnh Long An | G43: 0916 961 409
A44: 3 | B44: MN+TH Thái Sơn | C44: MN+TH | D44: KDC Thái Sơn, Cần Giuộc | E44: TX. Cần Giuộc, tỉnh Tây Ninh | F44: H. Cần Giuộc, tỉnh Long An | G44: 0916 961 409
A45: 4 | B45: MN+TH Mekong Xanh | C45: MN+TH | D45: Lô E7, KĐT Tây Bắc, TP. Rạch Giá | E45: TP. Rạch Giá, tỉnh An Giang | F45: TP. Rạch Giá, tỉnh Kiên Giang | G45: 0916 961 409
A46: 5 | B46: TH VA Gò Vấp | C46: TH | D46: 160/72 Phan Huy Ích | E46: Q. Gò Vấp, TP.HCM | F46: Q. Gò Vấp, TP.HCM (không đổi) | G46: 0916 961 409
A47: 6 | B47: TH VA Bình Tân | C47: TH | D47: Số 7 đường 38A, Tân Tạo | E47: Q. Bình Tân, TP.HCM | F47: Q. Bình Tân, TP.HCM (không đổi) | G47: 0916 961 409
A48: 7 | B48: THCS VA Gò Vấp | C48: THCS | D48: 160/72 Phan Huy Ích | E48: Q. Gò Vấp, TP.HCM | F48: Q. Gò Vấp, TP.HCM (không đổi) | G48: 091 696 1409
A49: 8 | B49: THPT VA Gò Vấp | C49: THPT | D49: 160/72 Phan Huy Ích | E49: Q. Gò Vấp, TP.HCM | F49: Q. Gò Vấp, TP.HCM (không đổi) | G49: 091 696 1409

Sheet 2. Paid Media
A1: MIX KÊNH PAID MEDIA – 8.5 TỶ (TÁCH SEARCH/DISPLAY, KHÔNG CÓ PHÚ NHUẬN)
A2: Kênh | B2: % Mix | C2: Ngân sách | D2: Vai trò | E2: KPI | F2: CPL mục tiêu | G2: Quản lý bởi | H2: Ghi chú
A3: Meta / Facebook + Instagram | B3: 0.38 | C3: =B3*'1. Input'!B15 -> 3230000000 | D3: Demand + lead local | E3: CPL, Volume | F3: 120000 | G3: Birch + GHL | H3: Kênh chủ lực
A4: Google Search (TÁCH RIÊNG) | B4: 0.18 | C4: =B4*'1. Input'!B15 -> 1530000000 | D4: Intent-based | E4: CPC, Quality | F4: 180000 | G4: Birch | H4: Đo riêng THCS/THPT
A5: Google Display / YouTube | B5: 0.07 | C5: =B5*'1. Input'!B15 -> 595000000 | D5: Phủ + video | E5: CPM, View | G5: Birch | H5: Testimonial 15-30s
A6: TikTok Ads | B6: 0.1 | C6: =B6*'1. Input'!B15 -> 850000000 | D6: Video social proof | E6: CPV, Lead | F6: 90000 | G6: Birch + GHL | H6: 100 video = vàng
A7: Zalo Ads + OA | B7: 0.07 | C7: =B7*'1. Input'!B15 -> 595000000 | D7: Nurture local | E7: Open, CTR | F7: 80000 | G7: GoHighLevel | H7: Hidden champion K12
A8: Webinar Ads (THCS/THPT) | B8: 0.05 | C8: =B8*'1. Input'!B15 -> 425000000 | D8: Webinar lộ trình | E8: Đăng ký | F8: 50000 | G8: Meta + GHL | H8: KHÔNG cho MN/TH
A9: Remarketing đa nền tảng | B9: 0.12 | C9: =B9*'1. Input'!B15 -> 1020000000 | D9: Đuổi lại khách | E9: ROAS, Conv | F9: 150000 | G9: Birch | H9: Giảm 15%→12%
A10: Local SEO / Google Business | B10: 0.05 | C10: =B10*'1. Input'!B15 -> 425000000 | D10: Local presence | E10: Map, Clicks | G10: Manual + GHL | H10: 8 địa điểm
A11: TỔNG | B11: =SUM(B3:B10) -> 1.02 | C11: =SUM(C3:C10) -> 8670000000
A13: NGÂN SÁCH PAID MEDIA THEO THÁNG
A14: Kênh | B14: T4 (12%) | C14: T5 (24%) | D14: T6 (28%) | E14: T7 (24%) | F14: T8 (8%) | G14: T9 (2%) | H14: Tổng 7 tháng
A15: Meta / FB+IG | B15: =0.12*C3 -> 387600000 | C15: =0.24*C3 -> 775200000 | D15: =0.28*C3 -> 904400000 | E15: =0.24*C3 -> 775200000 | F15: =0.08*C3 -> 258400000 | G15: =0.02*C3 -> 64600000 | H15: =SUM(B15:G15) -> 3165400000
A16: Google Search | B16: =0.12*C4 -> 183600000 | C16: =0.24*C4 -> 367200000 | D16: =0.28*C4 -> 428400000 | E16: =0.24*C4 -> 367200000 | F16: =0.08*C4 -> 122400000 | G16: =0.02*C4 -> 30600000 | H16: =SUM(B16:G16) -> 1499400000
A17: Google Display/YT | B17: =0.12*C5 -> 71400000 | C17: =0.24*C5 -> 142800000 | D17: =0.28*C5 -> 166600000 | E17: =0.24*C5 -> 142800000 | F17: =0.08*C5 -> 47600000 | G17: =0.02*C5 -> 11900000 | H17: =SUM(B17:G17) -> 583100000
A18: TikTok Ads | B18: =0.12*C6 -> 102000000 | C18: =0.24*C6 -> 204000000 | D18: =0.28*C6 -> 238000000 | E18: =0.24*C6 -> 204000000 | F18: =0.08*C6 -> 68000000 | G18: =0.02*C6 -> 17000000 | H18: =SUM(B18:G18) -> 833000000
A19: Zalo Ads+OA | B19: =0.12*C7 -> 71400000 | C19: =0.24*C7 -> 142800000 | D19: =0.28*C7 -> 166600000 | E19: =0.24*C7 -> 142800000 | F19: =0.08*C7 -> 47600000 | G19: =0.02*C7 -> 11900000 | H19: =SUM(B19:G19) -> 583100000
A20: Webinar Ads | B20: =0.12*C8 -> 51000000 | C20: =0.24*C8 -> 102000000 | D20: =0.28*C8 -> 119000000 | E20: =0.24*C8 -> 102000000 | F20: =0.08*C8 -> 34000000 | G20: =0.02*C8 -> 8500000 | H20: =SUM(B20:G20) -> 416500000
A21: Remarketing | B21: =0.12*C9 -> 122400000 | C21: =0.24*C9 -> 244800000 | D21: =0.28*C9 -> 285600000 | E21: =0.24*C9 -> 244800000 | F21: =0.08*C9 -> 81600000 | G21: =0.02*C9 -> 20400000 | H21: =SUM(B21:G21) -> 999600000
A22: Local SEO/GMB | B22: =0.12*C10 -> 51000000 | C22: =0.24*C10 -> 102000000 | D22: =0.28*C10 -> 119000000 | E22: =0.24*C10 -> 102000000 | F22: =0.08*C10 -> 34000000 | G22: =0.02*C10 -> 8500000 | H22: =SUM(B22:G22) -> 416500000
A24: CHI TIẾT VAI TRÒ TỪNG KÊNH
A25: Kênh | B25: Vai trò trong funnel | C25: Giai đoạn KH | D25: Resource cần | E25: Daily operations | F25: Weekly optimization | G25: Tool chính
A26: Meta Ads | B26: Demand generation + Lead local + Social proof | C26: Awareness → Consideration | D26: 30+ creative (image+video), 12 audiences | E26: Check CPL, scale/pause, creative refresh | F26: A/B test creative, audience expansion, budget realloc | G26: Meta Ads Manager + Birch
A27: Google Search | B27: Intent-based capture + Brand defense | C27: Consideration → Decision | D27: 20 campaigns, 200+ keywords, 15 RSA | E27: Search terms review, bid adjust, QS check | F27: Negative KW update, RSA test, campaign restructure | G27: Google Ads + Birch
A28: Google Display/YT | B28: Awareness phủ + Video retarget | C28: Awareness + Remarketing | D28: 5 display banners, 3 video 15-30s | E28: Check CPM, placement exclusion | F28: Placement review, video performance | G28: Google Ads + Birch
A29: TikTok Ads | B29: Video social proof + Gen Z/Millennial reach | C29: Awareness → Lead | D29: 100 video kho sẵn, 5 new/tháng | E29: Check CPV, engagement, 3s retention | F29: Video performance ranking, upload new | G29: TikTok Ads + Birch
A30: Zalo Ads+OA | B30: Local nurture + Broadcast + Remarketing | C30: Consideration → Decision | D30: 8 broadcast templates, 4 ad creatives | E30: Check OA messages, broadcast schedule | F30: Segment refresh, broadcast content planning | G30: Zalo Ads + GHL
A31: Webinar Ads | B31: Education + Trust building + Conversion | C31: Consideration → Decision | D31: LP webinar, email sequence, Zoom setup | E31: Monitor registrations, reminder blast | F31: Post-webinar analysis, follow-up sequence | G31: Meta + Google + GHL
A32: Remarketing | B32: Re-engage warm/hot leads across platforms | C32: Decision → Conversion | D32: Dynamic creative, countdown, offers | E32: Check frequency, exclude converted | F32: Audience refresh, creative rotation | G32: All platforms + Birch
A33: Local SEO/GMB | B33: Local presence + Map visibility + Reviews | C33: Awareness (local) | D33: Ảnh, posts, review management | E33: Reply reviews, check listing accuracy | F33: Post 1 bài/tuần, update photos | G33: Google Business + Manual

Sheet 3. Master Table
A1: PHÂN BỔ – BỎ PHÚ NHUẬN – 11 DÒNG CƠ SỞ (Cần Giuộc→Tây Ninh, Rạch Giá→An Giang)
A2: Cấp | B2: Địa điểm | C2: Địa chỉ / Tỉnh | D2: HS | E2: CAC | F2: Điểm | G2: % | H2: Tổng NS | I2: Paid | J2: Tour | K2: Meta | L2: G.Search | M2: G.Display | N2: TikTok | O2: Zalo | P2: Webinar | Q2: Remarket | R2: Local SEO
A3: MN | B3: MN VA Gò Vấp | C3: 573 Lê Đức Thọ, Gò Vấp, TP.HCM | D3: 200 | E3: 0.85 | F3: =D3*E3 -> 170 | G3: =F3/F$14 -> 0.12564671 | H3: =G3*'1. Input'!B4 -> 1.6334072e+09 | I3: =G3*'1. Input'!B15 -> 1.067997e+09 | J3: =G3*'1. Input'!B10 -> 1.0051737e+08 | K3: =I3*'2. Paid Media'!B3 -> 4.0583888e+08 | L3: =I3*'2. Paid Media'!B4 -> 1.9223947e+08 | M3: =I3*'2. Paid Media'!B5 -> 74759793 | N3: =I3*'2. Paid Media'!B6 -> 1.067997e+08 | O3: =I3*'2. Paid Media'!B7 -> 74759793 | P3: =I3*'2. Paid Media'!B8 -> 53399852 | Q3: =I3*'2. Paid Media'!B9 -> 1.2815965e+08 | R3: =I3*'2. Paid Media'!B10 -> 53399852
A4: MN | B4: MN Nhân Lễ | C4: 22 D2, KDC Cần Giuộc, Tây Ninh | D4: 60 | E4: 0.85 | F4: =D4*E4 -> 51 | G4: =F4/F$14 -> 0.037694013 | H4: =G4*'1. Input'!B4 -> 4.9002217e+08 | I4: =G4*'1. Input'!B15 -> 3.2039911e+08 | J4: =G4*'1. Input'!B10 -> 30155211 | K4: =I4*'2. Paid Media'!B3 -> 1.2175166e+08 | L4: =I4*'2. Paid Media'!B4 -> 57671840 | M4: =I4*'2. Paid Media'!B5 -> 22427938 | N4: =I4*'2. Paid Media'!B6 -> 32039911 | O4: =I4*'2. Paid Media'!B7 -> 22427938 | P4: =I4*'2. Paid Media'!B8 -> 16019956 | Q4: =I4*'2. Paid Media'!B9 -> 38447894 | R4: =I4*'2. Paid Media'!B10 -> 16019956
A5: MN | B5: MN Thái Sơn | C5: KDC Thái Sơn, Cần Giuộc, Tây Ninh | D5: 60 | E5: 0.85 | F5: =D5*E5 -> 51 | G5: =F5/F$14 -> 0.037694013 | H5: =G5*'1. Input'!B4 -> 4.9002217e+08 | I5: =G5*'1. Input'!B15 -> 3.2039911e+08 | J5: =G5*'1. Input'!B10 -> 30155211 | K5: =I5*'2. Paid Media'!B3 -> 1.2175166e+08 | L5: =I5*'2. Paid Media'!B4 -> 57671840 | M5: =I5*'2. Paid Media'!B5 -> 22427938 | N5: =I5*'2. Paid Media'!B6 -> 32039911 | O5: =I5*'2. Paid Media'!B7 -> 22427938 | P5: =I5*'2. Paid Media'!B8 -> 16019956 | Q5: =I5*'2. Paid Media'!B9 -> 38447894 | R5: =I5*'2. Paid Media'!B10 -> 16019956
A6: MN | B6: MN Mekong Xanh | C6: Lô E7, KĐT Tây Bắc, Rạch Giá, An Giang | D6: 60 | E6: 0.85 | F6: =D6*E6 -> 51 | G6: =F6/F$14 -> 0.037694013 | H6: =G6*'1. Input'!B4 -> 4.9002217e+08 | I6: =G6*'1. Input'!B15 -> 3.2039911e+08 | J6: =G6*'1. Input'!B10 -> 30155211 | K6: =I6*'2. Paid Media'!B3 -> 1.2175166e+08 | L6: =I6*'2. Paid Media'!B4 -> 57671840 | M6: =I6*'2. Paid Media'!B5 -> 22427938 | N6: =I6*'2. Paid Media'!B6 -> 32039911 | O6: =I6*'2. Paid Media'!B7 -> 22427938 | P6: =I6*'2. Paid Media'!B8 -> 16019956 | Q6: =I6*'2. Paid Media'!B9 -> 38447894 | R6: =I6*'2. Paid Media'!B10 -> 16019956
A7: TH | B7: TH VA Gò Vấp | C7: 160/72 Phan Huy Ích, Gò Vấp, TP.HCM | D7: 150 | E7: 1 | F7: =D7*E7 -> 150 | G7: =F7/F$14 -> 0.11086475 | H7: =G7*'1. Input'!B4 -> 1.4412417e+09 | I7: =G7*'1. Input'!B15 -> 9.4235033e+08 | J7: =G7*'1. Input'!B10 -> 88691796 | K7: =I7*'2. Paid Media'!B3 -> 3.5809313e+08 | L7: =I7*'2. Paid Media'!B4 -> 1.6962306e+08 | M7: =I7*'2. Paid Media'!B5 -> 65964523 | N7: =I7*'2. Paid Media'!B6 -> 94235033 | O7: =I7*'2. Paid Media'!B7 -> 65964523 | P7: =I7*'2. Paid Media'!B8 -> 47117517 | Q7: =I7*'2. Paid Media'!B9 -> 1.1308204e+08 | R7: =I7*'2. Paid Media'!B10 -> 47117517
A8: TH | B8: TH VA Bình Tân | C8: Số 7 đường 38A, Tân Tạo, Bình Tân, TP.HCM | D8: 150 | E8: 1 | F8: =D8*E8 -> 150 | G8: =F8/F$14 -> 0.11086475 | H8: =G8*'1. Input'!B4 -> 1.4412417e+09 | I8: =G8*'1. Input'!B15 -> 9.4235033e+08 | J8: =G8*'1. Input'!B10 -> 88691796 | K8: =I8*'2. Paid Media'!B3 -> 3.5809313e+08 | L8: =I8*'2. Paid Media'!B4 -> 1.6962306e+08 | M8: =I8*'2. Paid Media'!B5 -> 65964523 | N8: =I8*'2. Paid Media'!B6 -> 94235033 | O8: =I8*'2. Paid Media'!B7 -> 65964523 | P8: =I8*'2. Paid Media'!B8 -> 47117517 | Q8: =I8*'2. Paid Media'!B9 -> 1.1308204e+08 | R8: =I8*'2. Paid Media'!B10 -> 47117517
A9: TH | B9: TH Thái Sơn | C9: KDC Thái Sơn, Cần Giuộc, Tây Ninh | D9: 60 | E9: 1 | F9: =D9*E9 -> 60 | G9: =F9/F$14 -> 0.044345898 | H9: =G9*'1. Input'!B4 -> 5.7649667e+08 | I9: =G9*'1. Input'!B15 -> 3.7694013e+08 | J9: =G9*'1. Input'!B10 -> 35476718 | K9: =I9*'2. Paid Media'!B3 -> 1.4323725e+08 | L9: =I9*'2. Paid Media'!B4 -> 67849224 | M9: =I9*'2. Paid Media'!B5 -> 26385809 | N9: =I9*'2. Paid Media'!B6 -> 37694013 | O9: =I9*'2. Paid Media'!B7 -> 26385809 | P9: =I9*'2. Paid Media'!B8 -> 18847007 | Q9: =I9*'2. Paid Media'!B9 -> 45232816 | R9: =I9*'2. Paid Media'!B10 -> 18847007
A10: TH | B10: TH Mekong Xanh | C10: Lô E7, KĐT Tây Bắc, Rạch Giá, An Giang | D10: 60 | E10: 1 | F10: =D10*E10 -> 60 | G10: =F10/F$14 -> 0.044345898 | H10: =G10*'1. Input'!B4 -> 5.7649667e+08 | I10: =G10*'1. Input'!B15 -> 3.7694013e+08 | J10: =G10*'1. Input'!B10 -> 35476718 | K10: =I10*'2. Paid Media'!B3 -> 1.4323725e+08 | L10: =I10*'2. Paid Media'!B4 -> 67849224 | M10: =I10*'2. Paid Media'!B5 -> 26385809 | N10: =I10*'2. Paid Media'!B6 -> 37694013 | O10: =I10*'2. Paid Media'!B7 -> 26385809 | P10: =I10*'2. Paid Media'!B8 -> 18847007 | Q10: =I10*'2. Paid Media'!B9 -> 45232816 | R10: =I10*'2. Paid Media'!B10 -> 18847007
A11: THCS | B11: THCS VA Gò Vấp | C11: 160/72 Phan Huy Ích, Gò Vấp, TP.HCM | D11: 200 | E11: 1.2 | F11: =D11*E11 -> 240 | G11: =F11/F$14 -> 0.17738359 | H11: =G11*'1. Input'!B4 -> 2.3059867e+09 | I11: =G11*'1. Input'!B15 -> 1.5077605e+09 | J11: =G11*'1. Input'!B10 -> 1.4190687e+08 | K11: =I11*'2. Paid Media'!B3 -> 5.72949e+08 | L11: =I11*'2. Paid Media'!B4 -> 2.713969e+08 | M11: =I11*'2. Paid Media'!B5 -> 1.0554324e+08 | N11: =I11*'2. Paid Media'!B6 -> 1.5077605e+08 | O11: =I11*'2. Paid Media'!B7 -> 1.0554324e+08 | P11: =I11*'2. Paid Media'!B8 -> 75388027 | Q11: =I11*'2. Paid Media'!B9 -> 1.8093126e+08 | R11: =I11*'2. Paid Media'!B10 -> 75388027
A12: THPT | B12: THPT VA Gò Vấp | C12: 160/72 Phan Huy Ích, Gò Vấp, TP.HCM | D12: 200 | E12: 1.35 | F12: =D12*E12 -> 270 | G12: =F12/F$14 -> 0.19955654 | H12: =G12*'1. Input'!B4 -> 2.594235e+09 | I12: =G12*'1. Input'!B15 -> 1.6962306e+09 | J12: =G12*'1. Input'!B10 -> 1.5964523e+08 | K12: =I12*'2. Paid Media'!B3 -> 6.4456763e+08 | L12: =I12*'2. Paid Media'!B4 -> 3.0532151e+08 | M12: =I12*'2. Paid Media'!B5 -> 1.1873614e+08 | N12: =I12*'2. Paid Media'!B6 -> 1.6962306e+08 | O12: =I12*'2. Paid Media'!B7 -> 1.1873614e+08 | P12: =I12*'2. Paid Media'!B8 -> 84811530 | Q12: =I12*'2. Paid Media'!B9 -> 2.0354767e+08 | R12: =I12*'2. Paid Media'!B10 -> 84811530
A13: Liên cấp | B13: Brand hệ thống | C13: Retarget + brand awareness chung | D13: 100 | E13: 1 | F13: =D13*E13 -> 100 | G13: =F13/F$14 -> 0.07390983 | H13: =G13*'1. Input'!B4 -> 9.6082779e+08 | I13: =G13*'1. Input'!B15 -> 6.2823356e+08 | J13: =G13*'1. Input'!B10 -> 59127864 | K13: =I13*'2. Paid Media'!B3 -> 2.3872875e+08 | L13: =I13*'2. Paid Media'!B4 -> 1.1308204e+08 | M13: =I13*'2. Paid Media'!B5 -> 43976349 | N13: =I13*'2. Paid Media'!B6 -> 62823356 | O13: =I13*'2. Paid Media'!B7 -> 43976349 | P13: =I13*'2. Paid Media'!B8 -> 31411678 | Q13: =I13*'2. Paid Media'!B9 -> 75388027 | R13: =I13*'2. Paid Media'!B10 -> 31411678
A14: TỔNG | D14: =SUM(D3:D13) -> 1300 | F14: =SUM(F3:F13) -> 1353 | G14: =SUM(G3:G13) -> 1 | H14: =SUM(H3:H13) -> 13000000000 | I14: =SUM(I3:I13) -> 8500000000 | J14: =SUM(J3:J13) -> 800000000 | K14: =SUM(K3:K13) -> 3230000000 | L14: =SUM(L3:L13) -> 1530000000 | M14: =SUM(M3:M13) -> 595000000 | ... R14: =SUM(R3:R13) -> 425000000

Sheet 4. Funnel
A1: PHỄU TUYỂN SINH 2026 — CHI TIẾT TỪNG CHIẾN DỊCH, ĐỊA ĐIỂM, CHƯƠNG TRÌNH
A3: A. KIẾN TRÚC TỔNG THỂ — 24 PHỄU TUYỂN SINH
A4: Mỗi phễu gồm 4-6 trang (pages), mỗi trang có URL riêng, tracking riêng, và remarketing audience riêng.
A5: Tất cả landing pages được xây trên GoHighLevel (GHL), domain: forms.truongvietanh.com
A7: STT | B7: Tên Phễu (Funnel Name) | C7: Mã phễu | D7: Cấp học | E7: Cơ sở | F7: Số trang | G7: URL gốc | H7: Mục tiêu | I7: Traffic sources | J7: Target leads/tháng | K7: Remarketing audience | L7: Trạng thái
A8: 1 | B8: Tuyển Sinh Mầm Non — Tổng | C8: FNL-MN-MAIN | D8: Mầm non | E8: Tất cả | F8: 6 | G8: forms.truongvietanh.com/tuyen-sinh-mam-non | H8: Lead → Tour → Enroll | I8: Meta Ads, Zalo Ads, Google | J8: 80 | K8: mn_visitors, mn_form_start, mn_form_complete | L8: ⬜ Cần tạo
A9: 2 | B9: Tuyển Sinh Tiểu Học — Tổng | C9: FNL-TH-MAIN | D9: Tiểu học | E9: Tất cả | F9: 6 | G9: forms.truongvietanh.com/tuyen-sinh-tieu-hoc | H9: Lead → Tour → Enroll | I9: Meta Ads, Google, Zalo | J9: 60 | K9: th_visitors, th_form_start, th_form_complete | L9: ⬜ Cần tạo
A10: 3 | B10: Tuyển Sinh THCS — Tổng | C10: FNL-THCS-MAIN | D10: THCS | E10: VA Gò Vấp | F10: 6 | G10: forms.truongvietanh.com/tuyen-sinh-thcs | H10: Lead → Tour → Enroll | I10: Meta Ads, Google, TikTok | J10: 40 | K10: thcs_visitors, thcs_form_start | L10: ⬜ Cần tạo
A11: 4 | B11: Tuyển Sinh THPT — Tổng | C11: FNL-THPT-MAIN | D11: THPT | E11: VA Gò Vấp | F11: 6 | G11: forms.truongvietanh.com/tuyen-sinh-thpt | H11: Lead → Tour → Enroll | I11: Meta Ads, Google, TikTok | J11: 30 | K11: thpt_visitors, thpt_form_start | L11: ⬜ Cần tạo
A12: 5 | B12: MN VA Gò Vấp — Campus Funnel | C12: FNL-MN-GV | D12: Mầm non | E12: MN VA Gò Vấp | F12: 5 | G12: forms.truongvietanh.com/mn-go-vap | H12: Lead → Tour cơ sở | I12: Meta (geo GV), Zalo | J12: 20 | K12: mn_gv_visitors | L12: ⬜ Cần tạo
A13: 6 | B13: MN Nhân Lễ — Campus Funnel | C13: FNL-MN-NL | D13: Mầm non | E13: MN Nhân Lễ | F13: 5 | G13: forms.truongvietanh.com/mn-nhan-le | H13: Lead → Tour cơ sở | I13: Meta (geo NL), Zalo | J13: 15 | K13: mn_nl_visitors | L13: ⬜ Cần tạo
A14: 7 | B14: MN+TH Thái Sơn — Campus Funnel | C14: FNL-TS | D14: MN+TH | E14: Thái Sơn | F14: 5 | G14: forms.truongvietanh.com/thai-son | H14: Lead → Tour cơ sở | I14: Meta (geo TS), Zalo | J14: 15 | K14: ts_visitors | L14: ⬜ Cần tạo
A15: 8 | B15: MN+TH Mekong Xanh — Campus Funnel | C15: FNL-MK | D15: MN+TH | E15: Mekong Xanh | F15: 5 | G15: forms.truongvietanh.com/mekong-xanh | H15: Lead → Tour cơ sở | I15: Meta (geo MK), Zalo | J15: 15 | K15: mk_visitors | L15: ⬜ Cần tạo
A16: 9 | B16: TH VA Gò Vấp — Campus Funnel | C16: FNL-TH-GV | D16: Tiểu học | E16: TH VA Gò Vấp | F16: 5 | G16: forms.truongvietanh.com/th-go-vap | H16: Lead → Tour cơ sở | I16: Meta (geo GV), Google | J16: 20 | K16: th_gv_visitors | L16: ⬜ Cần tạo
A17: 10 | B17: TH VA Bình Tân — Campus Funnel | C17: FNL-TH-BT | D17: Tiểu học | E17: TH VA Bình Tân | F17: 5 | G17: forms.truongvietanh.com/th-binh-tan | H17: Lead → Tour cơ sở | I17: Meta (geo BT), Zalo | J17: 15 | K17: th_bt_visitors | L17: ⬜ Cần tạo
A18: 11 | B18: Open Day T4 — Event Funnel | C18: FNL-OD-T4 | D18: Tất cả | E18: GV + GV | F18: 4 | G18: forms.truongvietanh.com/open-day-thang-4 | H18: Register → Attend | I18: All channels | J18: 100 đăng ký | K18: od_t4_visitors, od_t4_registered | L18: ⬜ Cần tạo
... A31: 24 | B31: Khai Giảng 2026 — Welcome | C31: FNL-KG | D31: Tất cả | E31: Tất cả | F31: 3 | G31: forms.truongvietanh.com/khai-giang-2026 | H31: Info → Confirm → Welcome | I31: Email, Zalo, SMS | J31: All enrolled | K31: kg_visitors | L31: ⬜ Cần tạo
A34: B. CHI TIẾT TỪNG TRANG — PHỄU "TUYỂN SINH MẦM NON" (FNL-MN-MAIN)
A35: Đây là mẫu chi tiết cho 1 phễu. Các phễu khác có cấu trúc tương tự, customize theo cấp học/cơ sở.
A37: Trang | B37: URL đầy đủ | C37: Tên trang (Page Title) | D37: Mục đích | E37: Nội dung chính trên trang | F37: Form fields | G37: CTA Button | H37: Pixel Events fired | I37: Remarketing Audience tạo | J37: Next step nếu submit | K37: Next step nếu KHÔNG submit | L37: A/B Test variants | M37: Ghi chú
A38: Trang 1: Landing Page chính | B38: https://forms.truongvietanh.com/tuyen-sinh-mam-non | C38: Tuyển Sinh Mầm Non 2026 — Trường Việt Anh | Nơi Con Yêu Lớn Khôn | D38: Thu hút → Giữ chân → Điền form | E38: Hero banner (hình HS mầm non vui vẻ) + Headline "Cho Con Khởi Đầu Tốt Nhất" → 3 USP icons (An toàn, Chương trình quốc tế, Giáo viên tận tâm) → Video tour trường 60s (autoplay muted) → 6 cơ sở trên bản đồ (click → campus page) → Chương trình học: Montessori, STEM, Song ngữ → 3 Testimonials PH (video + quote) → FAQ accordion (5 câu hỏi phổ biến) → CTA form cuối trang | F38: Họ tên PH*, SĐT*, Email, Tên bé, Năm sinh bé, Cơ sở quan tâm (dropdown 6), Nguồn biết (hidden UTM) | G38: ĐĂNG KÝ TƯ VẤN MIỄN PHÍ → | H38: PageView, ViewContent, InitiateCheckout (scroll 70%), Lead (form submit) | I38: mn_page_visitors (PageView) mn_page_engaged (ViewContent, >30s) mn_form_started (InitiateCheckout) mn_form_complete (Lead) | J38: → Trang 2: Thank You + Booking Tour | K38: → Retarget sau 1 ngày: Ad "Bạn đã xem chương trình MN — Đặt lịch tham quan ngay" → KHÔNG quay lại trang 1, đưa sang Trang 3 (Testimonial) | L38: Variant A: Hero = Video Variant B: Hero = Carousel hình Test 2 tuần, 50/50 traffic | M38: Mobile-first, load <3s, Lazy load images
A39: Trang 2: Thank You + Book Tour | B39: https://forms.truongvietanh.com/tuyen-sinh-mam-non/cam-on | C39: Cảm Ơn Bạn! Đặt Lịch Tham Quan Trường Ngay | D39: Confirm lead + Book tour ngay | E39: Heading: "Cảm ơn [Tên PH]! Chúng tôi sẽ liên hệ trong 30 phút" → GHL Calendar embed: chọn cơ sở → chọn ngày/giờ tour → Checklist "Khi đến tham quan, bạn sẽ được:" → Video "Một buổi tham quan tại Việt Anh" 2 phút → Social proof: "200+ PH đã đăng ký tham quan tháng này" → Share buttons: FB, Zalo | F39: Cơ sở (pre-filled), Ngày tour, Giờ tour, Số người đi cùng | G39: ĐẶT LỊCH THAM QUAN → | H39: Purchase (=Tour booked), Schedule | I39: mn_tour_booked (Purchase) | J39: → Trang 2b: Tour Confirmation + Add to Calendar | K39: → Nếu không book: GHL workflow Day+1 Email nhắc, Day+3 SMS, Day+5 Zalo | L39: Variant A: Calendar trước Variant B: Video trước rồi Calendar | M39: Pre-fill tên PH từ form trước
A40: Trang 2b: Tour Confirmation | B40: https://forms.truongvietanh.com/tuyen-sinh-mam-non/xac-nhan-tour | C40: Xác Nhận Lịch Tham Quan — [Cơ sở] — [Ngày/Giờ] | D40: Confirm + prepare PH cho tour | E40: Heading: "Tuyệt vời! Hẹn gặp bạn tại [Cơ sở] vào [Ngày/Giờ]" → Bản đồ Google Maps cơ sở → Hướng dẫn đường đi + chỗ đậu xe → Checklist chuẩn bị: mang theo CMND, bé đi cùng → Add to Google Calendar / iCal buttons → Zalo OA QR code: "Follow để nhận nhắc nhở" | F40: Không có form (confirmation only) | G40: THÊM VÀO LỊCH → | H40: CompleteRegistration | I40: mn_tour_confirmed | J40: → GHL: -24h SMS reminder, -2h Zalo reminder | K40: → Nếu no-show: Day+1 email "Rất tiếc bạn không đến — Đặt lại lịch?" | L40: N/A | M40: Auto-generate từ GHL calendar data
A41: Trang 3: Testimonial Social Proof | B41: https://forms.truongvietanh.com/tuyen-sinh-mam-non/phu-huynh-noi-gi | C41: Phụ Huynh Nói Gì Về Trường Việt Anh? — Mầm Non | D41: Build trust cho leads đã visit trang 1 nhưng chưa submit form | E41: Heading: "Hơn 5,000 Phụ Huynh Đã Tin Tưởng Chọn Việt Anh" → 10 video testimonials PH (30-60s mỗi video) → 20 quote cards với hình PH + con → Rating stars: 4.8/5 (500+ đánh giá) → Before/After stories: "Bé nhút nhát → Tự tin sau 3 tháng" → CTA form: "Bạn cũng muốn con trải nghiệm?" | F41: Họ tên PH*, SĐT*, Cấp học quan tâm | G41: ĐĂNG KÝ TRẢI NGHIỆM → | H41: ViewContent, Lead (form submit) | I41: mn_testimonial_viewers | J41: → Trang 2: Thank You + Book Tour | K41: → Retarget: Ad "Xem thêm câu chuyện PH" → Trang 4 (Chương trình) | L41: Variant A: Video testimonials trước Variant B: Quote cards trước | M41: REMARKETING PAGE — chỉ cho người đã visit Trang 1 mà chưa submit
A42: Trang 4: Chương Trình Học Chi Tiết | B42: https://forms.truongvietanh.com/tuyen-sinh-mam-non/chuong-trinh | C42: Chương Trình Mầm Non Quốc Tế — Montessori, STEM, Song Ngữ | D42: Cung cấp thông tin sâu cho PH đang so sánh trường | E42: Heading: "Chương Trình Được Thiết Kế Riêng Cho Từng Giai Đoạn Phát Triển" → Infographic: Lộ trình 3 năm MN (Nhà trẻ → Mầm → Lá) → 5 tab content: Montessori, STEM, Song ngữ, Kỹ năng sống, Thể chất → So sánh bảng: Việt Anh vs Trường công vs Trường tư khác → Download PDF: "Cẩm Nang Chọn Trường Mầm Non" (lead magnet) → CTA: "Đăng ký để nhận tư vấn chương trình phù hợp cho bé" | F42: Họ tên PH*, SĐT*, Email*, Tên bé, Tuổi bé, Chương trình quan tâm (multi-select) | G42: TẢI CẨM NANG + TƯ VẤN → | H42: ViewContent, AddToCart (download PDF), Lead (form) | I42: mn_program_viewers mn_pdf_downloaded (AddToCart) | J42: → Trang 2: Thank You + Book Tour (nếu form) → Email: Gửi PDF + Nurture sequence | K42: → Retarget: Ad "So sánh chương trình — Tham quan để cảm nhận" → Trang 5 | L42: Variant A: Tab content Variant B: Long scroll | M42: REMARKETING PAGE — cho người đã xem Trang 3 hoặc Trang 1 lần 2+
A43: Trang 5: Học Phí & Ưu Đãi | B43: https://forms.truongvietanh.com/tuyen-sinh-mam-non/hoc-phi | C43: Học Phí Mầm Non 2026 — Ưu Đãi Đặc Biệt Khi Đăng Ký Sớm | D43: Cuối funnel — quyết định tài chính, push enrollment | E43: Heading: "Đầu Tư Cho Con — Học Phí Minh Bạch, Ưu Đãi Hấp Dẫn" → Bảng học phí theo cơ sở (6 cơ sở) → Phí bao gồm: ăn, xe, đồng phục, sách, ngoại khóa → Ưu đãi: Giảm 10% nếu đăng ký trước 30/6, Giảm 5% con thứ 2 → Phương thức thanh toán: trả góp, học kỳ, năm → Học bổng: link đến FNL-HB → Countdown timer: "Ưu đãi còn [X] ngày" → CTA: "Đăng ký ngay để nhận ưu đãi" | F43: Họ tên PH*, SĐT*, Cơ sở*, Cấp học*, Phương thức TT, Mã giới thiệu (optional) | G43: ĐĂNG KÝ NHẬN ƯU ĐÃI → | H43: ViewContent, AddPaymentInfo (view học phí), Lead (form), Purchase (nếu đặt cọc online) | I43: mn_tuition_viewers mn_tuition_engaged (>60s) | J43: → Trang 2: Thank You + Book Tour → GHL: High-priority lead, auto-call trong 15 phút | K43: → Retarget: Ad "Chỉ còn [X] ngày ưu đãi — Đăng ký ngay!" (urgency) | L43: Variant A: Countdown timer Variant B: Social proof counter | M43: BOTTOM FUNNEL — người xem trang này = ý định cao, ưu tiên follow up nhanh
A46: C. REMARKETING SEQUENCES — LOGIC CHUYỂN TRANG PHỄU
A47: Nguyên tắc vàng: KHÔNG BAO GIỜ cho khách hàng xem lại trang họ đã thấy. Luôn đưa sang trang tiếp theo trong phễu.
A49: Hành vi khách hàng | B49: Audience tạo | C49: Audience loại trừ (Exclude) | D49: Ads hiển thị | E49: Landing page đích | F49: Thời gian trigger | G49: Budget/ngày | H49: Kênh chạy | I49: Duration | J49: Ghi chú
A50: Đã vào Trang 1 (LP chính) nhưng CHƯA điền form | B50: mn_page_visitors | C50: mn_form_complete (đã điền form) mn_tour_booked (đã book tour) | D50: Ad: "Hơn 5,000 PH đã tin tưởng — Xem họ nói gì" Format: Video testimonial 30s | E50: Trang 3: forms.truongvietanh.com/tuyen-sinh-mam-non/phu-huynh-noi-gi | F50: Sau 1 ngày (24h) | G50: 200,000 VND | H50: Meta Ads, TikTok | I50: 14 ngày | J50: KHÔNG đưa về Trang 1. Đưa sang Testimonial để build trust
A51: Đã vào Trang 1 LẦN 2+ (return visitor) nhưng chưa submit | B51: mn_page_visitors (frequency ≥2) | C51: mn_form_complete | D51: Ad: "Chương trình MN Quốc Tế — So sánh chi tiết" Format: Carousel 5 slides | E51: Trang 4: forms.truongvietanh.com/tuyen-sinh-mam-non/chuong-trinh | F51: Ngay lập tức | G51: 150,000 VND | H51: Meta Ads | I51: 14 ngày | J51: Return visitor = quan tâm cao. Cung cấp thông tin sâu hơn
A52: Đã xem Trang 3 (Testimonial) nhưng chưa submit form | B52: mn_testimonial_viewers | C52: mn_form_complete mn_page_visitors (Trang 4 đã xem) | D52: Ad: "So sánh chương trình — Montessori vs STEM vs Song ngữ" Format: Infographic carousel | E52: Trang 4: forms.truongvietanh.com/tuyen-sinh-mam-non/chuong-trinh | F52: Sau 2 ngày | G52: 150,000 VND | H52: Meta Ads | I52: 14 ngày | J52: Đã tin tưởng (xem testimonial) → giờ cần thông tin chương trình
A53: Đã xem Trang 4 (Chương trình) nhưng chưa submit | B53: mn_program_viewers | C53: mn_form_complete mn_tuition_viewers | D53: Ad: "Học phí MN 2026 — Ưu đãi giảm 10% đăng ký sớm" Format: Single image + countdown | E53: Trang 5: forms.truongvietanh.com/tuyen-sinh-mam-non/hoc-phi | F53: Sau 2 ngày | G53: 200,000 VND | H53: Meta Ads, Zalo | I53: 14 ngày | J53: Đã nghiên cứu chương trình → giờ quan tâm giá cả
A54: Đã xem Trang 5 (Học phí) nhưng chưa submit | B54: mn_tuition_viewers | C54: mn_form_complete | D54: Ad: "Ưu đãi chỉ còn [X] ngày — Đăng ký tư vấn ngay" Format: Video urgency 15s + CTA | E54: Trang 1: forms.truongvietanh.com/tuyen-sinh-mam-non (quay lại LP với variant B) | F54: Sau 1 ngày | G54: 300,000 VND | H54: Meta, Zalo, TikTok | I54: 7 ngày | J54: Đã xem hết funnel → urgency push. Lần này dùng Variant B của Trang 1
A55: Đã điền form Trang 1 nhưng CHƯA book tour | B55: mn_form_complete | C55: mn_tour_booked | D55: Ad: "Bạn đã đăng ký — Đặt lịch tham quan ngay hôm nay!" Format: Dynamic với tên cơ sở | E55: Trang 2: forms.truongvietanh.com/tuyen-sinh-mam-non/cam-on (scroll to calendar) | F55: Sau 2 ngày | G55: 150,000 VND | H55: Meta Ads | I55: 14 ngày | J55: Lead đã có nhưng chưa book tour. Push booking
A56: Đã book tour nhưng NO-SHOW | B56: mn_tour_booked | C56: mn_tour_confirmed (actually attended) | D56: Ad: "Rất tiếc bạn chưa đến — Đặt lại lịch tham quan" Format: Friendly reminder video | E56: Trang 2: forms.truongvietanh.com/tuyen-sinh-mam-non/cam-on | F56: Sau 1 ngày sau tour date | G56: 100,000 VND | H56: Meta, Zalo | I56: 14 ngày | J56: GHL tag "no-show" → trigger remarketing + email + Zalo message
A57: Đã tham quan (Tour completed) nhưng chưa enroll | B57: mn_tour_confirmed | C57: mn_enrolled | D57: Ad: "Bé [dynamic] đã rất thích — Đăng ký ngay để giữ chỗ" Format: Testimonial + Urgency | E57: Trang 5: forms.truongvietanh.com/tuyen-sinh-mam-non/hoc-phi | F57: Sau 3 ngày sau tour | G57: 200,000 VND | H57: Meta, Zalo, Email | I57: 30 ngày | J57: BOTTOM FUNNEL remarketing — conversion push mạnh nhất
A58: Đã download PDF cẩm nang nhưng chưa điền form tư vấn | B58: mn_pdf_downloaded | C58: mn_form_complete | D58: Ad: "Bạn đã tải Cẩm Nang — Đăng ký tư vấn để chọn chương trình phù hợp" Format: Carousel tips | E58: Trang 1: forms.truongvietanh.com/tuyen-sinh-mam-non (variant B) | F58: Sau 3 ngày | G58: 100,000 VND | H58: Meta Ads | I58: 14 ngày | J58: Lead magnet đã capture interest → push form submission
A59: Cold lead 30+ ngày không hoạt động | B59: All mn_* audiences | C59: mn_enrolled mn_active_last_14_days | D59: Ad: "Cơ hội cuối — Ưu đãi đặc biệt chỉ dành cho bạn" Format: Personalized offer | E59: Trang 5: forms.truongvietanh.com/tuyen-sinh-mam-non/hoc-phi (với param ?offer=winback) | F59: Sau 30 ngày cold | G59: 100,000 VND | H59: Meta, Zalo | I59: 14 ngày | J59: Win-back campaign. Special discount code.
A62: D. URL MAP — TẤT CẢ CÁC TRANG PHỄU THEO CƠ SỞ
A64: Cơ sở | B64: Landing Page chính | C64: Thank You | D64: Tour Confirmation | E64: Testimonial | F64: Chương trình | G64: Học phí
A65: MN VA Gò Vấp | B65: forms.truongvietanh.com/mn-go-vap | C65: forms.truongvietanh.com/mn-go-vap/cam-on | D65: forms.truongvietanh.com/mn-go-vap/xac-nhan | E65: forms.truongvietanh.com/mn-go-vap/review | F65: forms.truongvietanh.com/mn-go-vap/chuong-trinh | G65: forms.truongvietanh.com/mn-go-vap/hoc-phi
A66: MN Nhân Lễ | B66: forms.truongvietanh.com/mn-nhan-le | C66: forms.truongvietanh.com/mn-nhan-le/cam-on | D66: forms.truongvietanh.com/mn-nhan-le/xac-nhan | E66: forms.truongvietanh.com/mn-nhan-le/review | F66: forms.truongvietanh.com/mn-nhan-le/chuong-trinh | G66: forms.truongvietanh.com/mn-nhan-le/hoc-phi
A67: MN+TH Thái Sơn | B67: forms.truongvietanh.com/thai-son | C67: forms.truongvietanh.com/thai-son/cam-on | D67: forms.truongvietanh.com/thai-son/xac-nhan | E67: forms.truongvietanh.com/thai-son/review | F67: forms.truongvietanh.com/thai-son/chuong-trinh | G67: forms.truongvietanh.com/thai-son/hoc-phi
A68: MN+TH Mekong Xanh | B68: forms.truongvietanh.com/mekong-xanh | C68: forms.truongvietanh.com/mekong-xanh/cam-on | D68: forms.truongvietanh.com/mekong-xanh/xac-nhan | E68: forms.truongvietanh.com/mekong-xanh/review | F68: forms.truongvietanh.com/mekong-xanh/chuong-trinh | G68: forms.truongvietanh.com/mekong-xanh/hoc-phi
A69: TH VA Gò Vấp | B69: forms.truongvietanh.com/th-go-vap | C69: forms.truongvietanh.com/th-go-vap/cam-on | D69: forms.truongvietanh.com/th-go-vap/xac-nhan | E69: forms.truongvietanh.com/th-go-vap/review | F69: forms.truongvietanh.com/th-go-vap/chuong-trinh | G69: forms.truongvietanh.com/th-go-vap/hoc-phi
A70: TH VA Bình Tân | B70: forms.truongvietanh.com/th-binh-tan | C70: forms.truongvietanh.com/th-binh-tan/cam-on | D70: forms.truongvietanh.com/th-binh-tan/xac-nhan | E70: forms.truongvietanh.com/th-binh-tan/review | F70: forms.truongvietanh.com/th-binh-tan/chuong-trinh | G70: forms.truongvietanh.com/th-binh-tan/hoc-phi
A71: THCS VA Gò Vấp | B71: forms.truongvietanh.com/tuyen-sinh-thcs | C71: forms.truongvietanh.com/tuyen-sinh-thcs/cam-on | D71: forms.truongvietanh.com/tuyen-sinh-thcs/xac-nhan | E71: forms.truongvietanh.com/tuyen-sinh-thcs/review | F71: forms.truongvietanh.com/tuyen-sinh-thcs/chuong-trinh | G71: forms.truongvietanh.com/tuyen-sinh-thcs/hoc-phi
A72: THPT VA Gò Vấp | B72: forms.truongvietanh.com/tuyen-sinh-thpt | C72: forms.truongvietanh.com/tuyen-sinh-thpt/cam-on | D72: forms.truongvietanh.com/tuyen-sinh-thpt/xac-nhan | E72: forms.truongvietanh.com/tuyen-sinh-thpt/review | F72: forms.truongvietanh.com/tuyen-sinh-thpt/chuong-trinh | G72: forms.truongvietanh.com/tuyen-sinh-thpt/hoc-phi
A73: Open Day T6 | B73: forms.truongvietanh.com/mega-open-day-2026 | C73: forms.truongvietanh.com/mega-open-day-2026/cam-on | D73: forms.truongvietanh.com/mega-open-day-2026/xac-nhan | E73: N/A | F73: N/A | G73: N/A
A74: Webinar MN | B74: forms.truongvietanh.com/webinar-mam-non | C74: forms.truongvietanh.com/webinar-mam-non/cam-on | D74: forms.truongvietanh.com/webinar-mam-non/replay | E74: N/A | F74: N/A | G74: N/A
A75: Học Bổng | B75: forms.truongvietanh.com/hoc-bong-2026 | C75: forms.truongvietanh.com/hoc-bong-2026/cam-on | D75: forms.truongvietanh.com/hoc-bong-2026/ket-qua | E75: N/A | F75: N/A | G75: N/A
A76: Referral | B76: forms.truongvietanh.com/gioi-thieu-ban | C76: forms.truongvietanh.com/gioi-thieu-ban/cam-on | D76: N/A | E76: N/A | F76: N/A | G76: N/A
A79: E. PHỄU SỰ KIỆN — OPEN DAY T6 "MEGA OPEN DAY 2026" (FNL-OD-T6)
A81: Trang | B81: URL | C81: Nội dung | D81: Form fields | E81: Pixel Events | F81: Remarketing | G81: Next Step
A82: 1. Landing Page Sự kiện | B82: forms.truongvietanh.com/mega-open-day-2026 | C82: Hero: "MEGA OPEN DAY 2026 — Tham Quan 6 Cơ Sở Cùng Lúc!" → Countdown timer → Date/Time → 6 locations trên map → Agenda: 8:00 Welcome, 8:30 Tour, 9:30 Q&A, 10:30 Ưu đãi → Speakers: Hiệu trưởng 6 cơ sở → Quà tặng: Ba lô, sách, voucher giảm học phí → Testimonial từ Open Day trước → Form đăng ký | D82: Họ tên*, SĐT*, Email, Số con, Tuổi con, Cấp học*, Cơ sở muốn tham quan* (multi), Xe đưa đón (Y/N) | E82: PageView, ViewContent, Lead (form submit) | F82: od_visitors → nếu chưa submit: Ad "Chỉ còn [X] ngày — Đăng ký ngay!" | G82: → Trang 2: Confirmation
A83: 2. Confirmation + Details | B83: forms.truongvietanh.com/mega-open-day-2026/cam-on | C83: "Bạn đã đăng ký thành công! Hẹn gặp [Ngày]" → QR code check-in → Map + hướng dẫn đường đi từng cơ sở → Add to Calendar buttons → Share invite: "Mời bạn bè cùng đi" | D83: Không có form | E83: Purchase (confirmed), CompleteRegistration | F83: od_confirmed → -3d, -1d, -2h reminder ads | G83: → GHL workflow: -24h SMS, -2h Zalo reminder
A84: 3. Post-Event Follow-up | B84: forms.truongvietanh.com/mega-open-day-2026/cam-nhan | C84: "Cảm ơn bạn đã tham dự! Chia sẻ cảm nhận" → Feedback form: rating 1-5, comments → Photo gallery sự kiện → Video recap 3 phút → CTA: "Đăng ký nhận ưu đãi đặc biệt dành cho PH tham dự" | D84: Rating*, Feedback, Quan tâm cấp học, Muốn đăng ký (Y/N) | E84: ViewContent, Lead (feedback form) | F84: od_attended_not_enrolled → Ads: Ưu đãi đặc biệt cho PH đã tham dự | G84: → GHL: If "Muốn đăng ký = Y" → Priority follow-up trong 2h
A85: 4. Ưu đãi Post-Event | B85: forms.truongvietanh.com/mega-open-day-2026/uu-dai | C85: "Ưu Đãi Đặc Biệt — Chỉ Dành Cho PH Tham Dự Open Day" → Giảm 15% phí ghi danh (vs 10% bình thường) → Tặng đồng phục + ba lô → Countdown: "Ưu đãi hết hạn sau 7 ngày" → CTA: Đăng ký ngay | D85: Họ tên*, SĐT*, Cơ sở*, Cấp học*, Mã ưu đãi (auto-fill) | E85: ViewContent, AddPaymentInfo, Lead | F85: od_offer_viewers → If not convert in 3d: SMS reminder | G85: → GHL: Hot lead, auto-assign tư vấn viên → Call trong 1h

Sheet 5. Google Ads Chi Tiết
A1: KẾ HOẠCH GOOGLE ADS – CẤU TRÚC TÀI KHOẢN + CAMPAIGN + KEYWORD + RSA + BIRCH
A3: A. CẤU TRÚC TÀI KHOẢN GOOGLE ADS
A4: Cấp độ | B4: Tên | C4: Mô tả | D4: Ngân sách | E4: Ghi chú
A5: Account | B5: VA_TuyenSinh_2026 | C5: Tài khoản chính cho tuyển sinh | D5: ='1. Input'!B15*0.25 -> 2125000000 | E5: Tổng Google = 25% Paid Media
A6: Campaign | B6: S_BRAND_System | C6: Brand search toàn hệ thống | D6: Auto | E6: Luôn bật, không pause
A7: Campaign | B7: S_MN_GV_Generic | C7: Search mầm non Gò Vấp generic | D7: Daily cap | E7: Keyword: mầm non song ngữ gò vấp
A8: Campaign | B8: S_MN_GV_HighIntent | C8: Search mầm non Gò Vấp high intent | D8: Daily cap | E8: Keyword: học phí mầm non, tuyển sinh mầm non
A9: Campaign | B9: S_MN_Tinh_Generic | C9: Search mầm non tỉnh (Tây Ninh, An Giang) | D9: Daily cap | E9: Local intent tỉnh
A10: Campaign | B10: S_TH_GV_Generic | C10: Search tiểu học Gò Vấp | D10: Daily cap | E10: Lớp 1, song ngữ, học phí
A11: Campaign | B11: S_TH_BT_Generic | C11: Search tiểu học Bình Tân | D11: Daily cap | E11: Local + song ngữ
A12: Campaign | B12: S_TH_Tinh_Generic | C12: Search tiểu học tỉnh | D12: Daily cap | E12: Thái Sơn + Mekong Xanh
A13: Campaign | B13: S_THCS_GV_Generic | C13: Search THCS Gò Vấp generic | D13: Daily cap | E13: Lớp 6, trường cấp 2
A14: Campaign | B14: S_THCS_GV_HighIntent | C14: Search THCS Gò Vấp high intent | D14: Daily cap | E14: Tuyển sinh lớp 6, học phí
A15: Campaign | B15: S_THPT_GV_Generic | C15: Search THPT Gò Vấp generic | D15: Daily cap | E15: Lớp 10, trường cấp 3
A16: Campaign | B16: S_THPT_GV_HighIntent | C16: Search THPT Gò Vấp high intent | D16: Daily cap | E16: Tuyển sinh lớp 10, học bổng
A17: Campaign | B17: S_THPT_GV_Webinar | C17: Search THPT webinar | D17: Daily cap | E17: Hội thảo, lộ trình, chọn trường
... A24: Campaign | B24: PMAX_Test | C24: Performance Max test | D24: Daily cap 2% | E24: Chỉ test từ T6, không scale sớm
A26: B. KEYWORD BANK (EXACT + PHRASE)
A27: Cấp | B27: Nhóm | C27: Match | D27: Keyword | E27: Campaign | F27: Ghi chú
A28: MN | B28: Brand | C28: Exact | D28: [trường mầm non việt anh gò vấp] | E28: S_BRAND
A29: MN | B29: Brand | C29: Exact | D29: [mầm non việt anh lê đức thọ] | E29: S_BRAND
A30: MN | B30: Generic | C30: Exact | D30: [trường mầm non song ngữ gò vấp] | E30: S_MN_GV_Generic | F30: Top KW
A31: MN | B31: Generic | C31: Exact | D31: [trường mầm non tư thục gò vấp] | E31: S_MN_GV_Generic
A32: MN | B32: Generic | C32: Phrase | D32: "trường mầm non gần nhà" | E32: S_MN_GV_Generic | F32: Local
A33: MN | B33: Generic | C33: Phrase | D33: "mầm non song ngữ" | E33: S_MN_GV_Generic
A34: MN | B34: HighIntent | C34: Exact | D34: [học phí mầm non song ngữ gò vấp] | E34: S_MN_GV_HighIntent | F34: HOT
A35: MN | B35: HighIntent | C35: Exact | D35: [tuyển sinh mầm non gò vấp] | E35: S_MN_GV_HighIntent | F35: HOT
A36: MN | B36: Pain | C36: Phrase | D36: "trường mầm non an toàn" | E36: S_MN_GV_Generic
A37: MN | B37: Pain | C37: Phrase | D37: "trường mầm non có camera" | E37: S_MN_GV_Generic
A38: TH | B38: Brand | C38: Exact | D38: [trường việt anh gò vấp] | E38: S_BRAND
A39: TH | B39: Brand | C39: Exact | D39: [trường việt anh bình tân] | E39: S_BRAND
A40: TH | B40: Generic | C40: Exact | D40: [trường tiểu học song ngữ gò vấp] | E40: S_TH_GV_Generic
A41: TH | B41: Generic | C41: Exact | D41: [trường tiểu học tư thục bình tân] | E41: S_TH_BT_Generic
A42: TH | B42: HighIntent | C42: Exact | D42: [tuyển sinh lớp 1 trường tư] | E42: S_TH_GV_HighIntent | F42: HOT
A43: TH | B43: HighIntent | C43: Exact | D43: [học phí tiểu học song ngữ] | E43: S_TH_GV_HighIntent | F43: HOT
A44: THCS | B44: Generic | C44: Exact | D44: [trường thcs tư thục gò vấp] | E44: S_THCS_GV_Generic
A45: THCS | B45: Generic | C45: Phrase | D45: "trường cấp 2 song ngữ" | E45: S_THCS_GV_Generic
A46: THCS | B46: HighIntent | C46: Exact | D46: [tuyển sinh lớp 6 trường tư] | E46: S_THCS_GV_HighIntent | F46: HOT
A47: THCS | B47: HighIntent | C47: Exact | D47: [học phí thcs song ngữ] | E47: S_THCS_GV_HighIntent
A48: THPT | B48: Generic | C48: Exact | D48: [trường thpt tư thục gò vấp] | E48: S_THPT_GV_Generic
A49: THPT | B49: Generic | C49: Phrase | D49: "trường cấp 3 song ngữ" | E49: S_THPT_GV_Generic
A50: THPT | B50: HighIntent | C50: Exact | D50: [tuyển sinh lớp 10 trường tư] | E50: S_THPT_GV_HighIntent | F50: HOT
A51: THPT | B51: HighIntent | C51: Exact | D51: [học bổng lớp 10] | E51: S_THPT_GV_HighIntent | F51: HOT
A52: THPT | B52: HighIntent | C52: Exact | D52: [chuyển trường cấp 3] | E52: S_THPT_GV_HighIntent | F52: Late intake
A53: THPT | B53: Webinar | C53: Phrase | D53: "hội thảo chọn trường lớp 10" | E53: S_THPT_GV_Webinar
A55: C. NEGATIVE KEYWORDS
A56: Scope | B56: Match | C56: Keyword | D56: Lý do
A57: Toàn TK | B57: Phrase | C57: miễn phí | D57: Không phù hợp
A58: Toàn TK | B58: Phrase | C58: giáo án | D58: Không phù hợp
A59: Toàn TK | B59: Phrase | C59: tuyển dụng | D59: Nhầm
A60: Toàn TK | B60: Phrase | C60: việc làm | D60: Nhầm
A61: Toàn TK | B61: Phrase | C61: giáo viên | D61: Nhầm
A62: Toàn TK | B62: Phrase | C62: đại học | D62: Sai cấp
A63: Toàn TK | B63: Phrase | C63: du học | D63: Sai
A64: Toàn TK | B64: Phrase | C64: gia sư | D64: Sai
A65: Toàn TK | B65: Phrase | C65: trường công | D65: Sai đối tượng
A66: Toàn TK | B66: Phrase | C66: điểm chuẩn | D66: Sai intent
A67: Toàn TK | B67: Phrase | C67: đề thi | D67: Sai intent
... A72: THPT | B72: Phrase | C72: đề toán | D72: Sai
A74: D. RSA – MẪU QUẢNG CÁO
A75: Cấp | B75: Loại | C75: Nội dung | D75: Pin vị trí | E75: Ghi chú
A76: MN | B76: Headline | C76: Tuyển Sinh Mầm Non 2026 | D76: H1
A77: MN | B77: Headline | C77: Trường Mầm Non Song Ngữ Gò Vấp | D77: H2 | E77: Campus
A78: MN | B78: Headline | C78: Môi Trường An Toàn Cho Bé | E78: USP
A79: MN | B79: Headline | C79: Đăng Ký School Tour Ngay | E79: CTA
A80: MN | B80: Headline | C80: Học Phí Phù Hợp, Minh Bạch
A81: MN | B81: Headline | C81: Gần Nhà, Thuận Tiện Đưa Đón | E81: Local
A82: MN | B82: Description | C82: Tìm hiểu chương trình mầm non và lịch tham quan trường. Đăng ký tư vấn nhanh. | D82: D1
A83: MN | B83: Description | C83: Môi trường an toàn, giáo viên tận tâm. Xem cơ sở thực tế ngay. | D83: D2
A84: TH | B84: Headline | C84: Tuyển Sinh Lớp 1 Năm Học 2026 | D84: H1
A85: TH | B85: Headline | C85: Trường Tiểu Học Song Ngữ Gò Vấp | D85: H2
A86: TH | B86: Headline | C86: Tiếng Anh Có Lộ Trình Rõ Ràng | E86: USP
A87: TH | B87: Headline | C87: Mời Tham Quan Trường Ngay | E87: CTA
A88: TH | B88: Description | C88: Tìm hiểu chương trình tiểu học và lộ trình tiếng Anh phù hợp cho con. | D88: D1
A89: THCS | B89: Headline | C89: Tuyển Sinh Lớp 6 Năm 2026 | D89: H1
A90: THCS | B90: Headline | C90: Trường THCS Việt Anh Gò Vấp | D90: H2
A91: THCS | B91: Headline | C91: Theo Sát Học Sinh Giai Đoạn Bản Lề | E91: USP
A92: THCS | B92: Description | C92: THCS cần môi trường nghiêm túc, theo sát từng học sinh. Đăng ký tư vấn. | D92: D1
A93: THPT | B93: Headline | C93: Tuyển Sinh Lớp 10 Năm 2026 | D93: H1
A94: THPT | B94: Headline | C94: Trường THPT Việt Anh Gò Vấp | D94: H2
A95: THPT | B95: Headline | C95: Học Bổng Tuyển Sinh Lớp 10 | E95: Offer
A96: THPT | B96: Headline | C96: Định Hướng Đại Học Và Tương Lai | E96: USP
A97: THPT | B97: Description | C97: Đăng ký tư vấn lớp 10, học bổng và tham quan campus ngay hôm nay. | D97: D1
A99: E. BIRCH PPC – CẤU HÌNH CHI TIẾT
A100: Bước | B100: Hành động | C100: Chi tiết | D100: Tool/Nơi thực hiện | E100: Timeline | F100: Trạng thái
A101: 1 | B101: Tạo Workspace | C101: TruongVietAnh_GoogleAds_2026 | D101: Birch > Workspace | E101: Ngày 1 | F101: ☐
A102: 2 | B102: Kết nối Google Ads | C102: Link account có admin rights | D102: Birch > Settings > Ad Platforms | E102: Ngày 1 | F102: ☐
A103: 3 | B103: Kết nối GA4 | C103: Link GA4 property website + LP | D103: Birch > Settings > Google Analytics | E103: Ngày 1 | F103: ☐
A104: 4 | B104: Kết nối Google Sheets | C104: Share sheet cho service account Birch | D104: Google Sheets > Share | E104: Ngày 1 | F104: ☐
A105: 5 | B105: Tạo Custom Metrics | C105: Qualified Rate, Booked Tour Rate, Cost/Tour, CAC | D105: Birch > Custom Metrics | E105: Ngày 2 | F105: ☐
A106: 6 | B106: Rule: Alert CPL cao | C106: IF CPL > target 20% for 3 days → Slack alert | D106: Birch > Automation Rules | E106: Ngày 2 | F106: ☐
A107: 7 | B107: Rule: Alert zero lead | C107: IF spend > 500K + leads = 0 for 3 days → alert | D107: Birch > Automation Rules | E107: Ngày 2 | F107: ☐
A108: 8 | B108: Rule: Scale campaign tốt | C108: IF CPL < target + Qualified > 50% → tăng budget 15% | D108: Birch > Automation Rules | E108: Tuần 2 | F108: ☐
A109: 9 | B109: Rule: Giảm campaign yếu | C109: IF CPL > target 30% + tour = 0 → giảm 15% | D109: Birch > Automation Rules | E109: Tuần 2 | F109: ☐
A110: 10 | B110: Rule: Pause KW lãng phí | C110: IF KW spend > 500K + conv = 0 → pause | D110: Birch > Automation Rules | E110: Tuần 2 | F110: ☐
A111: 11 | B111: Rule: Brand always-on | C111: IF brand campaign paused → auto-notify | D111: Birch > Automation Rules | E111: Ngày 2 | F111: ☐
... A113: 13 | B113: Negative KW auto-check | C113: Shared negative list, auto-update weekly | D113: Birch > Rules + Manual | E113: Tuần 1 | F113: ☐
A115: F. LANDING PAGE BLUEPRINT
A116: LP | B116: URL slug | C116: Cấp học | D116: Cơ sở | E116: Khối cần có | F116: Form fields | G116: GTM Events
A117: LP_MN_GV | B117: /mam-non-go-vap | C117: MN | D117: Gò Vấp | E117: Hero video + USP + Ảnh + Testi + FAQ + Map + Form | F117: Tên, SĐT, Cơ sở, Cấp, Nhu cầu | G117: form_submit, click_call, click_zalo
...

Sheet 6. Meta Ads Chi Tiết
A1: KẾ HOẠCH META ADS – CẤU TRÚC + AUDIENCE + CREATIVE + PIXEL + GHL
A3: A. CẤU TRÚC TÀI KHOẢN META ADS (BỎ PHÚ NHUẬN)
A4: Campaign | B4: Objective | C4: Audience | D4: Creative | E4: Budget/tháng | F4: LP | G4: GHL Pipeline | H4: GTM/Pixel Events
A5: MN_GV_LeadGen | B5: Lead Generation | C5: Geo 5km MN GV | Age 25-40 | Interest Parenting | Lookalike 1-3% | D5: Video testi PH 15-30s + Carousel campus + Lead form | E5: =0.38*'1. Input'!B15*0.25/6 -> 1.3458333e+08 | F5: LP_MN_GV | G5: Pipeline MN | H5: Lead, ViewContent, CompleteRegistration
A6: MN_Tinh_LeadGen | B6: Lead Generation | C6: Geo Cần Giuộc (Tây Ninh) + Rạch Giá (An Giang) | Age 25-40 | D6: Video testi + Ảnh campus local + Lead form | E6: =0.38*'1. Input'!B15*0.12/6 -> 64600000 | F6: LP_MN_Tinh | G6: Pipeline MN | H6: Lead, ViewContent
A7: TH_GV_LeadGen | B7: Lead Generation | C7: Geo 8km TH GV | Age 28-45 | Lookalike PH TH | D7: Video lớp học + Carousel chương trình + Messenger | E7: =0.38*'1. Input'!B15*0.18/6 -> 96900000 | F7: LP_TH_GV | G7: Pipeline TH | H7: Lead, ViewContent
A8: TH_BT_LeadGen | B8: Lead Generation | C8: Geo 8km Bình Tân | Age 28-45 | D8: Video + Lead form | E8: =0.38*'1. Input'!B15*0.15/6 -> 80750000 | F8: LP_TH_BT | G8: Pipeline TH | H8: Lead
A9: TH_Tinh_LeadGen | B9: Lead Generation | C9: Geo Thái Sơn + Mekong Xanh | D9: Video local + Lead form | E9: =0.38*'1. Input'!B15*0.08/6 -> 43066667 | F9: LP_TH_Tinh | G9: Pipeline TH | H9: Lead
A10: THCS_GV_Conv | B10: Conversions | C10: Geo TP.HCM | Age 30-50 | Custom: Web 30d | D10: Video HS+GV + Testi 60s + Webinar ads | E10: =0.38*'1. Input'!B15*0.2/6 -> 1.0766667e+08 | F10: LP_THCS_GV | G10: Pipeline THCS | H10: Lead, WebinarReg, ViewContent
A11: THPT_GV_Conv | B11: Conversions | C11: Geo TP.HCM + miền Nam | Age 35-55 | Lookalike PH THPT | D11: Video đầu ra + Học bổng + Testi | E11: =0.38*'1. Input'!B15*0.2/6 -> 1.0766667e+08 | F11: LP_THPT_GV | G11: Pipeline THPT | H11: Lead, ScholarshipClick
A12: Remarketing_All | B12: Conversions | C12: PageView 7-30d | Exclude enrolled | Dynamic by cấp | D12: Carousel campus + ưu đãi + Countdown | E12: =0.12*'1. Input'!B15*0.5/6 -> 85000000 | F12: Dynamic | G12: Retarget tag | H12: Purchase, Lead
A14: B. PIXEL + CAPI + GTM SETUP
A15: Bước | B15: Hành động | C15: Chi tiết | D15: Tool | E15: Timeline | F15: Trạng thái
A16: 1 | B16: Cài Meta Pixel qua GTM | C16: Tạo tag Meta Pixel Base Code trong GTM → fire on All Pages | D16: GTM + Meta | E16: Ngày 1 | F16: ☐
A17: 2 | B17: Tạo Custom Events trong GTM | C17: form_submit, click_call, click_zalo, webinar_register, scholarship_click | D17: GTM | E17: Ngày 1 | F17: ☐
A18: 3 | B18: Cài Conversion API (CAPI) | C18: Server-side tracking qua GHL webhook → Meta CAPI endpoint | D18: GHL + Meta | E18: Ngày 2 | F18: ☐
A19: 4 | B19: Tạo Custom Conversions | C19: 4 events: Form MN, Form TH, Form THCS/THPT, Tour Scheduled | D19: Meta Events Manager | E19: Ngày 2 | F19: ☐
A20: 5 | B20: Verify domain | C20: Xác minh domain truongvietanh.com trong Business Manager | D20: Meta Business Suite | E20: Ngày 1 | F20: ☐
A21: 6 | B21: Tạo Audience Library | C21: 8 saved audiences (4 cấp × 2 geo) + Lookalike 1%/3%/5% + Custom 7d/14d/30d/60d | D21: Meta Ads Manager | E21: Ngày 2 | F21: ☐
A22: 7 | B22: Sync GHL → Meta | C22: Upload enrolled parents list → Exclusion | Monthly refresh | D22: GHL + Meta | E22: Tuần 2 | F22: ☐
A23: 8 | B23: Setup Birch cho Meta | C23: Kết nối Meta Ads → Birch | Tạo rules CPL, budget pacing | D23: Birch | E23: Ngày 3 | F23: ☐
A25: C. CREATIVE RESOURCE PLAN – PHÂN BỔ ẢNH/VIDEO CHO META ADS
A26: Campaign | B26: Loại Creative | C26: Số lượng | D26: Format | E26: Nội dung | F26: Nguồn ảnh/video | G26: Refresh cycle | H26: A/B Test | I26: Ghi chú
A27: MN_GV_LeadGen | B27: Video testimonial PH | C27: 3 | D27: 9:16 Reel 15-30s | E27: PH chia sẻ: "Con tôi vui khi đến trường" | F27: Quay tại campus, PH thật | G27: 3 tuần | H27: Test 3 PH khác nhau | I27: Hook 3s quan trọng nhất
A28: MN_GV_LeadGen | B28: Carousel campus | C28: 2 | D28: 1:1 1080x1080 | E28: 6 slides: Sân chơi, Phòng học, Bếp ăn, Camera, GV, Hoạt động | F28: Chụp tại campus GV | G28: 4 tuần | H28: Test order slides | I28: Ảnh thật, không stock
A29: MN_GV_LeadGen | B29: Lead Form ad | C29: 2 | D29: 1:1 1080x1080 | E29: Image + text: "Đăng ký tour MN Việt Anh" | Form prefill | F29: Thiết kế Canva | G29: 2 tuần | H29: Test benefit vs offer | I29: Form ngắn: Tên+SĐT+Cấp
A30: TH_GV_LeadGen | B30: Video "Nền tảng lớp 1" | C30: 2 | D30: 9:16 Reel 30-60s | E30: Lớp học thực tế, HS đọc TA, GV tương tác | F30: Quay tại TH GV | G30: 4 tuần | H30: Test 30s vs 60s | I30: Show HS thật đang học
A31: TH_GV_LeadGen | B31: Carousel chương trình | C31: 2 | D31: 1:1 1080x1080 | E31: 6 slides: Chương trình, TA, STEM, Ngoại khóa, Sĩ số, Tour | F31: Chụp + thiết kế | G31: 4 tuần | H31: Test headline | I31: Infographic style
A32: TH_BT_LeadGen | B32: Image + text local | C32: 3 | D32: 1:1 1080x1080 | E32: Ảnh campus BT + text "Trường tư song ngữ Bình Tân" | F32: Chụp tại campus BT | G32: 3 tuần | H32: Test 3 images | I32: Local feel quan trọng
A33: THCS_GV_LeadGen | B33: Video testi HS + GV | C33: 3 | D33: 9:16 Reel 30-60s | E33: HS THCS chia sẻ + GV chủ nhiệm nói về lộ trình | F33: Quay tại THCS GV | G33: 3 tuần | H33: Test HS vs GV focus | I33: Emotional storytelling
A34: THCS_GV_Webinar | B34: Video invite webinar | C34: 2 | D34: 9:16 Reel 15s | E34: Teaser: "Hội thảo chuyển cấp 5→6 – Miễn phí" | F34: Thiết kế motion | G34: 2 tuần | H34: Test countdown vs benefit | I34: Urgency + value
A35: THPT_GV_LeadGen | B35: Video "Lộ trình THPT" | C35: 3 | D35: 9:16 Reel 30-60s | E35: Alumni ĐH chia sẻ + BGH nói về đầu ra | F35: Quay tại THPT + ĐH | G35: 3 tuần | H35: Test alumni vs BGH | I35: Data-driven: % ĐH top
A36: THPT_HocBong | B36: Image học bổng | C36: 3 | D36: 1:1 1080x1080 | E36: "Học bổng lên đến 100% – Deadline [ngày]" | Bold design | F36: Thiết kế Canva/AI | G36: 2 tuần | H36: Test % vs giá trị tiền | I36: Deadline rõ ràng
A37: Retarget_7d_Hot | B37: Dynamic creative | C37: 4 | D37: 1:1 multi-format | E37: Testimonial + ưu đãi + countdown + campus | F37: Mix từ kho | G37: 2 tuần | H37: Auto by Meta | I37: DCO cho remarketing
A38: Brand_Awareness | B38: Brand video 15s | C38: 2 | D38: 16:9 + 9:16 | E38: Montage: 8 campus, HS vui, USP overlay, logo end | F38: Quay + edit pro | G38: 6 tuần | H38: Test 15s vs 30s | I38: CPM optimize
A41: D. DAILY OPERATIONS – META ADS HÀNG NGÀY
A42: Thời gian | B42: Công việc | C42: Chi tiết | D42: Tool | E42: KPI check | F42: Action nếu lệch | G42: Ai làm
A43: 8:00 | B43: Check delivery & spend | C43: Ads Manager → Campaign overview → Check pacing 24h | D43: Meta Ads Manager / Birch | E43: Spend vs daily target ±10% | F43: Overspend → lower budget | Underspend → check ad set | G43: Performance
A44: 8:15 | B44: Check CPL by campaign | C44: Filter last 3 days → Sort by CPL → Identify top/bottom | D44: Meta Ads Manager | E44: CPL < target kênh | F44: CPL > 150% target → pause ad set → review creative | G44: Performance
A45: 8:30 | B45: Check ad set learning phase | C45: Review ad sets: Learning, Active, Learning Limited | D45: Meta Ads Manager | E45: 50 conversions / 7 ngày | F45: Learning Limited → consolidate ad sets hoặc tăng budget | G45: Performance
A46: 8:45 | B46: Review ad rejections | C46: Check ad review status → Fix rejected ads | D46: Meta Ads Manager | E46: No rejected ads | F46: Edit ad → resubmit → nếu lặp lại → contact support | G46: Performance
A47: 9:00 | B47: Check Frequency & CTR | C47: Campaign level → Frequency col + CTR | D47: Meta Ads Manager | E47: Freq < 3, CTR > 1% | F47: Freq > 3 → refresh creative | CTR < 0.8% → new copy/image | G47: Performance
A48: 14:00 | B48: Audience overlap check | C48: Meta → Audience overlap tool → Check cross-campaign | D48: Meta Audience Tool | E48: Overlap < 30% | F48: > 30% → exclude hoặc merge audiences | G48: Performance
A49: 15:00 | B49: Scale decision (daily) | C49: Top 3 ad sets by CPL + quality → increase 15-20% | D49: Meta Ads Manager | E49: CPL < target + Q.Rate > 45% | F49: Scale immediately, monitor 24h | G49: Performance
A50: 17:00 | B50: Log daily metrics | C50: Ghi spend, leads, CPL, CTR vào KPI tracker | D50: Excel/Sheets | E50: - | F50: - | G50: Performance
A53: E. AUDIENCE LIBRARY – DANH SÁCH AUDIENCE CHI TIẾT
A54: Audience Name | B54: Type | C54: Targeting chi tiết | D54: Size est. | E54: Dùng cho Campaign | F54: Refresh | G54: Ghi chú
A55: Prospecting_MN_GV | B55: Saved | C55: Geo: Gò Vấp 5km | Age 25-40 | Female | Interest: Parenting, Preschool, Child development | D55: 200K-400K | E55: MN_GV_LeadGen | F55: Đầu mùa | G55: Core audience MN
A56: Prospecting_TH_GV | B56: Saved | C56: Geo: Gò Vấp 8km | Age 28-45 | Parents | Interest: Education, Primary school | D56: 300K-500K | E56: TH_GV_LeadGen | F56: Đầu mùa | G56: Core audience TH
A57: Prospecting_TH_BT | B57: Saved | C57: Geo: Bình Tân 8km | Age 28-45 | Parents | D57: 250K-400K | E57: TH_BT_LeadGen | F57: Đầu mùa | G57: Bình Tân local
A58: Prospecting_THCS | B58: Saved | C58: Geo: TP.HCM | Age 32-48 | Interest: Secondary education, Exam prep | D58: 500K-800K | E58: THCS_GV_LeadGen | F58: Đầu mùa | G58: Broader for THCS
A59: Prospecting_THPT | B59: Saved | C59: Geo: TP.HCM + miền Nam | Age 36-55 | Interest: High school, Scholarship, University | D59: 600K-1M | E59: THPT_GV_LeadGen | F59: Đầu mùa | G59: Broadest for THPT
A60: LAL_1%_Enrolled | B60: Lookalike | C60: Source: Enrolled parents list | 1% lookalike VN | D60: 700K-1M | E60: All Lead Gen | F60: Hàng tháng | G60: Best quality LAL
A61: LAL_3%_Leads | B61: Lookalike | C61: Source: All qualified leads | 3% lookalike VN | D61: 2M-3M | E61: Scale campaigns | F61: Hàng tháng | G61: Volume LAL
A62: Custom_Web_7d | B62: Custom | C62: Website visitors last 7 days | All pages | D62: 5K-20K | E62: Retarget_7d_Hot | F62: Auto | G62: Hottest remarketing
A63: Custom_Web_30d | B63: Custom | C63: Website visitors last 30 days | D63: 20K-50K | E63: Retarget_21d_Warm | F63: Auto | G63: Warm remarketing
A64: Custom_Fee_Page | B64: Custom | C64: Visitors to /hoc-phi pages | Last 14 days | D64: 2K-8K | E64: Retarget_7d_Hot | F64: Auto | G64: Highest intent
A65: Custom_Video_50 | B65: Custom | C65: Video viewers 50%+ | Last 30 days | D65: 10K-30K | E65: Retarget_21d_Warm | F65: Auto | G65: Engaged viewers
A66: Exclusion_Enrolled | B66: Custom | C66: Upload enrolled parents list | D66: 1K-5K | E66: ALL campaigns | F66: Hàng tháng | G66: MUST exclude always
A69: CHI TIẾT CREATIVE QUẢNG CÁO (Detailed Ad Creative Specs)
A71: Tên Ad | B71: Campaign | C71: Format | D71: Tiêu Đề (25 ký tự) | E71: Văn Bản Chính (125 ký tự) | F71: Mô Tả | G71: CTA | H71: Kích Thước Hình | I71: Đối Tượng | J71: Vị Trí | K71: Landing Page | L71: Variant | M71: CTR % Kỳ Vọng | N71: Budget/Ngày (VND)
A72: MN_Carousel_01 | B72: Q1: MN Awareness | C72: Carousel | D72: Mầm Non Chất Lượng | E72: Khám phá mầm non tuyệt vời với giáo viên chuyên nghiệp, môi trường an toàn và chương trình song ngữ. | F72: Học tập vui vẻ, phát triển toàn diện | G72: Xem Chi Tiết | H72: 1200x628px | I72: P: 25-45 tuổi, con 3-5 | J72: Feed, Stories | K72: https://khoaviet.edu.vn/mn | L72: A (Hero) | M72: 2.8 | N72: 300000
A73: MN_Video_01 | B73: Q1: MN Awareness | C73: Video | D73: Ngày Hạnh Phúc Tại MN | E73: Video 30s giới thiệu hoạt động mầm non: chơi, học, vui cùng bạn. Kết thúc: "Ghi danh ngay!" | F73: 30s video, 1920x1080 | G73: Ghi Danh Ngay | H73: 1920x1080px | I73: P: 25-45 tuổi, con 3-5 | J73: Feed, Reels | K73: https://khoaviet.edu.vn/mn-video | L73: A | M73: 3.2 | N73: 350000
A74: TH_Image_01 | B74: Q2: TH Enrollment | C74: Image | D74: Tiểu Học Tuyệt Vời | E74: Con bạn sẽ học với giáo viên giỏi, có cơ sở vật chất hiện đại, chương trình quốc tế. Ghi danh lớp 1 2026! | F74: Chương trình đa năng, cơ sở hiện đại | G74: Đăng Ký Tư Vấn | H74: 1200x628px | I74: P: 30-50 tuổi, con 6-8 | J74: Feed, Stories | K74: https://khoaviet.edu.vn/th-lop1 | L74: B (Social Proof) | M74: 2.5 | N74: 280000
A75: TH_Carousel_01 | B75: Q2: TH Enrollment | C75: Carousel | D75: Lớp 1 Năm 2026 | E75: Slides: (1) Con nhà bạn học gì? (2) Cơ sở vật chất (3) Giáo viên tuyệt vời (4) Học bổng | F75: Tuyển sinh lớp 1 2026 - Open Day 20/4 | G75: Dự Open Day | H75: 1200x628px | I75: P: 30-50, con 6-8 | J75: Feed, Stories | K75: https://khoaviet.edu.vn/openday | L75: A | M75: 3.1 | N75: 320000
A76: THCS_Image_01 | B76: Q2: THCS Enrollment | C76: Image | D76: Cấp 1 Chất Lượng Cao | E76: Lớp 7 2026: Chương trình hiện đại, có học sinh giỏi, cơ sở phòng thí nghiệm đầy đủ. | F76: Chương trình chuẩn quốc tế, giáo viên chuyên | G76: Tư Vấn Miễn Phí | H76: 1200x628px | I76: P: 35-55, con 10-12 | J76: Feed, Stories | K76: https://khoaviet.edu.vn/thcs | L76: A | M76: 2.3 | N76: 260000
A77: THCS_Video_01 | B77: Q2: THCS Enrollment | C77: Video | D77: THCS Xứng Đáng | E77: 30s video: học sinh làm thí nghiệm, thảo luận, dự hội thi. "Con yêu trường từ ngày đầu" | F77: Video testimonial học sinh, 30s | G77: Xem Video | H77: 1920x1080px | I77: P: 35-55, con 10-12 | J77: Feed, Reels | K77: https://khoaviet.edu.vn/thcs-video | L77: B | M77: 2.9 | N77: 300000
A78: THPT_Carousel_01 | B78: Q2: THPT Enrollment | C78: Carousel | D78: Lớp 10 2026 Tuyệt Vời | E78: Slides: (1) Lớp 10 là bước ngoặt (2) Giáo viên đầu ngành (3) Học bổng & hỗ trợ (4) Cơ sở xịn | F78: Lớp 10 2026 - Ghi danh ngay! | G78: Ghi Danh | H78: 1200x628px | I78: P: 40-60, con 14-16 | J78: Feed, Stories | K78: https://khoaviet.edu.vn/lop10 | L78: A | M78: 2.7 | N78: 310000
A79: THPT_Video_01 | B79: Q2: THPT Enrollment | C79: Video | D79: Lớp 10 Xứng Đáng Chọn | E79: 30s: học sinh nói về học tập, bạn bè, giáo viên. "Quyết định tốt nhất của tôi" | F79: Testimonial video cử nhân, 30s | G79: Liên Hệ | H79: 1920x1080px | I79: P: 40-60, con 14-16 | J79: Feed, Reels | K79: https://khoaviet.edu.vn/thpt-video | L79: B | M79: 2.8 | N79: 320000
A80: OpenDay_Carousel_01 | B80: Q1: Launch | C80: Carousel | D80: Mở Cửa Ngày 20/4 | E80: Slides: (1) Lớp mầm non (2) Lớp tiểu học (3) Lớp THCS (4) Lớp THPT + Đặt vé | F80: Open Day 20/4 - Miễn phí vé - Có quà tặng | G80: Đặt Vé Ngay | H80: 1200x628px | I80: All: 25-60 | J80: Feed, Stories | K80: https://khoaviet.edu.vn/openday | L80: A | M80: 4.2 | N80: 400000
A81: Scholarship_Image_01 | B81: Q3: Consideration | C81: Image | D81: Học Bổng Đến 20 Triệu | E81: Năm 2026, Trường Việt Anh cấp học bổng cho 50 học sinh xuất sắc. Bạn có tư cách không? | F81: Học bổng, hỗ trợ tài chính | G81: Xem Điều Kiện | H81: 1200x628px | I81: P: 35-60, con >6 | J81: Feed | K81: https://khoaviet.edu.vn/scholarship | L81: A | M81: 2.1 | N81: 220000
A82: Teachers_Image_01 | B82: Q1: Brand Awareness | C82: Image | D82: Đội Ngũ Giáo Viên Tuyệt Vời | E82: Hơn 80 giáo viên có trình độ cao, kinh nghiệm 10+ năm. Hết lòng vì con em. | F82: Giáo viên giỏi, yêu thương, trách nhiệm | G82: Tìm Hiểu | H82: 1200x628px | I82: All: 25-60 | J82: Feed, Stories | K82: https://khoaviet.edu.vn/teachers | L82: A | M82: 2.4 | N82: 240000
A83: Facilities_Carousel_01 | B83: Q1: Brand Awareness | C83: Carousel | D83: Cơ Sở Vật Chất Hiện Đại | E83: Slides: (1) Phòng học xịn (2) Sân chơi an toàn (3) Phòng máy tính (4) Thư viện | F83: 6 cơ sở, 100% an toàn, hiện đại | G83: Xem Tour | H83: 1200x628px | I83: All: 25-60 | J83: Feed, Stories | K83: https://khoaviet.edu.vn/facilities | L83: A | M83: 2.6 | N83: 260000
... A90: Promo_Limited_01 | B90: Q1: Launch | C90: Image | D90: Ưu Đãi Sớm Ghi Danh T4 | E90: Ghi danh từ 1-15/4: Giảm 10% học phí tháng 4. Số lượng hạn chế! | F90: Khuyến mãi sớm ghi danh, hạn chế | G90: Ghi Danh Ngay | H90: 1200x628px | I90: All: 25-60 | J90: Feed, Stories | K90: https://khoaviet.edu.vn/promo | L90: A | M90: 3.8 | N90: 350000
A93: B. CAMPAIGNS THEO PHỄU — CHI TIẾT TỪNG AD SET + AD
A95: Campaign Name | B95: Objective | C95: Ad Set Name | D95: Audience (Include) | E95: Audience (Exclude) | F95: Age | G95: Location | H95: Budget/day | I95: Ad Name | J95: Format | K95: Headline | L95: Primary Text | M95: CTA | N95: Landing Page URL | O95: Pixel Events | P95: Remark
A96: MN_Awareness_T4-T9_TopFunnel | B96: Brand Awareness | C96: LAL_Enrolled_1% | D96: LAL_Enrolled 1% | GV+BT+TS area | E96: FormSubmitted, Enrolled | F96: 25-40 | G96: HCM - District 1,3,7 | H96: 200000 | I96: MN_Carousel_5Reasons | J96: Carousel | K96: 5 lý do chọn Việt Anh | L96: Lợi ích tối ưu cho con em. Môi trường song ngữ, tự do sáng tạo, cơ sở vật chất hiện đại. | M96: Tìm hiểu thêm | N96: forms.truongvietanh.com/tuyen-sinh-mam-non | O96: ViewContent | P96: Top funnel carousel
A97: MN_Awareness_T4-T9_TopFunnel | B97: Brand Awareness | C97: LAL_Enrolled_1% | D97: LAL_Enrolled 1% | GV+BT+TS area | E97: FormSubmitted, Enrolled | F97: 25-40 | G97: HCM - District 1,3,7 | H97: 200000 | I97: MN_Video_TourSchool | J97: Video | K97: Ngôi trường nào cho con? | L97: Chuyến tham quan Việt Anh - nơi con yêu thích | M97: Đăng ký tư vấn | N97: forms.truongvietanh.com/tuyen-sinh-mam-non | O97: ViewContent | P97: 30s video hook
A98: MN_Awareness_T4-T9_TopFunnel | B98: Brand Awareness | C98: LAL_Enrolled_1% | D98: LAL_Enrolled 1% | GV+BT+TS area | E98: FormSubmitted, Enrolled | F98: 25-40 | G98: HCM - District 1,3,7 | H98: 200000 | I98: MN_Reels_BTS | J98: Reels | K98: Behind the scenes Mầm Non | L98: Ngày hôm nay ở Việt Anh... | M98: Xem thêm | N98: forms.truongvietanh.com/tuyen-sinh-mam-non | O98: ViewContent | P98: 15s trending music
A99: MN_Awareness_T4-T9_TopFunnel | B99: Brand Awareness | C99: Interest_Parents_25-40 | D99: Parents with 2-5yo kids | Parenting interest | E99: FormSubmitted, Enrolled | F99: 25-40 | G99: HCM | H99: 150000 | I99: MN_Carousel_Campus | J99: Carousel | K99: Cơ sở vật chất tuyệt vời | L99: Tham tour và trải nghiệm | M99: Tìm hiểu thêm | N99: forms.truongvietanh.com/tuyen-sinh-mam-non | O99: ViewContent | P99: Interest targeting
A100: MN_Awareness_T4-T9_TopFunnel | B100: Brand Awareness | C100: Interest_Parents_25-40 | D100: Parents with 2-5yo kids | Parenting interest | E100: FormSubmitted, Enrolled | F100: 25-40 | G100: HCM | H100: 150000 | I100: MN_Video_Curriculum | J100: Video | K100: Chương trình học Mầm Non | L100: Tương tác, chơi, học - cân bằng hoàn hảo | M100: Đăng ký tư vấn | N100: forms.truongvietanh.com/tuyen-sinh-mam-non | O100: ViewContent | P100: 30s curriculum overview
A101: MN_Awareness_T4-T9_TopFunnel | B101: Brand Awareness | C101: Interest_Parents_25-40 | D101: Parents with 2-5yo kids | Parenting interest | E101: FormSubmitted, Enrolled | F101: 25-40 | G101: HCM | H101: 150000 | I101: MN_Reels_Activities | J101: Reels | K101: Hoạt động tại lớp | L101: Trẻ vui vẻ, tự tin | M101: Xem thêm | N101: forms.truongvietanh.com/tuyen-sinh-mam-non | O101: ViewContent | P101: 15s activities
A102: MN_Awareness_T4-T9_TopFunnel | B102: Brand Awareness | C102: Custom_MN_PageVisitors_Exclude_FormComplete | D102: Website visitors MN pages | E102: FormSubmitted | F102: 25-40 | G102: HCM | H102: 100000 | I102: MN_Testimonial_PH | J102: Video | K102: Phụ huynh nói gì? | L102: Nghe từ bố mẹ như mình... | M102: Xem lời khen | N102: forms.truongvietanh.com/tuyen-sinh-mam-non/phu-huynh-noi-gi | O102: ViewContent, Lead | P102: Retargeting to testimonial
A103: MN_Awareness_T4-T9_TopFunnel | B103: Brand Awareness | C103: Custom_MN_PageVisitors_Exclude_FormComplete | D103: Website visitors MN pages | E103: FormSubmitted | F103: 25-40 | G103: HCM | H103: 100000 | I103: MN_Carousel_Testimonials | J103: Carousel | K103: Niềm tin từ phụ huynh | L103: 5 câu chuyện thành công | M103: Tìm hiểu thêm | N103: forms.truongvietanh.com/tuyen-sinh-mam-non/phu-huynh-noi-gi | O103: ViewContent, Lead | P103: Testimonial carousel
A104: MN_LeadGen_T4-T9_MidFunnel | B104: Lead Generation | C104: MN_Testimonial_Viewers_Exclude_FormComplete | D104: Viewed testimonial pages | E104: FormSubmitted | F104: 25-40 | G104: HCM | H104: 120000 | I104: MN_Program_Details | J104: Carousel | K104: Chương trình chi tiết | L104: Từ Trang 3 sang Trang 4 | M104: Xem chương trình | N104: forms.truongvietanh.com/tuyen-sinh-mam-non/chuong-trinh | O104: ViewContent, Lead | P104: Mid-funnel promotion
A105: MN_LeadGen_T4-T9_MidFunnel | B105: Lead Generation | C105: MN_Program_Viewers_Exclude_FormComplete | D105: Viewed program page | E105: FormSubmitted | F105: 25-40 | G105: HCM | H105: 120000 | I105: MN_Tuition_Info | J105: Video | K105: Học phí minh bạch | L105: Không bất ngờ về chi phí | M105: Xem học phí | N105: forms.truongvietanh.com/tuyen-sinh-mam-non/hoc-phi | O105: ViewContent, Lead | P105: Tuition page promotion
A106: MN_LeadGen_T4-T9_MidFunnel | B106: Lead Generation | C106: MN_Tuition_Viewers_Exclude_FormComplete | D106: Viewed tuition page | E106: FormSubmitted | F106: 25-40 | G106: HCM | H106: 120000 | I106: MN_CTA_FormVariantB | J106: Video | K106: Hạn chế chỗ, Đăng ký ngay | L106: Chỉ còn 3 chỗ trống tháng này | M106: Đăng ký ngay | N106: forms.truongvietanh.com/tuyen-sinh-mam-non/form-variant-b | O106: Lead, CompleteRegistration | P106: Urgency variant
... A148: All_Levels_Community_Engagement | B148: Engagement | C148: All_Parents_Community | D148: Parents all children ages | E148: ViewContent | F148: 25-55 | G148: HCM | H148: 60000 | I148: Community_Activity_Showcase | J148: Video | K148: Cộng đồng Việt Anh - Kết nối | L148: Sự kiện, hoạt động hàng tháng | M148: Theo dõi | N148: forms.truongvietanh.com/ | O148: ViewContent | P148: Community engagement

Sheet 7. TikTok Ads Chi Tiết
A1: KẾ HOẠCH TIKTOK ADS – 100 VIDEO TESTIMONIAL + CẤU TRÚC + GTM
A3: A. CẤU TRÚC CAMPAIGN TIKTOK
A4: Campaign | B4: Objective | C4: Targeting | D4: Creative (từ kho 100 video) | E4: Budget/tháng | F4: KPI | G4: GTM Events | H4: Ghi chú
A5: Spark_Testi_MN | B5: Traffic/Lead | C5: Age 25-45 | Parenting | Geo HCM+Tỉnh | D5: Boost organic testi PH MN | Hook 3s | 15-30s | E5: =0.1*'1. Input'!B15*0.3/6 -> 42500000 | F5: CPV ≤ 2K | Engage ≥ 5% | G5: ViewContent, ClickLink | H5: Dùng 100 video có sẵn
A6: Spark_Testi_THPT | B6: Traffic/Lead | C6: Age 30-55 | Education | Geo HCM | D6: Boost testi HS THPT + GV | Hook 3s | E6: =0.1*'1. Input'!B15*0.25/6 -> 35416667 | F6: CPV ≤ 2.5K | Lead | G6: ViewContent, Lead | H6: Social proof
A7: InFeed_CampusTour | B7: Traffic | C7: Age 25-45 | Geo radius 10km | D7: Virtual tour video | Day-in-the-life | CTA tour | E7: =0.1*'1. Input'!B15*0.2/6 -> 28333333 | F7: CPL ≤ 90K | CTR ≥ 1.5% | G7: ViewContent, ClickLink | H7: Quay sẵn hoặc UGC
A8: LeadGen_Form | B8: Lead Gen | C8: Age 28-45 | School selection | Lookalike | D8: Video HS + Instant form: Tên+SĐT+Cấp | E8: =0.1*'1. Input'!B15*0.2/6 -> 28333333 | F8: CPL ≤ 80K | Form ≥ 3% | G8: Lead, FormSubmit | H8: Form → GHL auto
A9: TopView_Brand | B9: Reach | C9: Broad 25-50 HCM | 1 ngày | D9: Video 15s brand hệ thống | 8 cơ sở | E9: =0.1*'1. Input'!B15*0.05/6 -> 7083333.3 | F9: Reach ≥ 2M | CPM ≤ 50K | G9: Impression | H9: Chỉ 2-3 ngày peak
A11: B. TIKTOK PIXEL + GTM SETUP
A12: Bước | B12: Hành động | C12: Chi tiết | D12: Tool | E12: Timeline | F12: Trạng thái
A13: 1 | B13: Tạo TikTok Pixel | C13: Tạo pixel trong TikTok Ads Manager | D13: TikTok Ads | E13: Ngày 1 | F13: ☐
A14: 2 | B14: Cài qua GTM | C14: Tạo Custom HTML tag với TikTok Pixel base code → All Pages | D14: GTM | E14: Ngày 1 | F14: ☐
A15: 3 | B15: Tạo Event tags | C15: ViewContent (LP view), ClickButton (CTA), SubmitForm, CompleteRegistration | D15: GTM | E15: Ngày 1 | F15: ☐
A16: 4 | B16: Test với TikTok Pixel Helper | C16: Verify events firing đúng trên mỗi LP | D16: Chrome Extension | E16: Ngày 1 | F16: ☐
A17: 5 | B17: Tạo Custom Audiences | C17: Website visitors 7d/14d/30d + Video viewers 50%+ + Form submitters | D17: TikTok Ads | E17: Ngày 2 | F17: ☐
A18: 6 | B18: Tạo Lookalike | C18: Từ enrolled parents list + Form submitters | D18: TikTok Ads | E18: Tuần 2 | F18: ☐
A19: 7 | B19: Setup Birch cho TikTok | C19: Kết nối TikTok → Birch | Budget pacing rules | D19: Birch | E19: Ngày 3 | F19: ☐
A22: CHI TIẾT QUẢNG CÁO TIKTOK (Detailed TikTok Ad Specs)
A24: Tên Ad | B24: Mục Tiêu | C24: Format | D24: Thời Lượng (s) | E24: Hook (3s đầu) | F24: Script Outline | G24: Hashtag | H24: Nhạc/Sound | I24: Đối Tượng (Age) | J24: Sở Thích | K24: Vị Trí | L24: Budget/Ngày (VND) | M24: KPI Kỳ Vọng
A25: TK_MN_Challenge_01 | B25: Engagement | C25: In-Feed | D25: 15 | E25: "Thử thách: Con bạn lên sân trường!" | F25: Trẻ chơi, cười, vui vẻ tại trường. Hashtag challenge. | G25: #MầmNonTrườngViệtAnh #ConYêuTrường | H25: Nhạc trending vui nhộn | I25: 16-40 | J25: Phụ huynh, Giáo viên | K25: HCMC | L25: 250000 | M25: Views 500K+, Engagement 5%
A26: TK_TH_DayInLife_01 | B26: Awareness | C26: In-Feed | D26: 30 | E26: "Một ngày học tiểu học siêu vui!" | F26: Vlog 30s: sáng: lớp học, giảng dạy, trưa: ăn cơm, chơi, chiều: ngoại khóa | G26: #MộtNgàyTạiTrườngViệtAnh #TiểuHọcTuyệtVời | H26: Nhạc inspirational nhẹ | I26: 20-50 | J26: Phụ huynh, Mẹ | K26: HCMC, Bình Dương | L26: 280000 | M26: Views 800K+, Save 3%
A27: TK_THCS_Experiment_01 | B27: Engagement | C27: In-Feed | D27: 20 | E27: "Thí nghiệm quá bất ngờ!" | F27: STEM thí nghiệm hóa học, vật lý. Kết thúc bất ngờ. | G27: #ThíNghiệmTHCS #KhoaPháoHóa | H27: Nhạc suspense trending | I27: 25-50 | J27: Giáo viên, Phụ huynh | K27: HCMC | L27: 270000 | M27: Views 1M+, Comments 2%
A28: TK_THPT_Success_01 | B28: Awareness | C28: In-Feed | D28: 25 | E28: "Lớp 10 đã giúp tôi thay đổi" | F28: Testimonial: học sinh kể chuyện thay đổi + kết quả học tập. | G28: #Lớp10TrườngViệtAnh #SuccessStory | H28: Nhạc motivational | I28: 30-60 | J28: Phụ huynh, Học sinh cũ | K28: HCMC | L28: 290000 | M28: Views 600K+, Save 2.5%
A29: TK_OpenDay_Countdown_01 | B29: Conversion | C29: In-Feed | D29: 15 | E29: "3 NGÀY NỮA MỚI OPEN DAY!" | F29: Countdown hype: show các hoạt động, cơ sở sẽ thấy tại open day. | G29: #OpenDay20Tháng4 #ĐợiChưa | H29: Nhạc hype trending | I29: 20-50 | J29: Phụ huynh | K29: HCMC | L29: 320000 | M29: Saves 4%, Conversions 1.5%
A30: TK_Scholarship_Promo_01 | B30: Conversion | C30: In-Feed | D30: 18 | E30: "Học bổng 20 TRIỆU CHỜ BẠN!" | F30: Giới thiệu học bổng, cách apply, deadline sắp tới. | G30: #HọcBổng #CơHộiVàng | H30: Nhạc excited upbeat | I30: 25-50 | J30: Phụ huynh, Học sinh | K30: HCMC | L30: 260000 | M30: Clicks 2.5%, Conversions 1.2%
A31: TK_Teachers_Spotlight_01 | B31: Awareness | C31: In-Feed | D31: 20 | E31: "Nghe các cô giáo nói!" | F31: Giáo viên tự giới thiệu, vì sao yêu thích công việc tại trường. | G31: #GiáoViênTrườngViệtAnh #LaThầnTượng | H31: Nhạc warm & friendly | I31: 25-60 | J31: Phụ huynh | K31: HCMC | L31: 240000 | M31: Views 700K+, Engagement 4%
A32: TK_Facilities_Tour_01 | B32: Awareness | C32: In-Feed | D32: 30 | E32: "Tour cơ sở 2 phút!" | F32: Quick tour: phòng học, sân chơi, thư viện, phòng máy tính. | G32: #TourCơSở #CơSởXịn | H32: Nhạc exploration upbeat | I32: 20-50 | J32: Phụ huynh | K32: HCMC | L32: 250000 | M32: Views 900K+, Saves 2.8%
A33: TK_Student_Life_01 | B33: Engagement | C33: In-Feed | D33: 25 | E33: "Sự thật về học sinh Việt Anh" | F33: Funny/relatable: học sinh kể lại sự thật vui vẻ về trường. | G33: #ĐứcSinhhọcViệtAnh #Sựthật | H33: Nhạc funny trending | I33: 15-40 | J33: Học sinh cũ, bạn bè | K33: HCMC, các tỉnh | L33: 200000 | M33: Views 1.2M+, Comments 3%
A34: TK_Bilingual_Journey_01 | B34: Awareness | C34: In-Feed | D34: 20 | E34: "Hành trình tiếng Anh của tôi" | F34: Học sinh kể lại sự tiến bộ từ lớp mầm non đến cấp ba. | G34: #HànhTrìnhTiếngAnh #NgoạiNgữ | H34: Nhạc inspirational | I34: 25-50 | J34: Phụ huynh | K34: HCMC | L34: 270000 | M34: Views 700K+, Saves 3%
A35: TK_Activities_Montage_01 | B35: Engagement | C35: In-Feed | D35: 15 | E35: "Con yêu trường vì..." | F35: Montage nhanh: thể thao, nghệ thuật, khám phá. 1 activity/1 giây. | G35: #HoạtĐộngNgoàiKhóa #ConYêuTrường | H35: Nhạc energetic upbeat | I35: 20-55 | J35: Phụ huynh, Giáo viên | K35: HCMC | L35: 260000 | M35: Views 1.1M+, Engagement 5%
A36: TK_Safety_Trust_01 | B36: Awareness | C36: In-Feed | D36: 20 | E36: "An toàn 100% - Bố mẹ yên tâm" | F36: Show camera system, bảo vệ, hệ thống báo động. | G36: #AnToàn #BốMẹYênTâm | H36: Nhạc calm reassuring | I36: 30-60 | J36: Phụ huynh | K36: HCMC | L36: 220000 | M36: Views 500K+, Save 2%
... A39: TK_Community_Family_01 | B39: Awareness | C39: In-Feed | D39: 25 | E39: "Cộng đồng nơi bạn là gia đình" | F39: Montage: học sinh chơi cùng, giáo viên chăm sóc, sự gắn kết. | G39: #CộngĐồngGiáoD #GiàĐìnhTrườngHọc | H39: Nhạc warm emotional | I39: 20-55 | J39: Phụ huynh | K39: HCMC | L39: 250000 | M39: Views 800K+, Saves 3.2%
A42: B. TIKTOK ADS CAMPAIGNS THEO PHỄU + CREATIVE SCRIPTS
A44: Campaign Name | B44: Objective | C44: Audience Targeting | D44: Ad Type | E44: Creative Hook (0-3s) | F44: Creative Body (3-18s) | G44: Creative CTA (18-30s) | H44: Budget/day | I44: KPI Target | J44: Landing Page URL | K44: GTM Events | L44: Remark
A45: Spark_Testimonial_MN | B45: Lead Generation | C45: Age 25-40 | Parenting interest | Parents 0-5yo | D45: Spark Ad (boost organic) | E45: "Mình lo gì khi con đi mầm non?" Phụ huynh Việt Anh chia sẻ... | F45: Video PH kể về con, tiếp cận giáo dục, sự phát triển sau 1 năm tại Việt Anh | G45: Xem thêm testimonial tại Việt Anh. Tham tour miễn phí hôm nay! | H45: 80000 | I45: CPV ≤ 3K, Engage ≥ 8% | J45: forms.truongvietanh.com/tuyen-sinh-mam-non/phu-huynh-noi-gi | K45: ViewContent, ClickLink | L45: Organic boost - testimonial
A46: Spark_Tour_MN | B46: Lead Generation | C46: Age 25-40 | New parents | HCM geo | D46: Spark Ad (boost organic) | E46: "Cơ sở mầm non như thế nào là tốt?" Tour nhanh Việt Anh... | F46: Video 15s tour các phòng học, sân chơi, bếp ăn, thư viện | G46: Đặt lịch tham tour hôm nay - chỗ giới hạn! Zalo hoặc form đăng ký | H46: 70000 | I46: CPV ≤ 2.5K, Save ≥ 10% | J46: forms.truongvietanh.com/tuyen-sinh-mam-non/dat-lich-tham-quan | K46: ViewContent, ClickLink, AddToCart | L46: Campus tour spark
A47: Spark_ActivitiesMN | B47: Engagement | C47: Age 25-40 | Parents 2-5yo | Lifestyle interest | D47: Spark Ad (boost organic) | E47: "Cô giáo dạy gì cho con?" Xem hoạt động thường ngày... | F47: Montage 20s: vẽ, chơi, học tiếng anh, ăn cơm, ngủ trưa, chơi ngoài trời | G47: Theo dõi Việt Anh để xem thêm videos. Like và chia sẻ cho bạn bè! | H47: 50000 | I47: Engagement ≥ 12%, CPV ≤ 2K | J47: forms.truongvietanh.com/tuyen-sinh-mam-non | K47: ViewContent, ClickLink, Like | L47: Activities showcase
A48: Spark_AlumniSuccess_TH | B48: Lead Generation | C48: Age 25-45 | Parents 5-8yo | Education interest | D48: Spark Ad (boost organic) | E48: "Cô con học Tiểu Học Việt Anh rồi" - Phụ huynh chia sẻ... | F48: Alumni success stories: vào lớp 6 chuyên, SAT score cao, tự tin kỹ năng mềm | G48: Tham tour TH hoặc tư vấn chi tiết. Link trong bio | H48: 100000 | I48: CPV ≤ 3K, Save ≥ 12% | J48: forms.truongvietanh.com/tuyen-sinh-tieu-hoc | K48: ViewContent, ClickLink, Lead | L48: Alumni success TH
A49: Spark_Grade1Prep_TH | B49: Lead Generation | C49: Age 25-40 | Parents preparing for grade 1 | D49: Spark Ad (boost organic) | E49: "Chuẩn bị con vào lớp 1 - bắt đầu từ đâu?" Chuyên gia Việt Anh... | F49: Tips video: kỹ năng cơ bản, môi trường học tập, chương trình chuẩn bị | G49: Tìm hiểu chương trình chuẩn bị lớp 1 tại Việt Anh. Đặt lịch ngay! | H49: 85000 | I49: CPV ≤ 3.2K, Engage ≥ 9% | J49: forms.truongvietanh.com/tuyen-sinh-tieu-hoc/chuong-trinh | K49: ViewContent, ClickLink, Lead | L49: Grade 1 prep TH
A50: Spark_ExamPrep_THCS | B50: Lead Generation | C50: Age 30-50 | Parents 11-12yo | Exam preparation interest | D50: Spark Ad (boost organic) | E50: "Chuẩn bị thi lớp 6 - Kinh nghiệm từ trường THCS hàng đầu" | F50: Exam tips, success rate stats, student testimonials, study methods | G50: Tham tour THCS + tư vấn chuẩn bị thi. Liên hệ qua Zalo hoặc form | H50: 120000 | I50: CPV ≤ 3.5K, Save ≥ 15% | J50: forms.truongvietanh.com/tuyen-sinh-thcs | K50: ViewContent, ClickLink, Lead | L50: Exam prep THCS
A51: Spark_UniversitySAT_THPT | B51: Lead Generation | C51: Age 35-55 | Parents 14-17yo | Career + education interest | D51: Spark Ad (boost organic) | E51: "Con muốn vào ĐH nước ngoài? Bắt đầu từ THPT Việt Anh" | F51: SAT prep, IELTS classes, university admission success stories, alumni at top universities | G51: Tư vấn lộ trình SAT/IELTS + Đại học. Tham tour THPT Việt Anh | H51: 150000 | I51: CPV ≤ 4K, Save ≥ 12% | J51: forms.truongvietanh.com/tuyen-sinh-thpt | K51: ViewContent, ClickLink, Lead | L51: University prep THPT
A52: Spark_OpenDay_Event | B52: Event Promotion | C52: Age 25-50 | Parents all levels | HCM location | D52: Spark Ad (boost organic) | E52: "Ghé thăm Việt Anh vào thứ 7 - Open Day tháng 6!" Đăng ký miễn phí | F52: Video highlights: tour cơ sở, gặp thầy cô, vui chơi cùng học sinh | G52: Đăng ký Open Day ngay - Hạn chế 100 gia đình. Zalo: xxx-xxx-xxx | H52: 100000 | I52: CPV ≤ 2.5K, Engage ≥ 15% | J52: forms.truongvietanh.com/tuyen-sinh-mam-non/open-day-t6 | K52: ViewContent, ClickLink, AddToCalendar | L52: OpenDay event
A53: Spark_Webinar_EduTalk | B53: Lead Generation | C53: Age 25-50 | Parents interested in education | D53: Spark Ad (boost organic) | E53: "5 Tips để con tự tin và sáng tạo - Từ chuyên gia giáo dục" | F53: Educational tips, expert talking head, interactive elements, key takeaways | G53: Đăng ký Webinar miễn phí - Ngồn theo giáo dục con em. Link dưới | H53: 70000 | I53: CPV ≤ 2.8K, Save ≥ 8% | J53: forms.truongvietanh.com/tuyen-sinh-mam-non/webinar-5-tips | K53: ViewContent, ClickLink, Lead | L53: Webinar promo
A54: Spark_ScholarshipHighAchiever | B54: Lead Generation | C54: Age 30-50 | High-income parents | HCM District 1,3,7 | D54: Spark Ad (boost organic) | E54: "Con xuất sắc? Học bổng Việt Anh cho học sinh giỏi" | F54: Scholarship info, application process, past scholarship recipients testimonials | G54: Tìm hiểu điều kiện và hồ sơ học bổng. Tư vấn miễn phí | H54: 50000 | I54: CPV ≤ 3K, Save ≥ 10% | J54: forms.truongvietanh.com/tuyen-sinh-mam-non/hoc-bong | K54: ViewContent, ClickLink, Lead | L54: Scholarship campaign
A55: Spark_Referral_Bonus | B55: Lead Generation | C55: Age 25-45 | Parents + alumni network | D55: Spark Ad (boost organic) | E55: "Giới thiệu bạn đến Việt Anh - Nhận quà tặng trị giá 2 triệu" | F55: Referral reward program, how-to apply, previous referrers sharing experience | G55: Tham gia chương trình giới thiệu ngay. Quy tắc chi tiết trong link | H55: 60000 | I55: CPV ≤ 2.5K, Click ≥ 18% | J55: forms.truongvietanh.com/tuyen-sinh-mam-non/chuong-trinh-gioi-thieu | K55: ViewContent, ClickLink, Lead | L55: Referral incentive
... A68: Spark_SocialResponsibility_AllLevels | B68: Awareness | C68: Age 25-55 | Socially conscious parents | D68: Spark Ad | E68: "Giáo dục không chỉ là điểm số - Giáo dục tâm hồn, trách nhiệm xã hội" | F68: Community service, environmental awareness, charity programs, social values education | G68: Việt Anh nuôi dạy những công dân toàn cầu có tâm, có trách nhiệm | H68: 65000 | I68: CPV ≤ 2.5K, Engage ≥ 13% | J68: forms.truongvietanh.com/ | K68: ViewContent, ClickLink, Like | L68: Social responsibility focus

Sheet 8. GoHighLevel Setup
A1: GOHIGHLEVEL – SETUP TỪ ĐẦU + CRM + AUTOMATION + SALES + ZALO
A3: A. SETUP TÀI KHOẢN GHL TỪ ĐẦU
A4: Bước | B4: Module | C4: Hành động chi tiết | D4: Kết quả cần có | E4: Timeline | F4: Trạng thái
A5: 1 | B5: Account | C5: Tạo sub-account cho Việt Anh | Timezone VN | Currency VND | D5: Account live | E5: Ngày 1 | F5: ☐
A6: 2 | B6: Custom Fields | C6: Tạo fields: Campus, Grade, Source Channel, Campaign ID, Campaign Name, Keyword Theme, Lead Status, Qualified Flag, Tour Date, Tour Attended, Application, Deposit, Enrollment | D6: Tất cả fields có | E6: Ngày 1 | F6: ☐
A7: 3 | B7: Pipelines | C7: Tạo 4 pipelines: MN, TH, THCS, THPT | Stages: New → Contacted → Qualified → Tour Booked → Tour Done → Offer → Enrolled → Lost | D7: 4 pipelines active | E7: Ngày 1 | F7: ☐
A8: 4 | B8: Tags | C8: Tạo tag system: src_google, src_meta, src_tiktok, src_zalo, src_organic, campus_gv, campus_bt, campus_tinh, grade_mn, grade_th, grade_thcs, grade_thpt, qualified, booked_tour, tour_attended, enrolled, lost | D8: Tags ready | E8: Ngày 1 | F8: ☐
A9: 5 | B9: Users & Teams | C9: Tạo users cho sales team | Assign theo campus | Round-robin rules | D9: Team assigned | E9: Ngày 1 | F9: ☐
A10: 6 | B10: Phone & SMS | C10: Setup Twilio / VN SMS provider | Verify phone numbers | SMS templates | D10: SMS working | E10: Ngày 2 | F10: ☐
A11: 7 | B11: Zalo OA | C11: Kết nối Zalo OA | Tạo 8 template messages | Auto-reply menu | D11: Zalo connected | E11: Ngày 2 | F11: ☐
A12: 8 | B12: Email | C12: Setup domain, DKIM, SPF | Email templates: Welcome, Tour reminder, Follow-up, Scholarship, Thank you | D12: Email verified | E12: Ngày 2 | F12: ☐
A13: 9 | B13: Calendar | C13: Tạo booking calendar cho 6 cơ sở (bỏ PN) | Availability slots | Auto SMS confirm | D13: Calendar live | E13: Ngày 2 | F13: ☐
A14: 10 | B14: Forms | C14: Tạo 8 forms (1/LP) | UTM auto-capture | Pipeline auto-assign | D14: Forms embedded | E14: Ngày 3 | F14: ☐
A15: 11 | B15: Landing Pages | C15: Build hoặc embed 8 LP trong GHL | Form + tracking + Zalo widget | D15: LPs live | E15: Ngày 3-5 | F15: ☐
A17: B. AUTOMATION WORKFLOWS
A18: Workflow | B18: Trigger | C18: Actions | D18: SLA | E18: Kết quả | F18: Timeline | G18: Trạng thái
A19: Auto-assign lead | B19: New contact created | C19: Round-robin assign theo campus + Push notification + SMS to sales | D19: < 5 phút | E19: Lead có owner ngay | F19: Ngày 3 | G19: ☐
A20: Welcome sequence | B20: New lead + src_google/meta/tiktok | C20: SMS welcome 30s + Zalo message 5 phút + Email brochure 1h | D20: Tự động | E20: Mọi lead được chào | F20: Ngày 3 | G20: ☐
A21: Nurture chưa tour | B21: Lead > 48h chưa book tour | C21: SMS Day 2 → Zalo Day 4 → Email Day 7 → Call task Day 10 | D21: 4 touchpoints | E21: Tăng Lead→Tour | F21: Ngày 4 | G21: ☐
A22: Tour reminder | B22: Appointment booked | C22: SMS 48h trước + Zalo 2h trước + Email confirm | D22: Auto | E22: Giảm no-show | F22: Ngày 4 | G22: ☐
A23: Post-tour follow-up | B23: Tour completed (status changed) | C23: Thank you SMS 2h + Offer email 24h + Call task 48h | D23: 3 touchpoints | E23: Tăng Tour→Enroll | F23: Ngày 4 | G23: ☐
A24: Lost re-engage | B24: Marked Lost > 30 ngày | C24: Monthly email + SMS promo | Re-enter pipeline nếu click | D24: Monthly | E24: Reactivation | F24: Tuần 2 | G24: ☐
A25: Webinar sequence | B25: Webinar registered | C25: Confirm email + SMS 24h + Zalo 2h + Post-webinar call 24h | D25: 4 touchpoints | E25: Tăng attend + tour | F25: Ngày 5 | G25: ☐
A26: Scholarship workflow | B26: Scholarship form submitted | C26: Auto email confirm + Assign to senior counselor + Task create | D26: Immediate | E26: THPT priority | F26: Ngày 5 | G26: ☐
A27: Webhook → Sheets | B27: Any status change (qualified/tour/enroll) | C27: Custom webhook → Middleware → Google Sheets → Birch reads | D27: Real-time | E27: Birch data sync | F27: Tuần 2 | G27: ☐
A29: C. CRM + SALES INTEGRATION
A30: Module | B30: Setup | C30: Mục đích | D30: Ai dùng | E30: Ghi chú
A31: Pipeline Dashboard | B31: Kanban view theo campus + cấp | C31: Theo dõi real-time | D31: Sales Manager | E31: Filter by campus
A32: Conversations | B32: Unified inbox: SMS + Zalo + Email + FB Messenger | C32: Tất cả kênh 1 chỗ | D32: Sales team | E32: Reply nhanh
A33: Opportunities | B33: Gắn giá trị = học phí năm 1 | Track close rate | C33: Forecast revenue | D33: Manager + BGH | E33: Dự báo doanh thu
A34: Reporting | B34: Lead by source, campaign, campus | Conversion funnel | SLA tracking | C34: Đo hiệu quả | D34: Marketing + Sales | E34: Auto weekly email
A35: Call tracking | B35: Ghi âm cuộc gọi + log duration + outcome | C35: QA + Training | D35: QA team | E35: Mystery call chấm điểm
A36: Review request | B36: Sau enrollment → auto gửi review link Google Business | C36: Tăng review organic | D36: Auto | E36: Giúp Local SEO
A38: D. GHL + BIRCH INTEGRATION CHI TIẾT
A39: # | B39: Bước | C39: Hành động | D39: Chi tiết kỹ thuật | E39: Kết quả cần có | F39: Tool | G39: Timeline | H39: Trạng thái
A40: 1 | B40: Webhook Setup | C40: Tạo webhook từ GHL → Google Sheets | D40: GHL Workflow → Custom Webhook → POST to Sheets API middleware | E40: Data sync real-time | F40: GHL + Apps Script | G40: Ngày 3 | H40: ☐
A41: 2 | B41: Middleware Build | C41: Xây middleware nhận webhook GHL | D41: Node.js/Apps Script → Parse payload → Write to Google Sheets | E41: Middleware running 24/7 | F41: Apps Script / Cloud Run | G41: Ngày 3-4 | H41: ☐
A42: 3 | B42: Sheet Structure | C42: Tạo Google Sheet cho Birch đọc | D42: Columns: Date, Contact ID, Campus, Grade, Source, Campaign, Status, Qualified, Tour, Enrolled | E42: Sheet ready for Birch | F42: Google Sheets | G42: Ngày 3 | H42: ☐
A43: 4 | B43: Birch Connect Sheet | C43: Kết nối Birch với Google Sheets | D43: Birch Settings → Data Sources → Google Sheets → Share sheet | E43: Birch reads GHL data | F43: Birch | G43: Ngày 4 | H43: ☐
A44: 5 | B44: Custom Metrics Birch | C44: Tạo metrics kết hợp ads + CRM | D44: Qualified Rate = Q.Leads/Total Leads | Tour Rate = Tours/Leads | CAC = Spend/Enrolled | E44: Birch shows CRM metrics | F44: Birch Custom Metrics | G44: Ngày 4 | H44: ☐
A45: 6 | B45: Auto Scale Rule | C45: Rule: Scale campaign nếu quality tốt | D45: IF CPL < target AND Qualified Rate > 50% AND Tour Rate > 20% → Increase budget 15% | E45: Auto budget increase | F45: Birch Automation | G45: Tuần 2 | H45: ☐
A46: 7 | B46: Auto Pause Rule | C46: Rule: Pause nếu quality xấu | D46: IF CPL > target 30% AND Tour Rate < 10% for 5 days → Pause adset + Alert | E46: Auto protection | F46: Birch Automation | G46: Tuần 2 | H46: ☐
A47: 8 | B47: Campus Alert Rule | C47: Rule: Alert khi campus hụt target | D47: IF Campus X enrolled < monthly target 20% by mid-month → Alert Slack | E47: Campus gap detection | F47: Birch Automation | G47: Tuần 2 | H47: ☐
A48: 9 | B48: Meta CAPI Setup | C48: Conversion API từ GHL → Meta | D48: GHL Workflow → On status change → POST to Meta CAPI endpoint with event data | E48: Server-side tracking active | F48: GHL + Meta CAPI | G48: Ngày 4 | H48: ☐
A49: 10 | B49: Google Offline Conv | C49: Upload offline conversions Google | D49: GHL → Tour completed → Upload to Google Ads as offline conversion via API | E49: Google Ads sees tour data | F49: GHL + Google Ads API | G49: Ngày 5 | H49: ☐
A50: 11 | B50: Lead Scoring Setup | C50: Xây lead scoring trong GHL | D50: Score: +10 form submit, +20 call answered, +30 tour booked, +50 tour attended, -10 no answer 3x | E50: Lead priority ranking | F50: GHL Lead Scoring | G50: Ngày 5 | H50: ☐
A51: 12 | B51: Dashboard GHL | C51: Build dashboard CRM realtime | D51: Pipeline view + Lead by source + Tour calendar + SLA tracker + Revenue forecast | E51: Dashboard live | F51: GHL Dashboard Builder | G51: Ngày 5-6 | H51: ☐
A54: E. GHL + ADS PLATFORMS INTEGRATION MAP
A55: Nền tảng Ads | B55: Loại Integration | C55: Data Flow | D55: Mục đích | E55: Setup Tool | F55: Automation | G55: Trạng thái
A56: Meta Ads | B56: Lead Form Sync | C56: Meta Lead Form → GHL (instant) | D56: Auto-import lead từ Meta form vào GHL pipeline | E56: GHL Integration + Zapier | F56: New lead → Auto-assign → Welcome SMS 30s | G56: ☐
A57: Meta Ads | B57: CAPI (Server) | C57: GHL Status Change → Meta CAPI | D57: Gửi offline events: Qualified, Tour, Enrolled về Meta | E57: GHL Webhook + Meta CAPI | F57: Improve Meta optimization + audience quality | G57: ☐
A58: Meta Ads | B58: Audience Sync | C58: GHL Enrolled List → Meta Custom Audience | D58: Exclude enrolled + Create lookalike từ best leads | E58: GHL Export + Meta Upload | F58: Monthly refresh audience exclusion | G58: ☐
A59: Google Ads | B59: Offline Conversion | C59: GHL Tour/Enroll → Google Ads Offline Conv | D59: Google Ads optimize cho Tour thay vì chỉ form submit | E59: GHL → Sheets → Google Ads API | F59: Weekly upload offline conversions | G59: ☐
A60: Google Ads | B60: Birch Bridge | C60: GHL → Sheets → Birch → Google Ads | D60: Birch dùng CRM data để auto-optimize budget | E60: Birch + Google Sheets | F60: Auto scale/pause dựa trên CRM quality | G60: ☐
A61: TikTok Ads | B61: Lead Form Sync | C61: TikTok Lead Form → GHL | D61: Import TikTok leads vào GHL auto | E61: Zapier / Make.com | F61: New lead → Pipeline + Welcome seq | G61: ☐
A62: TikTok Ads | B62: Pixel Events | C62: Website → TikTok Pixel → Events | D62: Track form submit, call click cho TikTok optimization | E62: GTM + TikTok Pixel | F62: Event-based optimization | G62: ☐
A63: Zalo Ads | B63: OA Connect | C63: Zalo OA → GHL Conversations | D63: Tất cả Zalo message hiện trong GHL inbox | E63: GHL Zalo Integration | F63: Auto-reply + broadcast từ GHL | G63: ☐
A64: Zalo Ads | B64: Pixel Sync | C64: Website → Zalo Pixel → Remarketing | D64: Build Zalo remarketing audience từ web visitors | E64: GTM + Zalo Pixel | F64: Retarget OA followers + web visitors | G64: ☐
A65: All Platforms | B65: UTM Tracking | C65: UTM params → GHL Custom Fields | D65: Attribution chính xác: biết lead từ campaign/keyword nào | E65: GHL Form + Hidden fields | F65: Auto-capture UTM vào contact record | G65: ☐
A66: Birch PPC | B66: Cross-platform | C66: All Ads → Birch → Rules + Reports | D66: Quản lý budget, pacing, alerts tất cả ads từ 1 dashboard | E66: Birch Workspace | F66: Auto email report T2+T5 cho team | G66: ☐
A69: F. GHL AUTOMATION WORKFLOWS – CHI TIẾT TỪNG BƯỚC
A70: Workflow | B70: Bước | C70: Action | D70: Delay | E70: Channel | F70: Nội dung tóm tắt | G70: Condition | H70: KPI đo
A71: Welcome Sequence | B71: 1 | C71: SMS gửi ngay | D71: 30 giây | E71: SMS | F71: Chào [Tên], cảm ơn bạn quan tâm Việt Anh. Tư vấn viên sẽ gọi trong 5 phút! | G71: New lead created | H71: Delivery rate
A72: Welcome Sequence | B72: 2 | C72: Assign to Sales | D72: 1 phút | E72: System | F72: Round-robin assign theo campus + grade → Push notification | G72: Auto | H72: Assign time < 2 min
A73: Welcome Sequence | B73: 3 | C73: Zalo message | D73: 5 phút | E73: Zalo | F73: Chào [Tên]! Tôi là [Sales]. Rất vui được tư vấn. Bạn quan tâm cấp nào? | G73: IF Zalo connected | H73: Reply rate ≥ 25%
A74: Welcome Sequence | B74: 4 | C74: Email brochure | D74: 1 giờ | E74: Email | F74: Email chào đón + brochure PDF + link website + CTA book tour | G74: All leads | H74: Open rate ≥ 30%
A75: Welcome Sequence | B75: 5 | C75: Internal alert | D75: 5 phút | E75: System | F75: IF lead chưa được gọi sau 5 min → Alert manager Slack/Zalo | G75: No call logged | H75: SLA compliance
A76: Nurture No-Tour | B76: 1 | C76: SMS nhắc nhẹ | D76: Day 2 | E76: SMS | F76: [Tên] ơi, đã tìm hiểu về trường chưa? Mời bạn đặt lịch tour miễn phí! | G76: Lead > 48h, no tour booked | H76: Reply rate
A77: Nurture No-Tour | B77: 2 | C77: Zalo article | D77: Day 4 | E77: Zalo | F77: Gửi article: "5 tiêu chí chọn trường [Cấp] cho con" + CTA tour | G77: Still no tour | H77: Click rate
A78: Nurture No-Tour | B78: 3 | C78: Email testimonial | D78: Day 7 | E78: Email | F78: Email testimonial video PH + campus photos + CTA book tour | G78: Still no tour | H78: Open + Click
A79: Nurture No-Tour | B79: 4 | C79: Task: Gọi điện | D79: Day 10 | E79: System | F79: Tạo task cho sales: Gọi [Tên] – lead chưa tour 10 ngày | G79: Still no tour | H79: Call outcome
A80: Nurture No-Tour | B80: 5 | C80: SMS ưu đãi | D80: Day 14 | E80: SMS | F80: Ưu đãi đặc biệt cho [Tên]: Giảm [X]% nếu nộp hồ sơ trong tuần! | G80: Still no tour | H80: Conv rate
A81: Post-Tour | B81: 1 | C81: SMS cảm ơn | D81: 2 giờ | E81: SMS | F81: Cảm ơn [Tên] đã đến tham quan! Nếu cần thêm thông tin, nhắn ngay! | G81: Tour completed | H81: Reply rate
... A85: Post-Tour | B85: 5 | C85: SMS deadline | D85: Day 7 | E85: SMS | F85: Cuối cùng! Ưu đãi [X]% hết hạn [Ngày]. Nộp hồ sơ ngay! | G85: No enrollment | H85: Conv rate
A88: ═══ TÍCH HỢP VỚI PANCAKE CRM + MAKE.COM ═══
A90: Tính năng GHL | B90: Đồng bộ với Pancake | C90: Qua Make.com | D90: Hướng đi dữ liệu | E90: Ghi chú
A91: Contacts | B91: Đồng bộ 2 chiều | C91: Scenario 1 + 2 | D91: GHL ↔ Pancake | E91: Contact fields phải match 1:1
A92: Tags | B92: Đồng bộ 2 chiều | C92: Scenario 3 | D92: GHL ↔ Pancake | E92: Cẩn thận infinite loop
A93: Pipeline/Stages | B93: GHL → Pancake | C93: Scenario 4 | D93: GHL → Pancake | E93: GHL là master cho pipeline
A94: Appointments | B94: GHL → Pancake (note) | C94: Scenario 7 | D94: GHL → Pancake | E94: Pancake nhận note, không calendar
A95: Workflows/Automation | B95: GHL only | C95: N/A | D95: N/A | E95: Pancake không có workflow engine
A96: Email Marketing | B96: GHL only | C96: N/A | D96: N/A | E96: GHL gửi email, Pancake chỉ chat
A97: SMS | B97: GHL only | C97: N/A | D97: N/A | E97: Qua eSMS/SpeedSMS API
A98: FB/Zalo Chat | B98: Pancake only | C98: N/A | D98: N/A | E98: Pancake là master cho chat
A99: Chatbot | B99: Pancake primary | C99: N/A | D99: N/A | E99: FB + Zalo chatbot qua Pancake
A100: Reporting | B100: Cả hai | C100: Scenario 5 + 8 | D100: Both → Google Sheets | E100: Google Sheets là backup/dashboard
A101: Landing Pages | B101: GHL only | C101: N/A | D101: N/A | E101: forms.truongvietanh.com
A102: Ads Tracking | B102: GHL + Birch | C102: Scenario 9 | D102: Birch → GHL → Make → Pancake | E102: Full attribution chain

Sheet 9. GTM Tracking
A1: GOOGLE TAG MANAGER – TRACKING SETUP TOÀN BỘ KÊNH
A3: A. TAGS CẦN CÀI TRONG GTM
A4: Tag | B4: Type | C4: Platform | D4: Trigger | E4: Ghi chú | F4: Timeline | G4: Trạng thái
A5: GA4 Config | B5: GA4 Configuration | C5: Google Analytics | D5: All Pages | E5: GA4 property chính | F5: Ngày 1 | G5: ☐
A6: GA4 - form_submit | B6: GA4 Event | C6: Google Analytics | D6: Form submission (all LPs) | E6: Khi form được submit | F6: Ngày 1 | G6: ☐
A7: GA4 - click_call | B7: GA4 Event | C7: Google Analytics | D7: Click on tel: links | E7: Bấm gọi hotline | F7: Ngày 1 | G7: ☐
A8: GA4 - click_zalo | B8: GA4 Event | C8: Google Analytics | D8: Click on Zalo widget/link | E8: Bấm Zalo | F8: Ngày 1 | G8: ☐
A9: GA4 - webinar_register | B9: GA4 Event | C9: Google Analytics | D9: Webinar form submit | E9: Đăng ký webinar | F9: Ngày 1 | G9: ☐
A10: GA4 - scholarship_click | B10: GA4 Event | C10: Google Analytics | D10: Click scholarship CTA | E10: THPT scholarship | F10: Ngày 1 | G10: ☐
A11: Meta Pixel Base | B11: Custom HTML | C11: Meta | D11: All Pages | E11: Pixel ID + PageView event | F11: Ngày 1 | G11: ☐
A12: Meta - Lead | B12: Custom HTML | C12: Meta | D12: Form submission | E12: Conversion event cho Meta | F12: Ngày 1 | G12: ☐
A13: Meta - ViewContent | B13: Custom HTML | C13: Meta | D13: LP Page View | E13: Content view tracking | F13: Ngày 1 | G13: ☐
A14: Meta - CompleteRegistration | B14: Custom HTML | C14: Meta | D14: Thank you page view | E14: Tour/webinar confirmed | F14: Ngày 1 | G14: ☐
A15: TikTok Pixel Base | B15: Custom HTML | C15: TikTok | D15: All Pages | E15: Pixel ID + PageView | F15: Ngày 1 | G15: ☐
... A20: Zalo Pixel | B20: Custom HTML | C20: Zalo | D20: All Pages + Form | E20: Zalo Ads tracking | F20: Ngày 2 | G20: ☐
A22: B. TRIGGERS CẦN TẠO
A23: Trigger | B23: Type | C23: Condition | D23: Dùng cho tags | E23: Ghi chú
A24: All Pages | B24: Page View | C24: Mọi trang | D24: GA4, Meta, TikTok, Google Ads RMKT, Zalo | E24: Base trigger
A25: Form Submit - All | B25: Form Submission | C25: Form ID contains 'ghl' hoặc class | D25: GA4 form, Meta Lead, TikTok Submit, GG Ads Conv | E25: Tất cả form trên LP
A26: Click Call | B26: Click - Just Links | C26: Click URL contains 'tel:' | D26: GA4 click_call, Google Ads call conv | E26: Hotline click
A27: Click Zalo | B27: Click - Just Links | C27: Click URL contains 'zalo.me' | D27: GA4 click_zalo | E27: Zalo widget click
A28: Click CTA Button | B28: Click - All Elements | C28: CSS selector cho CTA buttons | D28: TikTok ClickButton | E28: Tour / tư vấn buttons
A29: Thank You Page | B29: Page View | C29: Page URL contains '/thank-you' hoặc '/cam-on' | D29: Meta CompleteReg, GA4 conversion | E29: Sau form submit
A30: Webinar Form | B30: Form Submission | C30: Form contains 'webinar' | D30: GA4 webinar_register | E30: Chỉ webinar forms
A31: Scholarship CTA | B31: Click - All Elements | C31: Element contains 'scholarship' / 'hoc-bong' | D31: GA4 scholarship_click | E31: THPT only
A34: ═══ GTM TRACKING THEO TỪNG TRANG PHỄU ═══
A36: Phễu | B36: Trang | C36: URL | D36: Tags fire | E36: Events | F36: Custom Dimensions | G36: Audiences tạo
A37: FNL-MN-MAIN | B37: Trang 1: LP chính | C37: forms.truongvietanh.com/tuyen-sinh-mam-non | D37: GA4 Config, Meta PageView, Meta ViewContent (scroll 50%), Meta InitiateCheckout (form focus), Meta Lead (submit), TikTok PageView, Zalo PageView, Google Remarketing | E37: PageView, ViewContent, InitiateCheckout, Lead | F37: campus=all_mn, grade=mn, page_type=lp_main | G37: mn_page_visitors, mn_page_engaged, mn_form_started, mn_form_complete
A38: FNL-MN-MAIN | B38: Trang 2: Thank You | C38: forms.truongvietanh.com/tuyen-sinh-mam-non/cam-on | D38: GA4 Config, GA4 Tour Booked, Meta Schedule, Google Ads Conv (Lead), TikTok SubmitForm | E38: PageView, Schedule, CompleteRegistration | F38: campus=from_form, grade=mn, page_type=thank_you | G38: mn_tour_booked
A39: FNL-MN-MAIN | B39: Trang 2b: Confirmation | C39: forms.truongvietanh.com/tuyen-sinh-mam-non/xac-nhan | D39: GA4 Config, GA4 CompleteRegistration | E39: PageView, CompleteRegistration | F39: campus=from_booking, grade=mn | G39: mn_tour_confirmed
A40: FNL-MN-MAIN | B40: Trang 3: Testimonial | C40: forms.truongvietanh.com/tuyen-sinh-mam-non/phu-huynh-noi-gi | D40: GA4 Config, Meta ViewContent, Meta Lead (if form), Video tracking | E40: PageView, ViewContent, Lead | F40: grade=mn, page_type=testimonial | G40: mn_testimonial_viewers
A41: FNL-MN-MAIN | B41: Trang 4: Chương trình | C41: forms.truongvietanh.com/tuyen-sinh-mam-non/chuong-trinh | D41: GA4 Config, Meta ViewContent, Meta AddToCart (PDF), Meta Lead (form) | E41: PageView, ViewContent, AddToCart, Lead | F41: grade=mn, page_type=program | G41: mn_program_viewers, mn_pdf_downloaded
A42: FNL-MN-MAIN | B42: Trang 5: Học phí | C42: forms.truongvietanh.com/tuyen-sinh-mam-non/hoc-phi | D42: GA4 Config, Meta ViewContent, Meta AddPaymentInfo, Meta Lead, Google Ads Conv (Lead) | E42: PageView, ViewContent, AddPaymentInfo, Lead | F42: grade=mn, page_type=tuition | G42: mn_tuition_viewers, mn_tuition_engaged
A43: FNL-TH-MAIN | B43: Trang 1: LP Tiểu học | C43: forms.truongvietanh.com/tuyen-sinh-tieu-hoc | D43: Tương tự FNL-MN nhưng grade=th | E43: PageView, ViewContent, InitiateCheckout, Lead | F43: grade=th, page_type=lp_main | G43: th_page_visitors, th_form_complete
A44: FNL-THCS-MAIN | B44: Trang 1: LP THCS | C44: forms.truongvietanh.com/tuyen-sinh-thcs | D44: Tương tự + TikTok Pixel (THCS target trẻ hơn) | E44: PageView, ViewContent, Lead | F44: grade=thcs, page_type=lp_main | G44: thcs_page_visitors, thcs_form_complete
A45: FNL-THPT-MAIN | B45: Trang 1: LP THPT | C45: forms.truongvietanh.com/tuyen-sinh-thpt | D45: Tương tự + TikTok Pixel | E45: PageView, ViewContent, Lead | F45: grade=thpt, page_type=lp_main | G45: thpt_page_visitors, thpt_form_complete
A46: FNL-OD-T6 | B46: LP Mega Open Day | C46: forms.truongvietanh.com/mega-open-day-2026 | D46: GA4, Meta, TikTok, Zalo, Google — all Lead events | E46: PageView, ViewContent, Lead | F46: event=open_day_t6 | G46: od_t6_visitors, od_t6_registered
A47: FNL-WB-MN | B47: LP Webinar MN | C47: forms.truongvietanh.com/webinar-mam-non | D47: GA4, Meta, Zalo Lead events | E47: PageView, Lead, CompleteRegistration | F47: event=webinar_mn | G47: wb_mn_visitors, wb_mn_registered
A48: FNL-HB | B48: LP Học Bổng | C48: forms.truongvietanh.com/hoc-bong-2026 | D48: GA4, Meta, Google Lead events | E48: PageView, Lead | F48: campaign=scholarship | G48: hb_visitors, hb_applied

Sheet 10. Lịch Công Việc Marketer
A1: LỊCH CÔNG VIỆC MARKETER – HÀNG NGÀY / TUẦN / THÁNG / QUÝ / NĂM
A3: A. CÔNG VIỆC HÀNG NGÀY (MỖI NGÀY LÀM VIỆC)
A4: STT | B4: Kênh | C4: Công việc | D4: Chi tiết | E4: Thời gian | F4: Ai làm | G4: Checklist
A5: 1 | B5: Google Ads | C5: Kiểm tra spend vs budget | D5: Login Birch → check pacing alert | Nếu overspend → giảm | E5: 8:00-8:15 | F5: Performance | G5: ☐
A6: 2 | B6: Google Ads | C6: Rà search terms | D6: Birch Explorer → Search terms | Thêm negative nếu cần | E6: 8:15-8:30 | F6: Performance | G6: ☐
A7: 3 | B7: Meta Ads | C7: Kiểm tra CPL và lead volume | D7: Birch hoặc Meta Ads Manager → check CPL by campaign | E7: 8:30-8:45 | F7: Performance | G7: ☐
A8: 4 | B8: TikTok | C8: Kiểm tra CPV và engagement | D8: TikTok Ads Manager → check Spark Ads performance | E8: 8:45-9:00 | F8: Performance | G8: ☐
A9: 5 | B9: GHL/CRM | C9: Kiểm tra lead mới từ đêm qua | D9: GHL Dashboard → New leads → Verify source tags đúng | E9: 9:00-9:15 | F9: Marketing Manager | G9: ☐
A10: 6 | B10: GHL/CRM | C10: Check SLA phản hồi | D10: GHL → Pipeline → Lead chưa được gọi > 5 phút → escalate | E10: 9:15-9:30 | F10: Marketing Manager | G10: ☐
A11: 7 | B11: Content | C11: Đăng bài social media | D11: 3-4 bài/ngày: FB + IG + TikTok organic | Dùng kho 2,000 bài | E11: 9:30-10:30 | F11: Content Creator | G11: ☐
A12: 8 | B12: Zalo | C12: Kiểm tra Zalo OA messages | D12: Reply tin nhắn mới + Check broadcast schedule | E12: 10:30-11:00 | F12: Content/Sales | G12: ☐
A13: 9 | B13: All | C13: Báo cáo nhanh buổi sáng | D13: Gửi Slack/Zalo group: lead hôm qua, booked tour, spend | E13: 11:00-11:15 | F13: Marketing Manager | G13: ☐
A14: 10 | B14: All | C14: Sync với Sales | D14: 15 phút meeting: lead quality, objection, tour feedback | E14: 14:00-14:15 | F14: MM + Sales Lead | G14: ☐
A16: B. CÔNG VIỆC HÀNG TUẦN (MỖI THỨ HAI + THỨ NĂM)
A17: STT | B17: Kênh | C17: Công việc | D17: Chi tiết | E17: Ngày | F17: Ai làm | G17: Checklist
A18: 1 | B18: Google Ads | C18: Tối ưu bidding | D18: Review CPA targets | Adjust bids by campaign | Pause KW yếu | E18: Thứ 2 | F18: Performance | G18: ☐
A19: 2 | B19: Google Ads | C19: Cập nhật negative KW | D19: Rà search terms tuần | Thêm negative | Check quality score | E19: Thứ 2 | F19: Performance | G19: ☐
A20: 3 | B20: Meta Ads | C20: A/B test creative | D20: Test 2 creative mới / tuần | Compare CTR, CPL, quality | E20: Thứ 2 | F20: Performance + Content | G20: ☐
A21: 4 | B21: TikTok | C21: Upload video mới | D21: 2-3 video mới từ kho testimonial | Test hook mới | E21: Thứ 2 | F21: Content | G21: ☐
A22: 5 | B22: Zalo | C22: Broadcast schedule | D22: Lên lịch broadcast tour/ưu đãi cho tuần | Segment by campus | E22: Thứ 2 | F22: Content | G22: ☐
A23: 6 | B23: GHL | C23: Pipeline review | D23: Rà pipeline: leads stuck, overdue follow-ups, tour no-shows | E23: Thứ 2 | F23: MM + Sales | G23: ☐
A24: 7 | B24: Birch | C24: Review rules | D24: Kiểm tra rules nào fired | CPL alerts | Budget pacing | E24: Thứ 2 | F24: Performance | G24: ☐
A25: 8 | B25: All | C25: Báo cáo tuần | D25: Weekly report: spend, leads, tours, enrollments by campus | E25: Thứ 5 | F25: Marketing Manager | G25: ☐
A26: 9 | B26: All | C26: Họp tuần MKT + Sales | D26: 30 phút: KPI review, blockers, campus feedback, action items | E26: Thứ 5 | F26: All team | G26: ☐
A27: 10 | B27: Local SEO | C27: Check Google Business | D27: Reply reviews mới | Post bài mới | Check info chính xác | E27: Thứ 5 | F27: Content | G27: ☐
A29: C. CÔNG VIỆC HÀNG THÁNG
A30: STT | B30: Kênh | C30: Công việc | D30: Chi tiết | E30: Ngày | F30: Ai làm | G30: Checklist
A31: 1 | B31: All | C31: Monthly report | D31: Tổng spend, leads, tours, enrollments, CAC by campus + channel | E31: Ngày 1-3 | F31: MM | G31: ☐
A32: 2 | B32: Google Ads | C32: Cấu trúc lại campaigns | D32: Pause campaigns yếu | Tạo campaigns mới nếu cần | Shift budget | E32: Ngày 1-5 | F32: Performance | G32: ☐
A33: 3 | B33: Meta Ads | C33: Refresh audiences | D33: Update Lookalike | Refresh Custom audiences | Exclude enrolled | E33: Ngày 1-5 | F33: Performance | G33: ☐
A34: 4 | B34: TikTok | C34: Content refresh | D34: Quay 3-5 video mới nếu cần | Update Spark Ads library | E34: Ngày 5-10 | F34: Content + Campus | G34: ☐
A35: 5 | B35: GHL | C35: CRM cleanup | D35: Merge duplicates | Update lost reasons | Archive old leads | E35: Ngày 5-10 | F35: Sales + MM | G35: ☐
A36: 6 | B36: GHL | C36: Automation review | D36: Kiểm tra workflow performance | Adjust nurture timing | Test SMS | E36: Ngày 5-10 | F36: MM | G36: ☐
A37: 7 | B37: Birch | C37: Rule optimization | D37: Review rule performance | Adjust thresholds | Add new rules | E37: Ngày 5-10 | F37: Performance | G37: ☐
A38: 8 | B38: All | C38: Họp tháng với BGH | D38: CAC, ROI, campus performance, budget shift proposal, next month plan | E38: Ngày 5-7 | F38: MM + BGH | G38: ☐
A39: 9 | B39: Content | C39: Kế hoạch content tháng sau | D39: Calendar editorial: 90 bài social + 4-8 blog + video plan | E39: Ngày 25-30 | F39: Content Lead | G39: ☐
A40: 10 | B40: Local SEO | C40: GMB monthly update | D40: Cập nhật ảnh, bài viết, sự kiện cho 6 cơ sở | Review response | E40: Ngày 15 | F40: Content | G40: ☐
A42: D. CÔNG VIỆC HÀNG QUÝ
A43: STT | B43: Công việc | C43: Chi tiết | D43: Ai làm | E43: Checklist
A44: 1 | B44: Review chiến lược tổng | C44: So sánh KPI thực vs plan | Điều chỉnh mix kênh | Shift budget | D44: MM + BGH | E44: ☐
A45: 2 | B45: Audit toàn bộ tracking | C45: GTM audit: tất cả tags fire đúng? | Pixel health check | CAPI verify | D45: Performance + Dev | E45: ☐
A46: 3 | B46: Competitor analysis | C46: Rà đối thủ: ads library, keyword, LP, ưu đãi, positioning | D46: MM | E46: ☐
A47: 4 | B47: Content audit | C47: Rà kho content: video nào perform tốt? Bài nào traffic cao? | Gap analysis | D47: Content Lead | E47: ☐
A48: 5 | B48: CRM & automation review | C48: Workflow nào convert tốt? Nurture nào cần sửa? SLA trend? | D48: MM + Sales | E48: ☐
A49: 6 | B49: Training team | C49: Cập nhật kỹ năng: Google Ads mới, Meta policy, TikTok trends, GHL features | D49: MM | E49: ☐
A51: E. CÔNG VIỆC HÀNG NĂM (CUỐI MÙA)
A52: STT | B52: Công việc | C52: Chi tiết | D52: Ai làm | E52: Checklist
A53: 1 | B53: Post-mortem toàn chiến dịch | C53: Tổng kết: spend, leads, tours, enrollments, CAC, ROI theo campus + kênh | D53: MM + Sales + BGH | E53: ☐
A54: 2 | B54: Lưu playbook | C54: Ghi lại: top campaigns, top keywords, top creatives, best practices, lessons learned | D54: MM | E54: ☐
A55: 3 | B55: Chuẩn bị mùa sau | C55: Budget proposal + Channel mix + Campus priority + Content plan cho năm sau | D55: MM | E55: ☐
A56: 4 | B56: Cập nhật assets | C56: Refresh video, ảnh, testimonial mới | Quay phụ huynh mới nhập học | D56: Content + Campus | E56: ☐
A57: 5 | B57: Review tools & contracts | C57: GHL, Birch, domain, hosting, SMS credits, Zalo OA | Renew/upgrade nếu cần | D57: MM + IT | E57: ☐

Sheet 11. Timeline
A1: TIMELINE GIẢI NGÂN 03-09/2026
A2: Giai đoạn | B2: % | C2: Ngân sách | D2: Trọng tâm | E2: Paid Media | F2: KPI | G2: Checkpoint
A3: 26/03–31/03 | B3: 0.04 | C3: =B3*'1. Input'!B4 -> 520000000 | D3: Setup Birch+GHL+GTM+Pixel+LP | E3: =0.02*'1. Input'!B15 -> 170000000 | F3: Tracking live | G3: Go/No-go 31/03
A4: Tháng 4 | B4: 0.14 | C4: =B4*'1. Input'!B4 -> 1820000000 | D4: Meta+TikTok mở phủ | Webinar #1-2 | Tour #1-3 | E4: =0.12*'1. Input'!B15 -> 1020000000 | F4: 1,400 leads/420 tours | G4: CPL review tuần 2
A5: Tháng 5 | B5: 0.22 | C5: =B5*'1. Input'!B4 -> 2860000000 | D5: Scale paid | Open Day #1 | Zalo broadcast tỉnh | E5: =0.24*'1. Input'!B15 -> 2040000000 | F5: 2,400 leads/720 tours | G5: Lead→Tour<25%→dừng
A6: Tháng 6 | B6: 0.24 | C6: =B6*'1. Input'!B4 -> 3120000000 | D6: Tour cao điểm | Remarket mạnh | Open Day #2 | E6: =0.28*'1. Input'!B15 -> 2380000000 | F6: 2,800 leads/840 tours | G6: Check 53% target
A7: Tháng 7 | B7: 0.22 | C7: =B7*'1. Input'!B4 -> 2860000000 | D7: Chốt sale | Học bổng cuối | Pipeline GHL | E7: =0.24*'1. Input'!B15 -> 2040000000 | F7: 2,400 leads/720 tours | G7: <73%→dự phòng
A8: Tháng 8 | B8: 0.1 | C8: =B8*'1. Input'!B4 -> 1300000000 | D8: Vét cuối | Retarget database | E8: =0.08*'1. Input'!B15 -> 680000000 | F8: 1,200 leads/360 tours | G8: Gần đạt target
A9: Tháng 9 | B9: 0.04 | C9: =B9*'1. Input'!B4 -> 520000000 | D9: Late intake | Chuyển trường | Brand defense | E9: =0.02*'1. Input'!B15 -> 170000000 | F9: 400 leads/120 tours | G9: Post-mortem
A10: TỔNG | B10: =SUM(B3:B9) -> 1 | C10: =SUM(C3:C9) -> 13000000000

Sheet 12. Danh bạ
A1: DANH BẠ CƠ SỞ (BỎ PHÚ NHUẬN – CẬP NHẬT ĐỊA GIỚI MỚI)
A2: Khu vực | B2: Tên trường | C2: Cấp | D2: Địa chỉ | E2: Hotline | F2: Trạng thái | G2: Ghi chú
A3: TP.HCM | B3: Việt Anh Gò Vấp | C3: TH+THCS+THPT | D3: 160/72 Phan Huy Ích, Gò Vấp | E3: 091 696 1409 | F3: ✅ | G3: Cơ sở lớn, 3 cấp
A4: TP.HCM | B4: Việt Anh Bình Tân | C4: Tiểu học | D4: Số 7 đường 38A, Tân Tạo, Bình Tân | E4: 0916 961 409 | F4: ✅ | G4: Khu đông dân
A5: TP.HCM | B5: MN Việt Anh Gò Vấp | C5: Mầm non | D5: 573 Đ. Lê Đức Thọ, P. An Hội Tây, Gò Vấp | E5: 0916 961 409 | F5: ✅ | G5: Flagship MN
A6: Tây Ninh | B6: MN Nhân Lễ | C6: Mầm non | D6: 22 Đường D2, KDC Cần Giuộc, Tây Ninh | E6: 0916 961 409 | F6: ✅ | G6: Cần Giuộc → Tây Ninh
A7: Tây Ninh | B7: MN+TH Thái Sơn | C7: MN+TH | D7: KDC Thái Sơn, Cần Giuộc, Tây Ninh | E7: 0916 961 409 | F7: ✅ | G7: Cần Giuộc → Tây Ninh
A8: An Giang | B8: MN+TH Mekong Xanh | C8: MN+TH | D8: Lô E7, KĐT Tây Bắc, TP. Rạch Giá, An Giang | E8: 0916 961 409 | F8: ✅ | G8: Rạch Giá → An Giang
A10: ⚠️ Phú Nhuận ĐÃ BỎ (sắp đóng cửa). Ngân sách Phú Nhuận phân bổ lại cho các cơ sở còn lại.
A11: 📌 Cần Giuộc → thuộc tỉnh TÂY NINH (trước là Long An). Rạch Giá → thuộc tỉnh AN GIANG (trước là Kiên Giang).

Sheet 13. Zalo Ads + OA
A1: KẾ HOẠCH ZALO ADS + ZALO OA – NURTURE LOCAL + BROADCAST
A3: A. ZALO ADS CAMPAIGNS
A4: Campaign | B4: Audience | C4: Creative | D4: Budget/tháng | E4: KPI | F4: GHL Integration | G4: GTM
A5: Zalo_MN_Local | B5: Geo Gò Vấp+Tỉnh | Age 25-40 | Interest Parenting | C5: Image+text: Tour invitation, campus ảnh, ưu đãi | D5: =0.07*'1. Input'!B15*0.35/6 -> 34708333 | E5: Open ≥ 40% | CTR ≥ 5% | F5: Lead → Pipeline MN | G5: Zalo Pixel via GTM
A6: Zalo_TH_Local | B6: Geo Gò Vấp+BT+Tỉnh | Age 28-45 | C6: Image+text: Tuyển sinh lớp 1, chương trình | D6: =0.07*'1. Input'!B15*0.25/6 -> 24791667 | E6: Open ≥ 35% | CTR ≥ 4% | F6: Lead → Pipeline TH | G6: Zalo Pixel
A7: Zalo_THCS_THPT | B7: Geo TP.HCM | Age 30-55 | C7: Webinar invite, lộ trình, học bổng | D7: =0.07*'1. Input'!B15*0.2/6 -> 19833333 | E7: Open ≥ 35% | Reg ≥ 3% | F7: Lead → Pipeline THCS/THPT | G7: Zalo Pixel
A8: Zalo_Remarketing | B8: OA followers + Web visitors | C8: Tour reminder, ưu đãi cuối, deadline | D8: =0.07*'1. Input'!B15*0.2/6 -> 19833333 | E8: Conv ≥ 5% | F8: Retarget pipeline | G8: Zalo Pixel
A10: B. ZALO OA SETUP + BROADCAST
A11: Bước | B11: Hành động | C11: Chi tiết | D11: Timeline | E11: Trạng thái
A12: 1 | B12: Tạo/Verify Zalo OA | C12: 1 OA chính cho hệ thống Việt Anh | Verify business | D12: Ngày 1 | E12: ☐
A13: 2 | B13: Kết nối GHL | C13: API Zalo OA → GHL | Auto-reply + Broadcast + Nurture | D13: Ngày 2 | E13: ☐
A14: 3 | B14: Tạo menu auto-reply | C14: Menu: Tư vấn MN | TH | THCS | THPT | Học phí | Tour | Hotline | D14: Ngày 2 | E14: ☐
A15: 4 | B15: Tạo 8 broadcast templates | C15: Welcome, Tour invite, Tour reminder, Ưu đãi, Webinar, Scholarship, Thank you, Re-engage | D15: Ngày 3 | E15: ☐
A16: 5 | B16: Segment followers | C16: By campus, cấp, trạng thái lead | Auto-tag từ GHL | D16: Ngày 3 | E16: ☐
A17: 6 | B17: Lịch broadcast tuần | C17: Thứ 3: Tour invite | Thứ 6: Ưu đãi/content | Trước webinar: Reminder | D17: Tuần 1 | E17: ☐
A18: 7 | B18: Cài Zalo Pixel qua GTM | C18: Custom HTML tag trong GTM | Events: PageView, Lead, Form | D18: Ngày 2 | E18: ☐
A20: C. CHIẾN LƯỢC CONTENT ZALO OA – 8 MẪU BROADCAST
A21: # | B21: Template Name | C21: Mục đích | D21: Nội dung mẫu | E21: CTA | F21: Segment gửi | G21: Tần suất | H21: GHL Trigger | I21: KPI
A22: 1 | B22: Welcome Message | C22: Chào đón lead mới | D22: Chào [Tên]! Cảm ơn bạn quan tâm Trường Việt Anh. Chúng tôi có MN, TH, THCS, THPT tại 8 cơ sở. Nhấn menu để tìm hiểu thêm! | E22: Chọn cấp học quan tâm | F22: New OA follower | G22: Auto (khi follow) | H22: New contact → Welcome seq | I22: Reply rate ≥ 30%
A23: 2 | B23: Tour Invitation | C23: Mời tham quan trường | D23: [Tên] ơi, cuối tuần này Việt Anh mở cửa đón PH tham quan. Cơ sở [Campus]: [Địa chỉ]. Đăng ký tour tại đây! | E23: Đăng ký tour ngay | F23: Lead chưa book tour | G23: 2 lần/tuần (T3, T6) | H23: Lead > 48h no tour | I23: Tour booked rate ≥ 8%
A24: 3 | B24: Tour Reminder | C24: Nhắc lịch tour | D24: [Tên] ơi, lịch tham quan trường của bạn vào [Ngày] lúc [Giờ] tại [Campus]. Chúng tôi rất mong gặp bạn! | E24: Xác nhận tham dự | F24: Lead đã book tour | G24: Auto (48h + 2h trước) | H24: Tour booked trigger | I24: Show-up rate ≥ 70%
A25: 4 | B25: Ưu đãi tuyển sinh | C25: Push ưu đãi/học bổng | D25: Tin vui! Việt Anh dành ưu đãi [%] cho hồ sơ nộp trước [Deadline]. Áp dụng [Cấp]. Liên hệ ngay! | E25: Nhận ưu đãi ngay | F25: Lead qualified chưa enroll | G25: 1-2 lần/tháng | H25: Manual schedule | I25: CTR ≥ 5%
A26: 5 | B26: Webinar Invitation | C26: Mời dự hội thảo online | D26: Hội thảo "[Tên WB]" – [Ngày] lúc [Giờ]. Chủ đề: [Topic]. Đăng ký miễn phí ngay! | E26: Đăng ký webinar | F26: Lead theo cấp phù hợp | G26: Trước WB 7 ngày + 2 ngày | H26: Manual + GHL | I26: Reg rate ≥ 5%
A27: 6 | B27: Scholarship Alert | C27: Thông báo học bổng | D27: Chương trình học bổng [Cấp] 2026 đã mở đăng ký! Giá trị đến [X]%. Deadline: [Ngày]. Đăng ký thi ngay! | E27: Đăng ký thi HB | F27: THCS/THPT leads | G27: 1 lần/tháng | H27: Manual | I27: Reg rate ≥ 8%
A28: 7 | B28: Thank You / Post-tour | C28: Cảm ơn sau tour | D28: Cảm ơn [Tên] đã đến tham quan Việt Anh! Hy vọng bạn ấn tượng. Nếu cần thêm thông tin, nhắn ngay cho chúng tôi. | E28: Nộp hồ sơ ngay | F28: Lead đã tour | G28: Auto (2h sau tour) | H28: Tour completed trigger | I28: Reply rate ≥ 20%
A29: 8 | B29: Re-engage / Win-back | C29: Kích hoạt lại lead cũ | D29: [Tên] ơi, Việt Anh vẫn còn chỗ cho [Cấp]. Ưu đãi đặc biệt cho PH quay lại. Hẹn gặp bạn tuần này! | E29: Đặt lịch lại | F29: Lead lost > 30 ngày | G29: 1 lần/tháng | H29: Lost 30d trigger | I29: Reactivation ≥ 3%
A32: D. LỊCH BROADCAST ZALO OA HÀNG TUẦN
A33: Ngày | B33: Giờ gửi | C33: Template | D33: Segment | E33: Nội dung tóm tắt | F33: KPI | G33: Ghi chú
A34: Thứ 3 | B34: 10:00 | C34: Tour Invitation | D34: Lead chưa tour + campus tương ứng | E34: Mời tour cuối tuần | Cơ sở phù hợp | F34: Open ≥ 40%, CTR ≥ 5% | G34: Segment theo campus, cấp
A35: Thứ 5 | B35: 14:00 | C35: Ưu đãi / Webinar | D35: Tất cả lead active | E35: Ưu đãi tuần hoặc reminder webinar | F35: Open ≥ 35%, CTR ≥ 4% | G35: Tuần có WB → WB invite
A36: Thứ 6 | B36: 09:00 | C36: Tour Reminder | D36: Lead đã book tour T7/CN | E36: Nhắc tour cuối tuần + địa chỉ + parking | F36: Open ≥ 60% | G36: Auto từ GHL
A37: Thứ 7 | B37: 08:00 | C37: Tour Reminder 2h | D37: Lead tour hôm nay | E37: Nhắc tour sáng nay + SĐT liên hệ | F37: Open ≥ 70% | G37: Auto từ GHL
A38: Cuối tháng | B38: 10:00 | C38: Scholarship / Deadline | D38: Lead qualified THCS/THPT | E38: Deadline ưu đãi, học bổng sắp hết | F38: CTR ≥ 6% | G38: 1 lần/tháng
A39: Đầu tháng | B39: 10:00 | C39: Re-engage | D39: Lost leads > 30 ngày | E39: Win-back message + ưu đãi quay lại | F39: Reactivation ≥ 3% | G39: Monthly, manual approval
A42: E. ZALO ADS – CHI TIẾT AUDIENCE & CREATIVE THEO CHIẾN DỊCH
A43: Campaign | B43: Audience Size est. | C43: Detailed Targeting | D43: Placement | E43: Creative Type | F43: Số lượng creative | G43: A/B Test | H43: Daily Budget | I43: Optimization Goal | J43: Tracking
A44: Zalo_MN_Local | B44: 150,000-300,000 | C44: Geo: Gò Vấp 5km + Cần Giuộc + Rạch Giá | Age 25-40 | Female 85% | Interest: Parenting, Baby, Preschool | D44: Zalo Feed + Article | E44: Image card + Short text | F44: 5 image + 3 article | G44: Test 2 headline, 2 image | H44: =0.07*8500000000*0.35/6/30 -> 1156944.4 | I44: Click to OA / Lead form | J44: Zalo Pixel + UTM → GA4
A45: Zalo_TH_Local | B45: 200,000-400,000 | C45: Geo: Gò Vấp + Bình Tân + Tỉnh | Age 28-45 | Parents | Interest: Education, School | D45: Zalo Feed + Article | E45: Image card + Carousel | F45: 4 image + 2 carousel | G45: Test headline + CTA | H45: =0.07*8500000000*0.25/6/30 -> 826388.89 | I45: Click to OA / Lead form | J45: Zalo Pixel + UTM → GA4
A46: Zalo_THCS_THPT | B46: 300,000-500,000 | C46: Geo: TP.HCM rộng | Age 30-55 | Interest: Education, University prep, Scholarship | D46: Zalo Feed + Article + Banner | E46: Image + Video teaser 15s | F46: 4 image + 2 video + 2 article | G46: Test video vs image | H46: =0.07*8500000000*0.2/6/30 -> 661111.11 | I46: Lead form / Webinar reg | J46: Zalo Pixel + UTM → GA4
A47: Zalo_Remarketing | B47: 50,000-100,000 | C47: OA followers + Website pixel visitors | All ages | Exclude enrolled | D47: Zalo Feed + Push notification | E47: Countdown + Ưu đãi + Tour reminder | F47: 3 countdown + 2 offer | G47: Test urgency vs benefit | H47: =0.07*8500000000*0.2/6/30 -> 661111.11 | I47: Conversion / Tour booked | J47: Zalo Pixel + GHL sync
A50: F. ZALO OA AUTO-REPLY MENU CHI TIẾT
A51: Menu Level 1 | B51: Menu Level 2 | C51: Auto-reply Content | D51: GHL Action | E51: Next Step
A52: 📚 Tư vấn Mầm non | B52: - | C52: Cảm ơn bạn! MN Việt Anh có 4 cơ sở: GV, Nhân Lễ, Thái Sơn, Mekong Xanh. Bạn muốn tìm hiểu cơ sở nào? | D52: Tag: grade_mn + Assign sales | E52: Chọn cơ sở → Info + Book tour
A53: 📖 Tư vấn Tiểu học | B53: - | C53: TH Việt Anh có tại: Gò Vấp, Bình Tân, Thái Sơn, Mekong Xanh. Song ngữ từ lớp 1. Bạn quan tâm cơ sở nào? | D53: Tag: grade_th + Assign sales | E53: Chọn cơ sở → Info + Book tour
A54: 🎓 Tư vấn THCS | B54: - | C54: THCS Việt Anh tại Gò Vấp. Lộ trình 6→12 liên cấp, GV chủ nhiệm theo sát. Để lại SĐT để được tư vấn chi tiết! | D54: Tag: grade_thcs + Create contact | E54: Sales gọi lại < 5 phút
A55: 🏫 Tư vấn THPT | B55: - | C55: THPT Việt Anh Gò Vấp. Học bổng đến 100%, đầu ra ĐH top. Để lại SĐT hoặc nhấn "Đăng ký thi học bổng"! | D55: Tag: grade_thpt + Create contact | E55: Sales gọi + Gửi brochure
A56: 💰 Học phí | B56: - | C56: Học phí Việt Anh dao động theo cấp và cơ sở. Nhấn cấp học để xem chi tiết hoặc liên hệ hotline 0916 961 409. | D56: Tag: fee_inquiry + Hot lead | E56: Gửi bảng phí → Book tour
A57: 📅 Đặt lịch Tour | B57: - | C57: Tuyệt vời! Chọn cơ sở và thời gian phù hợp. Chúng tôi sẽ xác nhận ngay! | D57: Create appointment in GHL | E57: Confirm SMS + Zalo 2h trước
A58: 📞 Gọi Hotline | B58: - | C58: Hotline: 0916 961 409 (tất cả cơ sở). Giờ tư vấn: 7:30-17:30 T2-T7, 8:00-12:00 CN. | D58: Log call_intent | E58: Track click_call
A59: 🎯 Hội thảo/Webinar | B59: - | C59: Hội thảo miễn phí sắp tới: [Tên WB] ngày [Date]. Đăng ký ngay! | D59: Tag: webinar_interest | E59: Gửi link đăng ký WB
A62: ZALO ADS CAMPAIGNS THEO PHỄU
A63: Loại Ads | B63: Cấp Học | C63: Tiêu Đề Article | D63: Thumbnail URL | E63: Target Audience | F63: Landing Page | G63: Budget/Tháng | H63: Ghi Chú
A64: Zalo Article Ads | B64: Mầm Non | C64: Tại sao chọn trường Mầm Non Trường Việt Anh? | D64: https://example.com/zalo-MN.jpg | E64: Phụ huynh có con MN, tuổi 3-18, tại Tp.HCM | F64: forms.truongvietanh.com/zalo-mn | G64: 2,000,000 VND | H64: Focus: Mầm Non
A65: Zalo Article Ads | B65: Tiểu Học | C65: Tại sao chọn trường Tiểu Học Trường Việt Anh? | D65: https://example.com/zalo-TH.jpg | E65: Phụ huynh có con TH, tuổi 3-18, tại Tp.HCM | F65: forms.truongvietanh.com/zalo-th | G65: 2,000,000 VND | H65: Focus: Tiểu Học
A66: Zalo Article Ads | B66: THCS | C66: Tại sao chọn trường THCS Trường Việt Anh? | D66: https://example.com/zalo-THCS.jpg | E66: Phụ huynh có con THCS, tuổi 3-18, tại Tp.HCM | F66: forms.truongvietanh.com/zalo-thcs | G66: 2,000,000 VND | H66: Focus: THCS
A67: Zalo Article Ads | B67: THPT | C67: Tại sao chọn trường THPT Trường Việt Anh? | D67: https://example.com/zalo-THPT.jpg | E67: Phụ huynh có con THPT, tuổi 3-18, tại Tp.HCM | F67: forms.truongvietanh.com/zalo-thpt | G67: 2,000,000 VND | H67: Focus: THPT
A68: Zalo OA Message Ads | B68: All | C68: Mở khóa học online miễn phí | D68: https://example.com/webinar.jpg | E68: Phụ huynh toàn quốc | F68: forms.truongvietanh.com/zalo-webinar | G68: 1,500,000 VND | H68: Broadcast template
A69: Zalo Display Ads | B69: Segment 1 | C69: Khám phá môi trường học tập quốc tế | D69: https://example.com/display-1.jpg | E69: Audience segment 1 | F69: forms.truongvietanh.com/zalo-display-1 | G69: 800,000 VND | H69: Week 1
A70: Zalo Display Ads | B70: Segment 2 | C70: Khám phá môi trường học tập quốc tế | D70: https://example.com/display-2.jpg | E70: Audience segment 2 | F70: forms.truongvietanh.com/zalo-display-2 | G70: 800,000 VND | H70: Week 2
A71: Zalo Display Ads | B71: Segment 3 | C71: Khám phá môi trường học tập quốc tế | D71: https://example.com/display-3.jpg | E71: Audience segment 3 | F71: forms.truongvietanh.com/zalo-display-3 | G71: 800,000 VND | H71: Week 3
A72: Zalo Display Ads | B72: Segment 4 | C72: Khám phá môi trường học tập quốc tế | D72: https://example.com/display-4.jpg | E72: Audience segment 4 | F72: forms.truongvietanh.com/zalo-display-4 | G72: 800,000 VND | H72: Week 4
A73: Zalo Display Ads | B73: Segment 5 | C73: Khám phá môi trường học tập quốc tế | D73: https://example.com/display-5.jpg | E73: Audience segment 5 | F73: forms.truongvietanh.com/zalo-display-5 | G73: 800,000 VND | H73: Week 5
A74: Zalo Display Ads | B74: Segment 6 | C74: Khám phá môi trường học tập quốc tế | D74: https://example.com/display-6.jpg | E74: Audience segment 6 | F74: forms.truongvietanh.com/zalo-display-6 | G74: 800,000 VND | H74: Week 6
... A76: Zalo Display Ads | B76: Segment 8 | C76: Khám phá môi trường học tập quốc tế | D76: https://example.com/display-8.jpg | E76: Audience segment 8 | F76: forms.truongvietanh.com/zalo-display-8 | G76: 800,000 VND | H76: Week 8
A78: ZALO OA AUTOMATION WORKFLOWS
A79: Tên Workflow | B79: Trigger | C79: Số Message | D79: Timing | E79: CTA Button | F79: Landing Page | G79: Target KPI | H79: Status
A80: Welcome Follower | B80: User follow OA | C80: 3 | D80: Immediate + 1h + 24h | E80: Xem thêm | F80: forms.truongvietanh.com/zalo-welcome | G80: Engagement 80% | H80: Active
A81: Nurture Sequence | B81: Viewed article | C81: 5 | D81: Day 0,1,2,3,7 | E81: Đăng ký tour | F81: forms.truongvietanh.com/zalo-tour | G81: Tour signup 30% | H81: Active
A82: Tour Reminder | B82: Registered tour | C82: 2 | D82: 7 days, 1 day before | E82: Nhắc nhở | F82: forms.truongvietanh.com/zalo-reminder | G82: Attendance 90% | H82: Active
A83: Post-Tour Follow-up | B83: Tour completed | C83: 3 | D83: Immediate + 24h + 72h | E83: Ghi danh | F83: forms.truongvietanh.com/zalo-enroll | G83: Conversion 25% | H83: Active
A84: Webinar Series | B84: Webinar signup | C84: 4 | D84: Day 1,3,5,7 before | E84: Tham dự | F84: forms.truongvietanh.com/zalo-webinar | G84: Attendance 70% | H84: Active
A85: Scholarship Info | B85: Inquiry received | C85: 2 | D85: Immediate + 48h | E85: Chi tiết HT | F85: forms.truongvietanh.com/zalo-scholarship | G85: Inquiry->Lead 40% | H85: Active
A86: Re-engagement | B86: No action 14 days | C86: 2 | D86: Day 14, 21 | E86: Quay lại | F86: forms.truongvietanh.com/zalo-comeback | G86: Re-engagement 15% | H86: Paused
A87: Birthday Message | B87: Birthday date | C87: 1 | D87: Birthday morning | E87: Quà tặng | F87: forms.truongvietanh.com/zalo-birthday | G87: Open rate 50% | H87: Active
A88: Referral Program | B88: Made referral | C88: 3 | D88: Immediate + 7d + 30d | E88: Giới thiệu | F88: forms.truongvietanh.com/zalo-refer | G88: Referral conversion 20% | H88: Active
A89: Khai Giảng Alert | B89: User inactive | C89: 2 | D89: Week before khai giảng | E89: Nộp hồ sơ | F89: forms.truongvietanh.com/zalo-enroll | G89: Last-minute signup 10% | H89: Active

Sheet 14. Weekly Battleplan
A1: KẾ HOẠCH TÁC CHIẾN TUẦN 1-28 (03-09/2026)
A2: Tuần | B2: Ngày | C2: Giai đoạn | D2: Mục tiêu tuần | E2: Marketing Action | F2: Sales Action | G2: Campus Action | H2: Trạng thái
A3: 1 | B3: 26/03-01/04 | C3: Setup | D3: Dựng nền tảng | E3: Setup GTM+Pixel+GHL+Birch+LP | F3: Chốt SLA+script+CRM tags | G3: Hotline+GMB+Tour slots | H3: ☐
A4: 2 | B4: 02-08/04 | C4: Setup | D4: Chuẩn hóa LP+Forms | E4: Test LP 6 cơ sở + Forms → GHL | F4: Test nhận lead+gọi lại | G4: Chụp ảnh+video bổ sung | H4: ☐
A5: 3 | B5: 09-15/04 | C5: Pilot | D5: Pilot campaign đợt 1 | E5: Bật Brand+Generic+HighIntent | 2 RSA/adgroup | F5: Gọi 100% lead <5 phút | G5: Tour slots ít nhất 2/tuần | H5: ☐
A6: 4 | B6: 16-22/04 | C6: Pilot | D6: Đánh giá pilot | E6: Rà search terms+pause yếu+keep tốt | F6: QA 20 cuộc gọi đầu | G6: Đánh giá 5 tour đầu | H6: ☐
A7: 5 | B7: 23-29/04 | C7: Scale 1 | D7: Scale sau pilot | E7: Tăng budget campaigns thắng+mở thêm cơ sở | F7: 4 touchpoints/lead 3 ngày | G7: Open campus cuối tuần | H7: ☐
A8: 6 | B8: 30/04-06/05 | C8: Scale 1 | D8: Mở webinar | E8: LP webinar THCS+THPT+Search webinar ads | F8: Script gọi webinar lead | G8: Diễn giả+slide+CTA | H8: ☐
A9: 7 | B9: 07-13/05 | C9: Scale 1 | D9: Tối ưu quality | E9: Tách HI/webinar/brand+bidding optimize | F9: Rà Lead→Tour by counselor | G9: Show-up rate report | H9: ☐
A10: 8 | B10: 14-20/05 | C10: Scale 1 | D10: Mở competitor | E10: Competitor THCS+THPT GV+LP compare | F10: Script xử lý so sánh | G10: Bảng so sánh mềm | H10: ☐
A11: 9 | B11: 21-27/05 | C11: Scale 1 | D11: Khóa baseline T4-5 | E11: Tổng hợp CPL/campus/quality | Plan T6 | F11: Top 5 lost reasons | G11: Best practice tour | H11: ☐
A12: 10 | B12: 28/05-03/06 | C12: Scale 2 | D12: Scale mạnh T6 | E12: Tăng NS THCS+THPT GV+brand defense | F12: Ưu tiên lead Google | G12: Tăng tour slots | H12: ☐
A13: 11 | B13: 04-10/06 | C13: Scale 2 | D13: YouTube+DG | E13: Video testi THCS/THPT+YouTube retarget | F13: Tag video-engaged lead | G13: Quay thêm testimonial | H13: ☐
A14: 12 | B14: 11-17/06 | C14: Scale 2 | D14: Test PMax | E14: PMax test 2% | Track riêng | F14: Source PMax riêng | G14: Giữ nguyên quy trình | H14: ☐
... A30: 28 | B30: 29-30/09 | C30: Close | D30: Đóng mùa | E30: Tổng kết: spend/leads/tours/enrollments/CAC | Playbook | F30: Tổng kết per counselor | Lost reasons | G30: Tổng kết tour+testimonial mới | H30: ☐
A33: BATTLEPLAN MẪU — TUẦN PEAK (T6/2026)
A34: Ngày | B34: Giờ | C34: Task | D34: Người Phụ Trách | E34: Kênh | F34: Mục Tiêu | G34: Output/KPI
A35: Thứ 2 | B35: 08:00 | C35: Weekly kickoff + Ads performance review | D35: Marketing Lead | E35: Team meeting | F35: Review ROI từ tuần trước | G35: Action items list
A36: Thứ 2 | B36: 10:00 | C36: Content calendar planning + Design briefing | D36: Content Manager + Designer | E36: Internal | F36: Lên kế hoạch content tuần | G36: 7 content pieces planned
A37: Thứ 2 | B37: 14:00 | C37: Ads optimization + Budget allocation | D37: PPC Specialist | E37: All ads channels | F37: Tối ưu ROAS | G37: Budget split confirmed
A38: Thứ 3 | B38: 08:30 | C38: Video production: Student testimonials | D38: Video Producer | E38: TikTok + Instagram | F38: 3 video assets | G38: 3 videos edited
A39: Thứ 3 | B39: 13:00 | C39: Livestream: Campus tour showcase | D39: Social Media Manager | E39: Facebook Live + Instagram Live | F39: 500+ live viewers | G39: Engagement rate 8%+
A40: Thứ 3 | B40: 16:00 | C40: Email campaign: Enrollment reminder | D40: Email Specialist | E40: Email marketing | F40: Send to 10k leads | G40: Open rate 35%+
A41: Thứ 4 | B41: 08:00 | C41: Midweek performance check-in | D41: Analytics Manager | E41: All channels | F41: Verify KPI progress | G41: Dashboard updated
A42: Thứ 4 | B42: 10:00 | C42: New creative development | D42: Designer + Copywriter | E42: Ads creative | F42: 5 new ad creatives | G42: A/B test ready
A43: Thứ 4 | B43: 15:00 | C43: Zalo OA: Nurture broadcast | D43: Zalo Specialist | E43: Zalo OA | F43: Send to 5k followers | G43: Click rate 12%+
A44: Thứ 5 | B44: 09:00 | C44: Community engagement: Comments & DMs | D44: Social Media Manager | E44: Facebook + Instagram + Zalo | F44: 100% response rate | G44: Reply time <1hr
A45: Thứ 5 | B45: 14:00 | C45: Webinar preparation: Tech & content check | D45: Webinar Manager | E45: Zoom/GoToWebinar | F45: Ready for Friday webinar | G45: Dry-run completed
... A52: Chủ Nhật | B52: 14:00 | C52: Content prep: Design & copy review | D52: Designer + Copywriter | E52: Internal | F52: Ready for Monday posting | G52: 20 content pieces ready

Sheet A. KPI Weekly Tracker
B1: 📈 KPI WEEKLY TRACKER – 3 ĐỘI (Marketing | Tuyển Sinh | Ban Cơ Sở)
B2: Hướng dẫn: Nhập dữ liệu thực tế vào cột "Thực tế" mỗi tuần. Cột "Vs Target" tự tính. Tô màu xanh=đạt, vàng=cần theo dõi, đỏ=cần can thiệp.
B3: KPI / Chỉ số | C3: Tuần 1 26/03 | D3: Tuần 2 02/04 | E3: Tuần 3 09/04 | F3: Tuần 4 16/04 | G3: Tuần 5 23/04 | H3: Tuần 6 30/04 | I3: MTD Tích lũy | J3: Target | K3: Vs Target | L3: % đạt | M3: Cảnh báo
B4: 🎯 MARKETING – GOOGLE ADS
B5: Spend Google (đ) | C5: 0 | D5: 0 | E5: 0 | F5: 0 | G5: 0 | H5: 0 | I5: =SUM(C5:H5) -> 0 | J5: 0 | K5: =IF(J5>0,I5/J5,0) -> 0 | L5: =IF(J5>0,I5/J5,"N/A") -> N/A | M5: -
B6: Impressions | C6: 0 | D6: 0 | E6: 0 | F6: 0 | G6: 0 | H6: 0 | I6: =SUM(C6:H6) -> 0 | J6: 0 | K6: =IF(J6>0,I6/J6,0) -> 0 | L6: =IF(J6>0,I6/J6,"N/A") -> N/A | M6: -
B7: Clicks | C7: 0 | D7: 0 | E7: 0 | F7: 0 | G7: 0 | H7: 0 | I7: =SUM(C7:H7) -> 0 | J7: 0 | K7: =IF(J7>0,I7/J7,0) -> 0 | L7: =IF(J7>0,I7/J7,"N/A") -> N/A | M7: -
B8: CTR (%) | C8: 0 | D8: 0 | E8: 0 | F8: 0 | G8: 0 | H8: 0 | I8: =SUM(C8:H8) -> 0 | J8: 0.06 | K8: =IF(J8>0,I8/J8,0) -> 0 | L8: =IF(J8>0,I8/J8,"N/A") -> 0 | M8: Ngưỡng: 0.05
B9: CPC trung bình (đ) | C9: 0 | D9: 0 | E9: 0 | F9: 0 | G9: 0 | H9: 0 | I9: =SUM(C9:H9) -> 0 | J9: 0 | K9: =IF(J9>0,I9/J9,0) -> 0 | L9: =IF(J9>0,I9/J9,"N/A") -> N/A | M9: -
B10: Leads (Google) | C10: 0 | D10: 0 | E10: 0 | F10: 0 | G10: 0 | H10: 0 | I10: =SUM(C10:H10) -> 0 | J10: 0 | K10: =IF(J10>0,I10/J10,0) -> 0 | L10: =IF(J10>0,I10/J10,"N/A") -> N/A | M10: -
B11: Qualified Leads (Google) | C11: 0 | D11: 0 | E11: 0 | F11: 0 | G11: 0 | H11: 0 | I11: =SUM(C11:H11) -> 0 | J11: 0 | K11: =IF(J11>0,I11/J11,0) -> 0 | L11: =IF(J11>0,I11/J11,"N/A") -> N/A | M11: -
B12: CPL Google (đ) | C12: 0 | D12: 0 | E12: 0 | F12: 0 | G12: 0 | H12: 0 | I12: =SUM(C12:H12) -> 0 | J12: 180000 | K12: =IF(J12>0,I12/J12,0) -> 0 | L12: =IF(J12>0,I12/J12,"N/A") -> 0 | M12: Ngưỡng: 220000
B13: Qualified Rate | C13: 0 | D13: 0 | E13: 0 | F13: 0 | G13: 0 | H13: 0 | I13: =SUM(C13:H13) -> 0 | J13: 0.5 | K13: =IF(J13>0,I13/J13,0) -> 0 | L13: =IF(J13>0,I13/J13,"N/A") -> 0 | M13: Ngưỡng: 0.4
B14: Booked Tours (Google) | C14: 0 | D14: 0 | E14: 0 | F14: 0 | G14: 0 | H14: 0 | I14: =SUM(C14:H14) -> 0 | J14: 0 | K14: =IF(J14>0,I14/J14,0) -> 0 | L14: =IF(J14>0,I14/J14,"N/A") -> N/A | M14: -
B15: Cost / Booked Tour | C15: 0 | D15: 0 | E15: 0 | F15: 0 | G15: 0 | H15: 0 | I15: =SUM(C15:H15) -> 0 | J15: 0 | K15: =IF(J15>0,I15/J15,0) -> 0 | L15: =IF(J15>0,I15/J15,"N/A") -> N/A | M15: -
B17: 🎯 MARKETING – META ADS
B18: Spend Meta (đ) | C18: 0 | D18: 0 | E18: 0 | F18: 0 | G18: 0 | H18: 0 | I18: =SUM(C18:H18) -> 0 | J18: 0 | K18: =IF(J18>0,I18/J18,0) -> 0 | L18: =IF(J18>0,I18/J18,"N/A") -> N/A | M18: -
B19: Reach / Impressions | C19: 0 | D19: 0 | E19: 0 | F19: 0 | G19: 0 | H19: 0 | I19: =SUM(C19:H19) -> 0 | J19: 0 | K19: =IF(J19>0,I19/J19,0) -> 0 | L19: =IF(J19>0,I19/J19,"N/A") -> N/A | M19: -
B20: CPM (đ) | C20: 0 | D20: 0 | E20: 0 | F20: 0 | G20: 0 | H20: 0 | I20: =SUM(C20:H20) -> 0 | J20: 0 | K20: =IF(J20>0,I20/J20,0) -> 0 | L20: =IF(J20>0,I20/J20,"N/A") -> N/A | M20: -
B21: CTR Meta (%) | C21: 0 | D21: 0 | E21: 0 | F21: 0 | G21: 0 | H21: 0 | I21: =SUM(C21:H21) -> 0 | J21: 0.015 | K21: =IF(J21>0,I21/J21,0) -> 0 | L21: =IF(J21>0,I21/J21,"N/A") -> 0 | M21: Ngưỡng: 0.01
B22: Leads (Meta) | C22: 0 | D22: 0 | E22: 0 | F22: 0 | G22: 0 | H22: 0 | I22: =SUM(C22:H22) -> 0 | J22: 0 | K22: =IF(J22>0,I22/J22,0) -> 0 | L22: =IF(J22>0,I22/J22,"N/A") -> N/A | M22: -
B23: CPL Meta (đ) | C23: 0 | D23: 0 | E23: 0 | F23: 0 | G23: 0 | H23: 0 | I23: =SUM(C23:H23) -> 0 | J23: 120000 | K23: =IF(J23>0,I23/J23,0) -> 0 | L23: =IF(J23>0,I23/J23,"N/A") -> 0 | M23: Ngưỡng: 180000
B24: Qualified Rate Meta | C24: 0 | D24: 0 | E24: 0 | F24: 0 | G24: 0 | H24: 0 | I24: =SUM(C24:H24) -> 0 | J24: 0.45 | K24: =IF(J24>0,I24/J24,0) -> 0 | L24: =IF(J24>0,I24/J24,"N/A") -> 0 | M24: Ngưỡng: 0.35
B25: Booked Tours (Meta) | C25: 0 | D25: 0 | E25: 0 | F25: 0 | G25: 0 | H25: 0 | I25: =SUM(C25:H25) -> 0 | J25: 0 | K25: =IF(J25>0,I25/J25,0) -> 0 | L25: =IF(J25>0,I25/J25,"N/A") -> N/A | M25: -
B27: 🎯 MARKETING – TIKTOK / ZALO
B28: Spend TikTok (đ) | C28: 0 | D28: 0 | E28: 0 | F28: 0 | G28: 0 | H28: 0 | I28: =SUM(C28:H28) -> 0 | J28: 0 | K28: =IF(J28>0,I28/J28,0) -> 0 | L28: =IF(J28>0,I28/J28,"N/A") -> N/A | M28: -
B29: Views / CPV | C29: 0 | D29: 0 | E29: 0 | F29: 0 | G29: 0 | H29: 0 | I29: =SUM(C29:H29) -> 0 | J29: 0 | K29: =IF(J29>0,I29/J29,0) -> 0 | L29: =IF(J29>0,I29/J29,"N/A") -> N/A | M29: -
B30: Leads TikTok | C30: 0 | D30: 0 | E30: 0 | F30: 0 | G30: 0 | H30: 0 | I30: =SUM(C30:H30) -> 0 | J30: 0 | K30: =IF(J30>0,I30/J30,0) -> 0 | L30: =IF(J30>0,I30/J30,"N/A") -> N/A | M30: -
B31: CPL TikTok (đ) | C31: 0 | D31: 0 | E31: 0 | F31: 0 | G31: 0 | H31: 0 | I31: =SUM(C31:H31) -> 0 | J31: 90000 | K31: =IF(J31>0,I31/J31,0) -> 0 | L31: =IF(J31>0,I31/J31,"N/A") -> 0 | M31: Ngưỡng: 130000
B32: Spend Zalo (đ) | C32: 0 | D32: 0 | E32: 0 | F32: 0 | G32: 0 | H32: 0 | I32: =SUM(C32:H32) -> 0 | J32: 0 | K32: =IF(J32>0,I32/J32,0) -> 0 | L32: =IF(J32>0,I32/J32,"N/A") -> N/A | M32: -
B33: Leads Zalo | C33: 0 | D33: 0 | E33: 0 | F33: 0 | G33: 0 | H33: 0 | I33: =SUM(C33:H33) -> 0 | J33: 0 | K33: =IF(J33>0,I33/J33,0) -> 0 | L33: =IF(J33>0,I33/J33,"N/A") -> N/A | M33: -
B34: CPL Zalo (đ) | C34: 0 | D34: 0 | E34: 0 | F34: 0 | G34: 0 | H34: 0 | I34: =SUM(C34:H34) -> 0 | J34: 80000 | K34: =IF(J34>0,I34/J34,0) -> 0 | L34: =IF(J34>0,I34/J34,"N/A") -> 0 | M34: Ngưỡng: 120000
B36: 🏃 TUYỂN SINH – PIPELINE
B37: Leads mới (tất cả kênh) | C37: 0 | D37: 0 | E37: 0 | F37: 0 | G37: 0 | H37: 0 | I37: =SUM(C37:H37) -> 0 | J37: 0 | K37: =IF(J37>0,I37/J37,0) -> 0 | L37: =IF(J37>0,I37/J37,"N/A") -> N/A | M37: -
B38: Leads đã gọi | C38: 0 | D38: 0 | E38: 0 | F38: 0 | G38: 0 | H38: 0 | I38: =SUM(C38:H38) -> 0 | J38: 0 | K38: =IF(J38>0,I38/J38,0) -> 0 | L38: =IF(J38>0,I38/J38,"N/A") -> N/A | M38: -
B39: Response < 5 phút (%) | C39: 0 | D39: 0 | E39: 0 | F39: 0 | G39: 0 | H39: 0 | I39: =SUM(C39:H39) -> 0 | J39: 0.85 | K39: =IF(J39>0,I39/J39,0) -> 0 | L39: =IF(J39>0,I39/J39,"N/A") -> 0 | M39: Ngưỡng: 0.7
B40: Tỷ lệ bắt máy (%) | C40: 0 | D40: 0 | E40: 0 | F40: 0 | G40: 0 | H40: 0 | I40: =SUM(C40:H40) -> 0 | J40: 0.45 | K40: =IF(J40>0,I40/J40,0) -> 0 | L40: =IF(J40>0,I40/J40,"N/A") -> 0 | M40: Ngưỡng: 0.35
B41: Lịch tour đặt (Booked) | C41: 0 | D41: 0 | E41: 0 | F41: 0 | G41: 0 | H41: 0 | I41: =SUM(C41:H41) -> 0 | J41: 0 | K41: =IF(J41>0,I41/J41,0) -> 0 | L41: =IF(J41>0,I41/J41,"N/A") -> N/A | M41: -
B42: Lead → Tour rate (%) | C42: 0 | D42: 0 | E42: 0 | F42: 0 | G42: 0 | H42: 0 | I42: =SUM(C42:H42) -> 0 | J42: 0.3 | K42: =IF(J42>0,I42/J42,0) -> 0 | L42: =IF(J42>0,I42/J42,"N/A") -> 0 | M42: Ngưỡng: 0.2
B43: Tour Attended (Show-up) | C43: 0 | D43: 0 | E43: 0 | F43: 0 | G43: 0 | H43: 0 | I43: =SUM(C43:H43) -> 0 | J43: 0 | K43: =IF(J43>0,I43/J43,0) -> 0 | L43: =IF(J43>0,I43/J43,"N/A") -> N/A | M43: -
B44: Show-up rate (%) | C44: 0 | D44: 0 | E44: 0 | F44: 0 | G44: 0 | H44: 0 | I44: =SUM(C44:H44) -> 0 | J44: 0.65 | K44: =IF(J44>0,I44/J44,0) -> 0 | L44: =IF(J44>0,I44/J44,"N/A") -> 0 | M44: Ngưỡng: 0.5
B45: Hồ sơ / Đăng ký | C45: 0 | D45: 0 | E45: 0 | F45: 0 | G45: 0 | H45: 0 | I45: =SUM(C45:H45) -> 0 | J45: 0 | K45: =IF(J45>0,I45/J45,0) -> 0 | L45: =IF(J45>0,I45/J45,"N/A") -> N/A | M45: -
B46: Deposits / Đặt cọc | C46: 0 | D46: 0 | E46: 0 | F46: 0 | G46: 0 | H46: 0 | I46: =SUM(C46:H46) -> 0 | J46: 0 | K46: =IF(J46>0,I46/J46,0) -> 0 | L46: =IF(J46>0,I46/J46,"N/A") -> N/A | M46: -
B47: Nhập học (Enrollment) | C47: 0 | D47: 0 | E47: 0 | F47: 0 | G47: 0 | H47: 0 | I47: =SUM(C47:H47) -> 0 | J47: 0 | K47: =IF(J47>0,I47/J47,0) -> 0 | L47: =IF(J47>0,I47/J47,"N/A") -> N/A | M47: -
B48: Tour → Enroll rate (%) | C48: 0 | D48: 0 | E48: 0 | F48: 0 | G48: 0 | H48: 0 | I48: =SUM(C48:H48) -> 0 | J48: 0.35 | K48: =IF(J48>0,I48/J48,0) -> 0 | L48: =IF(J48>0,I48/J48,"N/A") -> 0 | M48: Ngưỡng: 0.25
B50: 🏫 BAN CƠ SỞ – CAMPUS OPS
B51: Hotline uptime (%) | C51: 0 | D51: 0 | E51: 0 | F51: 0 | G51: 0 | H51: 0 | I51: =SUM(C51:H51) -> 0 | J51: 1 | K51: =IF(J51>0,I51/J51,0) -> 0 | L51: =IF(J51>0,I51/J51,"N/A") -> 0 | M51: Ngưỡng: 0.95
B52: GMB views | C52: 0 | D52: 0 | E52: 0 | F52: 0 | G52: 0 | H52: 0 | I52: =SUM(C52:H52) -> 0 | J52: 0 | K52: =IF(J52>0,I52/J52,0) -> 0 | L52: =IF(J52>0,I52/J52,"N/A") -> N/A | M52: -
B53: Tour slots tổng | C53: 0 | D53: 0 | E53: 0 | F53: 0 | G53: 0 | H53: 0 | I53: =SUM(C53:H53) -> 0 | J53: 0 | K53: =IF(J53>0,I53/J53,0) -> 0 | L53: =IF(J53>0,I53/J53,"N/A") -> N/A | M53: -
B54: Tour slots đã book | C54: 0 | D54: 0 | E54: 0 | F54: 0 | G54: 0 | H54: 0 | I54: =SUM(C54:H54) -> 0 | J54: 0 | K54: =IF(J54>0,I54/J54,0) -> 0 | L54: =IF(J54>0,I54/J54,"N/A") -> N/A | M54: -
B55: Slot fill rate (%) | C55: 0 | D55: 0 | E55: 0 | F55: 0 | G55: 0 | H55: 0 | I55: =SUM(C55:H55) -> 0 | J55: 0.7 | K55: =IF(J55>0,I55/J55,0) -> 0 | L55: =IF(J55>0,I55/J55,"N/A") -> 0 | M55: Ngưỡng: 0.5
B56: No-show count | C56: 0 | D56: 0 | E56: 0 | F56: 0 | G56: 0 | H56: 0 | I56: =SUM(C56:H56) -> 0 | J56: 0 | K56: =IF(J56>0,I56/J56,0) -> 0 | L56: =IF(J56>0,I56/J56,"N/A") -> N/A | M56: -
B57: Ảnh/video mới upload | C57: 0 | D57: 0 | E57: 0 | F57: 0 | G57: 0 | H57: 0 | I57: =SUM(C57:H57) -> 0 | J57: 0 | K57: =IF(J57>0,I57/J57,0) -> 0 | L57: =IF(J57>0,I57/J57,"N/A") -> N/A | M57: -

Sheet B. Todo Daily
B1: 📋 TODO LIST HÀNG NGÀY – MARKETING + TUYỂN SINH + CƠ SỞ
B2: Dùng mỗi ngày. Đánh dấu ✅ khi hoàn thành. Ghi chú vào cột Notes. Link đến Campaign Tracker để track số liệu.
B3: STT | C3: Kênh/Đội | D3: Công việc | E3: Chi tiết hành động | F3: Thời gian | G3: Ai làm | H3: Trạng thái | I3: Ghi chú
B4: ── BUỔI SÁNG (8:00–10:00) ──
B5: 2 | C5: Google Ads | D5: Check pacing & spend | E5: Login Birch → check daily pacing | Alert overspend >110% → giảm ngay | F5: 8:00 | G5: Performance Marketer | H5: ☐
B6: 3 | C6: Google Ads | D6: Rà search terms | E6: Xem search terms mới → Thêm negative nếu sai intent | Min 2 lần/tuần | F6: 8:15 | G6: Performance Marketer | H6: ☐
B7: 4 | C7: Meta Ads | D7: Check CPL & CPM | E7: Ads Manager → filter 3-day window | CPL >120k → review ad set | F7: 8:20 | G7: Performance Marketer | H7: ☐
B8: 5 | C8: Meta Ads | D8: Kiểm tra ad delivery | E8: Ad set nào learning phase? Nào đang scale? Nào bị từ chối? | F8: 8:30 | G8: Performance Marketer | H8: ☐
B9: 6 | C9: TikTok | D9: Check CPV và engagement | E9: TikTok Ads Manager → CPV, CTR, likes | Video nào dưới 3s quit rate cao? | F9: 8:40 | G9: Content + Perf. | H9: ☐
B10: 7 | C10: Zalo OA | D10: Kiểm tra broadcast | E10: Xem open rate, click | Gửi broadcast mới nếu có plan | F10: 8:50 | G10: CRM Executive | H10: ☐
B11: 8 | C11: GHL / CRM | D11: Review lead mới đêm qua | E11: GHL → All leads → Filter "Created yesterday" | Check source, stage | F11: 9:00 | G11: Sales Lead | H11: ☐
B12: 9 | C12: GHL / CRM | D12: Gọi lead chưa liên lạc | E12: Gọi tất cả lead >12h chưa gọi | Log trong CRM | F12: 9:10 | G12: Tư vấn viên | H12: ☐
B13: ── BUỔI TRƯA (12:00–13:00) ──
B14: 11 | C14: GHL / CRM | D14: Follow-up booked tour | E14: Nhắn Zalo/gọi lead có tour hôm nay/ngày mai | Xác nhận show-up | F14: 12:00 | G14: Tư vấn viên | H14: ☐
B15: 12 | C15: Google Ads | D15: Check Quality Score | E15: Review keyword QS thấp (<5) → cải thiện ad/LP | F15: 12:20 | G15: Performance Marketer | H15: ☐
B16: 13 | C16: Campus | D16: Chuẩn bị tour chiều | E16: Kiểm tra phòng tư vấn, tài liệu, bảng hiệu | Campus lead xác nhận | F16: 12:30 | G16: Campus Manager | H16: ☐
B17: ── BUỔI CHIỀU (14:00–17:00) ──
B18: 15 | C18: GHL / CRM | D18: Xử lý lead pipeline | E18: Review pipeline từng stage | Identify stuck leads | Update notes | F18: 14:00 | G18: Tư vấn viên | H18: ☐
B19: 16 | C19: Meta Ads | D19: Check top/bottom ad sets | E19: Identify top 3 performers → +15-20% budget | Bottom 2 → pause/fix | F19: 14:30 | G19: Performance Marketer | H19: ☐
B20: 17 | C20: Content | D20: Upload/boost nội dung | E20: Post Story, Reel, TikTok mới | Boost post organic nếu engaging | F20: 15:00 | G20: Content Creator | H20: ☐
B21: 18 | C21: Campus | D21: Tiến hành tour | E21: Đón phụ huynh, tư vấn, giới thiệu campus | Log feedback sau tour | F21: 15:00 | G21: Campus Manager | H21: ☐
B22: 19 | C22: GHL / CRM | D22: Post-tour follow-up | E22: Gọi/nhắn phụ huynh đã tour ngày hôm nay trong 2h | Note CRM | F22: 17:00 | G22: Tư vấn viên | H22: ☐
B23: ── CUỐI NGÀY (17:00–18:00) ──
B24: 21 | C24: Reporting | D24: Điền Daily Metrics | E24: Điền số vào A. KPI Weekly Tracker: leads, spend, tours, enrolls | F24: 17:00 | G24: Performance Marketer | H24: ☐
B25: 22 | C25: Google Ads | D25: Set bid adjustment nếu cần | E25: Device, location, time-of-day bid adj | Chạy cao hơn 9-11am, 7-9pm | F25: 17:15 | G25: Performance Marketer | H25: ☐
B26: 23 | C26: GHL | D26: Tag và phân loại leads cuối ngày | E26: GHL → Today leads → Verify tags đúng: source, campus, grade, intent | F26: 17:30 | G26: CRM Executive | H26: ☐
B27: 24 | C27: Reporting | D27: Báo cáo nhanh cho team | E27: Gửi Slack/Zalo: tổng leads hôm nay, tours, enrolls, anomaly | F27: 17:45 | G27: Marketing Lead | H27: ☐
B28: 25 | C28: Campus | D28: Cập nhật lead feedback | E28: Log tour feedback, câu hỏi PH, lý do chưa chốt vào CRM/sheet | F28: 17:50 | G28: Campus Manager | H28: ☐
A31: ═══ DANH SÁCH CÔNG VIỆC HÀNG NGÀY CỰC KỲ CHI TIẾT — TẤT CẢ KÊNH ═══
A33: A. CHECKLIST BUỔI SÁNG (7:00-8:30)
A34: STT | B34: Thời gian | C34: Kênh/Công cụ | D34: Công việc cụ thể | E34: Chi tiết thực hiện | F34: Người thực hiện | G34: Output | H34: Checklist hoàn thành | I34: Ưu tiên
A35: 1 | B35: 7:00-7:15 | C35: GHL + Pancake | D35: Check leads đêm qua | E35: Login GHL → Dashboard → New contacts (overnight). Login Pancake → Unread inbox. Ghi nhận số leads mới | F35: Marketing Lead | G35: Số leads mới, cần assign | H35: ☐ Check GHL ☐ Check Pancake ☐ Ghi log | I35: CAO
A36: 2 | B36: 7:15-7:30 | C36: GHL | D36: Assign leads chưa được phân | E36: GHL → Contacts → Unassigned → Assign theo cơ sở → Trigger welcome workflow | F36: Marketing Lead | G36: Tất cả leads đã assigned | H36: ☐ Assigned ☐ Workflow triggered | I36: CAO
A37: 3 | B37: 7:30-7:45 | C37: Facebook | D37: Check & reply comments overnight | E37: FB Pages (6) → Notifications → Reply comments, ẩn spam, chuyển lead inbox. Pancake → Unread → Reply | F37: Community Mgr | G37: Comments replied, leads captured | H37: ☐ All pages checked ☐ Spam removed | I37: CAO
A38: 4 | B38: 7:45-8:00 | C38: Zalo OA | D38: Check & reply Zalo messages | E38: Zalo OA Admin → Tin nhắn chưa đọc → Reply. Check chatbot misses → Manual reply. Sync leads to GHL | F38: Zalo Specialist | G38: Messages replied, leads synced | H38: ☐ All messages read ☐ Leads synced | I38: CAO
A39: 5 | B39: 8:00-8:15 | C39: Facebook Page | D39: Đăng bài sáng (hình ảnh/carousel) | E39: Đăng bài đã chuẩn bị hôm trước. 5-10 hình hoạt động HS. Caption + Hashtag + CTA. Tag location | F39: Content Writer | G39: Bài đăng live | H39: ☐ Đăng FB ☐ Check format ☐ Hashtag | I39: CAO
A40: 6 | B40: 8:00-8:15 | C40: Zalo OA | D40: Đăng bài Article Zalo | E40: Đăng article đã chuẩn bị. 300-800 từ, hình ảnh, CTA link form | F40: Content Writer | G40: Article live trên Zalo | H40: ☐ Article published ☐ Link working | I40: CAO
A41: 7 | B41: 8:15-8:30 | C41: Instagram | D41: Đăng bài/Reel IG | E41: Post carousel hoặc Reel. Optimize hashtags (30). Bio link check. Reply DMs | F41: IG Specialist | G41: IG post live, DMs replied | H41: ☐ Post live ☐ Hashtags ☐ DMs | I41: TRUNG BÌNH
A42: 8 | B42: 8:15-8:30 | C42: TikTok | D42: Đăng video TikTok sáng | E42: Upload video đã edit. Trending sound, hashtags, caption. Check analytics video hôm qua | F42: TikTok Creator | G42: TikTok video live | H42: ☐ Video up ☐ Sound ☐ Hashtags | I42: TRUNG BÌNH
A43: 9 | B43: 8:30 | C43: Google Sheets | D43: Cập nhật Morning Report | E43: Ghi số leads mới, messages overnight, engagement hôm trước. Update KPI tracker | F43: Marketing Lead | G43: Morning report complete | H43: ☐ Report updated | I43: CAO
A45: B. CHECKLIST BUỔI TRƯA (11:00-14:00)
A46: STT | B46: Thời gian | C46: Kênh/Công cụ | D46: Công việc cụ thể | E46: Chi tiết thực hiện | F46: Người thực hiện | G46: Output | H46: Checklist hoàn thành | I46: Ưu tiên
A47: 10 | B47: 11:00-11:30 | C47: Facebook | D47: Đăng Reels/Video trưa | E47: Video 30-60s đã edit. Upload trực tiếp (không share link). Trending format, hook 3s đầu | F47: Content Writer | G47: Reels live | H47: ☐ Video upload ☐ Thumbnail ☐ Caption | I47: CAO
A48: 11 | B48: 11:30-12:00 | C48: FB Groups | D48: Đăng bài trong 6 nhóm | E48: Mỗi nhóm 1 bài: hỏi đáp, tips, hoặc share bài Page. Caption riêng cho mỗi nhóm | F48: Community Mgr | G48: 6 bài group | H48: ☐ 6 nhóm đã đăng | I48: TRUNG BÌNH
A49: 12 | B49: 12:00-12:30 | C49: Ads | D49: Check performance ads buổi sáng | E49: Birch → Dashboard → Check CPA, CTR, Spend. Nếu CPA>target → điều chỉnh. GHL → Check ad leads | F49: Ads Specialist | G49: Ads optimized nếu cần | H49: ☐ Birch checked ☐ Adjustments made | I49: CAO
A50: 13 | B50: 12:00-12:30 | C50: YouTube | D50: Upload YouTube Shorts | E50: Upload Shorts đã chuẩn bị (repurpose từ TikTok). Title SEO, Description, Tags | F50: Video Team | G50: Shorts live | H50: ☐ Shorts uploaded ☐ SEO done | I50: TRUNG BÌNH
A51: 14 | B51: 12:30-13:00 | C51: Email | D51: Check email marketing performance | E51: GHL → Email → Check open rates, click rates, bounces. Resend to non-openers nếu cần | F51: Marketing Lead | G51: Email metrics logged | H51: ☐ Metrics checked ☐ Resend if needed | I51: TRUNG BÌNH
A52: 15 | B52: 13:00-13:30 | C52: Pancake CRM | D52: Check tư vấn viên response time | E52: Pancake → Reports → Response time. Nhắc nhở nếu >30 phút. Ghi nhận leads cần follow up | F52: Marketing Lead | G52: Response time report | H52: ☐ Response time OK ☐ Follow ups noted | I52: CAO
A53: 16 | B53: 13:00-14:00 | C53: Content | D53: Chuẩn bị nội dung ngày mai | E53: Viết caption, chọn hình, edit video. Lên lịch sáng/trưa/tối. Chuẩn bị cho FB, Zalo, IG, TikTok, YT | F53: Content Team | G53: Content ngày mai sẵn sàng | H53: ☐ FB ☐ Zalo ☐ IG ☐ TikTok ☐ YT | I53: CAO
A55: C. CHECKLIST BUỔI CHIỀU (14:00-17:00)
A56: STT | B56: Thời gian | C56: Kênh/Công cụ | D56: Công việc cụ thể | E56: Chi tiết thực hiện | F56: Người thực hiện | G56: Output | H56: Checklist hoàn thành | I56: Ưu tiên
A57: 17 | B57: 14:00-14:30 | C57: GHL | D57: Follow up leads hôm qua chưa convert | E57: GHL → Pipeline → Contacted stage >24h → Call/Zalo follow up. Update notes | F57: Tư vấn viên | G57: Leads followed up | H57: ☐ Leads contacted ☐ Notes updated | I57: CAO
A58: 18 | B58: 14:30-15:00 | C58: Video | D58: Quay/edit video cho TikTok + Reels ngày mai | E58: Quay cảnh HS hoạt động, GV giảng bài. Edit: CapCut 30-60s. Add text overlay, music | F58: Video Team | G58: 2-3 video ready | H58: ☐ Quay xong ☐ Edit xong ☐ Save | I58: TRUNG BÌNH
A59: 19 | B59: 15:00-15:30 | C59: Facebook | D59: Engage & Reply tất cả comments/inbox mới | E59: Check 6 Pages + 6 Groups → Reply comments → Chuyển lead inbox → Update Pancake | F59: Community Mgr | G59: All engaged | H59: ☐ Pages ☐ Groups ☐ Leads captured | I59: CAO
A60: 20 | B60: 15:00-15:30 | C60: Zalo | D60: Follow up Zalo messages + Broadcast (nếu có) | E60: Check tin nhắn mới → Reply → Nếu T3/T6: gửi broadcast theo segment | F60: Zalo Specialist | G60: Zalo up-to-date | H60: ☐ Messages ☐ Broadcast (if applicable) | I60: CAO
A61: 21 | B61: 15:30-16:00 | C61: Ads | D61: Optimize ads chiều | E61: Birch → Check afternoon performance. Adjust bids, budgets. Pause underperforming ads. Scale winners | F61: Ads Specialist | G61: Ads optimized | H61: ☐ Check performance ☐ Adjustments | I61: CAO
A62: 22 | B62: 16:00-16:30 | C62: GHL + Pancake | D62: Đồng bộ data kiểm tra | E62: Check Make.com → Scenario logs → Errors. Verify GHL contacts = Pancake contacts. Fix discrepancies | F62: IT Admin | G62: Data synced | H62: ☐ Make.com logs ☐ Sync verified | I62: TRUNG BÌNH
A63: 23 | B63: 16:30-17:00 | C63: Google Sheets | D63: Cập nhật KPI tracker hàng ngày | E63: Ghi nhận: leads, tours booked, cost, engagement, followers gained. Update all channels | F63: Marketing Lead | G63: Daily KPI updated | H63: ☐ All KPIs logged | I63: CAO
A65: D. CHECKLIST BUỔI TỐI (19:00-21:00)
A66: STT | B66: Thời gian | C66: Kênh/Công cụ | D66: Công việc cụ thể | E66: Chi tiết thực hiện | F66: Người thực hiện | G66: Output | H66: Checklist hoàn thành | I66: Ưu tiên
A67: 24 | B67: 19:00-19:30 | C67: Facebook | D67: Đăng bài tối (tips/chia sẻ giá trị) | E67: Bài viết dài 200-500 từ: tips nuôi con, chuẩn bị vào trường, review chương trình | F67: Content Writer | G67: Bài tối live | H67: ☐ Bài đăng ☐ Engagement monitor | I67: TRUNG BÌNH
A68: 25 | B68: 19:30-20:00 | C68: TikTok | D68: Đăng video TikTok tối | E68: Video trending/challenge. Thời điểm engagement cao nhất TikTok VN | F68: TikTok Creator | G68: TikTok video live | H68: ☐ Video posted | I68: TRUNG BÌNH
A69: 26 | B69: 20:00-21:00 | C69: Facebook/Zalo | D69: Livestream tư vấn (nếu T3/T5) | E69: Setup live: OBS/StreamYard → FB Page + Zalo Group. Slide + Q&A. Record | F69: GV/Hiệu trưởng | G69: Livestream done | H69: ☐ Live started ☐ Q&A ☐ Recording | I69: CAO (T3/T5)
A70: 27 | B70: 20:00-21:00 | C70: IG Stories | D70: Đăng Stories cuối ngày | E70: Behind the scenes hôm nay, poll cho ngày mai, countdown sự kiện sắp tới | F70: IG Specialist | G70: Stories posted | H70: ☐ 3-5 stories posted | I70: THẤP
A71: 28 | B71: 21:00 | C71: Tổng kết | D71: End-of-day review & Slack update | E71: Tóm tắt ngày: leads, engagement highlights, issues. Post vào Zalo group team | F71: Marketing Lead | G71: EOD report | H71: ☐ Summary sent to team | I71: CAO
A74: CÔNG VIỆC HÀNG NGÀY - CHI TIẾT THEO THÁNG
A76: Tháng 4 (T4) - SETUP
A77: 1 | B77: Cài đặt Google Ads campaigns: Copy templates, setup keyword groups
A78: 2 | B78: Setup Meta Ads: Audience segmentation, pixel tracking kiểm tra
A79: 3 | B79: Tạo landing pages: Form validation, follow-up automation setup
A80: 4 | B80: Cấu hình GHL: Pipelines, automation workflows, email sequences
A81: 5 | B81: Tạo template: Email, SMS, Chatbot flows cho tất cả cấp học
A82: 6 | B82: Kiểm tra UTM tracking: Tất cả channels, document parameters
A83: 7 | B83: Training team: Google Ads, Meta Ads basic, GHL hệ thống
A84: 8 | B84: Set up Zalo OA: Menu, auto-reply, khoa học tin nhắn
A85: 9 | B85: Tạo folder chia sẻ nội dung: Drive, Notion, asset libraries
A86: 10 | B86: Chuẩn bị Open Day: Form, venue setup, staff briefing
A87: 11 | B87: Tạo calendar quảng cáo: Timeline, deadlines, deliverables
A88: 12 | B88: Set up CRM: Contact import, lead score modeling, assignment rules
... A90: 14 | B90: Tạo brand assets folder: Logos, colors, templates, guidelines
A92: Tháng 5 (T5) - LAUNCH & SCALE
A93: 1 | B93: Khởi động Campaign Q1 Meta: 3 campaigns, 10 ad creatives đầu tiên
A94: 2 | B94: Khởi động Campaign Q1 Google: Brand + generic keywords
A95: 3 | B95: Launch Zalo campaign T5: Segment 1000+ contacts, blast message
A96: 4 | B96: Bắt đầu influencer outreach: Liên hệ 5-10 educators, content creators
A97: 5 | B97: Tạo 10 video content: MN tour, teacher intro, student testimonial
A98: 6 | B98: Setup content calendar: 30 posts/tháng, 4 canh, schedule all
A99: 7 | B99: Tạo FAQ document: 50 Q&A phổ biến, update GHL chatbot
A100: 8 | B100: Tuyển dụng consultants: 2-3 BDR, training đầu tiên
A101: 9 | B101: Tạo tracking: Phân biệt source, medium, campaign, content
A102: 10 | B102: Cold email sequence: Draft 3 versions, send to 100 đầu tiên
A103: 11 | B103: Setup Google Analytics: Conversion tracking, goals, audiences
A104: 12 | B104: First webinar planning: Date, speaker, topic, promotion channels
... A106: 14 | B106: Budget tracking setup: Daily spend monitoring, weekly reports
A108: Tháng 6 (T6) - PEAK SEASON
A109: 1 | B109: Scale Meta Ads: 50% budget increase, test 5 new creatives
A110: 2 | B110: Scale Google Ads: Add 20 new keywords, increase bids for converters
A111: 3 | B111: Launch TikTok campaigns: Khởi động với 5 organic seeding ads
A112: 4 | B112: Max content creation: 40 posts, 15 videos, daily stories
A113: 5 | B113: Daily optimization: Check ads CTR/CPC/ROAS, pause underperformers
...

Sheet C. Todo Weekly
B1: 📅 TODO LIST HÀNG TUẦN – MARKETING + TUYỂN SINH + BAN CƠ SỞ (28 TUẦN)
B2: Mỗi tuần họp ngắn Thứ 2 sáng để assign task. Họp review Thứ 6 chiều. Tất cả trạng thái phải cập nhật trước 17:00 Thứ 6.
B3: STT | C3: Đội | D3: Công việc | E3: Chi tiết / Tiêu chí hoàn thành | F3: Kết quả cần có | G3: Deadline | H3: Trạng thái | I3: Notes
B4: ── MARKETING – GOOGLE ADS ──
B5: 1 | C5: Marketing | D5: Review search terms report | E5: Download search terms tuần → Thêm negatives → Update Birch rule | F5: Negative list cập nhật | G5: Thứ 2 | H5: ☐
B6: 2 | C6: Marketing | D6: So sánh CPL theo campaign | E6: Birch → Campaign report → Sort by CPL | Scale top 3, pause bottom 2 | F6: Decision log | G6: Thứ 3 | H6: ☐
B7: 3 | C7: Marketing | D7: Kiểm tra Quality Score | E7: KW QS <5 → Cải thiện ad copy hoặc landing page phù hợp | F7: QS avg ≥7 | G7: Thứ 4 | H7: ☐
B8: 4 | C8: Marketing | D8: Cập nhật Birch automation rules | E8: Review rule performance → Điều chỉnh threshold nếu cần | F8: Rules live | G8: Thứ 4 | H8: ☐
B9: 5 | C9: Marketing | D9: A/B test report Google | E9: 2 RSA test → winner tiếp tục, loser pause | Document kết quả | F9: Test concluded | G9: Thứ 6 | H9: ☐
B10: ── MARKETING – META ADS ──
B11: 6 | C11: Marketing | D11: Creative refresh Meta | E11: Thay ad 7-10 ngày 1 lần | Freq >3 → cần creative mới ngay | F11: New creative live | G11: Thứ 2 | H11: ☐
B12: 7 | C12: Marketing | D12: Audience expansion review | E12: Lookalike tốt → expand 1% → 2% | Interest test mới | F12: Audience updated | G12: Thứ 3 | H12: ☐
B13: 8 | C13: Marketing | D13: Pixel health check | E13: Events Manager → check pixel events, match rate, deduplication | F13: Match rate ≥80% | G13: Thứ 4 | H13: ☐
B14: 9 | C14: Marketing | D14: Budget reallocation Meta | E14: Ad set thắng → +15-20% | Thua → pause hoặc pivot creative | F14: Budget optimized | G14: Thứ 5 | H14: ☐
B15: 10 | C15: Marketing | D15: Retargeting audience update | E15: Refresh audience lists: 7d/21d/60d | Loại lead đã enrolled | F15: Audience fresh | G15: Thứ 5 | H15: ☐
B16: ── MARKETING – TIKTOK / ZALO / WEBINAR ──
B17: 11 | C17: Marketing | D17: TikTok video performance | E17: 3-second retention, completion rate, CTR | Boost video tốt | F17: Top 3 identified | G17: Thứ 3 | H17: ☐
B18: 12 | C18: Marketing | D18: Zalo broadcast lên kế hoạch | E18: Draft nội dung tuần sau | Segment theo campus, grade, stage | F18: Draft approved | G18: Thứ 5 | H18: ☐
B19: 13 | C19: Marketing | D19: Webinar prep (nếu có tuần này) | E19: Landing page live, email sequence, reminder Zalo, test Zoom link | F19: Go/No-go | G19: Thứ 3 | H19: ☐
B20: ── TUYỂN SINH ──
B21: 14 | C21: Tuyển sinh | D21: Weekly pipeline review | E21: GHL → Review tất cả pipeline stages | Xác định stuck leads | F21: Pipeline clean | G21: Thứ 2 | H21: ☐
B22: 15 | C22: Tuyển sinh | D22: QA cuộc gọi ngẫu nhiên | E22: Nghe lại 5-10 cuộc gọi/tuần | Score theo 5 tiêu chí | Coaching | F22: QA report | G22: Thứ 4 | H22: ☐
B23: 16 | C23: Tuyển sinh | D23: Lost lead analysis | E23: Tổng hợp top 5 lý do lost | Cập nhật objection script | F23: Script updated | G23: Thứ 5 | H23: ☐
B24: 17 | C24: Tuyển sinh | D24: Confirm tours tuần sau | E24: Gọi tất cả lead đã booked tour tuần sau | Xác nhận 100% | F24: Confirmation rate | G24: Thứ 6 | H24: ☐
B25: 18 | C25: Tuyển sinh | D25: CRM data hygiene | E25: Xóa/merge duplicate | Verify tags | Update lost reasons | F25: CRM clean | G25: Thứ 6 | H25: ☐
B26: ── BAN CƠ SỞ ──
B27: 19 | C27: Campus | D27: Tour slot management | E27: Update slot availability tuần sau | Thêm slot nếu demand cao | F27: Slots published | G27: Thứ 2 | H27: ☐
B28: 20 | C28: Campus | D28: GMB (Google Business) update | E28: Post 1 bài/tuần | Cập nhật giờ mở cửa | Reply reviews mới | F28: Post live | G28: Thứ 3 | H28: ☐
B29: 21 | C29: Campus | D29: Testimonial collection | E29: Thu thập 1-2 testimonial PH/HS/tuần | Video ngắn hoặc text | F29: 1-2 pieces | G29: Thứ 5 | H29: ☐
B30: 22 | C30: Campus | D30: Hotline health check | E30: Test gọi hotline từng cơ sở | Verify pickup trong 3 ring | F30: 100% pickup | G30: Thứ 6 | H30: ☐
B31: ── REPORTING & REVIEW TUẦN ──
B32: 23 | C32: All | D32: Weekly KPI report | E32: Điền đủ vào A. KPI Weekly Tracker | Share với team | F32: Report sent | G32: Thứ 6 17:00 | H32: ☐
B33: 24 | C33: All | D33: Campaign Tracker update | E33: Điền spend, leads, tours, enrolls vào D. Campaign Tracker | F33: Tracker updated | G33: Thứ 6 17:00 | H33: ☐
B34: 25 | C34: Management | D34: Weekly review meeting | E34: Xem 12 KPI | Q: Scale gì, Pause gì, LP nào yếu, Campus nào cần fix | F34: Decision log | G34: Thứ 6 16:00 | H34: ☐
B35: 26 | C35: All | D35: Todo tuần sau prep | E35: Xem Battleplan tuần tiếp → Assign tasks → Set priorities | F35: Next week ready | G35: Thứ 6 17:30 | H35: ☐
A38: ═══ CÔNG VIỆC HÀNG TUẦN CỰC KỲ CHI TIẾT — THEO NGÀY TRONG TUẦN ═══
A40: THỨ HAI — Kick-off & Planning
A41: STT | B41: Thời gian | C41: Kênh | D41: Công việc | E41: Chi tiết | F41: Output | G41: Người thực hiện
A42: 1 | B42: 8:00-8:30 | C42: Team | D42: Weekly kickoff meeting | E42: Review KPIs tuần trước, goals tuần này, phân công việc. 15 phút standup | F42: Meeting notes, Task list | G42: Marketing Lead
A43: 2 | B43: 8:30-9:30 | C43: Birch + GHL | D43: Review weekly ads performance | E43: Birch → Weekly report. GHL → Pipeline movement. CPA, ROAS, leads by channel. Budget reallocation | F43: Weekly Ads Report | G43: Ads Specialist
A44: 3 | B44: 9:30-10:00 | C44: Make.com | D44: Kiểm tra sync errors tuần qua | E44: Make.com → Execution history → Failed scenarios. Fix errors, re-run if needed | F44: Error log clean | G44: IT Admin
A45: 4 | B45: 10:00-11:00 | C45: Content | D45: Lên content plan tuần | E45: Plan 7 ngày: FB (14 bài), TikTok (10 video), IG (7 posts + stories), YT (3 videos), Zalo (7 articles) | F45: Content calendar tuần | G45: Content Team Lead
A46: 5 | B46: 11:00-12:00 | C46: Pancake | D46: Phân tích lead quality tuần trước | E46: Pancake → Reports → Lead sources, Conversion by source, Response time, Lost reasons | F46: Lead quality report | G46: Marketing Lead
A47: 6 | B47: 14:00-15:00 | C47: GHL | D47: Clean up pipeline | E47: Move stale leads (>14 days no activity) to "Cold". Update tags. Clean duplicate contacts | F47: Pipeline cleaned | G47: Marketing Lead
A48: 7 | B48: 15:00-16:00 | C48: Social Media | D48: Phân tích social media tuần trước | E48: FB Insights, IG Insights, TikTok Analytics, YT Studio → Bài nào tốt nhất, worst. Learnings | F48: SM Weekly Report | G48: Content Team Lead
A49: 8 | B49: 16:00-17:00 | C49: Email | D49: Gửi newsletter tuần | E49: GHL → Email → Newsletter template → Nội dung: recap tuần, upcoming events, tips | F49: Newsletter sent | G49: Content Writer
A51: THỨ BA — Content Production & Livestream
A52: STT | B52: Thời gian | C52: Kênh | D52: Công việc | E52: Chi tiết | F52: Output | G52: Người thực hiện
A53: 9 | B53: 8:00-10:00 | C53: Video | D53: Quay video batch cho tuần | E53: Quay 5-10 clips tại trường: hoạt động, phỏng vấn GV, tour mini. Dùng gimbal + mic | F53: 10 raw clips | G53: Video Team
A54: 10 | B54: 10:00-12:00 | C54: Content | D54: Edit video TikTok + Reels | E54: CapCut: edit 5 videos ngắn (30-60s). Add text, music, transitions. Export 1080x1920 | F54: 5 videos ready | G54: TikTok Creator
A55: 11 | B55: 14:00-15:00 | C55: Facebook | D55: Engage FB Groups | E55: Comment, reply, start discussions trong 6 nhóm. Welcome new members. Remove spam | F55: Groups engaged | G55: Community Mgr
A56: 12 | B56: 15:00-16:00 | C56: Zalo | D56: Gửi Broadcast T3 (nếu có) | E56: Broadcast thông báo/tips/sự kiện. Segment theo cấp học. Track open rate | F56: Broadcast sent | G56: Zalo Specialist
A57: 13 | B57: 20:00-21:00 | C57: FB + Zalo | D57: Livestream tư vấn T3 | E57: Chủ đề tuần: MN→TH→THCS→THPT rotate. Setup OBS, slide, Q&A. Record for YT | F57: Livestream completed | G57: GV + Marketing Lead
A59: THỨ TƯ — Ads Optimization & Midweek Check
A60: STT | B60: Thời gian | C60: Kênh | D60: Công việc | E60: Chi tiết | F60: Output | G60: Người thực hiện
A61: 14 | B61: 8:00-9:00 | C61: Birch | D61: Midweek ads optimization | E61: Birch → Performance → Pause losers, scale winners. A/B test new creatives. Adjust targeting | F61: Ads optimized | G61: Ads Specialist
A62: 15 | B62: 9:00-10:00 | C62: Meta Ads | D62: Tạo/refresh ad creatives | E62: Canva → 3-5 new ad images/videos. Upload to Meta Ads. Split test | F62: New creatives live | G62: Designer + Ads
A63: 16 | B63: 10:00-11:00 | C63: Google Ads | D63: Optimize Google Search campaigns | E63: Search Terms Report → Add negatives, new keywords. Adjust bids. Check Quality Score | F63: Google Ads optimized | G63: Ads Specialist
A64: 17 | B64: 14:00-15:00 | C64: GHL | D64: Review workflows performance | E64: GHL → Workflows → Check email open rates, SMS delivery, step completion. Adjust timing/content | F64: Workflow report | G64: Marketing Lead
A65: 18 | B65: 15:00-16:00 | C65: YouTube | D65: Upload video dài (nếu có) | E65: Upload video tour/tips/phỏng vấn. Full SEO: title, description (500 từ), tags, thumbnail, end screen | F65: YT video live | G65: Video Team
A66: 19 | B66: 16:00-17:00 | C66: Pancake | D66: Midweek lead review | E66: Check lead pipeline. Follow up hot leads. Discuss with tư vấn viên about difficult cases | F66: Leads followed up | G66: Marketing Lead + TVV
A68: THỨ NĂM — Engagement & Livestream #2
A69: STT | B69: Thời gian | C69: Kênh | D69: Công việc | E69: Chi tiết | F69: Output | G69: Người thực hiện
A70: 20 | B70: 8:00-10:00 | C70: Content | D70: Batch write content weekend | E70: Viết 4-6 bài cho T6-CN: FB posts, Zalo articles, IG captions. Chuẩn bị hình ảnh | F70: Weekend content ready | G70: Content Writer
A71: 21 | B71: 10:00-11:00 | C71: Email | D71: Chuẩn bị email broadcast (nếu T5 gửi) | E71: GHL → Email → Create broadcast: tips/event reminder/testimonial. Segment audience | F71: Email ready to send | G71: Content Writer
A72: 22 | B72: 14:00-15:00 | C72: TikTok | D72: TikTok trend research | E72: Check trending sounds, hashtags, challenges. Plan 3-5 trend videos cho tuần tới | F72: Trend plan | G72: TikTok Creator
A73: 23 | B73: 15:00-16:00 | C73: IG | D73: Instagram engagement boost | E73: Reply all DMs, engage with followers, comment on relevant accounts. Story polls | F73: IG engagement done | G73: IG Specialist
A74: 24 | B74: 20:00-21:00 | C74: FB + Zalo | D74: Livestream tư vấn T5 | E74: Chủ đề khác T3. Focus: Q&A PH, giải đáp thắc mắc. Interactive | F74: Livestream completed | G74: GV + Marketing Lead
A76: THỨ SÁU — Optimization & Weekend Prep
A77: STT | B77: Thời gian | C77: Kênh | D77: Công việc | E77: Chi tiết | F77: Output | G77: Người thực hiện
A78: 25 | B78: 8:00-9:00 | C78: All Ads | D78: Friday ads review + weekend adjust | E78: Birch → Reduce/maintain weekend budgets. Schedule weekend campaigns. Check all pixels | F78: Weekend ads ready | G78: Ads Specialist
A79: 26 | B79: 9:00-10:00 | C79: FB Groups | D79: Mini-game/Contest T6 (nếu 2 lần/tháng) | E79: Đăng mini-game trong groups. Like+Share+Comment contest. Quà: voucher/sách | F79: Contest posted | G79: Community Mgr
A80: 27 | B80: 10:00-11:00 | C80: GHL | D80: Pipeline cleanup cuối tuần | E80: Review tất cả leads trong pipeline. Update stages. Ghi notes. Plan follow-up đầu tuần sau | F80: Pipeline updated | G80: Marketing Lead
A81: 28 | B81: 14:00-15:00 | C81: Zalo | D81: Broadcast T6 | E81: Gửi tin nhắn cuối tuần: event reminder, tips, weekend content. Segment phù hợp | F81: Broadcast sent | G81: Zalo Specialist
A82: 29 | B82: 15:00-17:00 | C82: Content | D82: Prepare content tuần tới | E82: Draft 3-4 ngày đầu tuần tới. Batch edit hình. Lên lịch auto-post nếu tool cho phép | F82: Next week content started | G82: Content Team
A84: THỨ BẢY — Event Day & Community
A85: STT | B85: Thời gian | C85: Kênh | D85: Công việc | E85: Chi tiết | F85: Output | G85: Người thực hiện
A86: 30 | B86: 7:00-8:00 | C86: Social Media | D86: Đăng bài sáng T7 (scheduled) | E86: Content đã chuẩn bị. Đăng FB + TikTok + IG. Zalo article | F86: Posts live | G86: Content Writer
A87: 31 | B87: 8:00-12:00 | C87: Event | D87: Hỗ trợ Open Day/Tour (nếu có) | E87: Photo/video coverage, live story IG/FB, welcome PH, hỗ trợ logistics | F87: Event coverage | G87: Cả team
A88: 32 | B88: 10:00-11:00 | C88: FB Group | D88: Livestream group T7 | E88: Live Q&A trong nhóm. Informal hơn T3/T5. Focus community building | F88: Live done | G88: Community Mgr
A89: 33 | B89: 14:00-15:00 | C89: TikTok | D89: TikTok Livestream T7 | E89: Live tour trường, Q&A, behind the scenes. Target PH trẻ | F89: TikTok live done | G89: TikTok Creator
A90: 34 | B90: 15:00-16:00 | C90: Ads | D90: Quick ads check T7 | E90: Birch → Weekend performance. Quick adjustments if needed | F90: Ads checked | G90: Ads Specialist
A92: CHỦ NHẬT — Light Work & Next Week Prep
A93: STT | B93: Thời gian | C93: Kênh | D93: Công việc | E93: Chi tiết | F93: Output | G93: Người thực hiện
A94: 35 | B94: 9:00-10:00 | C94: Social Media | D94: Đăng bài CN + Stories | E94: Bài nhẹ nhàng: throwback, motivation, family content. Stories poll | F94: Posts live | G94: Content Writer
A95: 36 | B95: 10:00-11:00 | C95: GHL + Pancake | D95: Check weekend leads | E95: Review leads từ T7-CN. Assign nếu urgent. Prepare follow-up T2 | F95: Leads noted | G95: Marketing Lead
A96: 37 | B96: 14:00-16:00 | C96: Planning | D96: Chuẩn bị tuần tới | E96: Finalize content T2-T4. Review tuần qua: what worked, what didn't. Adjust strategy | F96: Next week plan ready | G96: Marketing Lead
A97: 38 | B97: 16:00-17:00 | C97: Email | D97: Schedule weekly newsletter T2 sáng | E97: GHL → Email → Schedule newsletter cho T2 8:00. Final check content, links | F97: Newsletter scheduled | G97: Content Writer

Sheet D. Todo Monthly
B1: 📆 TODO LIST HÀNG THÁNG – REVIEW + PLANNING + TUYỂN SINH (Tháng 4–9/2026)
B3: STT | C3: Tháng/Đội | D3: Công việc | E3: Chi tiết / Tiêu chí | F3: KPI cần đạt | G3: Deadline | H3: Owner | I3: Status
B4: THÁNG 4/2026 – SETUP + PILOT
B5: 📌 Ngân sách: 1,820,000,000đ | Mục tiêu: 1,400 leads / 420 tours
B6: 1 | C6: Management | D6: Go/No-go decision 31/03 | E6: Tracking đã live? GHL nhận lead? LP hoạt động? Birch kết nối? | F6: All systems GO | G6: 31/03 | H6: ☐
B7: 2 | C7: Marketing | D7: Launch brand + generic search | E7: Bật Brand Search + Generic cho GV, BT | RSA 2 variant/adgroup | F7: CTR >6% | G7: 09/04 | H7: ☐
B8: 3 | C8: Marketing | D8: Mở Meta campaign đợt 1 | E8: Prospecting MN+TH | Lead Gen THCS+THPT | Test 10-15 creative | F8: CPL <150k | G8: 09/04 | H8: ☐
B9: 4 | C9: Marketing | D9: Webinar #1 (THCS) | E9: Chủ đề: Lộ trình lớp 6 | 100+ đăng ký | Chốt tour sau | F9: 100 reg | G9: 15/04 | H9: ☐
B10: 5 | C10: Tuyển sinh | D10: QA pipeline đầu tiên | E10: Nghe 20 cuộc gọi đầu | Score | Coaching ngay | Fix script | F10: QA report | G10: 15/04 | H10: ☐
B11: 6 | C11: Campus | D11: Confirm tour slots tháng 4 | E11: Tối thiểu 2 slot/campus/tuần | Brief campus manager | F11: Slots live | G11: 07/04 | H11: ☐
B12: 7 | C12: Management | D12: Mid-month CPL review | E12: CPL từng kênh, từng campus | Scale/pause decision | F12: Budget adj | G12: 15/04 | H12: ☐
B13: 8 | C13: Marketing | D13: A/B test landing pages | E13: Test 2 LP version cho THCS/THPT | Measure CVR | F13: Winner selected | G13: 30/04 | H13: ☐
B14: 9 | C14: Management | D14: Monthly review tháng 4 | E14: So với target: leads, tours, CPL, response rate | Plan tháng 5 | F14: Report + plan | G14: 30/04 | H14: ☐
B16: THÁNG 5/2026 – MỞ RỘNG + SCALE
B17: 📌 Ngân sách: 2,860,000,000đ | Mục tiêu: 2,400 leads / 720 tours
B18: 1 | C18: Marketing | D18: Scale campaign thắng tháng 4 | E18: Top 5 adset/campaign → +20-30% budget | KPI-based scaling | F18: Budget scaled | G18: 05/05 | H18: ☐
B19: 2 | C19: Marketing | D19: Mở competitor search | E19: THPT GV chọn lọc | Landing compare mềm | Budget riêng | F19: CPL competitor | G19: 07/05 | H19: ☐
B20: 3 | C20: Marketing | D20: Webinar #2 (THPT) | E20: Chủ đề: Tuyển sinh lớp 10, học bổng | 120+ đăng ký | F20: 120 reg | G20: 14/05 | H20: ☐
B21: 4 | C21: Marketing | D21: TikTok scale top videos | E21: Top 5 video by CPV → Spark Ads | Budget TikTok +30% | F21: CPV ≤2k | G21: 10/05 | H21: ☐
B22: 5 | C22: Tuyển sinh | D22: Open Day #1 | E22: Tổ chức open campus event | PR + paid + Zalo broadcast | F22: 50+ phụ huynh | G22: 17/05 | H22: ☐
B23: 6 | C23: Campus | D23: Zalo broadcast tỉnh | E23: Blast toàn bộ Zalo OA subscriber tỉnh | Mời tour tháng 6 | F23: Open ≥40% | G23: 20/05 | H23: ☐
B24: 7 | C24: Marketing | D24: Remarketing ramp-up | E24: Bật strong retarget: học phí visitors, form-not-submit, video viewers | F24: ROAS tracking | G24: 15/05 | H24: ☐
B25: 8 | C25: Management | D25: Mid-month review tháng 5 | E25: Check 53% target lead | Lead→Tour rate | School tour quality | F25: Decision | G25: 15/05 | H25: ☐
B26: 9 | C26: Management | D26: Monthly review tháng 5 | E26: Full KPI review | Budget reallocation tháng 6 | Creative refresh plan | F26: Report + plan | G26: 31/05 | H26: ☐
B28: THÁNG 6/2026 – CAO ĐIỂM TOUR
B29: 📌 Ngân sách: 3,120,000,000đ | Mục tiêu: 2,800 leads / 840 tours | Check 53% target
B30: 1 | C30: Marketing | D30: Tăng ngân sách THCS/THPT | E30: THCS PN, THCS GV, THPT GV → +25-30% | Dựa trên booked tour data | F30: Budget adj | G30: 01/06 | H30: ☐
B31: 2 | C31: Marketing | D31: Test PMax nhỏ | E31: PMax test 2% Google budget | Chỉ cho THPT | Track riêng quality | F31: Lead quality | G31: 07/06 | H31: ☐
B32: 3 | C32: Marketing | D32: YouTube/Demand Gen scale | E32: Testimonial video THCS/THPT → Retarget | Webinar reminder | F32: View-to-tour | G32: 07/06 | H32: ☐
B33: 4 | C33: Marketing | D33: Webinar #3 (THCS - chuyển cấp) | E33: Lộ trình con tôi học ở đâu sau lớp 5? | 100+ reg | F33: 100 reg | G33: 11/06 | H33: ☐
